Workbook

Sheet Översikt
B2: INVESTERINGSKALKYL — LEJONFASTIGHETER AB
B3: =IF(Indata!B26="","(projekt ej namngivet)","Projekt: " & Indata!B26) -> Projekt: Skola
B5: BINDANDE KRAVHYRA
B6: Årshyra (mål-utfall) | C6: =Resultat!D14 -> 11631222 | E6: Bindande krav | F6: =Resultat!D15 -> NPV
B7: Per kvm/år | C7: =Resultat!D16 -> 2326.2443 | E7: Total area | F7: =Indata!F31 & " m²" -> 5000 m²
B8: Total investering | C8: =Indata!R31 -> 200000000 | E8: Investering per kvm | F8: =IFERROR(Indata!R31/Indata!F31,0) -> 40000
B10: HYRESSPANN VID INVESTERINGSUTFALL
B11: Lägsta utfall (-X%) | C11: =Resultat!C14 -> 10726244 | E11: =Resultat!C7 -> 180000000
B12: Mål-utfall (bindande) | C12: =Resultat!D14 -> 11631222 | E12: =Resultat!D7 -> 200000000
B13: Högsta utfall (+X%) | C13: =Resultat!E14 -> 12536199 | E13: =Resultat!E7 -> 220000000
B15: LÖNSAMHETSKRAV — STATUS VID BINDANDE KRAVHYRA
B16: 1. NPV ≥ 0 | C16: =Lönsamhetskontroll!C9 -> 0 | E16: =Lönsamhetskontroll!D9 -> ✓ Uppfyllt
B17: 2. IRR EK ≥ avkastningskrav | C17: =Lönsamhetskontroll!C18 -> 10154924 | E17: =Lönsamhetskontroll!D18 -> ✓ Uppfyllt
B18: 3. MV år N ≥ Bokfört värde år N | C18: =Lönsamhetskontroll!C30 -> 1.5586973e+08 | E18: =Lönsamhetskontroll!D30 -> ✓ Uppfyllt
B20: Faktisk IRR EK | C20: =Lönsamhetskontroll!C45 -> 0.076451715 | E20: Marginal mot krav | F20: =Lönsamhetskontroll!C47 -> 0.013451715
B23: INNEHÅLLSFÖRTECKNING
B25: Indata | C25: Inmatning | E25: Marknadsförutsättningar, investering, hyresobjekt, drift, finansiering. Allt som ska fyllas i innan kalkylen körs.
B27: Resultat | C27: Vad blir hyran? | E27: Kravhyra för de tre lönsamhetskraven, bindande hyra och fördelning per hus. Tre scenarier (lägsta/mål/högsta investeringsutfall).
B29: Kassaflöde | C29: Driftnetto år för år | E29: Driftnetto-projektion vid bindande hyra (bruttohyra → nettohyra → driftnetto) plus infasning under uppstartsår.
B31: Finansiering | C31: Lån och avskrivning | E31: Lånebild över kalkylperioden: upptaget lån, amortering, räntekostnad, eget kapital och avskrivning år för år.
B33: Lönsamhetskontroll | C33: Är kraven uppfyllda? | E33: Verifiering av de tre lönsamhetskraven, faktisk IRR EK och känslighetsanalys för exit-värdet.
B35: Beräkningslogik | C35: Hur räknar mallen? | E35: Pedagogisk förklaring av delta-metoden + de tekniska beräkningsblocken (A-F) som ligger bakom kravhyran.
B37: Dokumentation | C37: Varför så här? | E37: Designprinciper, val, paritetstest mot LM 371 och backlog för framtida utveckling.

Sheet Indata
B1: INDATA
B2: Fält med ljusblå bakgrund ska fyllas i.
B4: 1. MARKNADS- OCH FASTIGHETSFÖRUTSÄTTNINGAR
B5: Kalkylstart (år) | C5: 2026 | D5: år | E5: Första året i kassaflödet
B6: Direktavkastning marknad | C6: 0.05 | D6: % | E6: Avkastningskrav, från senaste värdering
B7: Kalkylränta driftnetto | C7: 0.04 | D7: % | E7: Företagets diskonteringsränta (NPV-kravet)
B8: Inflation | C8: 0.02 | D8: % | E8: Årlig KPI-uppräkning
B9: Kalkylränta restvärde | C9: =C6+C8 -> 0.07 | D9: % | E9: Auto = direktavkastning + inflation
B10: Bolagsskatt | C10: 0.206 | D10: % | E10: För IRR-beräkning
B11: Långsiktig vakansnivå | C11: 0 | D11: % | E11: Default efter avtalsslut
B12: Momsregistreringsgrad före | C12: 1 | D12: %
B13: Momsregistreringsgrad efter | C13: 1 | D13: %
B15: 2. INVESTERING OCH AVSKRIVNING
B16: Kalkylperiod | C16: 20 | D16: år | E16: Standard 20
B17: Byggnadsvärde (avskrivningsbas) | C17: 200000000 | D17: kr | E17: Investering exkl. mark (påverkar avskrivning och IRR)
B18: Avskrivnings-% per år | C18: 0.03 | D18: % | E18: 3% = 33 års livslängd
B19: Avskrivningstid | C19: =ROUND(1/C18,0) -> 33 | D19: år | E19: Auto
B20: Fastighetsarea (mark) | C20: 10000 | D20: kvm | E20: Total markarea
B21: Markvärde | C21: 500 | D21: kr/kvm | E21: För minsta markvärde
B22: Minsta markvärde (totalt) | C22: =C20*C21 -> 5000000 | D22: kr | E22: Auto
B23: HYRESLÄGE | C23: Beräkna | E23: Beräkna = mallen räknar kravhyran. Ange = manuell (ej aktiv än)
B24: 3. HYRESOBJEKT (upp till 5)
B25: Objektnamn | C25: Typ | D25: Bef area | E25: Nyb area | F25: Total | G25: (ej använd) | H25: Index | I25: (ej använd) | J25: Andel | K25: Avtalsstart | L25: Avtalsslut | M25: Hyra efter avtal | N25: Vakans% | O25: Prod start | P25: Prod slut | Q25: Budget kr/kvm | R25: Investering
B26: Skola | C26: Nyb | D26: 0 | E26: 5000 | F26: =D26+E26 -> 5000 | G26: 0 | H26: 0.7 | I26: 0 | J26: =IFERROR(R26/$R$31,0) -> 1 | K26: 2026 | L26: 2045 | N26: 0 | O26: 2025 | P26: 2026 | Q26: 40000 | R26: =IFERROR(Q26*F26,0) -> 200000000
F27: =D27+E27 -> 0 | G27: 0 | I27: 0 | J27: =IFERROR(R27/$R$31,0) -> 0 | R27: =IFERROR(Q27*F27,0) -> 0
F28: =D28+E28 -> 0 | G28: 0 | I28: 0 | J28: =IFERROR(R28/$R$31,0) -> 0 | R28: =IFERROR(Q28*F28,0) -> 0
F29: =D29+E29 -> 0 | G29: 0 | I29: 0 | J29: =IFERROR(R29/$R$31,0) -> 0 | R29: =IFERROR(Q29*F29,0) -> 0
F30: =D30+E30 -> 0 | G30: 0 | I30: 0 | J30: =IFERROR(R30/$R$31,0) -> 0 | R30: =IFERROR(Q30*F30,0) -> 0
B31: Summa | D31: =SUM(D26:D30) -> 0 | E31: =SUM(E26:E30) -> 5000 | F31: =SUM(F26:F30) -> 5000 | R31: =SUM(R26:R30) -> 200000000
B32: ⓘ "Hyra efter avtal" (M) används endast efter avtalsslut. Lämna tomt för monopolmodell (samma kr/m² fortsätter). Fyll i för korta avtal. Se Dokumentation sektion 13.
B34: 4. DRIFT OCH UNDERHÅLL (kr/kvm/år)
B35: Kostnadspost | C35: Befintligt | D35: Nybyggnad | E35: DoU-höjning från år 11 | F35: Ytterligare höjning från år 16
B36: Fastighetsskötsel | C36: 0 | D36: 50 | E36: 0 | F36: 0
B37: Reparationer | C37: 0 | D37: 30 | E37: 0 | F37: 0
B38: Planerat underhåll | C38: 0 | D38: 40 | E38: 0 | F38: 0
B39: Media | C39: 0 | D39: 150 | E39: 0 | F39: 0
B40: Övriga förvaltningskostnader | C40: 0 | D40: 130 | E40: 0 | F40: 0
B41: Summa drift | C41: =SUM(C36:C40) -> 0 | D41: =SUM(D36:D40) -> 400
B43: 5. RE-INVESTERING / HYRESATT UH
B44: Åtgärd | C44: Objekt | D44: År | E44: kr/kvm | F44: Total
F45: =IFERROR(E45*VLOOKUP(C45,B26:F30,5,FALSE()),0) -> 0
F46: =IFERROR(E46*VLOOKUP(C46,B26:F30,5,FALSE()),0) -> 0
F47: =IFERROR(E47*VLOOKUP(C47,B26:F30,5,FALSE()),0) -> 0
F48: =IFERROR(E48*VLOOKUP(C48,B26:F30,5,FALSE()),0) -> 0
F49: =IFERROR(E49*VLOOKUP(C49,B26:F30,5,FALSE()),0) -> 0
F50: =IFERROR(E50*VLOOKUP(C50,B26:F30,5,FALSE()),0) -> 0
B52: 6. ÖVRIGA POSTER
B53: Central administration | C53: 80 | D53: kr/kvm | E53: Schablon för bolagsoverhead. Default: Lejonfastigheters snitt 80 kr/m²
B54: Fastighetsskatt (% av taxv) | C54: 0 | D54: %
B55: Taxeringsvärde | C55: 0 | D55: kr
B56: Tomträttsavgäld | C56: 0 | D56: kr/år
B57: Bokfört värde (befintligt) | C57: 0 | D57: kr | E57: Vid stora ombyggnader. Påverkar krav 3 (MV ≥ BV år N). 0 vid nybyggnation.
B58: Bokfört värde projektbelastning | C58: 0 | D58: kr | E58: Eventuell extra belastning, t.ex. balanserade kostnader. 0 vid nybyggnation.
B60: 7. FINANSIERING
B61: Byggnadskreditivränta | C61: 0.03 | D61: %
B62: Långsiktig ränta | C62: 0.04 | D62: %
B63: Amortering | C63: 0.02 | D63: %
B64: Belåningsgrad | C64: 0.37 | D64: % | E64: Lejonfastigheters snittbelåning
B65: Avkastningskrav eget kapital | C65: 0.063 | D65: % | E65: För IRR-kravet
B67: 8. HYRESSPANN
B68: Intervall på investeringen (±) | C68: 0.1 | D68: % | E68: Hyresspannet beräknas för lägsta, mål och högsta utfall

Sheet Kassaflöde
B1: KASSAFLÖDE
B3: Kalenderår | D3: =Indata!$C$5+0 -> 2026 | E3: =Indata!$C$5+1 -> 2027 | F3: =Indata!$C$5+2 -> 2028 | G3: =Indata!$C$5+3 -> 2029 | H3: =Indata!$C$5+4 -> 2030 | I3: =Indata!$C$5+5 -> 2031 | J3: =Indata!$C$5+6 -> 2032 | K3: =Indata!$C$5+7 -> 2033 | L3: =Indata!$C$5+8 -> 2034 | M3: =Indata!$C$5+9 -> 2035 | N3: =Indata!$C$5+10 -> 2036 | O3: =Indata!$C$5+11 -> 2037 | P3: =Indata!$C$5+12 -> 2038 | Q3: =Indata!$C$5+13 -> 2039 | R3: =Indata!$C$5+14 -> 2040 | S3: =Indata!$C$5+15 -> 2041 | T3: =Indata!$C$5+16 -> 2042 | U3: =Indata!$C$5+17 -> 2043 | V3: =Indata!$C$5+18 -> 2044 | W3: =Indata!$C$5+19 -> 2045 | X3: =Indata!$C$5+20 -> 2046 | Y3: =Indata!$C$5+21 -> 2047 | Z3: =Indata!$C$5+22 -> 2048 | AA3: =Indata!$C$5+23 -> 2049 | AB3: =Indata!$C$5+24 -> 2050
B4: År i kalkyl | D4: 1 | E4: 2 | F4: 3 | G4: 4 | H4: 5 | I4: 6 | J4: 7 | K4: 8 | L4: 9 | M4: 10 | N4: 11 | O4: 12 | P4: 13 | Q4: 14 | R4: 15 | S4: 16 | T4: 17 | U4: 18 | V4: 19 | W4: 20 | X4: 21 | Y4: 22 | Z4: 23 | AA4: 24 | AB4: 25
B5: Inom kalkylperiod | D5: =IF(D4<=Indata!$C$16,1,0) -> 1 | E5: =IF(E4<=Indata!$C$16,1,0) -> 1 | F5: =IF(F4<=Indata!$C$16,1,0) -> 1 | G5: =IF(G4<=Indata!$C$16,1,0) -> 1 | H5: =IF(H4<=Indata!$C$16,1,0) -> 1 | I5: =IF(I4<=Indata!$C$16,1,0) -> 1 | J5: =IF(J4<=Indata!$C$16,1,0) -> 1 | K5: =IF(K4<=Indata!$C$16,1,0) -> 1 | ... AB5: =IF(AB4<=Indata!$C$16,1,0) -> 0
B6: Area Nyb (aktiv) | D6: =SUMIFS(Indata!$E$26:$E$30,Indata!$C$26:$C$30,"Nyb",Indata!$P$26:$P$30,"<="&D3)+SUMIFS(Indata!$E$26:$E$30,Indata!$C$26:$C$30,"Omb",Indata!$P$26:$P$30,"<="&D3)+SUMIFS(Indata!$E$26:$E$30,Indata!$C$26:$C$30,"Ins",Indata!$P$26:$P$30,"<="&D3) -> 5000 | E6: =SUMIFS(Indata!$E$26:$E$30,Indata!$C$26:$C$30,"Nyb",Indata!$P$26:$P$30,"<="&E3)+SUMIFS(Indata!$E$26:$E$30,Indata!$C$26:$C$30,"Omb",Indata!$P$26:$P$30,"<="&E3)+SUMIFS(Indata!$E$26:$E$30,Indata!$C$26:$C$30,"Ins",Indata!$P$26:$P$30,"<="&E3) -> 5000 | F6: =SUMIFS(Indata!$E$26:$E$30,Indata!$C$26:$C$30,"Nyb",Indata!$P$26:$P$30,"<="&F3)+SUMIFS(Indata!$E$26:$E$30,Indata!$C$26:$C$30,"Omb",Indata!$P$26:$P$30,"<="&F3)+SUMIFS(Indata!$E$26:$E$30,Indata!$C$26:$C$30,"Ins",Indata!$P$26:$P$30,"<="&F3) -> 5000 | G6: =SUMIFS(Indata!$E$26:$E$30,Indata!$C$26:$C$30,"Nyb",Indata!$P$26:$P$30,"<="&G3)+SUMIFS(Indata!$E$26:$E$30,Indata!$C$26:$C$30,"Omb",Indata!$P$26:$P$30,"<="&G3)+SUMIFS(Indata!$E$26:$E$30,Indata!$C$26:$C$30,"Ins",Indata!$P$26:$P$30,"<="&G3) -> 5000 | H6: =SUMIFS(Indata!$E$26:$E$30,Indata!$C$26:$C$30,"Nyb",Indata!$P$26:$P$30,"<="&H3)+SUMIFS(Indata!$E$26:$E$30,Indata!$C$26:$C$30,"Omb",Indata!$P$26:$P$30,"<="&H3)+SUMIFS(Indata!$E$26:$E$30,Indata!$C$26:$C$30,"Ins",Indata!$P$26:$P$30,"<="&H3) -> 5000 | I6: =SUMIFS(Indata!$E$26:$E$30,Indata!$C$26:$C$30,"Nyb",Indata!$P$26:$P$30,"<="&I3)+SUMIFS(Indata!$E$26:$E$30,Indata!$C$26:$C$30,"Omb",Indata!$P$26:$P$30,"<="&I3)+SUMIFS(Indata!$E$26:$E$30,Indata!$C$26:$C$30,"Ins",Indata!$P$26:$P$30,"<="&I3) -> 5000 | J6: =SUMIFS(Indata!$E$26:$E$30,Indata!$C$26:$C$30,"Nyb",Indata!$P$26:$P$30,"<="&J3)+SUMIFS(Indata!$E$26:$E$30,Indata!$C$26:$C$30,"Omb",Indata!$P$26:$P$30,"<="&J3)+SUMIFS(Indata!$E$26:$E$30,Indata!$C$26:$C$30,"Ins",Indata!$P$26:$P$30,"<="&J3) -> 5000 | K6: =SUMIFS(Indata!$E$26:$E$30,Indata!$C$26:$C$30,"Nyb",Indata!$P$26:$P$30,"<="&K3)+SUMIFS(Indata!$E$26:$E$30,Indata!$C$26:$C$30,"Omb",Indata!$P$26:$P$30,"<="&K3)+SUMIFS(Indata!$E$26:$E$30,Indata!$C$26:$C$30,"Ins",Indata!$P$26:$P$30,"<="&K3) -> 5000 | ... AB6: =SUMIFS(Indata!$E$26:$E$30,Indata!$C$26:$C$30,"Nyb",Indata!$P$26:$P$30,"<="&AB3)+SUMIFS(Indata!$E$26:$E$30,Indata!$C$26:$C$30,"Omb",Indata!$P$26:$P$30,"<="&AB3)+SUMIFS(Indata!$E$26:$E$30,Indata!$C$26:$C$30,"Ins",Indata!$P$26:$P$30,"<="&AB3) -> 5000
B7: Area Bef (aktiv) | D7: =SUMIFS(Indata!$D$26:$D$30,Indata!$C$26:$C$30,"Bef",Indata!$P$26:$P$30,"<="&D3)+SUMIFS(Indata!$D$26:$D$30,Indata!$C$26:$C$30,"Omb",Indata!$P$26:$P$30,"<="&D3)+SUMIFS(Indata!$D$26:$D$30,Indata!$C$26:$C$30,"Nyb",Indata!$P$26:$P$30,"<="&D3)+SUMIFS(Indata!$D$26:$D$30,Indata!$C$26:$C$30,"Ins",Indata!$P$26:$P$30,"<="&D3) -> 0 | E7: =SUMIFS(Indata!$D$26:$D$30,Indata!$C$26:$C$30,"Bef",Indata!$P$26:$P$30,"<="&E3)+SUMIFS(Indata!$D$26:$D$30,Indata!$C$26:$C$30,"Omb",Indata!$P$26:$P$30,"<="&E3)+SUMIFS(Indata!$D$26:$D$30,Indata!$C$26:$C$30,"Nyb",Indata!$P$26:$P$30,"<="&E3)+SUMIFS(Indata!$D$26:$D$30,Indata!$C$26:$C$30,"Ins",Indata!$P$26:$P$30,"<="&E3) -> 0 | F7: =SUMIFS(Indata!$D$26:$D$30,Indata!$C$26:$C$30,"Bef",Indata!$P$26:$P$30,"<="&F3)+SUMIFS(Indata!$D$26:$D$30,Indata!$C$26:$C$30,"Omb",Indata!$P$26:$P$30,"<="&F3)+SUMIFS(Indata!$D$26:$D$30,Indata!$C$26:$C$30,"Nyb",Indata!$P$26:$P$30,"<="&F3)+SUMIFS(Indata!$D$26:$D$30,Indata!$C$26:$C$30,"Ins",Indata!$P$26:$P$30,"<="&F3) -> 0 | G7: =SUMIFS(Indata!$D$26:$D$30,Indata!$C$26:$C$30,"Bef",Indata!$P$26:$P$30,"<="&G3)+SUMIFS(Indata!$D$26:$D$30,Indata!$C$26:$C$30,"Omb",Indata!$P$26:$P$30,"<="&G3)+SUMIFS(Indata!$D$26:$D$30,Indata!$C$26:$C$30,"Nyb",Indata!$P$26:$P$30,"<="&G3)+SUMIFS(Indata!$D$26:$D$30,Indata!$C$26:$C$30,"Ins",Indata!$P$26:$P$30,"<="&G3) -> 0 | H7: =SUMIFS(Indata!$D$26:$D$30,Indata!$C$26:$C$30,"Bef",Indata!$P$26:$P$30,"<="&H3)+SUMIFS(Indata!$D$26:$D$30,Indata!$C$26:$C$30,"Omb",Indata!$P$26:$P$30,"<="&H3)+SUMIFS(Indata!$D$26:$D$30,Indata!$C$26:$C$30,"Nyb",Indata!$P$26:$P$30,"<="&H3)+SUMIFS(Indata!$D$26:$D$30,Indata!$C$26:$C$30,"Ins",Indata!$P$26:$P$30,"<="&H3) -> 0 | I7: =SUMIFS(Indata!$D$26:$D$30,Indata!$C$26:$C$30,"Bef",Indata!$P$26:$P$30,"<="&I3)+SUMIFS(Indata!$D$26:$D$30,Indata!$C$26:$C$30,"Omb",Indata!$P$26:$P$30,"<="&I3)+SUMIFS(Indata!$D$26:$D$30,Indata!$C$26:$C$30,"Nyb",Indata!$P$26:$P$30,"<="&I3)+SUMIFS(Indata!$D$26:$D$30,Indata!$C$26:$C$30,"Ins",Indata!$P$26:$P$30,"<="&I3) -> 0 | J7: =SUMIFS(Indata!$D$26:$D$30,Indata!$C$26:$C$30,"Bef",Indata!$P$26:$P$30,"<="&J3)+SUMIFS(Indata!$D$26:$D$30,Indata!$C$26:$C$30,"Omb",Indata!$P$26:$P$30,"<="&J3)+SUMIFS(Indata!$D$26:$D$30,Indata!$C$26:$C$30,"Nyb",Indata!$P$26:$P$30,"<="&J3)+SUMIFS(Indata!$D$26:$D$30,Indata!$C$26:$C$30,"Ins",Indata!$P$26:$P$30,"<="&J3) -> 0 | K7: =SUMIFS(Indata!$D$26:$D$30,Indata!$C$26:$C$30,"Bef",Indata!$P$26:$P$30,"<="&K3)+SUMIFS(Indata!$D$26:$D$30,Indata!$C$26:$C$30,"Omb",Indata!$P$26:$P$30,"<="&K3)+SUMIFS(Indata!$D$26:$D$30,Indata!$C$26:$C$30,"Nyb",Indata!$P$26:$P$30,"<="&K3)+SUMIFS(Indata!$D$26:$D$30,Indata!$C$26:$C$30,"Ins",Indata!$P$26:$P$30,"<="&K3) -> 0 | ... AB7: =SUMIFS(Indata!$D$26:$D$30,Indata!$C$26:$C$30,"Bef",Indata!$P$26:$P$30,"<="&AB3)+SUMIFS(Indata!$D$26:$D$30,Indata!$C$26:$C$30,"Omb",Indata!$P$26:$P$30,"<="&AB3)+SUMIFS(Indata!$D$26:$D$30,Indata!$C$26:$C$30,"Nyb",Indata!$P$26:$P$30,"<="&AB3)+SUMIFS(Indata!$D$26:$D$30,Indata!$C$26:$C$30,"Ins",Indata!$P$26:$P$30,"<="&AB3) -> 0
B8: Total area | D8: =D6+D7 -> 5000 | E8: =E6+E7 -> 5000 | F8: =F6+F7 -> 5000 | G8: =G6+G7 -> 5000 | H8: =H6+H7 -> 5000 | I8: =I6+I7 -> 5000 | J8: =J6+J7 -> 5000 | K8: =K6+K7 -> 5000 | ... AB8: =AB6+AB7 -> 5000
B10: DRIFTNETTO-PROJEKTION vid bindande kravhyra
B11: Projektets driftnetto år för år vid den hyra mallen räknat fram. Detta är kassaflödet före finansiering — för bokföringsmässig vy med ränta och avskrivning, se Finansiering-fliken.
B13: Bindande kravhyra (kr/år) | C13: =Resultat!D14 -> 11631222
B14: Bindande krav | C14: =Resultat!D15 -> NPV
B16: Bruttohyra | D16: =Beräkningslogik!D66+($C$13/1000000)*(Beräkningslogik!D129-Beräkningslogik!D66) -> 11631222 | E16: =Beräkningslogik!E66+($C$13/1000000)*(Beräkningslogik!E129-Beräkningslogik!E66) -> 11794059 | F16: =Beräkningslogik!F66+($C$13/1000000)*(Beräkningslogik!F129-Beräkningslogik!F66) -> 11959176 | G16: =Beräkningslogik!G66+($C$13/1000000)*(Beräkningslogik!G129-Beräkningslogik!G66) -> 12126604 | H16: =Beräkningslogik!H66+($C$13/1000000)*(Beräkningslogik!H129-Beräkningslogik!H66) -> 12296377 | I16: =Beräkningslogik!I66+($C$13/1000000)*(Beräkningslogik!I129-Beräkningslogik!I66) -> 12468526 | J16: =Beräkningslogik!J66+($C$13/1000000)*(Beräkningslogik!J129-Beräkningslogik!J66) -> 12643085 | K16: =Beräkningslogik!K66+($C$13/1000000)*(Beräkningslogik!K129-Beräkningslogik!K66) -> 12820088 | ... AB16: =Beräkningslogik!AB66+($C$13/1000000)*(Beräkningslogik!AB129-Beräkningslogik!AB66) -> 16238139
B17: Vakans | D17: =Beräkningslogik!D67+($C$13/1000000)*(Beräkningslogik!D130-Beräkningslogik!D67) -> 0 | E17: =Beräkningslogik!E67+($C$13/1000000)*(Beräkningslogik!E130-Beräkningslogik!E67) -> 0 | F17: =Beräkningslogik!F67+($C$13/1000000)*(Beräkningslogik!F130-Beräkningslogik!F67) -> 0 | G17: =Beräkningslogik!G67+($C$13/1000000)*(Beräkningslogik!G130-Beräkningslogik!G67) -> 0 | H17: =Beräkningslogik!H67+($C$13/1000000)*(Beräkningslogik!H130-Beräkningslogik!H67) -> 0 | I17: =Beräkningslogik!I67+($C$13/1000000)*(Beräkningslogik!I130-Beräkningslogik!I67) -> 0 | J17: =Beräkningslogik!J67+($C$13/1000000)*(Beräkningslogik!J130-Beräkningslogik!J67) -> 0 | K17: =Beräkningslogik!K67+($C$13/1000000)*(Beräkningslogik!K130-Beräkningslogik!K67) -> 0 | ... AB17: =Beräkningslogik!AB67+($C$13/1000000)*(Beräkningslogik!AB130-Beräkningslogik!AB67) -> 0
B18: Nettohyra | D18: =Beräkningslogik!D68+($C$13/1000000)*(Beräkningslogik!D131-Beräkningslogik!D68) -> 11631222 | E18: =Beräkningslogik!E68+($C$13/1000000)*(Beräkningslogik!E131-Beräkningslogik!E68) -> 11794059 | F18: =Beräkningslogik!F68+($C$13/1000000)*(Beräkningslogik!F131-Beräkningslogik!F68) -> 11959176 | G18: =Beräkningslogik!G68+($C$13/1000000)*(Beräkningslogik!G131-Beräkningslogik!G68) -> 12126604 | H18: =Beräkningslogik!H68+($C$13/1000000)*(Beräkningslogik!H131-Beräkningslogik!H68) -> 12296377 | I18: =Beräkningslogik!I68+($C$13/1000000)*(Beräkningslogik!I131-Beräkningslogik!I68) -> 12468526 | J18: =Beräkningslogik!J68+($C$13/1000000)*(Beräkningslogik!J131-Beräkningslogik!J68) -> 12643085 | K18: =Beräkningslogik!K68+($C$13/1000000)*(Beräkningslogik!K131-Beräkningslogik!K68) -> 12820088 | ... AB18: =Beräkningslogik!AB68+($C$13/1000000)*(Beräkningslogik!AB131-Beräkningslogik!AB68) -> 16238139
B19: Drift och underhåll | D19: =Beräkningslogik!D77 -> -2000000 | E19: =Beräkningslogik!E77 -> -2040000 | F19: =Beräkningslogik!F77 -> -2080800 | G19: =Beräkningslogik!G77 -> -2122416 | H19: =Beräkningslogik!H77 -> -2164864.3 | I19: =Beräkningslogik!I77 -> -2208161.6 | J19: =Beräkningslogik!J77 -> -2252324.8 | K19: =Beräkningslogik!K77 -> -2297371.3 | ... AB19: =Beräkningslogik!AB77 -> -3216874.5
B20: Fastighetsskatt | D20: =Beräkningslogik!D79 -> 0 | E20: =Beräkningslogik!E79 -> 0 | F20: =Beräkningslogik!F79 -> 0 | G20: =Beräkningslogik!G79 -> 0 | H20: =Beräkningslogik!H79 -> 0 | I20: =Beräkningslogik!I79 -> 0 | J20: =Beräkningslogik!J79 -> 0 | K20: =Beräkningslogik!K79 -> 0 | ... AB20: =Beräkningslogik!AB79 -> 0
B21: Tomträttsavgäld | D21: =Beräkningslogik!D80 -> 0 | E21: =Beräkningslogik!E80 -> 0 | F21: =Beräkningslogik!F80 -> 0 | G21: =Beräkningslogik!G80 -> 0 | H21: =Beräkningslogik!H80 -> 0 | I21: =Beräkningslogik!I80 -> 0 | J21: =Beräkningslogik!J80 -> 0 | K21: =Beräkningslogik!K80 -> 0 | ... AB21: =Beräkningslogik!AB80 -> 0
B22: Central administration | D22: =Beräkningslogik!D83 -> -400000 | E22: =Beräkningslogik!E83 -> -408000 | F22: =Beräkningslogik!F83 -> -416160 | G22: =Beräkningslogik!G83 -> -424483.2 | H22: =Beräkningslogik!H83 -> -432972.86 | I22: =Beräkningslogik!I83 -> -441632.32 | J22: =Beräkningslogik!J83 -> -450464.97 | K22: =Beräkningslogik!K83 -> -459474.27 | ... AB22: =Beräkningslogik!AB83 -> -643374.9
B23: DRIFTNETTO | D23: =Beräkningslogik!D82+($C$13/1000000)*(Beräkningslogik!D132-Beräkningslogik!D82) -> 9231221.7 | E23: =Beräkningslogik!E82+($C$13/1000000)*(Beräkningslogik!E132-Beräkningslogik!E82) -> 9346058.8 | F23: =Beräkningslogik!F82+($C$13/1000000)*(Beräkningslogik!F132-Beräkningslogik!F82) -> 9462215.6 | G23: =Beräkningslogik!G82+($C$13/1000000)*(Beräkningslogik!G132-Beräkningslogik!G82) -> 9579704.9 | H23: =Beräkningslogik!H82+($C$13/1000000)*(Beräkningslogik!H132-Beräkningslogik!H82) -> 9698539.4 | I23: =Beräkningslogik!I82+($C$13/1000000)*(Beräkningslogik!I132-Beräkningslogik!I82) -> 9818731.9 | J23: =Beräkningslogik!J82+($C$13/1000000)*(Beräkningslogik!J132-Beräkningslogik!J82) -> 9940295.4 | K23: =Beräkningslogik!K82+($C$13/1000000)*(Beräkningslogik!K132-Beräkningslogik!K82) -> 10063243 | ... AB23: =Beräkningslogik!AB82+($C$13/1000000)*(Beräkningslogik!AB132-Beräkningslogik!AB82) -> 12377890
B26: INFASNING — hyresintäkt under uppstart
B27: Vid mål-utfall och bindande kravhyra. Visar etappvis tillträde under uppstartsår.
B29: Objekt | D29: =Indata!$C$5+0 -> 2026 | E29: =Indata!$C$5+1 -> 2027 | F29: =Indata!$C$5+2 -> 2028 | G29: =Indata!$C$5+3 -> 2029 | H29: =Indata!$C$5+4 -> 2030 | I29: =Indata!$C$5+5 -> 2031 | J29: =Indata!$C$5+6 -> 2032 | K29: =Indata!$C$5+7 -> 2033 | L29: =Indata!$C$5+8 -> 2034 | M29: =Indata!$C$5+9 -> 2035
B30: =IF(Indata!B26="","",Indata!B26) -> Skola | D30: =IF(OR(Indata!$K$26="",D$29<Indata!$K$26),0,(Indata!$R$26/Indata!$R$31)*$E$7*(1+Indata!$C$8)^(D$29-Indata!$K$26)) -> 0 | E30: =IF(OR(Indata!$K$26="",E$29<Indata!$K$26),0,(Indata!$R$26/Indata!$R$31)*$E$7*(1+Indata!$C$8)^(E$29-Indata!$K$26)) -> 0 | F30: =IF(OR(Indata!$K$26="",F$29<Indata!$K$26),0,(Indata!$R$26/Indata!$R$31)*$E$7*(1+Indata!$C$8)^(F$29-Indata!$K$26)) -> 0 | G30: =IF(OR(Indata!$K$26="",G$29<Indata!$K$26),0,(Indata!$R$26/Indata!$R$31)*$E$7*(1+Indata!$C$8)^(G$29-Indata!$K$26)) -> 0 | H30: =IF(OR(Indata!$K$26="",H$29<Indata!$K$26),0,(Indata!$R$26/Indata!$R$31)*$E$7*(1+Indata!$C$8)^(H$29-Indata!$K$26)) -> 0 | I30: =IF(OR(Indata!$K$26="",I$29<Indata!$K$26),0,(Indata!$R$26/Indata!$R$31)*$E$7*(1+Indata!$C$8)^(I$29-Indata!$K$26)) -> 0 | J30: =IF(OR(Indata!$K$26="",J$29<Indata!$K$26),0,(Indata!$R$26/Indata!$R$31)*$E$7*(1+Indata!$C$8)^(J$29-Indata!$K$26)) -> 0 | K30: =IF(OR(Indata!$K$26="",K$29<Indata!$K$26),0,(Indata!$R$26/Indata!$R$31)*$E$7*(1+Indata!$C$8)^(K$29-Indata!$K$26)) -> 0 | ... M30: =IF(OR(Indata!$K$26="",M$29<Indata!$K$26),0,(Indata!$R$26/Indata!$R$31)*$E$7*(1+Indata!$C$8)^(M$29-Indata!$K$26)) -> 0
B31: =IF(Indata!B27="","",Indata!B27) | D31: =IF(OR(Indata!$K$27="",D$29<Indata!$K$27),0,(Indata!$R$27/Indata!$R$31)*$E$7*(1+Indata!$C$8)^(D$29-Indata!$K$27)) -> 0 | E31: =IF(OR(Indata!$K$27="",E$29<Indata!$K$27),0,(Indata!$R$27/Indata!$R$31)*$E$7*(1+Indata!$C$8)^(E$29-Indata!$K$27)) -> 0 | F31: =IF(OR(Indata!$K$27="",F$29<Indata!$K$27),0,(Indata!$R$27/Indata!$R$31)*$E$7*(1+Indata!$C$8)^(F$29-Indata!$K$27)) -> 0 | G31: =IF(OR(Indata!$K$27="",G$29<Indata!$K$27),0,(Indata!$R$27/Indata!$R$31)*$E$7*(1+Indata!$C$8)^(G$29-Indata!$K$27)) -> 0 | H31: =IF(OR(Indata!$K$27="",H$29<Indata!$K$27),0,(Indata!$R$27/Indata!$R$31)*$E$7*(1+Indata!$C$8)^(H$29-Indata!$K$27)) -> 0 | I31: =IF(OR(Indata!$K$27="",I$29<Indata!$K$27),0,(Indata!$R$27/Indata!$R$31)*$E$7*(1+Indata!$C$8)^(I$29-Indata!$K$27)) -> 0 | J31: =IF(OR(Indata!$K$27="",J$29<Indata!$K$27),0,(Indata!$R$27/Indata!$R$31)*$E$7*(1+Indata!$C$8)^(J$29-Indata!$K$27)) -> 0 | K31: =IF(OR(Indata!$K$27="",K$29<Indata!$K$27),0,(Indata!$R$27/Indata!$R$31)*$E$7*(1+Indata!$C$8)^(K$29-Indata!$K$27)) -> 0 | ... M31: =IF(OR(Indata!$K$27="",M$29<Indata!$K$27),0,(Indata!$R$27/Indata!$R$31)*$E$7*(1+Indata!$C$8)^(M$29-Indata!$K$27)) -> 0
B32: =IF(Indata!B28="","",Indata!B28) | D32: =IF(OR(Indata!$K$28="",D$29<Indata!$K$28),0,(Indata!$R$28/Indata!$R$31)*$E$7*(1+Indata!$C$8)^(D$29-Indata!$K$28)) -> 0 | E32: =IF(OR(Indata!$K$28="",E$29<Indata!$K$28),0,(Indata!$R$28/Indata!$R$31)*$E$7*(1+Indata!$C$8)^(E$29-Indata!$K$28)) -> 0 | F32: =IF(OR(Indata!$K$28="",F$29<Indata!$K$28),0,(Indata!$R$28/Indata!$R$31)*$E$7*(1+Indata!$C$8)^(F$29-Indata!$K$28)) -> 0 | G32: =IF(OR(Indata!$K$28="",G$29<Indata!$K$28),0,(Indata!$R$28/Indata!$R$31)*$E$7*(1+Indata!$C$8)^(G$29-Indata!$K$28)) -> 0 | H32: =IF(OR(Indata!$K$28="",H$29<Indata!$K$28),0,(Indata!$R$28/Indata!$R$31)*$E$7*(1+Indata!$C$8)^(H$29-Indata!$K$28)) -> 0 | I32: =IF(OR(Indata!$K$28="",I$29<Indata!$K$28),0,(Indata!$R$28/Indata!$R$31)*$E$7*(1+Indata!$C$8)^(I$29-Indata!$K$28)) -> 0 | J32: =IF(OR(Indata!$K$28="",J$29<Indata!$K$28),0,(Indata!$R$28/Indata!$R$31)*$E$7*(1+Indata!$C$8)^(J$29-Indata!$K$28)) -> 0 | K32: =IF(OR(Indata!$K$28="",K$29<Indata!$K$28),0,(Indata!$R$28/Indata!$R$31)*$E$7*(1+Indata!$C$8)^(K$29-Indata!$K$28)) -> 0 | ... M32: =IF(OR(Indata!$K$28="",M$29<Indata!$K$28),0,(Indata!$R$28/Indata!$R$31)*$E$7*(1+Indata!$C$8)^(M$29-Indata!$K$28)) -> 0
B33: =IF(Indata!B29="","",Indata!B29) | D33: =IF(OR(Indata!$K$29="",D$29<Indata!$K$29),0,(Indata!$R$29/Indata!$R$31)*$E$7*(1+Indata!$C$8)^(D$29-Indata!$K$29)) -> 0 | E33: =IF(OR(Indata!$K$29="",E$29<Indata!$K$29),0,(Indata!$R$29/Indata!$R$31)*$E$7*(1+Indata!$C$8)^(E$29-Indata!$K$29)) -> 0 | F33: =IF(OR(Indata!$K$29="",F$29<Indata!$K$29),0,(Indata!$R$29/Indata!$R$31)*$E$7*(1+Indata!$C$8)^(F$29-Indata!$K$29)) -> 0 | G33: =IF(OR(Indata!$K$29="",G$29<Indata!$K$29),0,(Indata!$R$29/Indata!$R$31)*$E$7*(1+Indata!$C$8)^(G$29-Indata!$K$29)) -> 0 | H33: =IF(OR(Indata!$K$29="",H$29<Indata!$K$29),0,(Indata!$R$29/Indata!$R$31)*$E$7*(1+Indata!$C$8)^(H$29-Indata!$K$29)) -> 0 | I33: =IF(OR(Indata!$K$29="",I$29<Indata!$K$29),0,(Indata!$R$29/Indata!$R$31)*$E$7*(1+Indata!$C$8)^(I$29-Indata!$K$29)) -> 0 | J33: =IF(OR(Indata!$K$29="",J$29<Indata!$K$29),0,(Indata!$R$29/Indata!$R$31)*$E$7*(1+Indata!$C$8)^(J$29-Indata!$K$29)) -> 0 | K33: =IF(OR(Indata!$K$29="",K$29<Indata!$K$29),0,(Indata!$R$29/Indata!$R$31)*$E$7*(1+Indata!$C$8)^(K$29-Indata!$K$29)) -> 0 | ... M33: =IF(OR(Indata!$K$29="",M$29<Indata!$K$29),0,(Indata!$R$29/Indata!$R$31)*$E$7*(1+Indata!$C$8)^(M$29-Indata!$K$29)) -> 0
B34: =IF(Indata!B30="","",Indata!B30) | D34: =IF(OR(Indata!$K$30="",D$29<Indata!$K$30),0,(Indata!$R$30/Indata!$R$31)*$E$7*(1+Indata!$C$8)^(D$29-Indata!$K$30)) -> 0 | E34: =IF(OR(Indata!$K$30="",E$29<Indata!$K$30),0,(Indata!$R$30/Indata!$R$31)*$E$7*(1+Indata!$C$8)^(E$29-Indata!$K$30)) -> 0 | F34: =IF(OR(Indata!$K$30="",F$29<Indata!$K$30),0,(Indata!$R$30/Indata!$R$31)*$E$7*(1+Indata!$C$8)^(F$29-Indata!$K$30)) -> 0 | G34: =IF(OR(Indata!$K$30="",G$29<Indata!$K$30),0,(Indata!$R$30/Indata!$R$31)*$E$7*(1+Indata!$C$8)^(G$29-Indata!$K$30)) -> 0 | H34: =IF(OR(Indata!$K$30="",H$29<Indata!$K$30),0,(Indata!$R$30/Indata!$R$31)*$E$7*(1+Indata!$C$8)^(H$29-Indata!$K$30)) -> 0 | I34: =IF(OR(Indata!$K$30="",I$29<Indata!$K$30),0,(Indata!$R$30/Indata!$R$31)*$E$7*(1+Indata!$C$8)^(I$29-Indata!$K$30)) -> 0 | J34: =IF(OR(Indata!$K$30="",J$29<Indata!$K$30),0,(Indata!$R$30/Indata!$R$31)*$E$7*(1+Indata!$C$8)^(J$29-Indata!$K$30)) -> 0 | K34: =IF(OR(Indata!$K$30="",K$29<Indata!$K$30),0,(Indata!$R$30/Indata!$R$31)*$E$7*(1+Indata!$C$8)^(K$29-Indata!$K$30)) -> 0 | ... M34: =IF(OR(Indata!$K$30="",M$29<Indata!$K$30),0,(Indata!$R$30/Indata!$R$31)*$E$7*(1+Indata!$C$8)^(M$29-Indata!$K$30)) -> 0
B35: Summa | D35: =SUM(D30:D34) -> 0 | E35: =SUM(E30:E34) -> 0 | F35: =SUM(F30:F34) -> 0 | G35: =SUM(G30:G34) -> 0 | H35: =SUM(H30:H34) -> 0 | I35: =SUM(I30:I34) -> 0 | J35: =SUM(J30:J34) -> 0 | K35: =SUM(K30:K34) -> 0 | ... M35: =SUM(M30:M34) -> 0
B36: Andel av fullt flöde | D36: =IFERROR(D35/MAX($D$35:$M$35),0) -> 0 | E36: =IFERROR(E35/MAX($D$35:$M$35),0) -> 0 | F36: =IFERROR(F35/MAX($D$35:$M$35),0) -> 0 | G36: =IFERROR(G35/MAX($D$35:$M$35),0) -> 0 | H36: =IFERROR(H35/MAX($D$35:$M$35),0) -> 0 | I36: =IFERROR(I35/MAX($D$35:$M$35),0) -> 0 | J36: =IFERROR(J35/MAX($D$35:$M$35),0) -> 0 | K36: =IFERROR(K35/MAX($D$35:$M$35),0) -> 0 | ... M36: =IFERROR(M35/MAX($D$35:$M$35),0) -> 0

Sheet Finansiering
B1: FINANSIERING
B3: Kalenderår | D3: =Indata!$C$5+0 -> 2026 | E3: =Indata!$C$5+1 -> 2027 | F3: =Indata!$C$5+2 -> 2028 | G3: =Indata!$C$5+3 -> 2029 | H3: =Indata!$C$5+4 -> 2030 | I3: =Indata!$C$5+5 -> 2031 | J3: =Indata!$C$5+6 -> 2032 | K3: =Indata!$C$5+7 -> 2033 | L3: =Indata!$C$5+8 -> 2034 | M3: =Indata!$C$5+9 -> 2035 | N3: =Indata!$C$5+10 -> 2036 | O3: =Indata!$C$5+11 -> 2037 | P3: =Indata!$C$5+12 -> 2038 | Q3: =Indata!$C$5+13 -> 2039 | R3: =Indata!$C$5+14 -> 2040 | S3: =Indata!$C$5+15 -> 2041 | T3: =Indata!$C$5+16 -> 2042 | U3: =Indata!$C$5+17 -> 2043 | V3: =Indata!$C$5+18 -> 2044 | W3: =Indata!$C$5+19 -> 2045 | X3: =Indata!$C$5+20 -> 2046 | Y3: =Indata!$C$5+21 -> 2047 | Z3: =Indata!$C$5+22 -> 2048 | AA3: =Indata!$C$5+23 -> 2049 | AB3: =Indata!$C$5+24 -> 2050
B4: År i kalkyl | D4: 1 | E4: 2 | F4: 3 | G4: 4 | H4: 5 | I4: 6 | J4: 7 | K4: 8 | L4: 9 | M4: 10 | N4: 11 | O4: 12 | P4: 13 | Q4: 14 | R4: 15 | S4: 16 | T4: 17 | U4: 18 | V4: 19 | W4: 20 | X4: 21 | Y4: 22 | Z4: 23 | AA4: 24 | AB4: 25
B5: Inom kalkylperiod | D5: =IF(D4<=Indata!$C$16,1,0) -> 1 | E5: =IF(E4<=Indata!$C$16,1,0) -> 1 | F5: =IF(F4<=Indata!$C$16,1,0) -> 1 | G5: =IF(G4<=Indata!$C$16,1,0) -> 1 | H5: =IF(H4<=Indata!$C$16,1,0) -> 1 | I5: =IF(I4<=Indata!$C$16,1,0) -> 1 | J5: =IF(J4<=Indata!$C$16,1,0) -> 1 | K5: =IF(K4<=Indata!$C$16,1,0) -> 1 | ... AB5: =IF(AB4<=Indata!$C$16,1,0) -> 0
B7: LÅN, RÄNTA, AMORTERING, AVSKRIVNING
B8: Lånebild över kalkylperioden enligt finansieringsantagandena på Indata-fliken. Bokföringsmässig vy: avskrivning enligt linjär K3-metod över avskrivningstiden.
B10: Upptaget lån (år) | D10: =SUMIFS(Indata!$R$26:$R$30,Indata!$P$26:$P$30,D3)*Indata!$C$64 -> 74000000 | E10: =SUMIFS(Indata!$R$26:$R$30,Indata!$P$26:$P$30,E3)*Indata!$C$64 -> 0 | F10: =SUMIFS(Indata!$R$26:$R$30,Indata!$P$26:$P$30,F3)*Indata!$C$64 -> 0 | G10: =SUMIFS(Indata!$R$26:$R$30,Indata!$P$26:$P$30,G3)*Indata!$C$64 -> 0 | H10: =SUMIFS(Indata!$R$26:$R$30,Indata!$P$26:$P$30,H3)*Indata!$C$64 -> 0 | I10: =SUMIFS(Indata!$R$26:$R$30,Indata!$P$26:$P$30,I3)*Indata!$C$64 -> 0 | J10: =SUMIFS(Indata!$R$26:$R$30,Indata!$P$26:$P$30,J3)*Indata!$C$64 -> 0 | K10: =SUMIFS(Indata!$R$26:$R$30,Indata!$P$26:$P$30,K3)*Indata!$C$64 -> 0 | ... AB10: =SUMIFS(Indata!$R$26:$R$30,Indata!$P$26:$P$30,AB3)*Indata!$C$64 -> 0
B11: Ack. upptaget lån | D11: =D10 -> 74000000 | E11: =D11+E10 -> 74000000 | F11: =E11+F10 -> 74000000 | G11: =F11+G10 -> 74000000 | H11: =G11+H10 -> 74000000 | I11: =H11+I10 -> 74000000 | J11: =I11+J10 -> 74000000 | K11: =J11+K10 -> 74000000 | L11: =K11+L10 -> 74000000 | ... AB11: =AA11+AB10 -> 74000000
B12: Amortering | D12: =-D11*Indata!$C$63 -> -1480000 | E12: =-D13*Indata!$C$63 -> -1450400 | F12: =-E13*Indata!$C$63 -> -1421392 | G12: =-F13*Indata!$C$63 -> -1392964.2 | H12: =-G13*Indata!$C$63 -> -1365104.9 | I12: =-H13*Indata!$C$63 -> -1337802.8 | J12: =-I13*Indata!$C$63 -> -1311046.7 | K12: =-J13*Indata!$C$63 -> -1284825.8 | L12: =-K13*Indata!$C$63 -> -1259129.3 | ... AB12: =-AA13*Indata!$C$63 -> -911354.9
B13: Återstående skuld | D13: =D11+D12 -> 72520000 | E13: =D13+E10+E12 -> 71069600 | F13: =E13+F10+F12 -> 69648208 | G13: =F13+G10+G12 -> 68255244 | H13: =G13+H10+H12 -> 66890139 | I13: =H13+I10+I12 -> 65552336 | J13: =I13+J10+J12 -> 64241289 | K13: =J13+K10+K12 -> 62956464 | L13: =K13+L10+L12 -> 61697334 | ... AB13: =AA13+AB10+AB12 -> 44656390
B14: Räntenivå | D14: =MIN(Indata!$C$62,Indata!$C$61+(Indata!$C$62-Indata!$C$61)*(D4/10)) -> 0.031 | E14: =MIN(Indata!$C$62,Indata!$C$61+(Indata!$C$62-Indata!$C$61)*(E4/10)) -> 0.032 | F14: =MIN(Indata!$C$62,Indata!$C$61+(Indata!$C$62-Indata!$C$61)*(F4/10)) -> 0.033 | G14: =MIN(Indata!$C$62,Indata!$C$61+(Indata!$C$62-Indata!$C$61)*(G4/10)) -> 0.034 | H14: =MIN(Indata!$C$62,Indata!$C$61+(Indata!$C$62-Indata!$C$61)*(H4/10)) -> 0.035 | I14: =MIN(Indata!$C$62,Indata!$C$61+(Indata!$C$62-Indata!$C$61)*(I4/10)) -> 0.036 | J14: =MIN(Indata!$C$62,Indata!$C$61+(Indata!$C$62-Indata!$C$61)*(J4/10)) -> 0.037 | K14: =MIN(Indata!$C$62,Indata!$C$61+(Indata!$C$62-Indata!$C$61)*(K4/10)) -> 0.038 | ... AB14: =MIN(Indata!$C$62,Indata!$C$61+(Indata!$C$62-Indata!$C$61)*(AB4/10)) -> 0.04
B15: Räntekostnad | D15: =-D13*D14 -> -2248120 | E15: =-E13*E14 -> -2274227.2 | F15: =-F13*F14 -> -2298390.9 | G15: =-G13*G14 -> -2320678.3 | H15: =-H13*H14 -> -2341154.9 | I15: =-I13*I14 -> -2359884.1 | J15: =-J13*J14 -> -2376927.7 | K15: =-K13*K14 -> -2392345.6 | ... AB15: =-AB13*AB14 -> -1786255.6
B17: Eget kapital-insats | D17: =-SUMIFS(Indata!$R$26:$R$30,Indata!$P$26:$P$30,D3)*(1-Indata!$C$64) -> -126000000 | E17: =-SUMIFS(Indata!$R$26:$R$30,Indata!$P$26:$P$30,E3)*(1-Indata!$C$64) -> 0 | F17: =-SUMIFS(Indata!$R$26:$R$30,Indata!$P$26:$P$30,F3)*(1-Indata!$C$64) -> 0 | G17: =-SUMIFS(Indata!$R$26:$R$30,Indata!$P$26:$P$30,G3)*(1-Indata!$C$64) -> 0 | H17: =-SUMIFS(Indata!$R$26:$R$30,Indata!$P$26:$P$30,H3)*(1-Indata!$C$64) -> 0 | I17: =-SUMIFS(Indata!$R$26:$R$30,Indata!$P$26:$P$30,I3)*(1-Indata!$C$64) -> 0 | J17: =-SUMIFS(Indata!$R$26:$R$30,Indata!$P$26:$P$30,J3)*(1-Indata!$C$64) -> 0 | K17: =-SUMIFS(Indata!$R$26:$R$30,Indata!$P$26:$P$30,K3)*(1-Indata!$C$64) -> 0 | ... AB17: =-SUMIFS(Indata!$R$26:$R$30,Indata!$P$26:$P$30,AB3)*(1-Indata!$C$64) -> 0
B18: Avskrivning (per år) | D18: =IF(D5=0,0,-Indata!$C$17/Indata!$C$19) -> -6060606.1 | E18: =IF(E5=0,0,-Indata!$C$17/Indata!$C$19) -> -6060606.1 | F18: =IF(F5=0,0,-Indata!$C$17/Indata!$C$19) -> -6060606.1 | G18: =IF(G5=0,0,-Indata!$C$17/Indata!$C$19) -> -6060606.1 | H18: =IF(H5=0,0,-Indata!$C$17/Indata!$C$19) -> -6060606.1 | I18: =IF(I5=0,0,-Indata!$C$17/Indata!$C$19) -> -6060606.1 | J18: =IF(J5=0,0,-Indata!$C$17/Indata!$C$19) -> -6060606.1 | K18: =IF(K5=0,0,-Indata!$C$17/Indata!$C$19) -> -6060606.1 | ... AB18: =IF(AB5=0,0,-Indata!$C$17/Indata!$C$19) -> 0

Sheet Resultat
B1: RESULTAT
B2: ="Projekt: " & IF(Indata!B26="","(ej angivet)",Indata!B26) & " — " & TEXT(Indata!F31,"#,##0") & " m², investering " & TEXT(Indata!R31,"#,##0") & " kr (" & TEXT(IFERROR(Indata!R31/Indata!F31,0),"#,##0") & " kr/m²)" -> Projekt: Skola — 5,000 m², investering 200,000,000 kr (40,000 kr/m²)
B3: =IF(SUMPRODUCT((Indata!M26:M30<>"")*(Indata!M26:M30<>0))=0,"⚠ Hyra efter avtal ej angiven på något objekt — kalkylen antar att samma kr/m² fortsätter efter avtalsslut (monopolmodell).","ⓘ Hyra efter avtal angiven — påverkar restvärde och kravhyra. Verifiera värdet och vakansprocent.") -> ⚠ Hyra efter avtal ej angiven på något objekt — kalkylen antar att samma kr/m² fortsätter efter avtalsslut (monopolmodell).
B4: KRAVHYRA — PROJEKTETS ÅRSHYRA
B6: Investeringsutfall | C6: Lägsta (−X%) | D6: Mål | E6: Högsta (+X%)
B7: Investering | C7: =Indata!R31*(1-Indata!C68) -> 180000000 | D7: =Indata!R31 -> 200000000 | E7: =Indata!R31*(1+Indata!C68) -> 220000000
B8: Investering per kvm | C8: =IFERROR(C7/Indata!F31,0) -> 36000 | D8: =IFERROR(D7/Indata!F31,0) -> 40000 | E8: =IFERROR(E7/Indata!F31,0) -> 44000
B10: 1. Kravhyra för NPV ≥ 0 | C10: =-(Beräkningslogik!C119-Indata!C68*Beräkningslogik!C118)/Beräkningslogik!C140 -> 10726244 | D10: =-Beräkningslogik!C119/Beräkningslogik!C140 -> 11631222 | E10: =-(Beräkningslogik!C119+Indata!C68*Beräkningslogik!C118)/Beräkningslogik!C140 -> 12536199
B11: 2. Kravhyra för IRR ≥ avkastningskrav | C11: =-(Beräkningslogik!C177+Indata!C68*Indata!R31*(1-Indata!C64))/Beräkningslogik!C193 -> 10507485 | D11: =-Beräkningslogik!C177/Beräkningslogik!C193 -> 11129728 | E11: =-(Beräkningslogik!C177-Indata!C68*Indata!R31*(1-Indata!C64))/Beräkningslogik!C193 -> 11751970
B12: 3. Kravhyra för MV ≥ BV år N | C12: =(Beräkningslogik!C204*(1-Indata!C68)-Beräkningslogik!C202)/Beräkningslogik!C203 -> 5426681 | D12: =(Beräkningslogik!C204-Beräkningslogik!C202)/Beräkningslogik!C203 -> 5729582.1 | E12: =(Beräkningslogik!C204*(1+Indata!C68)-Beräkningslogik!C202)/Beräkningslogik!C203 -> 6032483.3
B14: Bindande kravhyra | C14: =MAX(C10,C11,C12) -> 10726244 | D14: =MAX(D10,D11,D12) -> 11631222 | E14: =MAX(E10,E11,E12) -> 12536199 | F14: kr/år
B15: Bindande krav | C15: =IF(C14=C10,"NPV",IF(C14=C11,"IRR","MV")) -> NPV | D15: =IF(D14=D10,"NPV",IF(D14=D11,"IRR","MV")) -> NPV | E15: =IF(E14=E10,"NPV",IF(E14=E11,"IRR","MV")) -> NPV
B16: Genomsnitt kr/m²/år (totalarea) | C16: =IFERROR(C14/Indata!F31,0) -> 2145.2489 | D16: =IFERROR(D14/Indata!F31,0) -> 2326.2443 | E16: =IFERROR(E14/Indata!F31,0) -> 2507.2398
B18: Förklaring | C18: Bindande kravhyra = den lägsta årshyra som uppfyller alla tre lönsamhetskrav samtidigt. NPV, IRR och framtida marknadsvärde kontrolleras var för sig på fliken Lönsamhetskontroll.
B19: Tolkning | C19: ="Avtalet bör skriva hyresspann " & TEXT(C14,"#,##0") & "–" & TEXT(E14,"#,##0") & " kr/år. Slutlig hyra fastställs vid projektavslut." -> Avtalet bör skriva hyresspann 10,726,244–12,536,199 kr/år. Slutlig hyra fastställs vid projektavslut.
B22: FÖRDELNING PER HUS (VID MÅL-UTFALL)
B24: Objekt | C24: Andel | D24: Årshyra (kr/år) | E24: Hyra kr/m²/år | F24: Tillträde
B25: =IF(Indata!B26="","(ej ifyllt)",Indata!B26) -> Skola | C25: =IFERROR(Indata!R26/Indata!R31,0) -> 1 | D25: =C25*D$14 -> 11631222 | E25: =IFERROR(D25/Indata!F26,0) -> 2326.2443 | F25: =IF(Indata!K26="","",Indata!K26) -> 2026
B26: =IF(Indata!B27="","(ej ifyllt)",Indata!B27) -> (ej ifyllt) | C26: =IFERROR(Indata!R27/Indata!R31,0) -> 0 | D26: =C26*D$14 -> 0 | E26: =IFERROR(D26/Indata!F27,0) -> 0 | F26: =IF(Indata!K27="","",Indata!K27)
B27: =IF(Indata!B28="","(ej ifyllt)",Indata!B28) -> (ej ifyllt) | C27: =IFERROR(Indata!R28/Indata!R31,0) -> 0 | D27: =C27*D$14 -> 0 | E27: =IFERROR(D27/Indata!F28,0) -> 0 | F27: =IF(Indata!K28="","",Indata!K28)
B28: =IF(Indata!B29="","(ej ifyllt)",Indata!B29) -> (ej ifyllt) | C28: =IFERROR(Indata!R29/Indata!R31,0) -> 0 | D28: =C28*D$14 -> 0 | E28: =IFERROR(D28/Indata!F29,0) -> 0 | F28: =IF(Indata!K29="","",Indata!K29)
B29: =IF(Indata!B30="","(ej ifyllt)",Indata!B30) -> (ej ifyllt) | C29: =IFERROR(Indata!R30/Indata!R31,0) -> 0 | D29: =C29*D$14 -> 0 | E29: =IFERROR(D29/Indata!F30,0) -> 0 | F29: =IF(Indata!K30="","",Indata!K30)
B30: Totalt | C30: =SUM(C25:C29) -> 1 | D30: =SUM(D25:D29) -> 11631222

Sheet Lönsamhetskontroll
B1: LÖNSAMHETSKONTROLL
B2: Tre lönsamhetskrav vid mål-utfall och bindande kravhyra. Alla formler härleds direkt från Kassaflöde-fliken.
B4: 1. NPV ≥ 0 (vid kalkylränta driftnetto)
B6: Kalkylränta driftnetto | C6: =Indata!C7 -> 0.04
B7: Kravhyra NPV (mål) | C7: =Resultat!D10 -> 11631222
B8: NPV vid kravhyra NPV | C8: =Beräkningslogik!C119+Beräkningslogik!C140*Resultat!D10 -> 0 | E8: (ska vara ≈ 0)
B9: NPV vid bindande kravhyra | C9: =Beräkningslogik!C119+Beräkningslogik!C140*Resultat!D14 -> 0 | D9: =IF(C9>=0,"✓ Uppfyllt","✗ Ej uppfyllt") -> ✓ Uppfyllt
B12: 2. IRR eget kapital ≥ avkastningskrav
B14: Avkastningskrav eget kapital | C14: =Indata!C65 -> 0.063
B15: Belåningsgrad | C15: =Indata!C64 -> 0.37
B16: Kravhyra IRR (mål) | C16: =Resultat!D11 -> 11129728
B17: NPV EK vid avk.krav, vid kravhyra IRR | C17: =Beräkningslogik!C177+Beräkningslogik!C193*Resultat!D11 -> 0 | E17: (ska vara ≈ 0)
B18: NPV EK vid bindande kravhyra | C18: =Beräkningslogik!C177+Beräkningslogik!C193*Resultat!D14 -> 10154924 | D18: =IF(C18>=0,"✓ Uppfyllt","✗ Ej uppfyllt") -> ✓ Uppfyllt
B21: 3. Marknadsvärde år N ≥ bokfört värde år N
B23: Kalkylperiod (år N) | C23: =Indata!C16 -> 20
B24: Direktavkastning | C24: =Indata!C6 -> 0.05
B25: Byggnadsvärde (dag 1) | C25: =Indata!C17 -> 200000000
B26: Avskrivnings-% | C26: =Indata!C18 -> 0.03
B27: Bokfört värde år N | C27: =Beräkningslogik!C204 -> 80000000 | E27: Formel: (byggnadsv + bef BV + projbel) × (1 - N × avskr%)
B28: Driftnetto år N+1 vid bindande kravhyra | C28: =Beräkningslogik!C199+Beräkningslogik!C201*Resultat!D14 -> 11793486
B29: Marknadsvärde år N (Gordon) | C29: =C28/C24 -> 2.3586973e+08 | E29: Formel: driftnetto år N+1 / direktavkastning
B30: Differens (MV - BV) | C30: =C29-C27 -> 1.5586973e+08 | D30: =IF(C30>=0,"✓ Uppfyllt","✗ Nedskrivningsrisk") -> ✓ Uppfyllt
B42: FAKTISK IRR (vid bindande kravhyra)
B43: EK-cashflow vid bindande kravhyra | F43: =Beräkningslogik!D173+(Beräkningslogik!D188-Beräkningslogik!D173)*Resultat!$D$14/1000000 -> -1.204969e+08 | G43: =Beräkningslogik!E173+(Beräkningslogik!E188-Beräkningslogik!E173)*Resultat!$D$14/1000000 -> 5621431.6 | H43: =Beräkningslogik!F173+(Beräkningslogik!F188-Beräkningslogik!F173)*Resultat!$D$14/1000000 -> 5742432.8 | I43: =Beräkningslogik!G173+(Beräkningslogik!G188-Beräkningslogik!G173)*Resultat!$D$14/1000000 -> 5866062.5 | J43: =Beräkningslogik!H173+(Beräkningslogik!H188-Beräkningslogik!H173)*Resultat!$D$14/1000000 -> 5992279.6 | K43: =Beräkningslogik!I173+(Beräkningslogik!I188-Beräkningslogik!I173)*Resultat!$D$14/1000000 -> 6121045 | L43: =Beräkningslogik!J173+(Beräkningslogik!J188-Beräkningslogik!J173)*Resultat!$D$14/1000000 -> 6252321 | M43: =Beräkningslogik!K173+(Beräkningslogik!K188-Beräkningslogik!K173)*Resultat!$D$14/1000000 -> 6386071.4 | ... AD43: =Beräkningslogik!AB173+(Beräkningslogik!AB188-Beräkningslogik!AB173)*Resultat!$D$14/1000000 -> 9680279.1
B45: Faktisk IRR EK | C45: =IFERROR(IRR(F43:AD43),"Ej beräkningsbar") -> 0.076451715 | D45: =IF(ISNUMBER(C45),IF(C45>=C46,"✓ Uppfyllt","✗ Ej uppfyllt"),"") -> ✓ Uppfyllt
B46: Avkastningskrav | C46: =Indata!C65 -> 0.063
B47: Marginal mot krav | C47: =IFERROR(C45-C46,"") -> 0.013451715
B50: KÄNSLIGHETSANALYS — MARKNADSVÄRDE VID EXIT
B51: Hur sårbart är projektet om marknadsvärdet vid år N visar sig avvika från bedömningen? Bas-bedömningen är driftnetto år N+1 / direktavkastning.
B53: Scenario | C53: Marknadsvärde | D53: Diff mot BV | E53: IRR EK | F53: Status
B54: −40 % | C54: =$C$29*(1+-0.4) -> 1.4152184e+08 | D54: =C54-$C$27 -> 61521837 | E54: =IFERROR(IRR(F64:AD64),"") -> 0.063801866 | F54: =IF(ISNUMBER(E54),IF(E54>=Indata!$C$65,"✓","⚠ IRR<krav"),"") -> ✓
B55: −30 % | C55: =$C$29*(1+-0.3) -> 1.6510881e+08 | D55: =C55-$C$27 -> 85108810 | E55: =IFERROR(IRR(F65:AD65),"") -> 0.067427322 | F55: =IF(ISNUMBER(E55),IF(E55>=Indata!$C$65,"✓","⚠ IRR<krav"),"") -> ✓
B56: −20 % | C56: =$C$29*(1+-0.2) -> 1.8869578e+08 | D56: =C56-$C$27 -> 1.0869578e+08 | E56: =IFERROR(IRR(F66:AD66),"") -> 0.070702272 | F56: =IF(ISNUMBER(E56),IF(E56>=Indata!$C$65,"✓","⚠ IRR<krav"),"") -> ✓
B57: −10 % | C57: =$C$29*(1+-0.1) -> 2.1228276e+08 | D57: =C57-$C$27 -> 1.3228276e+08 | E57: =IFERROR(IRR(F67:AD67),"") -> 0.073694067 | F57: =IF(ISNUMBER(E57),IF(E57>=Indata!$C$65,"✓","⚠ IRR<krav"),"") -> ✓
B58: Bas | C58: =$C$29*(1+0) -> 2.3586973e+08 | D58: =C58-$C$27 -> 1.5586973e+08 | E58: =IFERROR(IRR(F68:AD68),"") -> 0.076451715 | F58: =IF(ISNUMBER(E58),IF(E58>=Indata!$C$65,"✓","⚠ IRR<krav"),"") -> ✓
B59: +10 % | C59: =$C$29*(1+0.1) -> 2.594567e+08 | D59: =C59-$C$27 -> 1.794567e+08 | E59: =IFERROR(IRR(F69:AD69),"") -> 0.079012102 | F59: =IF(ISNUMBER(E59),IF(E59>=Indata!$C$65,"✓","⚠ IRR<krav"),"") -> ✓
B60: +20 % | C60: =$C$29*(1+0.2) -> 2.8304367e+08 | D60: =C60-$C$27 -> 2.0304367e+08 | E60: =IFERROR(IRR(F70:AD70),"") -> 0.081403754 | F60: =IF(ISNUMBER(E60),IF(E60>=Indata!$C$65,"✓","⚠ IRR<krav"),"") -> ✓
F64: =F43 -> -1.204969e+08 | G64: =G43 -> 5621431.6 | H64: =H43 -> 5742432.8 | I64: =I43 -> 5866062.5 | J64: =J43 -> 5992279.6 | K64: =K43 -> 6121045 | L64: =L43 -> 6252321 | M64: =M43 -> 6386071.4 | ... AC64: =AC43 -> 9476721.8 | AD64: =AD43+$C54-$C$58 -> -84667612
F65: =F43 -> -1.204969e+08 | G65: =G43 -> 5621431.6 | H65: =H43 -> 5742432.8 | I65: =I43 -> 5866062.5 | J65: =J43 -> 5992279.6 | K65: =K43 -> 6121045 | L65: =L43 -> 6252321 | M65: =M43 -> 6386071.4 | ... AC65: =AC43 -> 9476721.8 | AD65: =AD43+$C55-$C$58 -> -61080639
F66: =F43 -> -1.204969e+08 | G66: =G43 -> 5621431.6 | H66: =H43 -> 5742432.8 | I66: =I43 -> 5866062.5 | J66: =J43 -> 5992279.6 | K66: =K43 -> 6121045 | L66: =L43 -> 6252321 | M66: =M43 -> 6386071.4 | ... AC66: =AC43 -> 9476721.8 | AD66: =AD43+$C56-$C$58 -> -37493667
F67: =F43 -> -1.204969e+08 | G67: =G43 -> 5621431.6 | H67: =H43 -> 5742432.8 | I67: =I43 -> 5866062.5 | J67: =J43 -> 5992279.6 | K67: =K43 -> 6121045 | L67: =L43 -> 6252321 | M67: =M43 -> 6386071.4 | ... AC67: =AC43 -> 9476721.8 | AD67: =AD43+$C57-$C$58 -> -13906694
F68: =F43 -> -1.204969e+08 | G68: =G43 -> 5621431.6 | H68: =H43 -> 5742432.8 | I68: =I43 -> 5866062.5 | J68: =J43 -> 5992279.6 | K68: =K43 -> 6121045 | L68: =L43 -> 6252321 | M68: =M43 -> 6386071.4 | ... AC68: =AC43 -> 9476721.8 | AD68: =AD43+$C58-$C$58 -> 9680279.1
F69: =F43 -> -1.204969e+08 | G69: =G43 -> 5621431.6 | H69: =H43 -> 5742432.8 | I69: =I43 -> 5866062.5 | J69: =J43 -> 5992279.6 | K69: =K43 -> 6121045 | L69: =L43 -> 6252321 | M69: =M43 -> 6386071.4 | ... AC69: =AC43 -> 9476721.8 | AD69: =AD43+$C59-$C$58 -> 33267252
F70: =F43 -> -1.204969e+08 | G70: =G43 -> 5621431.6 | H70: =H43 -> 5742432.8 | I70: =I43 -> 5866062.5 | J70: =J43 -> 5992279.6 | K70: =K43 -> 6121045 | L70: =L43 -> 6252321 | M70: =M43 -> 6386071.4 | ... AC70: =AC43 -> 9476721.8 | AD70: =AD43+$C60-$C$58 -> 56854225

Sheet Beräkningslogik
B1: BERÄKNINGSLOGIK — så fungerar mallens kärnberäkning
B3: Mallen löser kravhyran analytiskt utan iteration. Det är möjligt eftersom NPV är linjär i hyran — om hyran ökar med X kronor ändras NPV med X gånger en konstant. Genom att räkna NPV vid två hyresnivåer (0 och 1 Mkr/år) kan konstanten härledas och sedan används den för att lösa NPV = 0.
B6: STEG 1 — Två referenspunkter
B7: NPV vid årshyra = 0 kr | C7: =Beräkningslogik!C119 -> -257050000 | D7: (Kassaflöde C70)
B8: NPV vid årshyra = 1 000 000 kr | C8: =Beräkningslogik!C139 -> -234950000 | D8: (Kassaflöde C90)
B10: STEG 2 — Beräkna känsligheten
B11: Skillnad i NPV | C11: =C8-C7 -> 22100000 | D11: (per 1 Mkr hyra)
B12: Känslighet b (per kr hyra) | C12: =C11/1000000 -> 22.1 | D12: (Kassaflöde C91)
B14: STEG 3 — Lös ekvationen NPV(hyra) = 0
B15: Modell: NPV = NPV_0 + b × hyra
B16: Sätter NPV = 0 → hyra = −NPV_0 / b
B18: Kravhyra NPV (mål) | C18: =-C7/C12 -> 11631222 | D18: =-npv_0 / b -> #NAME?
B20: Kontroll mot Resultat | C20: =Resultat!D10 -> 11631222 | D20: (ska vara samma som C18)
B23: SAMMA PRINCIP FÖR ALLA TRE LÖNSAMHETSKRAVEN
B25: Krav | C25: Beräknad kravhyra | D25: Block i Kassaflöde
B26: 1. NPV ≥ 0 | C26: =Resultat!D10 -> 11631222 | D26: Block A (rad 10–70) + Block B (rad 72–91)
B27: 2. IRR EK ≥ avkastningskrav | C27: =Resultat!D11 -> 11129728 | D27: Block C (rad 100–110) + D (rad 115–128) + E (rad 130–144)
B28: 3. MV ≥ BV år N | C28: =Resultat!D12 -> 5729582.1 | D28: Block F (rad 148–156)
B30: Bindande kravhyra | C30: =MAX(C26,C27,C28) -> 11631222 | D30: =max av de tre -> #VALUE!
B33: VARFÖR METODEN ÄR EKVIVALENT MED ITERATIV MÅLSÖKNING
B35: Iterativ målsökning (Excel Goal Seek) startar med en gissning, räknar NPV, justerar gissningen, räknar igen, och fortsätter tills NPV är tillräckligt nära noll. Det är långsamt och fungerar inte automatiskt vid scenarier.
B37: Den linjära metoden använder samma underliggande matematik men löser ekvationen i ett enda steg. Eftersom NPV(hyra) = NPV_0 + b × hyra är en rät linje räcker det med två punkter för att hitta var den korsar noll. Resultatet är exakt — inte en approximation.
B40: Fördelar:
B41: • En enda omberäkning räcker — ingen iteration
B42: • Tre scenarier (låg/mål/hög) räknas automatiskt
B43: • Tre lönsamhetskrav räknas parallellt med samma metod
B44: • Resultaten är exakta, inte avrundade approximationer
B46: TEKNISKA BERÄKNINGSBLOCK — räknemekanik bakom kravhyran
B47: Här ligger de delberäkningar mallen använder för att lösa kravhyran. De är inte projektets riktiga kassaflöde — det visas på Kassaflöde-fliken.
B52: Kalenderår | D52: =Indata!$C$5+0 -> 2026 | E52: =Indata!$C$5+1 -> 2027 | F52: =Indata!$C$5+2 -> 2028 | G52: =Indata!$C$5+3 -> 2029 | H52: =Indata!$C$5+4 -> 2030 | I52: =Indata!$C$5+5 -> 2031 | J52: =Indata!$C$5+6 -> 2032 | K52: =Indata!$C$5+7 -> 2033 | L52: =Indata!$C$5+8 -> 2034 | M52: =Indata!$C$5+9 -> 2035 | N52: =Indata!$C$5+10 -> 2036 | O52: =Indata!$C$5+11 -> 2037 | P52: =Indata!$C$5+12 -> 2038 | Q52: =Indata!$C$5+13 -> 2039 | R52: =Indata!$C$5+14 -> 2040 | S52: =Indata!$C$5+15 -> 2041 | T52: =Indata!$C$5+16 -> 2042 | U52: =Indata!$C$5+17 -> 2043 | V52: =Indata!$C$5+18 -> 2044 | W52: =Indata!$C$5+19 -> 2045 | X52: =Indata!$C$5+20 -> 2046 | Y52: =Indata!$C$5+21 -> 2047 | Z52: =Indata!$C$5+22 -> 2048 | AA52: =Indata!$C$5+23 -> 2049 | AB52: =Indata!$C$5+24 -> 2050
B53: År i kalkyl | D53: 1 | E53: 2 | F53: 3 | G53: 4 | H53: 5 | I53: 6 | J53: 7 | K53: 8 | L53: 9 | M53: 10 | N53: 11 | O53: 12 | P53: 13 | Q53: 14 | R53: 15 | S53: 16 | T53: 17 | U53: 18 | V53: 19 | W53: 20 | X53: 21 | Y53: 22 | Z53: 23 | AA53: 24 | AB53: 25
B54: Inom kalkylperiod | D54: =IF(D53<=Indata!$C$16,1,0) -> 1 | E54: =IF(E53<=Indata!$C$16,1,0) -> 1 | F54: =IF(F53<=Indata!$C$16,1,0) -> 1 | G54: =IF(G53<=Indata!$C$16,1,0) -> 1 | H54: =IF(H53<=Indata!$C$16,1,0) -> 1 | I54: =IF(I53<=Indata!$C$16,1,0) -> 1 | J54: =IF(J53<=Indata!$C$16,1,0) -> 1 | K54: =IF(K53<=Indata!$C$16,1,0) -> 1 | ... AB54: =IF(AB53<=Indata!$C$16,1,0) -> 0
B55: Area Nyb (aktiv) | D55: =SUMIFS(Indata!$E$26:$E$79,Indata!$C$26:$C$79,"Nyb",Indata!$P$26:$P$79,"<="&D52)+SUMIFS(Indata!$E$26:$E$79,Indata!$C$26:$C$79,"Omb",Indata!$P$26:$P$79,"<="&D52)+SUMIFS(Indata!$E$26:$E$79,Indata!$C$26:$C$79,"Ins",Indata!$P$26:$P$79,"<="&D52) -> 5000 | E55: =SUMIFS(Indata!$E$26:$E$79,Indata!$C$26:$C$79,"Nyb",Indata!$P$26:$P$79,"<="&E52)+SUMIFS(Indata!$E$26:$E$79,Indata!$C$26:$C$79,"Omb",Indata!$P$26:$P$79,"<="&E52)+SUMIFS(Indata!$E$26:$E$79,Indata!$C$26:$C$79,"Ins",Indata!$P$26:$P$79,"<="&E52) -> 5000 | F55: =SUMIFS(Indata!$E$26:$E$79,Indata!$C$26:$C$79,"Nyb",Indata!$P$26:$P$79,"<="&F52)+SUMIFS(Indata!$E$26:$E$79,Indata!$C$26:$C$79,"Omb",Indata!$P$26:$P$79,"<="&F52)+SUMIFS(Indata!$E$26:$E$79,Indata!$C$26:$C$79,"Ins",Indata!$P$26:$P$79,"<="&F52) -> 5000 | G55: =SUMIFS(Indata!$E$26:$E$79,Indata!$C$26:$C$79,"Nyb",Indata!$P$26:$P$79,"<="&G52)+SUMIFS(Indata!$E$26:$E$79,Indata!$C$26:$C$79,"Omb",Indata!$P$26:$P$79,"<="&G52)+SUMIFS(Indata!$E$26:$E$79,Indata!$C$26:$C$79,"Ins",Indata!$P$26:$P$79,"<="&G52) -> 5000 | H55: =SUMIFS(Indata!$E$26:$E$79,Indata!$C$26:$C$79,"Nyb",Indata!$P$26:$P$79,"<="&H52)+SUMIFS(Indata!$E$26:$E$79,Indata!$C$26:$C$79,"Omb",Indata!$P$26:$P$79,"<="&H52)+SUMIFS(Indata!$E$26:$E$79,Indata!$C$26:$C$79,"Ins",Indata!$P$26:$P$79,"<="&H52) -> 5000 | I55: =SUMIFS(Indata!$E$26:$E$79,Indata!$C$26:$C$79,"Nyb",Indata!$P$26:$P$79,"<="&I52)+SUMIFS(Indata!$E$26:$E$79,Indata!$C$26:$C$79,"Omb",Indata!$P$26:$P$79,"<="&I52)+SUMIFS(Indata!$E$26:$E$79,Indata!$C$26:$C$79,"Ins",Indata!$P$26:$P$79,"<="&I52) -> 5000 | J55: =SUMIFS(Indata!$E$26:$E$79,Indata!$C$26:$C$79,"Nyb",Indata!$P$26:$P$79,"<="&J52)+SUMIFS(Indata!$E$26:$E$79,Indata!$C$26:$C$79,"Omb",Indata!$P$26:$P$79,"<="&J52)+SUMIFS(Indata!$E$26:$E$79,Indata!$C$26:$C$79,"Ins",Indata!$P$26:$P$79,"<="&J52) -> 5000 | K55: =SUMIFS(Indata!$E$26:$E$79,Indata!$C$26:$C$79,"Nyb",Indata!$P$26:$P$79,"<="&K52)+SUMIFS(Indata!$E$26:$E$79,Indata!$C$26:$C$79,"Omb",Indata!$P$26:$P$79,"<="&K52)+SUMIFS(Indata!$E$26:$E$79,Indata!$C$26:$C$79,"Ins",Indata!$P$26:$P$79,"<="&K52) -> 5000 | ... AB55: =SUMIFS(Indata!$E$26:$E$79,Indata!$C$26:$C$79,"Nyb",Indata!$P$26:$P$79,"<="&AB52)+SUMIFS(Indata!$E$26:$E$79,Indata!$C$26:$C$79,"Omb",Indata!$P$26:$P$79,"<="&AB52)+SUMIFS(Indata!$E$26:$E$79,Indata!$C$26:$C$79,"Ins",Indata!$P$26:$P$79,"<="&AB52) -> 5000
B56: Area Bef (aktiv) | D56: =SUMIFS(Indata!$D$26:$D$79,Indata!$C$26:$C$79,"Bef",Indata!$P$26:$P$79,"<="&D52)+SUMIFS(Indata!$D$26:$D$79,Indata!$C$26:$C$79,"Omb",Indata!$P$26:$P$79,"<="&D52)+SUMIFS(Indata!$D$26:$D$79,Indata!$C$26:$C$79,"Nyb",Indata!$P$26:$P$79,"<="&D52)+SUMIFS(Indata!$D$26:$D$79,Indata!$C$26:$C$79,"Ins",Indata!$P$26:$P$79,"<="&D52) -> 0 | E56: =SUMIFS(Indata!$D$26:$D$79,Indata!$C$26:$C$79,"Bef",Indata!$P$26:$P$79,"<="&E52)+SUMIFS(Indata!$D$26:$D$79,Indata!$C$26:$C$79,"Omb",Indata!$P$26:$P$79,"<="&E52)+SUMIFS(Indata!$D$26:$D$79,Indata!$C$26:$C$79,"Nyb",Indata!$P$26:$P$79,"<="&E52)+SUMIFS(Indata!$D$26:$D$79,Indata!$C$26:$C$79,"Ins",Indata!$P$26:$P$79,"<="&E52) -> 0 | F56: =SUMIFS(Indata!$D$26:$D$79,Indata!$C$26:$C$79,"Bef",Indata!$P$26:$P$79,"<="&F52)+SUMIFS(Indata!$D$26:$D$79,Indata!$C$26:$C$79,"Omb",Indata!$P$26:$P$79,"<="&F52)+SUMIFS(Indata!$D$26:$D$79,Indata!$C$26:$C$79,"Nyb",Indata!$P$26:$P$79,"<="&F52)+SUMIFS(Indata!$D$26:$D$79,Indata!$C$26:$C$79,"Ins",Indata!$P$26:$P$79,"<="&F52) -> 0 | G56: =SUMIFS(Indata!$D$26:$D$79,Indata!$C$26:$C$79,"Bef",Indata!$P$26:$P$79,"<="&G52)+SUMIFS(Indata!$D$26:$D$79,Indata!$C$26:$C$79,"Omb",Indata!$P$26:$P$79,"<="&G52)+SUMIFS(Indata!$D$26:$D$79,Indata!$C$26:$C$79,"Nyb",Indata!$P$26:$P$79,"<="&G52)+SUMIFS(Indata!$D$26:$D$79,Indata!$C$26:$C$79,"Ins",Indata!$P$26:$P$79,"<="&G52) -> 0 | H56: =SUMIFS(Indata!$D$26:$D$79,Indata!$C$26:$C$79,"Bef",Indata!$P$26:$P$79,"<="&H52)+SUMIFS(Indata!$D$26:$D$79,Indata!$C$26:$C$79,"Omb",Indata!$P$26:$P$79,"<="&H52)+SUMIFS(Indata!$D$26:$D$79,Indata!$C$26:$C$79,"Nyb",Indata!$P$26:$P$79,"<="&H52)+SUMIFS(Indata!$D$26:$D$79,Indata!$C$26:$C$79,"Ins",Indata!$P$26:$P$79,"<="&H52) -> 0 | I56: =SUMIFS(Indata!$D$26:$D$79,Indata!$C$26:$C$79,"Bef",Indata!$P$26:$P$79,"<="&I52)+SUMIFS(Indata!$D$26:$D$79,Indata!$C$26:$C$79,"Omb",Indata!$P$26:$P$79,"<="&I52)+SUMIFS(Indata!$D$26:$D$79,Indata!$C$26:$C$79,"Nyb",Indata!$P$26:$P$79,"<="&I52)+SUMIFS(Indata!$D$26:$D$79,Indata!$C$26:$C$79,"Ins",Indata!$P$26:$P$79,"<="&I52) -> 0 | J56: =SUMIFS(Indata!$D$26:$D$79,Indata!$C$26:$C$79,"Bef",Indata!$P$26:$P$79,"<="&J52)+SUMIFS(Indata!$D$26:$D$79,Indata!$C$26:$C$79,"Omb",Indata!$P$26:$P$79,"<="&J52)+SUMIFS(Indata!$D$26:$D$79,Indata!$C$26:$C$79,"Nyb",Indata!$P$26:$P$79,"<="&J52)+SUMIFS(Indata!$D$26:$D$79,Indata!$C$26:$C$79,"Ins",Indata!$P$26:$P$79,"<="&J52) -> 0 | K56: =SUMIFS(Indata!$D$26:$D$79,Indata!$C$26:$C$79,"Bef",Indata!$P$26:$P$79,"<="&K52)+SUMIFS(Indata!$D$26:$D$79,Indata!$C$26:$C$79,"Omb",Indata!$P$26:$P$79,"<="&K52)+SUMIFS(Indata!$D$26:$D$79,Indata!$C$26:$C$79,"Nyb",Indata!$P$26:$P$79,"<="&K52)+SUMIFS(Indata!$D$26:$D$79,Indata!$C$26:$C$79,"Ins",Indata!$P$26:$P$79,"<="&K52) -> 0 | ... AB56: =SUMIFS(Indata!$D$26:$D$79,Indata!$C$26:$C$79,"Bef",Indata!$P$26:$P$79,"<="&AB52)+SUMIFS(Indata!$D$26:$D$79,Indata!$C$26:$C$79,"Omb",Indata!$P$26:$P$79,"<="&AB52)+SUMIFS(Indata!$D$26:$D$79,Indata!$C$26:$C$79,"Nyb",Indata!$P$26:$P$79,"<="&AB52)+SUMIFS(Indata!$D$26:$D$79,Indata!$C$26:$C$79,"Ins",Indata!$P$26:$P$79,"<="&AB52) -> 0
B57: Total area | D57: =D55+D56 -> 5000 | E57: =E55+E56 -> 5000 | F57: =F55+F56 -> 5000 | G57: =G55+G56 -> 5000 | H57: =H55+H56 -> 5000 | I57: =I55+I56 -> 5000 | J57: =J55+J56 -> 5000 | K57: =K55+K56 -> 5000 | ... AB57: =AB55+AB56 -> 5000
B59: BLOCK A — Bas-kassaflöde vid årshyra = 0
B60: Intäkt objekt 1 (vid 0 hyra) | D60: =IF(Indata!$K$26="",0,IF(D52<=Indata!$L$26,0,IF(OR(Indata!$M$26="",Indata!$M$26=0),0,Indata!$M$26*Indata!$F$26*(1+Indata!$C$8*Indata!$H$26)^(D52-Indata!$K$26)))) -> 0 | E60: =IF(Indata!$K$26="",0,IF(E52<=Indata!$L$26,0,IF(OR(Indata!$M$26="",Indata!$M$26=0),0,Indata!$M$26*Indata!$F$26*(1+Indata!$C$8*Indata!$H$26)^(E52-Indata!$K$26)))) -> 0 | F60: =IF(Indata!$K$26="",0,IF(F52<=Indata!$L$26,0,IF(OR(Indata!$M$26="",Indata!$M$26=0),0,Indata!$M$26*Indata!$F$26*(1+Indata!$C$8*Indata!$H$26)^(F52-Indata!$K$26)))) -> 0 | G60: =IF(Indata!$K$26="",0,IF(G52<=Indata!$L$26,0,IF(OR(Indata!$M$26="",Indata!$M$26=0),0,Indata!$M$26*Indata!$F$26*(1+Indata!$C$8*Indata!$H$26)^(G52-Indata!$K$26)))) -> 0 | H60: =IF(Indata!$K$26="",0,IF(H52<=Indata!$L$26,0,IF(OR(Indata!$M$26="",Indata!$M$26=0),0,Indata!$M$26*Indata!$F$26*(1+Indata!$C$8*Indata!$H$26)^(H52-Indata!$K$26)))) -> 0 | I60: =IF(Indata!$K$26="",0,IF(I52<=Indata!$L$26,0,IF(OR(Indata!$M$26="",Indata!$M$26=0),0,Indata!$M$26*Indata!$F$26*(1+Indata!$C$8*Indata!$H$26)^(I52-Indata!$K$26)))) -> 0 | J60: =IF(Indata!$K$26="",0,IF(J52<=Indata!$L$26,0,IF(OR(Indata!$M$26="",Indata!$M$26=0),0,Indata!$M$26*Indata!$F$26*(1+Indata!$C$8*Indata!$H$26)^(J52-Indata!$K$26)))) -> 0 | K60: =IF(Indata!$K$26="",0,IF(K52<=Indata!$L$26,0,IF(OR(Indata!$M$26="",Indata!$M$26=0),0,Indata!$M$26*Indata!$F$26*(1+Indata!$C$8*Indata!$H$26)^(K52-Indata!$K$26)))) -> 0 | ... AB60: =IF(Indata!$K$26="",0,IF(AB52<=Indata!$L$26,0,IF(OR(Indata!$M$26="",Indata!$M$26=0),0,Indata!$M$26*Indata!$F$26*(1+Indata!$C$8*Indata!$H$26)^(AB52-Indata!$K$26)))) -> 0
B61: Intäkt objekt 2 (vid 0 hyra) | D61: =IF(Indata!$K$27="",0,IF(D52<=Indata!$L$27,0,IF(OR(Indata!$M$27="",Indata!$M$27=0),0,Indata!$M$27*Indata!$F$27*(1+Indata!$C$8*Indata!$H$27)^(D52-Indata!$K$27)))) -> 0 | E61: =IF(Indata!$K$27="",0,IF(E52<=Indata!$L$27,0,IF(OR(Indata!$M$27="",Indata!$M$27=0),0,Indata!$M$27*Indata!$F$27*(1+Indata!$C$8*Indata!$H$27)^(E52-Indata!$K$27)))) -> 0 | F61: =IF(Indata!$K$27="",0,IF(F52<=Indata!$L$27,0,IF(OR(Indata!$M$27="",Indata!$M$27=0),0,Indata!$M$27*Indata!$F$27*(1+Indata!$C$8*Indata!$H$27)^(F52-Indata!$K$27)))) -> 0 | G61: =IF(Indata!$K$27="",0,IF(G52<=Indata!$L$27,0,IF(OR(Indata!$M$27="",Indata!$M$27=0),0,Indata!$M$27*Indata!$F$27*(1+Indata!$C$8*Indata!$H$27)^(G52-Indata!$K$27)))) -> 0 | H61: =IF(Indata!$K$27="",0,IF(H52<=Indata!$L$27,0,IF(OR(Indata!$M$27="",Indata!$M$27=0),0,Indata!$M$27*Indata!$F$27*(1+Indata!$C$8*Indata!$H$27)^(H52-Indata!$K$27)))) -> 0 | I61: =IF(Indata!$K$27="",0,IF(I52<=Indata!$L$27,0,IF(OR(Indata!$M$27="",Indata!$M$27=0),0,Indata!$M$27*Indata!$F$27*(1+Indata!$C$8*Indata!$H$27)^(I52-Indata!$K$27)))) -> 0 | J61: =IF(Indata!$K$27="",0,IF(J52<=Indata!$L$27,0,IF(OR(Indata!$M$27="",Indata!$M$27=0),0,Indata!$M$27*Indata!$F$27*(1+Indata!$C$8*Indata!$H$27)^(J52-Indata!$K$27)))) -> 0 | K61: =IF(Indata!$K$27="",0,IF(K52<=Indata!$L$27,0,IF(OR(Indata!$M$27="",Indata!$M$27=0),0,Indata!$M$27*Indata!$F$27*(1+Indata!$C$8*Indata!$H$27)^(K52-Indata!$K$27)))) -> 0 | ... AB61: =IF(Indata!$K$27="",0,IF(AB52<=Indata!$L$27,0,IF(OR(Indata!$M$27="",Indata!$M$27=0),0,Indata!$M$27*Indata!$F$27*(1+Indata!$C$8*Indata!$H$27)^(AB52-Indata!$K$27)))) -> 0
B62: Intäkt objekt 3 (vid 0 hyra) | D62: =IF(Indata!$K$28="",0,IF(D52<=Indata!$L$28,0,IF(OR(Indata!$M$28="",Indata!$M$28=0),0,Indata!$M$28*Indata!$F$28*(1+Indata!$C$8*Indata!$H$28)^(D52-Indata!$K$28)))) -> 0 | E62: =IF(Indata!$K$28="",0,IF(E52<=Indata!$L$28,0,IF(OR(Indata!$M$28="",Indata!$M$28=0),0,Indata!$M$28*Indata!$F$28*(1+Indata!$C$8*Indata!$H$28)^(E52-Indata!$K$28)))) -> 0 | F62: =IF(Indata!$K$28="",0,IF(F52<=Indata!$L$28,0,IF(OR(Indata!$M$28="",Indata!$M$28=0),0,Indata!$M$28*Indata!$F$28*(1+Indata!$C$8*Indata!$H$28)^(F52-Indata!$K$28)))) -> 0 | G62: =IF(Indata!$K$28="",0,IF(G52<=Indata!$L$28,0,IF(OR(Indata!$M$28="",Indata!$M$28=0),0,Indata!$M$28*Indata!$F$28*(1+Indata!$C$8*Indata!$H$28)^(G52-Indata!$K$28)))) -> 0 | H62: =IF(Indata!$K$28="",0,IF(H52<=Indata!$L$28,0,IF(OR(Indata!$M$28="",Indata!$M$28=0),0,Indata!$M$28*Indata!$F$28*(1+Indata!$C$8*Indata!$H$28)^(H52-Indata!$K$28)))) -> 0 | I62: =IF(Indata!$K$28="",0,IF(I52<=Indata!$L$28,0,IF(OR(Indata!$M$28="",Indata!$M$28=0),0,Indata!$M$28*Indata!$F$28*(1+Indata!$C$8*Indata!$H$28)^(I52-Indata!$K$28)))) -> 0 | J62: =IF(Indata!$K$28="",0,IF(J52<=Indata!$L$28,0,IF(OR(Indata!$M$28="",Indata!$M$28=0),0,Indata!$M$28*Indata!$F$28*(1+Indata!$C$8*Indata!$H$28)^(J52-Indata!$K$28)))) -> 0 | K62: =IF(Indata!$K$28="",0,IF(K52<=Indata!$L$28,0,IF(OR(Indata!$M$28="",Indata!$M$28=0),0,Indata!$M$28*Indata!$F$28*(1+Indata!$C$8*Indata!$H$28)^(K52-Indata!$K$28)))) -> 0 | ... AB62: =IF(Indata!$K$28="",0,IF(AB52<=Indata!$L$28,0,IF(OR(Indata!$M$28="",Indata!$M$28=0),0,Indata!$M$28*Indata!$F$28*(1+Indata!$C$8*Indata!$H$28)^(AB52-Indata!$K$28)))) -> 0
B63: Intäkt objekt 4 (vid 0 hyra) | D63: =IF(Indata!$K$29="",0,IF(D52<=Indata!$L$29,0,IF(OR(Indata!$M$29="",Indata!$M$29=0),0,Indata!$M$29*Indata!$F$29*(1+Indata!$C$8*Indata!$H$29)^(D52-Indata!$K$29)))) -> 0 | E63: =IF(Indata!$K$29="",0,IF(E52<=Indata!$L$29,0,IF(OR(Indata!$M$29="",Indata!$M$29=0),0,Indata!$M$29*Indata!$F$29*(1+Indata!$C$8*Indata!$H$29)^(E52-Indata!$K$29)))) -> 0 | F63: =IF(Indata!$K$29="",0,IF(F52<=Indata!$L$29,0,IF(OR(Indata!$M$29="",Indata!$M$29=0),0,Indata!$M$29*Indata!$F$29*(1+Indata!$C$8*Indata!$H$29)^(F52-Indata!$K$29)))) -> 0 | G63: =IF(Indata!$K$29="",0,IF(G52<=Indata!$L$29,0,IF(OR(Indata!$M$29="",Indata!$M$29=0),0,Indata!$M$29*Indata!$F$29*(1+Indata!$C$8*Indata!$H$29)^(G52-Indata!$K$29)))) -> 0 | H63: =IF(Indata!$K$29="",0,IF(H52<=Indata!$L$29,0,IF(OR(Indata!$M$29="",Indata!$M$29=0),0,Indata!$M$29*Indata!$F$29*(1+Indata!$C$8*Indata!$H$29)^(H52-Indata!$K$29)))) -> 0 | I63: =IF(Indata!$K$29="",0,IF(I52<=Indata!$L$29,0,IF(OR(Indata!$M$29="",Indata!$M$29=0),0,Indata!$M$29*Indata!$F$29*(1+Indata!$C$8*Indata!$H$29)^(I52-Indata!$K$29)))) -> 0 | J63: =IF(Indata!$K$29="",0,IF(J52<=Indata!$L$29,0,IF(OR(Indata!$M$29="",Indata!$M$29=0),0,Indata!$M$29*Indata!$F$29*(1+Indata!$C$8*Indata!$H$29)^(J52-Indata!$K$29)))) -> 0 | K63: =IF(Indata!$K$29="",0,IF(K52<=Indata!$L$29,0,IF(OR(Indata!$M$29="",Indata!$M$29=0),0,Indata!$M$29*Indata!$F$29*(1+Indata!$C$8*Indata!$H$29)^(K52-Indata!$K$29)))) -> 0 | ... AB63: =IF(Indata!$K$29="",0,IF(AB52<=Indata!$L$29,0,IF(OR(Indata!$M$29="",Indata!$M$29=0),0,Indata!$M$29*Indata!$F$29*(1+Indata!$C$8*Indata!$H$29)^(AB52-Indata!$K$29)))) -> 0
B64: Intäkt objekt 5 (vid 0 hyra) | D64: =IF(Indata!$K$30="",0,IF(D52<=Indata!$L$30,0,IF(OR(Indata!$M$30="",Indata!$M$30=0),0,Indata!$M$30*Indata!$F$30*(1+Indata!$C$8*Indata!$H$30)^(D52-Indata!$K$30)))) -> 0 | E64: =IF(Indata!$K$30="",0,IF(E52<=Indata!$L$30,0,IF(OR(Indata!$M$30="",Indata!$M$30=0),0,Indata!$M$30*Indata!$F$30*(1+Indata!$C$8*Indata!$H$30)^(E52-Indata!$K$30)))) -> 0 | F64: =IF(Indata!$K$30="",0,IF(F52<=Indata!$L$30,0,IF(OR(Indata!$M$30="",Indata!$M$30=0),0,Indata!$M$30*Indata!$F$30*(1+Indata!$C$8*Indata!$H$30)^(F52-Indata!$K$30)))) -> 0 | G64: =IF(Indata!$K$30="",0,IF(G52<=Indata!$L$30,0,IF(OR(Indata!$M$30="",Indata!$M$30=0),0,Indata!$M$30*Indata!$F$30*(1+Indata!$C$8*Indata!$H$30)^(G52-Indata!$K$30)))) -> 0 | H64: =IF(Indata!$K$30="",0,IF(H52<=Indata!$L$30,0,IF(OR(Indata!$M$30="",Indata!$M$30=0),0,Indata!$M$30*Indata!$F$30*(1+Indata!$C$8*Indata!$H$30)^(H52-Indata!$K$30)))) -> 0 | I64: =IF(Indata!$K$30="",0,IF(I52<=Indata!$L$30,0,IF(OR(Indata!$M$30="",Indata!$M$30=0),0,Indata!$M$30*Indata!$F$30*(1+Indata!$C$8*Indata!$H$30)^(I52-Indata!$K$30)))) -> 0 | J64: =IF(Indata!$K$30="",0,IF(J52<=Indata!$L$30,0,IF(OR(Indata!$M$30="",Indata!$M$30=0),0,Indata!$M$30*Indata!$F$30*(1+Indata!$C$8*Indata!$H$30)^(J52-Indata!$K$30)))) -> 0 | K64: =IF(Indata!$K$30="",0,IF(K52<=Indata!$L$30,0,IF(OR(Indata!$M$30="",Indata!$M$30=0),0,Indata!$M$30*Indata!$F$30*(1+Indata!$C$8*Indata!$H$30)^(K52-Indata!$K$30)))) -> 0 | ... AB64: =IF(Indata!$K$30="",0,IF(AB52<=Indata!$L$30,0,IF(OR(Indata!$M$30="",Indata!$M$30=0),0,Indata!$M$30*Indata!$F$30*(1+Indata!$C$8*Indata!$H$30)^(AB52-Indata!$K$30)))) -> 0
B66: Bruttohyra | D66: =SUM(D60:D64) -> 0 | E66: =SUM(E60:E64) -> 0 | F66: =SUM(F60:F64) -> 0 | G66: =SUM(G60:G64) -> 0 | H66: =SUM(H60:H64) -> 0 | I66: =SUM(I60:I64) -> 0 | J66: =SUM(J60:J64) -> 0 | K66: =SUM(K60:K64) -> 0 | ... AB66: =SUM(AB60:AB64) -> 0
B67: Vakans | D67: =IF(AND(Indata!$L$26<>"",D52>Indata!$L$26),-D60*Indata!$N$26,0)+IF(AND(Indata!$L$27<>"",D52>Indata!$L$27),-D61*Indata!$N$27,0)+IF(AND(Indata!$L$28<>"",D52>Indata!$L$28),-D62*Indata!$N$28,0)+IF(AND(Indata!$L$29<>"",D52>Indata!$L$29),-D63*Indata!$N$29,0)+IF(AND(Indata!$L$30<>"",D52>Indata!$L$30),-D64*Indata!$N$30,0) -> 0 | E67: =IF(AND(Indata!$L$26<>"",E52>Indata!$L$26),-E60*Indata!$N$26,0)+IF(AND(Indata!$L$27<>"",E52>Indata!$L$27),-E61*Indata!$N$27,0)+IF(AND(Indata!$L$28<>"",E52>Indata!$L$28),-E62*Indata!$N$28,0)+IF(AND(Indata!$L$29<>"",E52>Indata!$L$29),-E63*Indata!$N$29,0)+IF(AND(Indata!$L$30<>"",E52>Indata!$L$30),-E64*Indata!$N$30,0) -> 0 | F67: =IF(AND(Indata!$L$26<>"",F52>Indata!$L$26),-F60*Indata!$N$26,0)+IF(AND(Indata!$L$27<>"",F52>Indata!$L$27),-F61*Indata!$N$27,0)+IF(AND(Indata!$L$28<>"",F52>Indata!$L$28),-F62*Indata!$N$28,0)+IF(AND(Indata!$L$29<>"",F52>Indata!$L$29),-F63*Indata!$N$29,0)+IF(AND(Indata!$L$30<>"",F52>Indata!$L$30),-F64*Indata!$N$30,0) -> 0 | G67: =IF(AND(Indata!$L$26<>"",G52>Indata!$L$26),-G60*Indata!$N$26,0)+IF(AND(Indata!$L$27<>"",G52>Indata!$L$27),-G61*Indata!$N$27,0)+IF(AND(Indata!$L$28<>"",G52>Indata!$L$28),-G62*Indata!$N$28,0)+IF(AND(Indata!$L$29<>"",G52>Indata!$L$29),-G63*Indata!$N$29,0)+IF(AND(Indata!$L$30<>"",G52>Indata!$L$30),-G64*Indata!$N$30,0) -> 0 | H67: =IF(AND(Indata!$L$26<>"",H52>Indata!$L$26),-H60*Indata!$N$26,0)+IF(AND(Indata!$L$27<>"",H52>Indata!$L$27),-H61*Indata!$N$27,0)+IF(AND(Indata!$L$28<>"",H52>Indata!$L$28),-H62*Indata!$N$28,0)+IF(AND(Indata!$L$29<>"",H52>Indata!$L$29),-H63*Indata!$N$29,0)+IF(AND(Indata!$L$30<>"",H52>Indata!$L$30),-H64*Indata!$N$30,0) -> 0 | I67: =IF(AND(Indata!$L$26<>"",I52>Indata!$L$26),-I60*Indata!$N$26,0)+IF(AND(Indata!$L$27<>"",I52>Indata!$L$27),-I61*Indata!$N$27,0)+IF(AND(Indata!$L$28<>"",I52>Indata!$L$28),-I62*Indata!$N$28,0)+IF(AND(Indata!$L$29<>"",I52>Indata!$L$29),-I63*Indata!$N$29,0)+IF(AND(Indata!$L$30<>"",I52>Indata!$L$30),-I64*Indata!$N$30,0) -> 0 | J67: =IF(AND(Indata!$L$26<>"",J52>Indata!$L$26),-J60*Indata!$N$26,0)+IF(AND(Indata!$L$27<>"",J52>Indata!$L$27),-J61*Indata!$N$27,0)+IF(AND(Indata!$L$28<>"",J52>Indata!$L$28),-J62*Indata!$N$28,0)+IF(AND(Indata!$L$29<>"",J52>Indata!$L$29),-J63*Indata!$N$29,0)+IF(AND(Indata!$L$30<>"",J52>Indata!$L$30),-J64*Indata!$N$30,0) -> 0 | K67: =IF(AND(Indata!$L$26<>"",K52>Indata!$L$26),-K60*Indata!$N$26,0)+IF(AND(Indata!$L$27<>"",K52>Indata!$L$27),-K61*Indata!$N$27,0)+IF(AND(Indata!$L$28<>"",K52>Indata!$L$28),-K62*Indata!$N$28,0)+IF(AND(Indata!$L$29<>"",K52>Indata!$L$29),-K63*Indata!$N$29,0)+IF(AND(Indata!$L$30<>"",K52>Indata!$L$30),-K64*Indata!$N$30,0) -> 0 | ... AB67: =IF(AND(Indata!$L$26<>"",AB52>Indata!$L$26),-AB60*Indata!$N$26,0)+IF(AND(Indata!$L$27<>"",AB52>Indata!$L$27),-AB61*Indata!$N$27,0)+IF(AND(Indata!$L$28<>"",AB52>Indata!$L$28),-AB62*Indata!$N$28,0)+IF(AND(Indata!$L$29<>"",AB52>Indata!$L$29),-AB63*Indata!$N$29,0)+IF(AND(Indata!$L$30<>"",AB52>Indata!$L$30),-AB64*Indata!$N$30,0) -> 0
B68: Nettohyra | D68: =D66+D67 -> 0 | E68: =E66+E67 -> 0 | F68: =F66+F67 -> 0 | G68: =G66+G67 -> 0 | H68: =H66+H67 -> 0 | I68: =I66+I67 -> 0 | J68: =J66+J67 -> 0 | K68: =K66+K67 -> 0 | ... AB68: =AB66+AB67 -> 0
B70: KOSTNADER
B71: Fastighetsskötsel | D71: =-((D56*Indata!$C36+D55*Indata!$D36)*(1+Indata!$C$8)^(D53-1))*(1+IF(D53-1>=10,Indata!$E36,0)+IF(D53-1>=15,Indata!$F36,0)) -> -250000 | E71: =-((E56*Indata!$C36+E55*Indata!$D36)*(1+Indata!$C$8)^(E53-1))*(1+IF(E53-1>=10,Indata!$E36,0)+IF(E53-1>=15,Indata!$F36,0)) -> -255000 | F71: =-((F56*Indata!$C36+F55*Indata!$D36)*(1+Indata!$C$8)^(F53-1))*(1+IF(F53-1>=10,Indata!$E36,0)+IF(F53-1>=15,Indata!$F36,0)) -> -260100 | G71: =-((G56*Indata!$C36+G55*Indata!$D36)*(1+Indata!$C$8)^(G53-1))*(1+IF(G53-1>=10,Indata!$E36,0)+IF(G53-1>=15,Indata!$F36,0)) -> -265302 | H71: =-((H56*Indata!$C36+H55*Indata!$D36)*(1+Indata!$C$8)^(H53-1))*(1+IF(H53-1>=10,Indata!$E36,0)+IF(H53-1>=15,Indata!$F36,0)) -> -270608.04 | I71: =-((I56*Indata!$C36+I55*Indata!$D36)*(1+Indata!$C$8)^(I53-1))*(1+IF(I53-1>=10,Indata!$E36,0)+IF(I53-1>=15,Indata!$F36,0)) -> -276020.2 | J71: =-((J56*Indata!$C36+J55*Indata!$D36)*(1+Indata!$C$8)^(J53-1))*(1+IF(J53-1>=10,Indata!$E36,0)+IF(J53-1>=15,Indata!$F36,0)) -> -281540.6 | K71: =-((K56*Indata!$C36+K55*Indata!$D36)*(1+Indata!$C$8)^(K53-1))*(1+IF(K53-1>=10,Indata!$E36,0)+IF(K53-1>=15,Indata!$F36,0)) -> -287171.42 | ... AB71: =-((AB56*Indata!$C36+AB55*Indata!$D36)*(1+Indata!$C$8)^(AB53-1))*(1+IF(AB53-1>=10,Indata!$E36,0)+IF(AB53-1>=15,Indata!$F36,0)) -> -402109.31
B72: Reparationer | D72: =-((D56*Indata!$C37+D55*Indata!$D37)*(1+Indata!$C$8)^(D53-1))*(1+IF(D53-1>=10,Indata!$E37,0)+IF(D53-1>=15,Indata!$F37,0)) -> -150000 | E72: =-((E56*Indata!$C37+E55*Indata!$D37)*(1+Indata!$C$8)^(E53-1))*(1+IF(E53-1>=10,Indata!$E37,0)+IF(E53-1>=15,Indata!$F37,0)) -> -153000 | F72: =-((F56*Indata!$C37+F55*Indata!$D37)*(1+Indata!$C$8)^(F53-1))*(1+IF(F53-1>=10,Indata!$E37,0)+IF(F53-1>=15,Indata!$F37,0)) -> -156060 | G72: =-((G56*Indata!$C37+G55*Indata!$D37)*(1+Indata!$C$8)^(G53-1))*(1+IF(G53-1>=10,Indata!$E37,0)+IF(G53-1>=15,Indata!$F37,0)) -> -159181.2 | H72: =-((H56*Indata!$C37+H55*Indata!$D37)*(1+Indata!$C$8)^(H53-1))*(1+IF(H53-1>=10,Indata!$E37,0)+IF(H53-1>=15,Indata!$F37,0)) -> -162364.82 | I72: =-((I56*Indata!$C37+I55*Indata!$D37)*(1+Indata!$C$8)^(I53-1))*(1+IF(I53-1>=10,Indata!$E37,0)+IF(I53-1>=15,Indata!$F37,0)) -> -165612.12 | J72: =-((J56*Indata!$C37+J55*Indata!$D37)*(1+Indata!$C$8)^(J53-1))*(1+IF(J53-1>=10,Indata!$E37,0)+IF(J53-1>=15,Indata!$F37,0)) -> -168924.36 | K72: =-((K56*Indata!$C37+K55*Indata!$D37)*(1+Indata!$C$8)^(K53-1))*(1+IF(K53-1>=10,Indata!$E37,0)+IF(K53-1>=15,Indata!$F37,0)) -> -172302.85 | ... AB72: =-((AB56*Indata!$C37+AB55*Indata!$D37)*(1+Indata!$C$8)^(AB53-1))*(1+IF(AB53-1>=10,Indata!$E37,0)+IF(AB53-1>=15,Indata!$F37,0)) -> -241265.59
B73: Planerat underhåll | D73: =-((D56*Indata!$C38+D55*Indata!$D38)*(1+Indata!$C$8)^(D53-1))*(1+IF(D53-1>=10,Indata!$E38,0)+IF(D53-1>=15,Indata!$F38,0)) -> -200000 | E73: =-((E56*Indata!$C38+E55*Indata!$D38)*(1+Indata!$C$8)^(E53-1))*(1+IF(E53-1>=10,Indata!$E38,0)+IF(E53-1>=15,Indata!$F38,0)) -> -204000 | F73: =-((F56*Indata!$C38+F55*Indata!$D38)*(1+Indata!$C$8)^(F53-1))*(1+IF(F53-1>=10,Indata!$E38,0)+IF(F53-1>=15,Indata!$F38,0)) -> -208080 | G73: =-((G56*Indata!$C38+G55*Indata!$D38)*(1+Indata!$C$8)^(G53-1))*(1+IF(G53-1>=10,Indata!$E38,0)+IF(G53-1>=15,Indata!$F38,0)) -> -212241.6 | H73: =-((H56*Indata!$C38+H55*Indata!$D38)*(1+Indata!$C$8)^(H53-1))*(1+IF(H53-1>=10,Indata!$E38,0)+IF(H53-1>=15,Indata!$F38,0)) -> -216486.43 | I73: =-((I56*Indata!$C38+I55*Indata!$D38)*(1+Indata!$C$8)^(I53-1))*(1+IF(I53-1>=10,Indata!$E38,0)+IF(I53-1>=15,Indata!$F38,0)) -> -220816.16 | J73: =-((J56*Indata!$C38+J55*Indata!$D38)*(1+Indata!$C$8)^(J53-1))*(1+IF(J53-1>=10,Indata!$E38,0)+IF(J53-1>=15,Indata!$F38,0)) -> -225232.48 | K73: =-((K56*Indata!$C38+K55*Indata!$D38)*(1+Indata!$C$8)^(K53-1))*(1+IF(K53-1>=10,Indata!$E38,0)+IF(K53-1>=15,Indata!$F38,0)) -> -229737.13 | ... AB73: =-((AB56*Indata!$C38+AB55*Indata!$D38)*(1+Indata!$C$8)^(AB53-1))*(1+IF(AB53-1>=10,Indata!$E38,0)+IF(AB53-1>=15,Indata!$F38,0)) -> -321687.45
B74: Media | D74: =-((D56*Indata!$C39+D55*Indata!$D39)*(1+Indata!$C$8)^(D53-1))*(1+IF(D53-1>=10,Indata!$E39,0)+IF(D53-1>=15,Indata!$F39,0)) -> -750000 | E74: =-((E56*Indata!$C39+E55*Indata!$D39)*(1+Indata!$C$8)^(E53-1))*(1+IF(E53-1>=10,Indata!$E39,0)+IF(E53-1>=15,Indata!$F39,0)) -> -765000 | F74: =-((F56*Indata!$C39+F55*Indata!$D39)*(1+Indata!$C$8)^(F53-1))*(1+IF(F53-1>=10,Indata!$E39,0)+IF(F53-1>=15,Indata!$F39,0)) -> -780300 | G74: =-((G56*Indata!$C39+G55*Indata!$D39)*(1+Indata!$C$8)^(G53-1))*(1+IF(G53-1>=10,Indata!$E39,0)+IF(G53-1>=15,Indata!$F39,0)) -> -795906 | H74: =-((H56*Indata!$C39+H55*Indata!$D39)*(1+Indata!$C$8)^(H53-1))*(1+IF(H53-1>=10,Indata!$E39,0)+IF(H53-1>=15,Indata!$F39,0)) -> -811824.12 | I74: =-((I56*Indata!$C39+I55*Indata!$D39)*(1+Indata!$C$8)^(I53-1))*(1+IF(I53-1>=10,Indata!$E39,0)+IF(I53-1>=15,Indata!$F39,0)) -> -828060.6 | J74: =-((J56*Indata!$C39+J55*Indata!$D39)*(1+Indata!$C$8)^(J53-1))*(1+IF(J53-1>=10,Indata!$E39,0)+IF(J53-1>=15,Indata!$F39,0)) -> -844621.81 | K74: =-((K56*Indata!$C39+K55*Indata!$D39)*(1+Indata!$C$8)^(K53-1))*(1+IF(K53-1>=10,Indata!$E39,0)+IF(K53-1>=15,Indata!$F39,0)) -> -861514.25 | ... AB74: =-((AB56*Indata!$C39+AB55*Indata!$D39)*(1+Indata!$C$8)^(AB53-1))*(1+IF(AB53-1>=10,Indata!$E39,0)+IF(AB53-1>=15,Indata!$F39,0)) -> -1206327.9
B75: Övriga förv.kost. | D75: =-((D56*Indata!$C40+D55*Indata!$D40)*(1+Indata!$C$8)^(D53-1))*(1+IF(D53-1>=10,Indata!$E40,0)+IF(D53-1>=15,Indata!$F40,0)) -> -650000 | E75: =-((E56*Indata!$C40+E55*Indata!$D40)*(1+Indata!$C$8)^(E53-1))*(1+IF(E53-1>=10,Indata!$E40,0)+IF(E53-1>=15,Indata!$F40,0)) -> -663000 | F75: =-((F56*Indata!$C40+F55*Indata!$D40)*(1+Indata!$C$8)^(F53-1))*(1+IF(F53-1>=10,Indata!$E40,0)+IF(F53-1>=15,Indata!$F40,0)) -> -676260 | G75: =-((G56*Indata!$C40+G55*Indata!$D40)*(1+Indata!$C$8)^(G53-1))*(1+IF(G53-1>=10,Indata!$E40,0)+IF(G53-1>=15,Indata!$F40,0)) -> -689785.2 | H75: =-((H56*Indata!$C40+H55*Indata!$D40)*(1+Indata!$C$8)^(H53-1))*(1+IF(H53-1>=10,Indata!$E40,0)+IF(H53-1>=15,Indata!$F40,0)) -> -703580.9 | I75: =-((I56*Indata!$C40+I55*Indata!$D40)*(1+Indata!$C$8)^(I53-1))*(1+IF(I53-1>=10,Indata!$E40,0)+IF(I53-1>=15,Indata!$F40,0)) -> -717652.52 | J75: =-((J56*Indata!$C40+J55*Indata!$D40)*(1+Indata!$C$8)^(J53-1))*(1+IF(J53-1>=10,Indata!$E40,0)+IF(J53-1>=15,Indata!$F40,0)) -> -732005.57 | K75: =-((K56*Indata!$C40+K55*Indata!$D40)*(1+Indata!$C$8)^(K53-1))*(1+IF(K53-1>=10,Indata!$E40,0)+IF(K53-1>=15,Indata!$F40,0)) -> -746645.68 | ... AB75: =-((AB56*Indata!$C40+AB55*Indata!$D40)*(1+Indata!$C$8)^(AB53-1))*(1+IF(AB53-1>=10,Indata!$E40,0)+IF(AB53-1>=15,Indata!$F40,0)) -> -1045484.2
B76: Re-investering / hyresatt UH | D76: =-IFERROR(SUMIF(Indata!$D$45:$D$99,D52,Indata!$F$45:$F$99),0) -> 0 | E76: =-IFERROR(SUMIF(Indata!$D$45:$D$99,E52,Indata!$F$45:$F$99),0) -> 0 | F76: =-IFERROR(SUMIF(Indata!$D$45:$D$99,F52,Indata!$F$45:$F$99),0) -> 0 | G76: =-IFERROR(SUMIF(Indata!$D$45:$D$99,G52,Indata!$F$45:$F$99),0) -> 0 | H76: =-IFERROR(SUMIF(Indata!$D$45:$D$99,H52,Indata!$F$45:$F$99),0) -> 0 | I76: =-IFERROR(SUMIF(Indata!$D$45:$D$99,I52,Indata!$F$45:$F$99),0) -> 0 | J76: =-IFERROR(SUMIF(Indata!$D$45:$D$99,J52,Indata!$F$45:$F$99),0) -> 0 | K76: =-IFERROR(SUMIF(Indata!$D$45:$D$99,K52,Indata!$F$45:$F$99),0) -> 0 | ... AB76: =-IFERROR(SUMIF(Indata!$D$45:$D$99,AB52,Indata!$F$45:$F$99),0) -> 0
B77: Summa drift och underhåll | D77: =SUM(D71:D76) -> -2000000 | E77: =SUM(E71:E76) -> -2040000 | F77: =SUM(F71:F76) -> -2080800 | G77: =SUM(G71:G76) -> -2122416 | H77: =SUM(H71:H76) -> -2164864.3 | I77: =SUM(I71:I76) -> -2208161.6 | J77: =SUM(J71:J76) -> -2252324.8 | K77: =SUM(K71:K76) -> -2297371.3 | ... AB77: =SUM(AB71:AB76) -> -3216874.5
B79: Fastighetsskatt | D79: =-Indata!$C$55*Indata!$C$54*(1+Indata!$C$8)^(D53-1) -> 0 | E79: =-Indata!$C$55*Indata!$C$54*(1+Indata!$C$8)^(E53-1) -> 0 | F79: =-Indata!$C$55*Indata!$C$54*(1+Indata!$C$8)^(F53-1) -> 0 | G79: =-Indata!$C$55*Indata!$C$54*(1+Indata!$C$8)^(G53-1) -> 0 | H79: =-Indata!$C$55*Indata!$C$54*(1+Indata!$C$8)^(H53-1) -> 0 | I79: =-Indata!$C$55*Indata!$C$54*(1+Indata!$C$8)^(I53-1) -> 0 | J79: =-Indata!$C$55*Indata!$C$54*(1+Indata!$C$8)^(J53-1) -> 0 | K79: =-Indata!$C$55*Indata!$C$54*(1+Indata!$C$8)^(K53-1) -> 0 | ... AB79: =-Indata!$C$55*Indata!$C$54*(1+Indata!$C$8)^(AB53-1) -> 0
B80: Tomträttsavgäld | D80: =-Indata!$C$56*(1+Indata!$C$8)^(D53-1) -> 0 | E80: =-Indata!$C$56*(1+Indata!$C$8)^(E53-1) -> 0 | F80: =-Indata!$C$56*(1+Indata!$C$8)^(F53-1) -> 0 | G80: =-Indata!$C$56*(1+Indata!$C$8)^(G53-1) -> 0 | H80: =-Indata!$C$56*(1+Indata!$C$8)^(H53-1) -> 0 | I80: =-Indata!$C$56*(1+Indata!$C$8)^(I53-1) -> 0 | J80: =-Indata!$C$56*(1+Indata!$C$8)^(J53-1) -> 0 | K80: =-Indata!$C$56*(1+Indata!$C$8)^(K53-1) -> 0 | ... AB80: =-Indata!$C$56*(1+Indata!$C$8)^(AB53-1) -> 0
B82: DRIFTNETTO (efter drift, skatt, CA) | D82: =D68+D77+D79+D80+D83 -> -2400000 | E82: =E68+E77+E79+E80+E83 -> -2448000 | F82: =F68+F77+F79+F80+F83 -> -2496960 | G82: =G68+G77+G79+G80+G83 -> -2546899.2 | H82: =H68+H77+H79+H80+H83 -> -2597837.2 | I82: =I68+I77+I79+I80+I83 -> -2649793.9 | J82: =J68+J77+J79+J80+J83 -> -2702789.8 | K82: =K68+K77+K79+K80+K83 -> -2756845.6 | ... AB82: =AB68+AB77+AB79+AB80+AB83 -> -3860249.4
B83: varav central administration | D83: =-Indata!$C$53*D57*(1+Indata!$C$8)^(D53-1) -> -400000 | E83: =-Indata!$C$53*E57*(1+Indata!$C$8)^(E53-1) -> -408000 | F83: =-Indata!$C$53*F57*(1+Indata!$C$8)^(F53-1) -> -416160 | G83: =-Indata!$C$53*G57*(1+Indata!$C$8)^(G53-1) -> -424483.2 | H83: =-Indata!$C$53*H57*(1+Indata!$C$8)^(H53-1) -> -432972.86 | I83: =-Indata!$C$53*I57*(1+Indata!$C$8)^(I53-1) -> -441632.32 | J83: =-Indata!$C$53*J57*(1+Indata!$C$8)^(J53-1) -> -450464.97 | K83: =-Indata!$C$53*K57*(1+Indata!$C$8)^(K53-1) -> -459474.27 | ... AB83: =-Indata!$C$53*AB57*(1+Indata!$C$8)^(AB53-1) -> -643374.9
B85: Driftnetto exkl. re-inv (för Gordon) | D85: =D82-D76 -> -2400000 | E85: =E82-E76 -> -2448000 | F85: =F82-F76 -> -2496960 | G85: =G82-G76 -> -2546899.2 | H85: =H82-H76 -> -2597837.2 | I85: =I82-I76 -> -2649793.9 | J85: =J82-J76 -> -2702789.8 | K85: =K82-K76 -> -2756845.6 | ... AB85: =AB82-AB76 -> -3860249.4
B87: PV driftnetto (kalkylränta C7) | D87: =IF(D54=0,0,D82/(1+Indata!$C$7)^D53) -> -2307692.3 | E87: =IF(E54=0,0,E82/(1+Indata!$C$7)^E53) -> -2263313.6 | F87: =IF(F54=0,0,F82/(1+Indata!$C$7)^F53) -> -2219788.3 | G87: =IF(G54=0,0,G82/(1+Indata!$C$7)^G53) -> -2177100.1 | H87: =IF(H54=0,0,H82/(1+Indata!$C$7)^H53) -> -2135232.8 | I87: =IF(I54=0,0,I82/(1+Indata!$C$7)^I53) -> -2094170.6 | J87: =IF(J54=0,0,J82/(1+Indata!$C$7)^J53) -> -2053898.1 | K87: =IF(K54=0,0,K82/(1+Indata!$C$7)^K53) -> -2014400.1 | ... AB87: =IF(AB54=0,0,AB82/(1+Indata!$C$7)^AB53) -> 0
B109: NPV vid 0 hyra (kalkylränta C7)
B111: Kalkylperiod | C111: =Indata!C16 -> 20
B112: Total investering | C112: =Indata!R31 -> 200000000
B113: Produktionsavslut (senaste) | C113: =MAX(Indata!P26:P79) -> 2026
B115: PV Driftnetto vid 0 hyra | C115: =ROUND(SUMIFS(D87:AB87,D54:AB54,1)/10000,0)*10000 -> -38620000
B116: Restvärde (Gordon) vid 0 hyra | C116: =ROUND(INDEX(D85:AB85,MATCH(Indata!C16+1,D53:AB53,0))/Indata!C6/10000,0)*10000 -> -71330000
B117: PV Restvärde vid 0 hyra | C117: =ROUND(C116/(1+Indata!C9)^Indata!C16/10000,0)*10000 -> -18430000
B118: PV Investering | C118: =-C112/(1+Indata!C8)^MAX(0,C113-Indata!C5) -> -200000000
B119: NPV vid 0 hyra | C119: =C115+C117+C118 -> -257050000
B121: BLOCK B — Delta-intäkter vid årshyra = 1 Mkr (för b_NPV)
B123: Intäkt obj 1 (med 1 Mkr testhyra) | D123: =IF(Indata!$K$26="",0,IF(D52<Indata!$K$26,0,IF(D52<=Indata!$L$26,Indata!$J$26*1000000*(1+Indata!$C$8*Indata!$H$26)^(D52-Indata!$K$26),IF(OR(Indata!$M$26="",Indata!$M$26=0),Indata!$J$26*1000000*(1+Indata!$C$8*Indata!$H$26)^(D52-Indata!$K$26),D60)))) -> 1000000 | E123: =IF(Indata!$K$26="",0,IF(E52<Indata!$K$26,0,IF(E52<=Indata!$L$26,Indata!$J$26*1000000*(1+Indata!$C$8*Indata!$H$26)^(E52-Indata!$K$26),IF(OR(Indata!$M$26="",Indata!$M$26=0),Indata!$J$26*1000000*(1+Indata!$C$8*Indata!$H$26)^(E52-Indata!$K$26),E60)))) -> 1014000 | F123: =IF(Indata!$K$26="",0,IF(F52<Indata!$K$26,0,IF(F52<=Indata!$L$26,Indata!$J$26*1000000*(1+Indata!$C$8*Indata!$H$26)^(F52-Indata!$K$26),IF(OR(Indata!$M$26="",Indata!$M$26=0),Indata!$J$26*1000000*(1+Indata!$C$8*Indata!$H$26)^(F52-Indata!$K$26),F60)))) -> 1028196 | G123: =IF(Indata!$K$26="",0,IF(G52<Indata!$K$26,0,IF(G52<=Indata!$L$26,Indata!$J$26*1000000*(1+Indata!$C$8*Indata!$H$26)^(G52-Indata!$K$26),IF(OR(Indata!$M$26="",Indata!$M$26=0),Indata!$J$26*1000000*(1+Indata!$C$8*Indata!$H$26)^(G52-Indata!$K$26),G60)))) -> 1042590.7 | H123: =IF(Indata!$K$26="",0,IF(H52<Indata!$K$26,0,IF(H52<=Indata!$L$26,Indata!$J$26*1000000*(1+Indata!$C$8*Indata!$H$26)^(H52-Indata!$K$26),IF(OR(Indata!$M$26="",Indata!$M$26=0),Indata!$J$26*1000000*(1+Indata!$C$8*Indata!$H$26)^(H52-Indata!$K$26),H60)))) -> 1057187 | I123: =IF(Indata!$K$26="",0,IF(I52<Indata!$K$26,0,IF(I52<=Indata!$L$26,Indata!$J$26*1000000*(1+Indata!$C$8*Indata!$H$26)^(I52-Indata!$K$26),IF(OR(Indata!$M$26="",Indata!$M$26=0),Indata!$J$26*1000000*(1+Indata!$C$8*Indata!$H$26)^(I52-Indata!$K$26),I60)))) -> 1071987.6 | J123: =IF(Indata!$K$26="",0,IF(J52<Indata!$K$26,0,IF(J52<=Indata!$L$26,Indata!$J$26*1000000*(1+Indata!$C$8*Indata!$H$26)^(J52-Indata!$K$26),IF(OR(Indata!$M$26="",Indata!$M$26=0),Indata!$J$26*1000000*(1+Indata!$C$8*Indata!$H$26)^(J52-Indata!$K$26),J60)))) -> 1086995.5 | K123: =IF(Indata!$K$26="",0,IF(K52<Indata!$K$26,0,IF(K52<=Indata!$L$26,Indata!$J$26*1000000*(1+Indata!$C$8*Indata!$H$26)^(K52-Indata!$K$26),IF(OR(Indata!$M$26="",Indata!$M$26=0),Indata!$J$26*1000000*(1+Indata!$C$8*Indata!$H$26)^(K52-Indata!$K$26),K60)))) -> 1102213.4 | ... AB123: =IF(Indata!$K$26="",0,IF(AB52<Indata!$K$26,0,IF(AB52<=Indata!$L$26,Indata!$J$26*1000000*(1+Indata!$C$8*Indata!$H$26)^(AB52-Indata!$K$26),IF(OR(Indata!$M$26="",Indata!$M$26=0),Indata!$J$26*1000000*(1+Indata!$C$8*Indata!$H$26)^(AB52-Indata!$K$26),AB60)))) -> 1396082
B124: Intäkt obj 2 (med 1 Mkr testhyra) | D124: =IF(Indata!$K$27="",0,IF(D52<Indata!$K$27,0,IF(D52<=Indata!$L$27,Indata!$J$27*1000000*(1+Indata!$C$8*Indata!$H$27)^(D52-Indata!$K$27),IF(OR(Indata!$M$27="",Indata!$M$27=0),Indata!$J$27*1000000*(1+Indata!$C$8*Indata!$H$27)^(D52-Indata!$K$27),D61)))) -> 0 | E124: =IF(Indata!$K$27="",0,IF(E52<Indata!$K$27,0,IF(E52<=Indata!$L$27,Indata!$J$27*1000000*(1+Indata!$C$8*Indata!$H$27)^(E52-Indata!$K$27),IF(OR(Indata!$M$27="",Indata!$M$27=0),Indata!$J$27*1000000*(1+Indata!$C$8*Indata!$H$27)^(E52-Indata!$K$27),E61)))) -> 0 | F124: =IF(Indata!$K$27="",0,IF(F52<Indata!$K$27,0,IF(F52<=Indata!$L$27,Indata!$J$27*1000000*(1+Indata!$C$8*Indata!$H$27)^(F52-Indata!$K$27),IF(OR(Indata!$M$27="",Indata!$M$27=0),Indata!$J$27*1000000*(1+Indata!$C$8*Indata!$H$27)^(F52-Indata!$K$27),F61)))) -> 0 | G124: =IF(Indata!$K$27="",0,IF(G52<Indata!$K$27,0,IF(G52<=Indata!$L$27,Indata!$J$27*1000000*(1+Indata!$C$8*Indata!$H$27)^(G52-Indata!$K$27),IF(OR(Indata!$M$27="",Indata!$M$27=0),Indata!$J$27*1000000*(1+Indata!$C$8*Indata!$H$27)^(G52-Indata!$K$27),G61)))) -> 0 | H124: =IF(Indata!$K$27="",0,IF(H52<Indata!$K$27,0,IF(H52<=Indata!$L$27,Indata!$J$27*1000000*(1+Indata!$C$8*Indata!$H$27)^(H52-Indata!$K$27),IF(OR(Indata!$M$27="",Indata!$M$27=0),Indata!$J$27*1000000*(1+Indata!$C$8*Indata!$H$27)^(H52-Indata!$K$27),H61)))) -> 0 | I124: =IF(Indata!$K$27="",0,IF(I52<Indata!$K$27,0,IF(I52<=Indata!$L$27,Indata!$J$27*1000000*(1+Indata!$C$8*Indata!$H$27)^(I52-Indata!$K$27),IF(OR(Indata!$M$27="",Indata!$M$27=0),Indata!$J$27*1000000*(1+Indata!$C$8*Indata!$H$27)^(I52-Indata!$K$27),I61)))) -> 0 | J124: =IF(Indata!$K$27="",0,IF(J52<Indata!$K$27,0,IF(J52<=Indata!$L$27,Indata!$J$27*1000000*(1+Indata!$C$8*Indata!$H$27)^(J52-Indata!$K$27),IF(OR(Indata!$M$27="",Indata!$M$27=0),Indata!$J$27*1000000*(1+Indata!$C$8*Indata!$H$27)^(J52-Indata!$K$27),J61)))) -> 0 | K124: =IF(Indata!$K$27="",0,IF(K52<Indata!$K$27,0,IF(K52<=Indata!$L$27,Indata!$J$27*1000000*(1+Indata!$C$8*Indata!$H$27)^(K52-Indata!$K$27),IF(OR(Indata!$M$27="",Indata!$M$27=0),Indata!$J$27*1000000*(1+Indata!$C$8*Indata!$H$27)^(K52-Indata!$K$27),K61)))) -> 0 | ... AB124: =IF(Indata!$K$27="",0,IF(AB52<Indata!$K$27,0,IF(AB52<=Indata!$L$27,Indata!$J$27*1000000*(1+Indata!$C$8*Indata!$H$27)^(AB52-Indata!$K$27),IF(OR(Indata!$M$27="",Indata!$M$27=0),Indata!$J$27*1000000*(1+Indata!$C$8*Indata!$H$27)^(AB52-Indata!$K$27),AB61)))) -> 0
B125: Intäkt obj 3 (med 1 Mkr testhyra) | D125: =IF(Indata!$K$28="",0,IF(D52<Indata!$K$28,0,IF(D52<=Indata!$L$28,Indata!$J$28*1000000*(1+Indata!$C$8*Indata!$H$28)^(D52-Indata!$K$28),IF(OR(Indata!$M$28="",Indata!$M$28=0),Indata!$J$28*1000000*(1+Indata!$C$8*Indata!$H$28)^(D52-Indata!$K$28),D62)))) -> 0 | E125: =IF(Indata!$K$28="",0,IF(E52<Indata!$K$28,0,IF(E52<=Indata!$L$28,Indata!$J$28*1000000*(1+Indata!$C$8*Indata!$H$28)^(E52-Indata!$K$28),IF(OR(Indata!$M$28="",Indata!$M$28=0),Indata!$J$28*1000000*(1+Indata!$C$8*Indata!$H$28)^(E52-Indata!$K$28),E62)))) -> 0 | F125: =IF(Indata!$K$28="",0,IF(F52<Indata!$K$28,0,IF(F52<=Indata!$L$28,Indata!$J$28*1000000*(1+Indata!$C$8*Indata!$H$28)^(F52-Indata!$K$28),IF(OR(Indata!$M$28="",Indata!$M$28=0),Indata!$J$28*1000000*(1+Indata!$C$8*Indata!$H$28)^(F52-Indata!$K$28),F62)))) -> 0 | G125: =IF(Indata!$K$28="",0,IF(G52<Indata!$K$28,0,IF(G52<=Indata!$L$28,Indata!$J$28*1000000*(1+Indata!$C$8*Indata!$H$28)^(G52-Indata!$K$28),IF(OR(Indata!$M$28="",Indata!$M$28=0),Indata!$J$28*1000000*(1+Indata!$C$8*Indata!$H$28)^(G52-Indata!$K$28),G62)))) -> 0 | H125: =IF(Indata!$K$28="",0,IF(H52<Indata!$K$28,0,IF(H52<=Indata!$L$28,Indata!$J$28*1000000*(1+Indata!$C$8*Indata!$H$28)^(H52-Indata!$K$28),IF(OR(Indata!$M$28="",Indata!$M$28=0),Indata!$J$28*1000000*(1+Indata!$C$8*Indata!$H$28)^(H52-Indata!$K$28),H62)))) -> 0 | I125: =IF(Indata!$K$28="",0,IF(I52<Indata!$K$28,0,IF(I52<=Indata!$L$28,Indata!$J$28*1000000*(1+Indata!$C$8*Indata!$H$28)^(I52-Indata!$K$28),IF(OR(Indata!$M$28="",Indata!$M$28=0),Indata!$J$28*1000000*(1+Indata!$C$8*Indata!$H$28)^(I52-Indata!$K$28),I62)))) -> 0 | J125: =IF(Indata!$K$28="",0,IF(J52<Indata!$K$28,0,IF(J52<=Indata!$L$28,Indata!$J$28*1000000*(1+Indata!$C$8*Indata!$H$28)^(J52-Indata!$K$28),IF(OR(Indata!$M$28="",Indata!$M$28=0),Indata!$J$28*1000000*(1+Indata!$C$8*Indata!$H$28)^(J52-Indata!$K$28),J62)))) -> 0 | K125: =IF(Indata!$K$28="",0,IF(K52<Indata!$K$28,0,IF(K52<=Indata!$L$28,Indata!$J$28*1000000*(1+Indata!$C$8*Indata!$H$28)^(K52-Indata!$K$28),IF(OR(Indata!$M$28="",Indata!$M$28=0),Indata!$J$28*1000000*(1+Indata!$C$8*Indata!$H$28)^(K52-Indata!$K$28),K62)))) -> 0 | ... AB125: =IF(Indata!$K$28="",0,IF(AB52<Indata!$K$28,0,IF(AB52<=Indata!$L$28,Indata!$J$28*1000000*(1+Indata!$C$8*Indata!$H$28)^(AB52-Indata!$K$28),IF(OR(Indata!$M$28="",Indata!$M$28=0),Indata!$J$28*1000000*(1+Indata!$C$8*Indata!$H$28)^(AB52-Indata!$K$28),AB62)))) -> 0
B126: Intäkt obj 4 (med 1 Mkr testhyra) | D126: =IF(Indata!$K$29="",0,IF(D52<Indata!$K$29,0,IF(D52<=Indata!$L$29,Indata!$J$29*1000000*(1+Indata!$C$8*Indata!$H$29)^(D52-Indata!$K$29),IF(OR(Indata!$M$29="",Indata!$M$29=0),Indata!$J$29*1000000*(1+Indata!$C$8*Indata!$H$29)^(D52-Indata!$K$29),D63)))) -> 0 | E126: =IF(Indata!$K$29="",0,IF(E52<Indata!$K$29,0,IF(E52<=Indata!$L$29,Indata!$J$29*1000000*(1+Indata!$C$8*Indata!$H$29)^(E52-Indata!$K$29),IF(OR(Indata!$M$29="",Indata!$M$29=0),Indata!$J$29*1000000*(1+Indata!$C$8*Indata!$H$29)^(E52-Indata!$K$29),E63)))) -> 0 | F126: =IF(Indata!$K$29="",0,IF(F52<Indata!$K$29,0,IF(F52<=Indata!$L$29,Indata!$J$29*1000000*(1+Indata!$C$8*Indata!$H$29)^(F52-Indata!$K$29),IF(OR(Indata!$M$29="",Indata!$M$29=0),Indata!$J$29*1000000*(1+Indata!$C$8*Indata!$H$29)^(F52-Indata!$K$29),F63)))) -> 0 | G126: =IF(Indata!$K$29="",0,IF(G52<Indata!$K$29,0,IF(G52<=Indata!$L$29,Indata!$J$29*1000000*(1+Indata!$C$8*Indata!$H$29)^(G52-Indata!$K$29),IF(OR(Indata!$M$29="",Indata!$M$29=0),Indata!$J$29*1000000*(1+Indata!$C$8*Indata!$H$29)^(G52-Indata!$K$29),G63)))) -> 0 | H126: =IF(Indata!$K$29="",0,IF(H52<Indata!$K$29,0,IF(H52<=Indata!$L$29,Indata!$J$29*1000000*(1+Indata!$C$8*Indata!$H$29)^(H52-Indata!$K$29),IF(OR(Indata!$M$29="",Indata!$M$29=0),Indata!$J$29*1000000*(1+Indata!$C$8*Indata!$H$29)^(H52-Indata!$K$29),H63)))) -> 0 | I126: =IF(Indata!$K$29="",0,IF(I52<Indata!$K$29,0,IF(I52<=Indata!$L$29,Indata!$J$29*1000000*(1+Indata!$C$8*Indata!$H$29)^(I52-Indata!$K$29),IF(OR(Indata!$M$29="",Indata!$M$29=0),Indata!$J$29*1000000*(1+Indata!$C$8*Indata!$H$29)^(I52-Indata!$K$29),I63)))) -> 0 | J126: =IF(Indata!$K$29="",0,IF(J52<Indata!$K$29,0,IF(J52<=Indata!$L$29,Indata!$J$29*1000000*(1+Indata!$C$8*Indata!$H$29)^(J52-Indata!$K$29),IF(OR(Indata!$M$29="",Indata!$M$29=0),Indata!$J$29*1000000*(1+Indata!$C$8*Indata!$H$29)^(J52-Indata!$K$29),J63)))) -> 0 | K126: =IF(Indata!$K$29="",0,IF(K52<Indata!$K$29,0,IF(K52<=Indata!$L$29,Indata!$J$29*1000000*(1+Indata!$C$8*Indata!$H$29)^(K52-Indata!$K$29),IF(OR(Indata!$M$29="",Indata!$M$29=0),Indata!$J$29*1000000*(1+Indata!$C$8*Indata!$H$29)^(K52-Indata!$K$29),K63)))) -> 0 | ... AB126: =IF(Indata!$K$29="",0,IF(AB52<Indata!$K$29,0,IF(AB52<=Indata!$L$29,Indata!$J$29*1000000*(1+Indata!$C$8*Indata!$H$29)^(AB52-Indata!$K$29),IF(OR(Indata!$M$29="",Indata!$M$29=0),Indata!$J$29*1000000*(1+Indata!$C$8*Indata!$H$29)^(AB52-Indata!$K$29),AB63)))) -> 0
B127: Intäkt obj 5 (med 1 Mkr testhyra) | D127: =IF(Indata!$K$30="",0,IF(D52<Indata!$K$30,0,IF(D52<=Indata!$L$30,Indata!$J$30*1000000*(1+Indata!$C$8*Indata!$H$30)^(D52-Indata!$K$30),IF(OR(Indata!$M$30="",Indata!$M$30=0),Indata!$J$30*1000000*(1+Indata!$C$8*Indata!$H$30)^(D52-Indata!$K$30),D64)))) -> 0 | E127: =IF(Indata!$K$30="",0,IF(E52<Indata!$K$30,0,IF(E52<=Indata!$L$30,Indata!$J$30*1000000*(1+Indata!$C$8*Indata!$H$30)^(E52-Indata!$K$30),IF(OR(Indata!$M$30="",Indata!$M$30=0),Indata!$J$30*1000000*(1+Indata!$C$8*Indata!$H$30)^(E52-Indata!$K$30),E64)))) -> 0 | F127: =IF(Indata!$K$30="",0,IF(F52<Indata!$K$30,0,IF(F52<=Indata!$L$30,Indata!$J$30*1000000*(1+Indata!$C$8*Indata!$H$30)^(F52-Indata!$K$30),IF(OR(Indata!$M$30="",Indata!$M$30=0),Indata!$J$30*1000000*(1+Indata!$C$8*Indata!$H$30)^(F52-Indata!$K$30),F64)))) -> 0 | G127: =IF(Indata!$K$30="",0,IF(G52<Indata!$K$30,0,IF(G52<=Indata!$L$30,Indata!$J$30*1000000*(1+Indata!$C$8*Indata!$H$30)^(G52-Indata!$K$30),IF(OR(Indata!$M$30="",Indata!$M$30=0),Indata!$J$30*1000000*(1+Indata!$C$8*Indata!$H$30)^(G52-Indata!$K$30),G64)))) -> 0 | H127: =IF(Indata!$K$30="",0,IF(H52<Indata!$K$30,0,IF(H52<=Indata!$L$30,Indata!$J$30*1000000*(1+Indata!$C$8*Indata!$H$30)^(H52-Indata!$K$30),IF(OR(Indata!$M$30="",Indata!$M$30=0),Indata!$J$30*1000000*(1+Indata!$C$8*Indata!$H$30)^(H52-Indata!$K$30),H64)))) -> 0 | I127: =IF(Indata!$K$30="",0,IF(I52<Indata!$K$30,0,IF(I52<=Indata!$L$30,Indata!$J$30*1000000*(1+Indata!$C$8*Indata!$H$30)^(I52-Indata!$K$30),IF(OR(Indata!$M$30="",Indata!$M$30=0),Indata!$J$30*1000000*(1+Indata!$C$8*Indata!$H$30)^(I52-Indata!$K$30),I64)))) -> 0 | J127: =IF(Indata!$K$30="",0,IF(J52<Indata!$K$30,0,IF(J52<=Indata!$L$30,Indata!$J$30*1000000*(1+Indata!$C$8*Indata!$H$30)^(J52-Indata!$K$30),IF(OR(Indata!$M$30="",Indata!$M$30=0),Indata!$J$30*1000000*(1+Indata!$C$8*Indata!$H$30)^(J52-Indata!$K$30),J64)))) -> 0 | K127: =IF(Indata!$K$30="",0,IF(K52<Indata!$K$30,0,IF(K52<=Indata!$L$30,Indata!$J$30*1000000*(1+Indata!$C$8*Indata!$H$30)^(K52-Indata!$K$30),IF(OR(Indata!$M$30="",Indata!$M$30=0),Indata!$J$30*1000000*(1+Indata!$C$8*Indata!$H$30)^(K52-Indata!$K$30),K64)))) -> 0 | ... AB127: =IF(Indata!$K$30="",0,IF(AB52<Indata!$K$30,0,IF(AB52<=Indata!$L$30,Indata!$J$30*1000000*(1+Indata!$C$8*Indata!$H$30)^(AB52-Indata!$K$30),IF(OR(Indata!$M$30="",Indata!$M$30=0),Indata!$J$30*1000000*(1+Indata!$C$8*Indata!$H$30)^(AB52-Indata!$K$30),AB64)))) -> 0
B129: Bruttohyra (delta) | D129: =SUM(D123:D127) -> 1000000 | E129: =SUM(E123:E127) -> 1014000 | F129: =SUM(F123:F127) -> 1028196 | G129: =SUM(G123:G127) -> 1042590.7 | H129: =SUM(H123:H127) -> 1057187 | I129: =SUM(I123:I127) -> 1071987.6 | J129: =SUM(J123:J127) -> 1086995.5 | K129: =SUM(K123:K127) -> 1102213.4 | ... AB129: =SUM(AB123:AB127) -> 1396082
B130: Vakans (delta) | D130: =IF(AND(Indata!$L$26<>"",D52>Indata!$L$26),-D123*Indata!$N$26,0)+IF(AND(Indata!$L$27<>"",D52>Indata!$L$27),-D124*Indata!$N$27,0)+IF(AND(Indata!$L$28<>"",D52>Indata!$L$28),-D125*Indata!$N$28,0)+IF(AND(Indata!$L$29<>"",D52>Indata!$L$29),-D126*Indata!$N$29,0)+IF(AND(Indata!$L$30<>"",D52>Indata!$L$30),-D127*Indata!$N$30,0) -> 0 | E130: =IF(AND(Indata!$L$26<>"",E52>Indata!$L$26),-E123*Indata!$N$26,0)+IF(AND(Indata!$L$27<>"",E52>Indata!$L$27),-E124*Indata!$N$27,0)+IF(AND(Indata!$L$28<>"",E52>Indata!$L$28),-E125*Indata!$N$28,0)+IF(AND(Indata!$L$29<>"",E52>Indata!$L$29),-E126*Indata!$N$29,0)+IF(AND(Indata!$L$30<>"",E52>Indata!$L$30),-E127*Indata!$N$30,0) -> 0 | F130: =IF(AND(Indata!$L$26<>"",F52>Indata!$L$26),-F123*Indata!$N$26,0)+IF(AND(Indata!$L$27<>"",F52>Indata!$L$27),-F124*Indata!$N$27,0)+IF(AND(Indata!$L$28<>"",F52>Indata!$L$28),-F125*Indata!$N$28,0)+IF(AND(Indata!$L$29<>"",F52>Indata!$L$29),-F126*Indata!$N$29,0)+IF(AND(Indata!$L$30<>"",F52>Indata!$L$30),-F127*Indata!$N$30,0) -> 0 | G130: =IF(AND(Indata!$L$26<>"",G52>Indata!$L$26),-G123*Indata!$N$26,0)+IF(AND(Indata!$L$27<>"",G52>Indata!$L$27),-G124*Indata!$N$27,0)+IF(AND(Indata!$L$28<>"",G52>Indata!$L$28),-G125*Indata!$N$28,0)+IF(AND(Indata!$L$29<>"",G52>Indata!$L$29),-G126*Indata!$N$29,0)+IF(AND(Indata!$L$30<>"",G52>Indata!$L$30),-G127*Indata!$N$30,0) -> 0 | H130: =IF(AND(Indata!$L$26<>"",H52>Indata!$L$26),-H123*Indata!$N$26,0)+IF(AND(Indata!$L$27<>"",H52>Indata!$L$27),-H124*Indata!$N$27,0)+IF(AND(Indata!$L$28<>"",H52>Indata!$L$28),-H125*Indata!$N$28,0)+IF(AND(Indata!$L$29<>"",H52>Indata!$L$29),-H126*Indata!$N$29,0)+IF(AND(Indata!$L$30<>"",H52>Indata!$L$30),-H127*Indata!$N$30,0) -> 0 | I130: =IF(AND(Indata!$L$26<>"",I52>Indata!$L$26),-I123*Indata!$N$26,0)+IF(AND(Indata!$L$27<>"",I52>Indata!$L$27),-I124*Indata!$N$27,0)+IF(AND(Indata!$L$28<>"",I52>Indata!$L$28),-I125*Indata!$N$28,0)+IF(AND(Indata!$L$29<>"",I52>Indata!$L$29),-I126*Indata!$N$29,0)+IF(AND(Indata!$L$30<>"",I52>Indata!$L$30),-I127*Indata!$N$30,0) -> 0 | J130: =IF(AND(Indata!$L$26<>"",J52>Indata!$L$26),-J123*Indata!$N$26,0)+IF(AND(Indata!$L$27<>"",J52>Indata!$L$27),-J124*Indata!$N$27,0)+IF(AND(Indata!$L$28<>"",J52>Indata!$L$28),-J125*Indata!$N$28,0)+IF(AND(Indata!$L$29<>"",J52>Indata!$L$29),-J126*Indata!$N$29,0)+IF(AND(Indata!$L$30<>"",J52>Indata!$L$30),-J127*Indata!$N$30,0) -> 0 | K130: =IF(AND(Indata!$L$26<>"",K52>Indata!$L$26),-K123*Indata!$N$26,0)+IF(AND(Indata!$L$27<>"",K52>Indata!$L$27),-K124*Indata!$N$27,0)+IF(AND(Indata!$L$28<>"",K52>Indata!$L$28),-K125*Indata!$N$28,0)+IF(AND(Indata!$L$29<>"",K52>Indata!$L$29),-K126*Indata!$N$29,0)+IF(AND(Indata!$L$30<>"",K52>Indata!$L$30),-K127*Indata!$N$30,0) -> 0 | ... AB130: =IF(AND(Indata!$L$26<>"",AB52>Indata!$L$26),-AB123*Indata!$N$26,0)+IF(AND(Indata!$L$27<>"",AB52>Indata!$L$27),-AB124*Indata!$N$27,0)+IF(AND(Indata!$L$28<>"",AB52>Indata!$L$28),-AB125*Indata!$N$28,0)+IF(AND(Indata!$L$29<>"",AB52>Indata!$L$29),-AB126*Indata!$N$29,0)+IF(AND(Indata!$L$30<>"",AB52>Indata!$L$30),-AB127*Indata!$N$30,0) -> 0
B131: Nettohyra (delta) | D131: =D129+D130 -> 1000000 | E131: =E129+E130 -> 1014000 | F131: =F129+F130 -> 1028196 | G131: =G129+G130 -> 1042590.7 | H131: =H129+H130 -> 1057187 | I131: =I129+I130 -> 1071987.6 | J131: =J129+J130 -> 1086995.5 | K131: =K129+K130 -> 1102213.4 | ... AB131: =AB129+AB130 -> 1396082
B132: Driftnetto delta (efter drift, skatt, CA) | D132: =D131+D77+D79+D80+D83 -> -1400000 | E132: =E131+E77+E79+E80+E83 -> -1434000 | F132: =F131+F77+F79+F80+F83 -> -1468764 | G132: =G131+G77+G79+G80+G83 -> -1504308.5 | H132: =H131+H77+H79+H80+H83 -> -1540650.2 | I132: =I131+I77+I79+I80+I83 -> -1577806.3 | J132: =J131+J77+J79+J80+J83 -> -1615794.3 | K132: =K131+K77+K79+K80+K83 -> -1654632.2 | ... AB132: =AB131+AB77+AB79+AB80+AB83 -> -2464167.4
B133: Driftnetto exkl. re-inv (delta) | D133: =D132-D76 -> -1400000 | E133: =E132-E76 -> -1434000 | F133: =F132-F76 -> -1468764 | G133: =G132-G76 -> -1504308.5 | H133: =H132-H76 -> -1540650.2 | I133: =I132-I76 -> -1577806.3 | J133: =J132-J76 -> -1615794.3 | K133: =K132-K76 -> -1654632.2 | ... AB133: =AB132-AB76 -> -2464167.4
B134: PV per år (delta, C7) | D134: =IF(D54=0,0,D132/(1+Indata!$C$7)^D53) -> -1346153.8 | E134: =IF(E54=0,0,E132/(1+Indata!$C$7)^E53) -> -1325813.6 | F134: =IF(F54=0,0,F132/(1+Indata!$C$7)^F53) -> -1305725.8 | G134: =IF(G54=0,0,G132/(1+Indata!$C$7)^G53) -> -1285889.2 | H134: =IF(H54=0,0,H132/(1+Indata!$C$7)^H53) -> -1266302.1 | I134: =IF(I54=0,0,I132/(1+Indata!$C$7)^I53) -> -1246963.2 | J134: =IF(J54=0,0,J132/(1+Indata!$C$7)^J53) -> -1227870.9 | K134: =IF(K54=0,0,K132/(1+Indata!$C$7)^K53) -> -1209023.5 | ... AB134: =IF(AB54=0,0,AB132/(1+Indata!$C$7)^AB53) -> 0
B136: PV Driftnetto (delta) | C136: =ROUND(SUMIFS(D134:AB134,D54:AB54,1)/10000,0)*10000 -> -23340000
B137: Restvärde (delta) | C137: =ROUND(INDEX(D133:AB133,MATCH(Indata!C16+1,D53:AB53,0))/Indata!C6/10000,0)*10000 -> -44910000
B138: PV Restvärde (delta) | C138: =ROUND(C137/(1+Indata!C9)^Indata!C16/10000,0)*10000 -> -11610000
B139: NPV vid 1 Mkr hyra | C139: =C136+C138+C118 -> -234950000
B140: b_NPV (ΔNPV per kr hyra) | C140: =(C139-C119)/1000000 -> 22.1
B164: BLOCK D — EK-kassaflöde vid årshyra = 0 (IRR-kravet, bas)
B166: EBITA (vid 0 hyra) | D166: =D82 -> -2400000 | E166: =E82 -> -2448000 | F166: =F82 -> -2496960 | G166: =G82 -> -2546899.2 | H166: =H82 -> -2597837.2 | I166: =I82 -> -2649793.9 | J166: =J82 -> -2702789.8 | K166: =K82 -> -2756845.6 | ... AB166: =AB82 -> -3860249.4
B167: Resultat efter finans (vid 0 hyra) | D167: =D166+Finansiering!D18+Finansiering!D15 -> -10708726 | E167: =E166+Finansiering!E18+Finansiering!E15 -> -10782833 | F167: =F166+Finansiering!F18+Finansiering!F15 -> -10855957 | G167: =G166+Finansiering!G18+Finansiering!G15 -> -10928184 | H167: =H166+Finansiering!H18+Finansiering!H15 -> -10999598 | I167: =I166+Finansiering!I18+Finansiering!I15 -> -11070284 | J167: =J166+Finansiering!J18+Finansiering!J15 -> -11140324 | K167: =K166+Finansiering!K18+Finansiering!K15 -> -11209797 | ... AB167: =AB166+Finansiering!AB18+Finansiering!AB15 -> -5646505
B168: Bolagsskatt (vid 0 hyra) | D168: =IF(D167<=0,0,-D167*Indata!$C$10) -> 0 | E168: =IF(E167<=0,0,-E167*Indata!$C$10) -> 0 | F168: =IF(F167<=0,0,-F167*Indata!$C$10) -> 0 | G168: =IF(G167<=0,0,-G167*Indata!$C$10) -> 0 | H168: =IF(H167<=0,0,-H167*Indata!$C$10) -> 0 | I168: =IF(I167<=0,0,-I167*Indata!$C$10) -> 0 | J168: =IF(J167<=0,0,-J167*Indata!$C$10) -> 0 | K168: =IF(K167<=0,0,-K167*Indata!$C$10) -> 0 | ... AB168: =IF(AB167<=0,0,-AB167*Indata!$C$10) -> 0
B169: Resultat efter skatt (vid 0 hyra) | D169: =D167+D168 -> -10708726 | E169: =E167+E168 -> -10782833 | F169: =F167+F168 -> -10855957 | G169: =G167+G168 -> -10928184 | H169: =H167+H168 -> -10999598 | I169: =I167+I168 -> -11070284 | J169: =J167+J168 -> -11140324 | K169: =K167+K168 -> -11209797 | ... AB169: =AB167+AB168 -> -5646505
B171: Cashflow EK (vid 0 hyra) | D171: =D169-Finansiering!D18+Finansiering!D17+Finansiering!D12 -> -132128120 | E171: =E169-Finansiering!E18+Finansiering!E17+Finansiering!E12 -> -6172627.2 | F171: =F169-Finansiering!F18+Finansiering!F17+Finansiering!F12 -> -6216742.9 | G171: =G169-Finansiering!G18+Finansiering!G17+Finansiering!G12 -> -6260541.7 | H171: =H169-Finansiering!H18+Finansiering!H17+Finansiering!H12 -> -6304096.9 | I171: =I169-Finansiering!I18+Finansiering!I17+Finansiering!I12 -> -6347480.8 | J171: =J169-Finansiering!J18+Finansiering!J17+Finansiering!J12 -> -6390764.2 | K171: =K169-Finansiering!K18+Finansiering!K17+Finansiering!K12 -> -6434017 | ... AB171: =AB169-Finansiering!AB18+Finansiering!AB17+Finansiering!AB12 -> -6557859.9
B172: Exit-värde (marknadsvärde − skuld) | D172: =IF(D53<>Indata!$C$16,0,IFERROR(INDEX(D82:AB82,MATCH(D52+1,D52:AB52,0))/Indata!$C$6,0)-Finansiering!D13) -> 0 | E172: =IF(E53<>Indata!$C$16,0,IFERROR(INDEX(D82:AB82,MATCH(E52+1,D52:AB52,0))/Indata!$C$6,0)-Finansiering!E13) -> 0 | F172: =IF(F53<>Indata!$C$16,0,IFERROR(INDEX(D82:AB82,MATCH(F52+1,D52:AB52,0))/Indata!$C$6,0)-Finansiering!F13) -> 0 | G172: =IF(G53<>Indata!$C$16,0,IFERROR(INDEX(D82:AB82,MATCH(G52+1,D52:AB52,0))/Indata!$C$6,0)-Finansiering!G13) -> 0 | H172: =IF(H53<>Indata!$C$16,0,IFERROR(INDEX(D82:AB82,MATCH(H52+1,D52:AB52,0))/Indata!$C$6,0)-Finansiering!H13) -> 0 | I172: =IF(I53<>Indata!$C$16,0,IFERROR(INDEX(D82:AB82,MATCH(I52+1,D52:AB52,0))/Indata!$C$6,0)-Finansiering!I13) -> 0 | J172: =IF(J53<>Indata!$C$16,0,IFERROR(INDEX(D82:AB82,MATCH(J52+1,D52:AB52,0))/Indata!$C$6,0)-Finansiering!J13) -> 0 | K172: =IF(K53<>Indata!$C$16,0,IFERROR(INDEX(D82:AB82,MATCH(K52+1,D52:AB52,0))/Indata!$C$6,0)-Finansiering!K13) -> 0 | L172: =IF(L53<>Indata!$C$16,0,IFERROR(INDEX(D82:AB82,MATCH(L52+1,D52:AB52,0))/Indata!$C$6,0)-Finansiering!L13) -> 0 | M172: =IF(M53<>Indata!$C$16,0,IFERROR(INDEX(D82:AB82,MATCH(M52+1,D52:AB52,0))/Indata!$C$6,0)-Finansiering!M13) -> 0 | N172: =IF(N53<>Indata!$C$16,0,IFERROR(INDEX(D82:AB82,MATCH(N52+1,D52:AB52,0))/Indata!$C$6,0)-Finansiering!N13) -> 0 | O172: =IF(O53<>Indata!$C$16,0,IFERROR(INDEX(D82:AB82,MATCH(O52+1,D52:AB52,0))/Indata!$C$6,0)-Finansiering!O13) -> 0 | P172: =IF(P53<>Indata!$C$16,0,IFERROR(INDEX(D82:AB82,MATCH(P52+1,D52:AB52,0))/Indata!$C$6,0)-Finansiering!P13) -> 0 | Q172: =IF(Q53<>Indata!$C$16,0,IFERROR(INDEX(D82:AB82,MATCH(Q52+1,D52:AB52,0))/Indata!$C$6,0)-Finansiering!Q13) -> 0 | R172: =IF(R53<>Indata!$C$16,0,IFERROR(INDEX(D82:AB82,MATCH(R52+1,D52:AB52,0))/Indata!$C$6,0)-Finansiering!R13) -> 0 | S172: =IF(S53<>Indata!$C$16,0,IFERROR(INDEX(D82:AB82,MATCH(S52+1,D52:AB52,0))/Indata!$C$6,0)-Finansiering!S13) -> 0 | T172: =IF(T53<>Indata!$C$16,0,IFERROR(INDEX(D82:AB82,MATCH(T52+1,D52:AB52,0))/Indata!$C$6,0)-Finansiering!T13) -> 0 | U172: =IF(U53<>Indata!$C$16,0,IFERROR(INDEX(D82:AB82,MATCH(U52+1,D52:AB52,0))/Indata!$C$6,0)-Finansiering!U13) -> 0 | V172: =IF(V53<>Indata!$C$16,0,IFERROR(INDEX(D82:AB82,MATCH(V52+1,D52:AB52,0))/Indata!$C$6,0)-Finansiering!V13) -> 0 | W172: =IF(W53<>Indata!$C$16,0,IFERROR(INDEX(D82:AB82,MATCH(W52+1,D52:AB52,0))/Indata!$C$6,0)-Finansiering!W13) -> -1.2072846e+08 | X172: =IF(X53<>Indata!$C$16,0,IFERROR(INDEX(D82:AB82,MATCH(X52+1,D52:AB52,0))/Indata!$C$6,0)-Finansiering!X13) -> 0 | Y172: =IF(Y53<>Indata!$C$16,0,IFERROR(INDEX(D82:AB82,MATCH(Y52+1,D52:AB52,0))/Indata!$C$6,0)-Finansiering!Y13) -> 0 | Z172: =IF(Z53<>Indata!$C$16,0,IFERROR(INDEX(D82:AB82,MATCH(Z52+1,D52:AB52,0))/Indata!$C$6,0)-Finansiering!Z13) -> 0 | AA172: =IF(AA53<>Indata!$C$16,0,IFERROR(INDEX(D82:AB82,MATCH(AA52+1,D52:AB52,0))/Indata!$C$6,0)-Finansiering!AA13) -> 0 | AB172: =IF(AB53<>Indata!$C$16,0,IFERROR(INDEX(D82:AB82,MATCH(AB52+1,D52:AB52,0))/Indata!$C$6,0)-Finansiering!AB13) -> 0
B173: Total cashflow EK (vid 0 hyra) | D173: =D171+D172 -> -132128120 | E173: =E171+E172 -> -6172627.2 | F173: =F171+F172 -> -6216742.9 | G173: =G171+G172 -> -6260541.7 | H173: =H171+H172 -> -6304096.9 | I173: =I171+I172 -> -6347480.8 | J173: =J171+J172 -> -6390764.2 | K173: =K171+K172 -> -6434017 | ... AB173: =AB171+AB172 -> -6557859.9
B175: PV EK-cashflow vid avkastningskrav (vid 0) | D175: =IF(D54=0,0,D173/(1+Indata!$C$65)^D53) -> -1.2429738e+08 | E175: =IF(E54=0,0,E173/(1+Indata!$C$65)^E53) -> -5462651.8 | F175: =IF(F54=0,0,F173/(1+Indata!$C$65)^F53) -> -5175628.7 | G175: =IF(G54=0,0,G173/(1+Indata!$C$65)^G53) -> -4903191.5 | H175: =IF(H54=0,0,H173/(1+Indata!$C$65)^H53) -> -4644688.1 | I175: =IF(I54=0,0,I173/(1+Indata!$C$65)^I53) -> -4399484.7 | J175: =IF(J54=0,0,J173/(1+Indata!$C$65)^J53) -> -4166965.9 | K175: =IF(K54=0,0,K173/(1+Indata!$C$65)^K53) -> -3946536.2 | ... AB175: =IF(AB54=0,0,AB173/(1+Indata!$C$65)^AB53) -> 0
B177: NPV EK vid 0 hyra (för IRR-kravet) | C177: =SUMIFS(D175:AB175,D54:AB54,1) -> -2.2536958e+08
B179: BLOCK E — EK-kassaflöde vid årshyra = 1 Mkr (IRR-kravet, delta)
B181: EBITA (vid 1 Mkr hyra) | D181: =D132 -> -1400000 | E181: =E132 -> -1434000 | F181: =F132 -> -1468764 | G181: =G132 -> -1504308.5 | H181: =H132 -> -1540650.2 | I181: =I132 -> -1577806.3 | J181: =J132 -> -1615794.3 | K181: =K132 -> -1654632.2 | ... AB181: =AB132 -> -2464167.4
B182: Resultat efter finans (vid 1 Mkr hyra) | D182: =D181+Finansiering!D18+Finansiering!D15 -> -9708726.1 | E182: =E181+Finansiering!E18+Finansiering!E15 -> -9768833.3 | F182: =F181+Finansiering!F18+Finansiering!F15 -> -9827760.9 | G182: =G181+Finansiering!G18+Finansiering!G15 -> -9885592.8 | H182: =H181+Finansiering!H18+Finansiering!H15 -> -9942411.1 | I182: =I181+Finansiering!I18+Finansiering!I15 -> -9998296.5 | J182: =J181+Finansiering!J18+Finansiering!J15 -> -10053328 | K182: =K181+Finansiering!K18+Finansiering!K15 -> -10107584 | ... AB182: =AB181+Finansiering!AB18+Finansiering!AB15 -> -4250423
B183: Bolagsskatt (vid 1 Mkr hyra) | D183: =IF(D182<=0,0,-D182*Indata!$C$10) -> 0 | E183: =IF(E182<=0,0,-E182*Indata!$C$10) -> 0 | F183: =IF(F182<=0,0,-F182*Indata!$C$10) -> 0 | G183: =IF(G182<=0,0,-G182*Indata!$C$10) -> 0 | H183: =IF(H182<=0,0,-H182*Indata!$C$10) -> 0 | I183: =IF(I182<=0,0,-I182*Indata!$C$10) -> 0 | J183: =IF(J182<=0,0,-J182*Indata!$C$10) -> 0 | K183: =IF(K182<=0,0,-K182*Indata!$C$10) -> 0 | ... AB183: =IF(AB182<=0,0,-AB182*Indata!$C$10) -> 0
B184: Resultat efter skatt (vid 1 Mkr hyra) | D184: =D182+D183 -> -9708726.1 | E184: =E182+E183 -> -9768833.3 | F184: =F182+F183 -> -9827760.9 | G184: =G182+G183 -> -9885592.8 | H184: =H182+H183 -> -9942411.1 | I184: =I182+I183 -> -9998296.5 | J184: =J182+J183 -> -10053328 | K184: =K182+K183 -> -10107584 | ... AB184: =AB182+AB183 -> -4250423
B186: Cashflow EK (vid 1 Mkr hyra) | D186: =D184-Finansiering!D18+Finansiering!D17+Finansiering!D12 -> -131128120 | E186: =E184-Finansiering!E18+Finansiering!E17+Finansiering!E12 -> -5158627.2 | F186: =F184-Finansiering!F18+Finansiering!F17+Finansiering!F12 -> -5188546.9 | G186: =G184-Finansiering!G18+Finansiering!G17+Finansiering!G12 -> -5217950.9 | H186: =H184-Finansiering!H18+Finansiering!H17+Finansiering!H12 -> -5246909.9 | I186: =I184-Finansiering!I18+Finansiering!I17+Finansiering!I12 -> -5275493.2 | J186: =J184-Finansiering!J18+Finansiering!J17+Finansiering!J12 -> -5303768.8 | K186: =K184-Finansiering!K18+Finansiering!K17+Finansiering!K12 -> -5331803.6 | ... AB186: =AB184-Finansiering!AB18+Finansiering!AB17+Finansiering!AB12 -> -5161777.9
...

Sheet Dokumentation
B1: DOKUMENTATION — Investeringskalkyl version 7
B2: April 2026. Ersätter LM 371.
B4: 1. Syfte
B5: Mallen beräknar lönsamhetsgränsen (kravhyran) för investeringar i Lejonfastigheters fastigheter. Kravhyran är den lägsta årshyra som uppfyller alla tre lönsamhetskrav samtidigt. Hyresspannet (±10% på investeringen) blir ett intervall som skrivs in i avtalet.
B7: 2. Grundprincip: en kalkyl = en hyresgäst = en verksamhet
B8: Mallen är byggd för EN hyresgäst och EN verksamhetstyp per fil. Vid projekt med flera hyresgäster (t.ex. vårdboende + förskola i samma hus) ska en separat kalkyl göras per hyresgäst. Gemensamma investeringar fördelas manuellt enligt BRA eller BTA innan beloppen matas in i respektive kalkyl.
B10: 3. Tre lönsamhetskrav
B12: Kravhyran beräknas så att alla tre följande krav uppfylls simultant:
B14: KRAV 1 — NPV ≥ 0
B15: Projektets nuvärde över kalkylperioden, diskonterat till kalkylräntan för driftnetto (Indata C7), ska vara minst 0.
B16: Formel: NPV = Σ(driftnetto/(1+kalkylränta)^år) + PV restvärde + PV investering
B17: Rad på Kassaflöde: C70 (NPV vid 0 hyra), C91 (känslighet), Resultat D10 (kravhyra NPV)
... B169: Reinvesteringsbehov hanteras explicit via Indata sektion 5 (re-investering / hyresatt UH), där användaren matar in faktiskt förväntat behov. Detta är den ekonomiskt korrekta platsen att hantera skick-relaterade kostnader.
