Workbook
Name BefFastighetsskötsel: '2. Kalkyldata'!$G$34
Name BefMedia: '2. Kalkyldata'!$G$37
Name BefPlaneratunderhåll: '2. Kalkyldata'!$G$36
Name BefReparationer: '2. Kalkyldata'!$G$35
Name BefÖvrigaförvaltningskostnader: '2. Kalkyldata'!$G$38
Name FemtonÅrFastighetsskötsel: '2. Kalkyldata'!$M$34
Name FemtonÅrMedia: '2. Kalkyldata'!$M$37
Name FemtonÅrPlaneratUnderhåll: '2. Kalkyldata'!$M$36
Name FemtonÅrReparationer: '2. Kalkyldata'!$M$35
Name FemtonÅrÖvrigaFörvaltningskostnader: '2. Kalkyldata'!$M$38
Name Höjnin1: '2. Kalkyldata'!$L$33
Name Höjning2: '2. Kalkyldata'!$M$33
Name Inflation: '2. Kalkyldata'!$M$9
Name NybFastighetsskötsel: '2. Kalkyldata'!$H$34
Name NybMedia: '2. Kalkyldata'!$H$37
Name NybPlaneratunderhåll: '2. Kalkyldata'!$H$36
Name NybReparationer: '2. Kalkyldata'!$H$35
Name NybÖvrigaförvaltningskostnader: '2. Kalkyldata'!$H$38
Name TioÅrFastighetsskötsel: '2. Kalkyldata'!$L$34
Name TioÅrMedia: '2. Kalkyldata'!$L$37
Name TioÅrPlaneratUnderhåll: '2. Kalkyldata'!$L$36
Name TioÅrReparationer: '2. Kalkyldata'!$L$35
Name TioÅrÖvrigaFörvaltningskostnader: '2. Kalkyldata'!$L$38

Sheet 1. Framskrivningsunderlag
J1: 1. Gamla Hjälptabeller Tryck på + -tecknen för att visa
B2: Investeringskalkyl, framskrivningsunderlag | R2: 2. Uppdateringshistorik Tryck på + -tecknen för att visa
B3: Projektnamn
B4: Kalkyl utförd av: | G4: Fyll i
B5: Fastighet: | G5: Fyll i | S5: Utförd av
B6: Objekt: | G6: Fyll i | K6: ='2. Kalkyldata'!$G$6 -> Fyll i | R6: 1. Möjliggjort redigering i fält som måste fyllas i - utan att ta bort bladets skydd
B7: Projektnummer: | G7: Fyll i | R7: 3. Avsevärt förenklat ifyllnaden i första bladet | S7: JW
B8: Fastighetsarea (markareal): | G8: Fyll i | K8: ='2. Kalkyldata'!$J$6 -> Fyll i | R8: 4. Flik 2: Lagt till indikation om vilka fält som är tvingande | S8: JW
B9: Area (BRA): | G9: Fyll i | K9: ='2. Kalkyldata'!$I$6 -> Fyll i | R9: 5. Flik 2: Lagt till notifikationer om t.ex. driftkostnader ej är angivna, eller om kalkylperiod inte matchar med avtalsperiod mm | S9: JW
B10: Area (BTA): | G10: Fyll i | R10: 6. Flik 4: Justerat så att indexpåslag på hyran endast utgår från året efter avtalet börjar gälla. Förut beräknades indexpåslag från Kalkylstart, även om avtalet började gälla i framtiden. På detta vis kan vi lättare lägga in "etappvisa" tillträden till lokaler utan att det blir stökigt i utfallet för hyran. | S10: JW
B11: Typ av projekt: | G11: Fyll i
B12: Momsregistreringsgrad före: | G12: Fyll i
B13: Momsregistreringsgrad efter: | G13: Fyll i | R13: 7. Lagt till indexuppräkning på "Central administration" | S13: JW
B15: Projektbeskrivning | K15: kvm | L15: BRA/plats | M15: Inv belopp | N15: kr/kvm | O15: Inv belopp per plats | P15: Antal platser | R15: 8. Lagt till indikation på flik 2. om eget antagande om restvärde fyllts i på flik 5. IRR. | S15: JW
B16: Åtgärder | E16: kvm (BRA) | F16: Investering | G16: kr/kvm | R16: 9. Tagit bort funktionen som uppräknar projektbudgeten med avseende på inflation om den sker i framtiden. Detta får vi själva ta hänsyn till när vi upprättar projektbudgeten. | S16: JW
B17: ='Kontoplan RR'!E6 -> Befintligt | E17: =SUMIF('2. Kalkyldata'!$E$23:$E$27,LEFT('1. Framskrivningsunderlag'!$B17,3),'2. Kalkyldata'!$H$23:$H$28) -> 0 | F17: =SUMIF('2. Kalkyldata'!$E$23:$E$27,LEFT('1. Framskrivningsunderlag'!$B17,3),'2. Kalkyldata'!$W$23:$W$28) -> 0 | G17: =IFERROR($M17/E17,0) -> 0 | K17: =SUMIF('2. Kalkyldata'!$E$23:$E$27,LEFT('1. Framskrivningsunderlag'!$B17,3),'2. Kalkyldata'!$H$23:$H$28) -> 0 | L17: =IFERROR($K17/$P17,0) -> 0 | M17: =SUMIF('2. Kalkyldata'!$E$23:$E$27,LEFT('1. Framskrivningsunderlag'!$B17,3),'2. Kalkyldata'!$W$23:$W$28) -> 0 | N17: =IFERROR($M17/$K17,0) -> 0 | O17: =IFERROR($E17/$P17,0) -> 0 | P17: =SUMIF('2. Kalkyldata'!$E$23:$E$27,LEFT('1. Framskrivningsunderlag'!$B17,3),'2. Kalkyldata'!$D$23:$D$28) -> 0
B18: ='Kontoplan RR'!E7 -> Ombyggnad | E18: =SUMIF('2. Kalkyldata'!$E$23:$E$27,LEFT('1. Framskrivningsunderlag'!$B18,3),'2. Kalkyldata'!$H$23:$H$28) -> 0 | F18: =SUMIF('2. Kalkyldata'!$E$23:$E$27,LEFT('1. Framskrivningsunderlag'!$B18,3),'2. Kalkyldata'!$W$23:$W$28) -> 0 | G18: =IFERROR($M18/E18,0) -> 0 | K18: =SUMIF('2. Kalkyldata'!$E$23:$E$27,LEFT('1. Framskrivningsunderlag'!$B18,3),'2. Kalkyldata'!$H$23:$H$28) -> 0 | L18: =IFERROR($K18/$P18,0) -> 0 | M18: =SUMIF('2. Kalkyldata'!$E$23:$E$27,LEFT('1. Framskrivningsunderlag'!$B18,3),'2. Kalkyldata'!$W$23:$W$28) -> 0 | N18: =IFERROR($M18/$K18,0) -> 0 | O18: =IFERROR($E18/$P18,0) -> 0 | P18: =SUMIF('2. Kalkyldata'!$E$23:$E$27,LEFT('1. Framskrivningsunderlag'!$B18,3),'2. Kalkyldata'!$D$23:$D$28) -> 0 | R18: 10. Dolt flikarna "6. Ack. Kapitalutlägg" och "7. Diagram" då funktionerna och nyckeltalen inte efterfrågas. Vid behov högerklicka på valfri flik och välj "Ta fram" | S18: JW
B19: ='Kontoplan RR'!E8 -> Nybyggnad | E19: =SUMIF('2. Kalkyldata'!$E$23:$E$27,LEFT('1. Framskrivningsunderlag'!$B19,3),'2. Kalkyldata'!$H$23:$H$28) -> 6100 | F19: =SUMIF('2. Kalkyldata'!$E$23:$E$27,LEFT('1. Framskrivningsunderlag'!$B19,3),'2. Kalkyldata'!$W$23:$W$28) -> 2.4e+08 | G19: =IFERROR($M19/E19,0) -> 39344.262 | K19: =SUMIF('2. Kalkyldata'!$E$23:$E$27,LEFT('1. Framskrivningsunderlag'!$B19,3),'2. Kalkyldata'!$H$23:$H$28) -> 6100 | L19: =IFERROR($K19/$P19,0) -> 0 | M19: =SUMIF('2. Kalkyldata'!$E$23:$E$27,LEFT('1. Framskrivningsunderlag'!$B19,3),'2. Kalkyldata'!$W$23:$W$28) -> 2.4e+08 | N19: =IFERROR($M19/$K19,0) -> 39344.262 | O19: =IFERROR($E19/$P19,0) -> 0 | P19: =SUMIF('2. Kalkyldata'!$E$23:$E$27,LEFT('1. Framskrivningsunderlag'!$B19,3),'2. Kalkyldata'!$D$23:$D$28) -> 0 | R19: 11. 2023-02-15 Justering av rubriker under "Projektbeskrivning" (borttagning av två kolumner: "Investering per plats" samt "BRA / plats" | S19: JW
B20: ='Kontoplan RR'!E9 -> Installationer | E20: =SUMIF('2. Kalkyldata'!$E$23:$E$27,LEFT('1. Framskrivningsunderlag'!$B20,3),'2. Kalkyldata'!$H$23:$H$28) -> 0 | F20: =SUMIF('2. Kalkyldata'!$E$23:$E$27,LEFT('1. Framskrivningsunderlag'!$B20,3),'2. Kalkyldata'!$W$23:$W$28) -> 0 | G20: =IFERROR($M20/E20,0) -> 0 | K20: =SUMIF('2. Kalkyldata'!$E$23:$E$27,LEFT('1. Framskrivningsunderlag'!$B20,3),'2. Kalkyldata'!$H$23:$H$28) -> 0 | L20: =IFERROR($K20/$P20,0) -> 0 | M20: =SUMIF('2. Kalkyldata'!$E$23:$E$27,LEFT('1. Framskrivningsunderlag'!$B20,3),'2. Kalkyldata'!$W$23:$W$28) -> 0 | N20: =IFERROR($M20/$K20,0) -> 0 | O20: =IFERROR($E20/$P20,0) -> 0 | P20: =SUMIF('2. Kalkyldata'!$E$23:$E$27,LEFT('1. Framskrivningsunderlag'!$B20,3),'2. Kalkyldata'!$D$23:$D$28) -> 0 | R20: 12. Bytt ut driftkostnadsposterna och döpt dem efter hur Lejonfastigheter är vana att fördela dem. | S20: JW
B21: ='Kontoplan RR'!E10 -> Mark | E21: =SUMIF('2. Kalkyldata'!$E$23:$E$27,LEFT('1. Framskrivningsunderlag'!$B21,3),'2. Kalkyldata'!$H$23:$H$28) -> 0 | F21: =SUMIF('2. Kalkyldata'!$E$23:$E$27,LEFT('1. Framskrivningsunderlag'!$B21,3),'2. Kalkyldata'!$W$23:$W$28) -> 0 | G21: =IFERROR($M21/E21,0) -> 0 | K21: =SUMIF('2. Kalkyldata'!$E$23:$E$27,LEFT('1. Framskrivningsunderlag'!$B21,3),'2. Kalkyldata'!$H$23:$H$28) -> 0 | L21: =IFERROR($K21/$P21,0) -> 0 | M21: =SUMIF('2. Kalkyldata'!$E$23:$E$27,LEFT('1. Framskrivningsunderlag'!$B21,3),'2. Kalkyldata'!$W$23:$W$28) -> 0 | N21: =IFERROR($M21/$K21,0) -> 0 | O21: =IFERROR($E21/$P21,0) -> 0 | P21: =SUMIF('2. Kalkyldata'!$E$23:$E$27,LEFT('1. Framskrivningsunderlag'!$B21,3),'2. Kalkyldata'!$D$23:$D$28) -> 0 | R21: 13. Börjat lägga till kommentarer av karaktären "Lathund". | S21: JW
B22: Summa investering | E22: =SUM(E17:E21) -> 6100 | F22: =SUM(F17:F21) -> 2.4e+08 | G22: =IFERROR($M22/D22,0) -> 0 | K22: =SUM(K17:K21) -> 6100 | L22: =IFERROR($K22/$P22,0) -> 0 | M22: =SUM(M17:M21) -> 2.4e+08 | N22: =IFERROR($M22/$K22,0) -> 39344.262 | O22: =IFERROR($E22/$P22,0) -> 0 | P22: =SUM(P17:P21) -> 0 | R22: 14. Justerat benämning av "Ränta" under 3.Finansiering" till Byggnadskreditiv, då vi inte har annan ränta att härleda | S22: JW
B23: Därutöver re-investeringar/hyressatt underhåll | F23: =IFERROR('2. Kalkyldata'!$X$39/'2. Kalkyldata'!$H$28,0) -> 0 | M23: ='2. Kalkyldata'!$X$39 -> 0 | R23: 15. Diverse malljusteringar 2024 | S23: JW
B24: Därutöver planerat underhåll | F24: 0 | R24: 16. 2026-09-30 v3: Restvärde = rent marknadsvärde vid justerad direktavkastning (flik 2 sektion 5, vikter 0/1/0 på flik 5). Bef-objekt = nollalternativ: krav 1–2 på tillkommande flöde (flik 4 rad 64–82), krav 3 på hela fastigheten, egen avskrivningstid för befintligt bokfört värde. Investeringsspecifikation som matris (sektion 4) styr Budget kr/kvm. Känslighet restvärde ±1,00 pp (flik 5 rad 53–61, flik 1). Kravhyra som output (flik 2 rad 17 / kolumn V, datatabell AC14:AI16). | S24: Claude/JW
B25: Total projektvolym | F25: =F22+F23+F24 -> 2.4e+08 | N25: ='2. Kalkyldata'!$X$39/'2. Kalkyldata'!$H$28 -> 0 | R25: 17. 2026-10-09 v3.1: Ett restvärde i alla krav (flik 4 rad 84–90: driftnetto år N+1, fullt uthyrt, exkl extraordinärt UH, / justerad yield). Kalkylränta restvärde = extern yield + inflation. Vakansfaktorn egen skala −0,25…+2,00 pp med ekvivalent vakans. Vakansgrad bara år efter avtal inom kalkylperioden (spärr + notis). Extraordinärt UH t.o.m. horisonten. | S25: Claude/JW
R26: 18. 2026-10-11 v3.2: Användarvänlighet och design efter agentgranskning — inmatningsmeddelanden på alla inmatningsfält, krav 1/2/3 namngivna överallt, två decimaler på räntor/IRR, stavfel och engelska rester rättade, arbetsgång på flik 2, källhänvisningar mellan flikar, hjälprader dolda, utskrift (sidbrytning flik 1, årsrubrik och sidordning flik 4), sidfot v3.2. Inga beräkningar ändrade. | S26: Claude/JW
B27: Projektbeskrivning:
B28: Fyll i
B35: Bild – klistra in här | E35: Karta – klistra in här
B54: Marknadssituation
B55: Marknadsvärde (senaste fastighetsvärdering) | G55: 0
B57: Kommentar marknadssituation och restvärde: | K57: Byggrätter | O57: Före projekt | P57: Efter projekt
B58: Hur har restvärdet bedömts (direktavkastning, kalkylränta)? Har värderaren tagit hänsyn till kommande investeringar för att upprätthålla hyresnivån? Vad händer med marknadsvärdet om vi inte investerar? Kommentera sannolikt scenario, t.ex. sjukt hus, tekniskt utdömt eller vakanser. Är byggrätterna optimerade? Förändras momsregistreringsgraden? | K58: Utnyttjade byggrätter | O58: 0 | P58: 0
K59: Outnyttjade byggrätter | O59: 0 | P59: 0
K60: Summa | O60: =SUM(O58:O59) -> 0 | P60: =SUM(P58:P59) -> 0
B65: ="Restvärdesbedömning — direktavkastning vid exit "&ROUND('2. Kalkyldata'!$M$11*100,2)&" % (marknad "&ROUND('2. Kalkyldata'!$M$6*100,2)&" % "&IF('2. Kalkyldata'!$M$10>=0,"+","")&ROUND('2. Kalkyldata'!$M$10*100,2)&" pp)" -> Restvärdesbedömning — direktavkastning vid exit 6,5 % (marknad 6,5 % +0 pp)
B66: Scenario | C66: Direktavk. | D66: IRR före skatt | E66: Restvärde (exit) | F66: Kravhyra, kr/kvm | G66: NPV tillkommande
B67: ='5. IRR'!B55 -> Optimistisk (−1,00 pp) | C67: ='5. IRR'!C55 -> 0.055 | D67: ='5. IRR'!E55 -> 0.087247261 | E67: ='5. IRR'!D55 -> 3.2138364e+08 | F67: ='5. IRR'!H55 -> 2480 | G67: ='5. IRR'!F55 -> 19970000
B68: ='5. IRR'!B56 -> Bedömt (2. Kalkyldata sektion 5) | C68: ='5. IRR'!C56 -> 0.065 | D68: ='5. IRR'!E56 -> 0.080803743 | E68: ='5. IRR'!D56 -> 271940000 | F68: ='5. IRR'!H56 -> 2559 | G68: ='5. IRR'!F56 -> 10300000
B69: ='5. IRR'!B57 -> Pessimistisk (+1,00 pp) | C69: ='5. IRR'!C57 -> 0.075 | D69: ='5. IRR'!E57 -> 0.075506366 | E69: ='5. IRR'!D57 -> 2.3568133e+08 | F69: ='5. IRR'!H57 -> 2621 | G69: ='5. IRR'!F57 -> 3200000
B71: Känslighet: direktavkastningen vid exit ±1,00 pp. Raden Bedömt är kalkylens restvärde (4. NPV rad 84–90).
B72: Kalkylantaganden | E72: Hämtas från 2. Kalkyldata
B73: Kalkylperiod | G73: ='2. Kalkyldata'!$P17 -> 20 | K73: ='2. Kalkyldata'!$P17 -> 20
B74: Avskrivningstid | G74: ='2. Kalkyldata'!$P16 -> 33 | K74: ='2. Kalkyldata'!$P16 -> 33
B75: Justerad direktavkastning (restvärde) | G75: ='2. Kalkyldata'!$M$11 -> 0.065 | K75: ='2. Kalkyldata'!$M$11 -> 0.065
B76: Kalkylränta för driftnetto | G76: ='2. Kalkyldata'!$M7 -> 0.0455 | K76: ='2. Kalkyldata'!$M7 -> 0.0455
B77: Kalkylränta för restvärde | G77: ='2. Kalkyldata'!$M8 -> 0.085 | K77: ='2. Kalkyldata'!$M8 -> 0.085
B78: Inflation | G78: ='2. Kalkyldata'!$M9 -> 0.02 | K78: ='2. Kalkyldata'!$M9 -> 0.02
B80: Hyresvärde år 1, befintligt (inkl. ombyggnad) | G80: ='2. Kalkyldata'!$L$28-SUMIF('2. Kalkyldata'!$E$23:$E$27,"nyb",'2. Kalkyldata'!$L$23:$L$27) -> 0 | K80: ='2. Kalkyldata'!$L$28-SUMIF('2. Kalkyldata'!$E$23:$E$27,"nyb",'2. Kalkyldata'!$L$23:$L$27) -> 0
B81: kr/kvm | G81: =IFERROR($K$80/('2. Kalkyldata'!$H$28-SUMIF('2. Kalkyldata'!$E$23:$E$27,"nyb",'2. Kalkyldata'!$H$23:$H$27)),0) -> 0 | K81: =IFERROR($K$80/('2. Kalkyldata'!$H$28-SUMIF('2. Kalkyldata'!$E$23:$E$27,"nyb",'2. Kalkyldata'!$H$23:$H$27)),0) -> 0
B82: Hyresvärde år 1, nyproduktion | G82: =SUMIF('2. Kalkyldata'!$E$23:$E$27,"nyb",'2. Kalkyldata'!$L$23:$L$27) -> 16165000 | K82: =SUMIF('2. Kalkyldata'!$E$23:$E$27,"nyb",'2. Kalkyldata'!$L$23:$L$27) -> 16165000
B83: kr/kvm | G83: =IFERROR(G82/(SUMIF('2. Kalkyldata'!$E23:$E27,"nyb",'2. Kalkyldata'!$H23:$H27)),0) -> 2650 | K83: =K82/(SUMIF('2. Kalkyldata'!$E23:$E27,"nyb",'2. Kalkyldata'!$H23:$H27)) -> 2650
B84: Summa hyresvärde, år 1 | G84: =G80+G82 -> 16165000 | K84: =K80+K82 -> 16165000
B85: kr/kvm | G85: =IFERROR(G84/$K$22,"") -> 2650 | K85: =K84/$K$22 -> 2650
B86: Marknadshyra / långsiktigt hyresvärde | G86: ='2. Kalkyldata'!$O$28 -> 16165000 | K86: ='2. Kalkyldata'!$O$28 -> 16165000
B87: kr/kvm | G87: =IFERROR(G86/'2. Kalkyldata'!$H$28,"") -> 2650 | K87: =K86/'2. Kalkyldata'!$H$28 -> 2650
B88: Vakans efter avtal inom kalkylperioden (viktad) | G88: ='2. Kalkyldata'!$M14 -> 0 | K88: ='2. Kalkyldata'!$M14 -> 0
B89: Drift- och underhållskostnader, år 1 | E89: Exkl. extraordinärt underhåll | G89: ='4. NPV'!$D$32 -> -405 | K89: ='4. NPV'!$D$32 -> -405
B91: Kommentar kalkylantaganden:
B92: Fyll i
B98: Finansieringsantagande | E98: Hämtas från 3. Finansiering
B99: Ränta år 1 (byggnadskreditiv) | G99: ='3. Finansiering'!$C$7 -> 0.0307 | K99: ='3. Finansiering'!$C$7 -> 0.0307
B100: Långsiktig ränta (från år 11) | G100: ='3. Finansiering'!$C$8 -> 0.0455 | K100: ='3. Finansiering'!$C$8 -> 0.0455
B101: Amortering | G101: ='3. Finansiering'!$C$9 -> 0.03 | K101: ='3. Finansiering'!$C$9 -> 0.03
B102: Belåningsgrad | G102: ='3. Finansiering'!$C$10 -> 0.37 | K102: ='3. Finansiering'!$C$10 -> 0.37
B104: Resultat & avkastning | D104: Krav | E104: Kalkylperiod | G104: Utfall
B105: ="IRR före skatt ("&ROUND(G102*100,0)&" % belåning, krav 2)" -> IRR före skatt (37 % belåning, krav 2) | D105: ='2. Kalkyldata'!F14 -> 0.0634 | E105: ='2. Kalkyldata'!$Q$17 -> 20 | G105: ='5. IRR'!$D$40 -> 0.080803743 | K105: ='5. IRR'!$D$40 -> 0.080803743
B107: Kravhyra krav 1–2, kr/kvm (tillkommande objekt, viktad) | D107: ='2. Kalkyldata'!$AE$19 -> NPV binder | G107: ='2. Kalkyldata'!$D$17 -> 2559
B108: NPV tillkommande, över-/undervärde (krav 1) | D108: ='2. Kalkyldata'!F13 -> >0 | E108: =$G$73 -> 20 | G108: ='4. NPV'!$E$82 -> 10300000 | K108: ='4. NPV'!$E$82 -> 10300000
B109: =CONCATENATE("PV ",'2. Kalkyldata'!$M$3) -> PV 2026 | G109: ='4. NPV'!$E$81 -> 250300000 | K109: ='4. NPV'!$E$81 -> 250300000
B110: Investering | G110: ='4. NPV'!$E$56 -> -2.4e+08 | K110: ='4. NPV'!$E$56 -> -2.4e+08
B111: PV jmf bokfört värde, hela fastigheten (krav 3) | D111: ='2. Kalkyldata'!F15 -> >0 | E111: =$G$73 -> 20 | G111: =G112-G113 -> 10300000 | K111: =K112-K113 -> 10300000
B112: =CONCATENATE("PV ",'2. Kalkyldata'!$M$3) -> PV 2026 | G112: ='4. NPV'!$E$52 -> 250300000 | K112: ='4. NPV'!$E$52 -> 250300000
B113: =CONCATENATE("Bokfört värde inkl investering ",'2. Kalkyldata'!$M$3) -> Bokfört värde inkl investering 2026 | G113: ='2. Kalkyldata'!$P$9+'2. Kalkyldata'!$X$28-'2. Kalkyldata'!$P$10 -> 2.4e+08 | K113: ='2. Kalkyldata'!$P$9+'2. Kalkyldata'!$X$28-'2. Kalkyldata'!$P$10 -> 2.4e+08
B114: Genomsnittlig överskottsgrad under kalkylperioden | D114: – | E114: =$G$73 -> 20 | G114: =AVERAGE('4. NPV'!D33:BA33) -> 0.8377785
B116: Kommentar resultat och rekommendation: | L116: Kontroll restvärde | N116: Kalkylperiod
B117: Fyll i | L117: Kalkylperiod | P117: 0 | Q117: ='2. Kalkyldata'!$Q$17 -> 20
L118: Bokfört värde | N118: =$E$112 -> 0 | P118: 0 | Q118: ='5. IRR'!$C$8 -> 94500000
L119: Lån | N119: =$E$112 -> 0 | P119: 0 | Q119: ='5. IRR'!$C$9 -> 35500000
L120: Försäljningsvärde | N120: =$E$112 -> 0 | P120: 0 | Q120: ='5. IRR'!$C$10 -> 271940000
L121: Hjälptabell hyresnivåer
B122: Investering rekommenderas | L122: Totalhyra, kr/kvm | M122: Marknadshyra, kr/kvm
B123: Namn: | D123: Datum:
B125: Sign:
B129: Namn: | D129: Datum:
B131: Sign:
B134: Bilagor | E134: Ja/Nej
B135: 2. Kalkyldata
B136: 3. Finansiering
B137: 4. NPV (nettonuvärde)
B138: 5. IRR (internränta)

Sheet 2. Kalkyldata
B1: INMATNING | C1: Arbetsgång: 1) Projektuppgifter på 1. Framskrivningsunderlag. 2) Blå fält här uppifrån och ned: kalkylstart och förutsättningar (1) → ytor, hyror och avtal (2) → drift (3) → investering per objekt (4) → restvärdesbedömning (5). 3) Läs resultatet i Nyckeltal kalkyl (rad 12–17) och på flik 1.
C2: Flik 3–7 räknas automatiskt; 3. Finansiering ändras bara efter OK från finansansvarig. Röd kolumnrubrik = obligatoriskt fält som saknar värde.
C3: FASTIGHETS- OCH MARKNADSFÖRUTSÄTTNINGAR | K3: KALKYLSTART | M3: 2026
A4: 1 | C4: Projektinfo — hämtas från flik 1 (fyll i där) | K4: Förutsättningar marknad | N4: Förutsättningar fastighet | S4: Avskrivning | AC4: Skala restvärdesbedömning | AK4: Skala långsiktig vakansrisk (pp)
C5: ='1. Framskrivningsunderlag'!$B$3 -> Projektnamn | E5: Fastighet | G5: Objekt | H5: BTA | I5: BRA | J5: Fastighetsarea | M5: =P5 -> 2026 | P5: =IF(M3<>"",M3,YEAR('3. Finansiering'!C1)) -> 2026 | Q5: =P5+10 -> 2036 | R5: =Q5+10 -> 2046 | S5: Del | T5: Avskrivning, %/år | U5: Värde (tkr) | AC5: Mycket positivt | AK5: Låg | AL5: -0.0025
C6: Fastighet: | E6: ='1. Framskrivningsunderlag'!$G$5 -> Fyll i | G6: ='1. Framskrivningsunderlag'!$G$6 -> Fyll i | H6: ='1. Framskrivningsunderlag'!G10 -> Fyll i | I6: ='1. Framskrivningsunderlag'!$G$9 -> Fyll i | J6: ='1. Framskrivningsunderlag'!$G$8 -> Fyll i | K6: Direktavkastningskrav, marknad | M6: 0.065 | N6: Tomträttsavgäld, kr/år | P6: 0 | Q6: 0 | R6: 0 | S6: Mark | T6: 0 | U6: 0 | AC6: Något positivt | AK6: Normal | AL6: 0
K7: Kalkylränta driftnetto | M7: 0.0455 | N7: Taxeringsvärde, kr | P7: 0 | Q7: 0 | R7: 0 | S7: Byggnad | T7: 0.03 | U7: 0 | AC7: Neutralt | AK7: Förhöjd | AL7: 0.005
C8: Typ av åtgärd: | E8: ='1. Framskrivningsunderlag'!$G$11 -> Fyll i | K8: Kalkylränta restvärde | M8: =$M$6+$M$9 -> 0.085 | N8: Fastighetsskatt, % | P8: 0 | S8: Övrigt 1 | T8: 0.03 | U8: 0 | AC8: Något negativt | AK8: Hög | AL8: 0.01
K9: Inflation | M9: 0.02 | N9: Bokfört värde, kr | P9: 0 | S9: Övrigt 2 | T9: 0 | U9: 0 | AC9: Mycket negativt | AK9: Mycket hög | AL9: 0.02
C10: Momsregistreringsgrad före | F10: ='1. Framskrivningsunderlag'!$G$12 -> Fyll i | K10: Justering (från sektion 5) | M10: =$H$79 -> 0 | N10: Bokfört värde - proj belastning | P10: 0 | Q10: Fr.o.m. år | R10: T.o.m. år | S10: Summa | T10: =IFERROR(SUMPRODUCT(T6:T9,U6:U9)/U10,"") | U10: =SUM(U6:U9) -> 0
C11: Momsregistreringsgrad efter | F11: ='1. Framskrivningsunderlag'!$G$13 -> Fyll i | K11: Justerad direktavkastning | M11: =$M$6+$M$10 -> 0.065 | N11: Ersättningslokaler, kr/år | P11: 0
C12: Nyckeltal kalkyl | D12: Resultat | F12: Krav | G12: Notiser | N12: Tillfälliga intäkter, kr/år | P12: 0 | AC12: Hyresmultiplikator m — teknisk cell för datatabellen, lämna 1 | AD12: 1
C13: NPV tillkommande (krav 1) | D13: =IF(G13<>"","",'4. NPV'!$E$82/1000) -> 10300 | F13: >0 | G13: =IF(COUNTA(M3,M6,M7,M9,Q15,Q17,C23:C27,E23:E27,F23:F27,G23:G27,I23:I27,J23:J27,M23:M27,N23:N27,O23:O27,Q23:Q27,S23:S27,R23:R27)<17,"Fyll i alla tvingande fält",IF(SUMPRODUCT(--($H$23:$H$27>0),--($E$23:$E$27<>"Bef"),--($T$23:$T$27=0))>0,"Investering saknas för objekt med area (sektion 4)",IF($AD$12<>1,"Hyresmultiplikator AD12 ≠ 1",""))) | I13: =IF(SUM(G39:H39)=0,"Inga driftkostnader angivna","") | N13: Avskr.tid befintligt | P13: =IF(Q13<>0,Q13,P16) -> 33 | R13: ← egen tid, år (valfri) | AC13: m | AD13: NPV tillk. | AE13: NPV vid IRR-krav | AF13: NPV tillk. opt | AG13: NPV tillk. pess | AH13: NPV vid krav, opt | AI13: NPV vid krav, pess
C14: IRR före skatt (krav 2) | D14: =IF('5. IRR'!D40="N/A"," ",'5. IRR'!D40) -> 0.080803743 | F14: 0.0634 | G14: =IF('5. IRR'!C11<>"","Eget restvärde ifyllt i 5. IRR. ","")&IF(M10<>0,"Yield "&IF(M10>0,"+","")&ROUND(M10*100,2)&" pp → "&ROUND(M11*100,2)&" %","") | I14: =IF(SUM(G39:H39)>0,IF(AND(H39=0,G28<>0),"Driftkostnad ev. angiven på fel yta",""),"") | K14: Vakans efter avtal, viktad | M14: =IFERROR(P28,"") -> 0 | N14: Central administration | P14: 80 | Q14: Justering | AD14: ='4. NPV'!$E$82 -> 10300000 | AE14: ='5. IRR'!$D$37+NPV('2. Kalkyldata'!$F$14,'5. IRR'!$E$37:$BA$37) -> 33005083 | AF14: ='5. IRR'!$F$55 -> 19970000 | AG14: ='5. IRR'!$F$57 -> 3200000 | AH14: ='5. IRR'!$D$59+NPV('2. Kalkyldata'!$F$14,'5. IRR'!$E$59:$BA$59) -> 48382166 | AI14: ='5. IRR'!$D$61+NPV('2. Kalkyldata'!$F$14,'5. IRR'!$E$61:$BA$61) -> 21728556
C15: PV mot bokfört värde (krav 3) | D15: =IF(G13<>"","",('4. NPV'!E52-('2. Kalkyldata'!$P$9+'2. Kalkyldata'!$X$28-'2. Kalkyldata'!$P$10))/1000) -> 10300 | F15: >0 | I15: =IF(OR(AND(M23<>0,M23<$M$3),AND(M24<>0,M24<$M$3),AND(M25<>0,M25<$M$3),AND(M26<>0,M26<$M$3),AND(M27<>0,M27<$M$3)),"Glapp, Avtalstid / Kalkylstart","") | N15: Årlig avskrivning | P15: =IF(Q15<>"",Q15,'2. Kalkyldata'!T10) -> 0.03 | Q15: 0.03 | S15: Minsta möjliga markvärde | AC15: 0 | AD15: -288810000 | AE15: -2.827158e+08 | AF15: -290820000 | AG15: -287340000 | AH15: -2.8590951e+08 | AI15: -2.8037374e+08
C16: Pay-off tid | D16: ='4. NPV'!$C$62 -> 15 | I16: =IF(OR(AND(R23<>0,R23<M23),AND(R24<>0,R24<M24),AND(R25<>0,R25<M25),AND(R26<>0,R26<M26),AND(R27<>0,R27<M27)),"Glapp, Prod.avslut / Avtalstid","") | K16: Bolagsskatt | M16: 0.206 | N16: Avskrivningstid | P16: =(FLOOR(100%/P15,1)) -> 33 | S16: Markareal | T16: kr/kvm | U16: Minsta värde | AC16: 1 | AD16: 10300000 | AE16: 33005083 | AF16: 19970000 | AG16: 3200000 | AH16: 48382166 | AI16: 21728556
C17: Kravhyra krav 1–2, kr/kvm | D17: =IF(G13<>"","",CEILING($AD$19*$AD$20,1)) -> 2559 | F17: =IF(G13<>"","",LEFT($AE$19,3)) -> NPV | I17: =IF(OR(AND(M23<>0,M23<R23),AND(M24<>0,M24<R24),AND(M25<>0,M25<R25),AND(M26<>0,M26<R26),AND(M27<>0,M27<R27)),"Glapp, Avtalstid / Prod.avslut. ","")&IF(G13<>"","",IF(D17>$AD$20,"Höj hyran "&ROUND(D17-$AD$20,0)&" kr/kvm för krav 1–2. ",""))&IF(COUNTIF(E23:E27,"Bef")+(P9>0)>0,"Bef/bokfört värde ingår bara i krav 3. ","")&IF(SUMPRODUCT(($P$23:$P$27>0)*(AM23:AM27=FALSE))>0,"Vakansgrad utan effekt — avtalet täcker kalkylperioden (se sektion 5).","") | N17: Kalkylperiod | P17: =IF(Q17<>0,Q17,(FLOOR(100%/P15,1))) -> 20 | Q17: 20 | S17: =J6 -> Fyll i | U17: =IFERROR($T$17*$J$6,0) -> 0
AC18: m per krav → | AD18: =IFERROR(-AD15/(AD16-AD15),1) -> 0.96556451 | AE18: =IFERROR(-AE15/(AE16-AE15),1) -> 0.8954612 | AF18: =IFERROR(-AF15/(AF16-AF15),1) -> 0.93574439 | AG18: =IFERROR(-AG15/(AG16-AG15),1) -> 0.98898603 | AH18: =IFERROR(-AH15/(AH16-AH15),1) -> 0.85526961 | AI18: =IFERROR(-AI15/(AI16-AI15),1) -> 0.9280755
C19: INTÄKTER OCH INVESTERINGAR | AC19: m* = MAX(krav 1, krav 2): bedömt | bindande | opt | pess | AD19: =MAX(AD18,AE18) -> 0.96556451 | AE19: =IF(AD18>=AE18,"NPV binder","IRR binder") -> NPV binder | AF19: =MAX(AF18,AH18) -> 0.93574439 | AG19: =MAX(AG18,AI18) -> 0.98898603 | AS19: Hjälptabeller - Ignorera dessa
C20: Ett objekt per rad (högst 5). Hyror i kr/kvm och år, kalkylstartens penningvärde. Budget kr/kvm räknas fram från sektion 4. | AC20: Angiven hyra, viktad kr/kvm (icke-Bef) | AD20: =IFERROR(SUMPRODUCT(--($E$23:$E$27<>"Bef"),$I$23:$I$27,$H$23:$H$27)/SUMPRODUCT(--($E$23:$E$27<>"Bef"),$H$23:$H$27),0) -> 2650
A21: 2 | C21: Ytor | F21: Area (BRA) | I21: Hyresvillkor | M21: Avtalsperiod | O21: Marknadshyra | P21: Vakansgrad | Q21: Investeringar | W21: Investering, kr | Y21: Bokfört värde
C22: Byggnad/lokal/objekt | D22: Antal platser | E22: Typ | F22: Befintligt | G22: Nybyggnad/ Tillbyggnad | H22: Totalt | I22: Hyra, kr/kvm | J22: Index, andel av inflation | K22: Tillägg, kr/kvm | L22: Totalhyra, kr/år | M22: Fr.o.m. år | N22: T.o.m. år | O22: =CONCATENATE(P5," kr/kvm") -> 2026 kr/kvm | P22: efter avtal, inom kalkylperioden | Q22: Produktions- start | R22: Produktions- avslut | S22: =CONCATENATE("Budget kr/kvm ",$R23) -> Budget kr/kvm 2026 | T22: Totalt kr/kvm | U22: Justering, kr/kvm | W22: Total investering | X22: PV exkl projektbelast | Y22: =CONCATENATE(" Budget inkl projektbelast.") -> Budget inkl projektbelast. | Z22: Bokfört värde kr/kvm | AA22: Varav bokfört värde | AC22: =M3 -> 2026 | AD22: =AC22+1 -> 2027 | AE22: =AD22+1 -> 2028 | AF22: =AE22+1 -> 2029 | AG22: =AF22+1 -> 2030 | AH22: =AG22+1 -> 2031 | AI22: =AH22+1 -> 2032 | AJ22: =AI22+1 -> 2033 | AK22: =AJ22+1 -> 2034 | AM22: Vakansgrad tillåten (avtal slutar före kalkylperiodens sista år) | AS22: =$M$5 -> 2026 | AT22: =AS22+1 -> 2027 | AU22: =AT22+1 -> 2028 | AV22: =AU22+1 -> 2029 | AW22: =AV22+1 -> 2030 | AX22: =AW22+1 -> 2031 | AY22: =AX22+1 -> 2032 | AZ22: =AY22+1 -> 2033 | BA22: =AZ22+1 -> 2034 | ... BZ22: =BY22+1 -> 2059
C23: Skola | E23: Nyb | G23: 6100 | H23: =SUM(F23:G23) -> 6100 | I23: 2650 | J23: 0.7 | L23: =((H23*I23*IF($E23="Bef",1,$AD$12))+(K23*H23)) -> 16165000 | M23: 2026 | N23: 2045 | O23: =I23*IF($E23="Bef",1,$AD$12) -> 2650 | Q23: 2026 | R23: 2026 | S23: =IFERROR(G$69/$H23,0) -> 39344.262 | T23: =IF(U23="",S23,U23) -> 39344.262 | W23: =IFERROR((T23*$H23),0) -> 2.4e+08 | X23: =$W23/((1+$M$9)^MAX(0,$R23-$M$5)) -> 2.4e+08 | Y23: =IFERROR((X23+(Z23*$H23)),0) -> 2.4e+08 | Z23: =IF(OR($E23="Bef",$E23=""),0,$P$10/($H$28-SUMIF($E$23:$E$27,"Bef",$H$23:$H$27))) -> 0 | AA23: =$Z23*$H23 -> 0 | AM23: =OR(N23="",N23<$P$5+$P$17-1) -> FALSE | AS23: =IF(AS$22=$R23,$S23*$H23,0) -> 2.4e+08 | AT23: =IF(AT$22=$R23,$S23*$H23,0) -> 0 | AU23: =IF(AU$22=$R23,$S23*$H23,0) -> 0 | AV23: =IF(AV$22=$R23,$S23*$H23,0) -> 0 | AW23: =IF(AW$22=$R23,$S23*$H23,0) -> 0 | AX23: =IF(AX$22=$R23,$S23*$H23,0) -> 0 | AY23: =IF(AY$22=$R23,$S23*$H23,0) -> 0 | AZ23: =IF(AZ$22=$R23,$S23*$H23,0) -> 0 | ... BZ23: =IF(BZ$22=$R23,$S23*$H23,0) -> 0
H24: =SUM(F24:G24) -> 0 | L24: =((H24*I24*IF($E24="Bef",1,$AD$12))+(K24*H24)) -> 0 | O24: =I24*IF($E24="Bef",1,$AD$12) -> 0 | S24: =IFERROR(H$69/$H24,0) -> 0 | T24: =IF(U24="",S24,U24) -> 0 | W24: =IFERROR((T24*$H24),0) -> 0 | X24: =$W24/((1+$M$9)^MAX(0,$R24-$M$5)) -> 0 | Y24: =IFERROR((X24+(Z24*$H24)),0) -> 0 | Z24: =IF(OR($E24="Bef",$E24=""),0,$P$10/($H$28-SUMIF($E$23:$E$27,"Bef",$H$23:$H$27))) -> 0 | AA24: =$Z24*$H24 -> 0 | AM24: =OR(N24="",N24<$P$5+$P$17-1) -> TRUE | AS24: =IF(AS$22=$R24,$S24*$H24,0) -> 0 | AT24: =IF(AT$22=$R24,$S24*$H24,0) -> 0 | AU24: =IF(AU$22=$R24,$S24*$H24,0) -> 0 | AV24: =IF(AV$22=$R24,$S24*$H24,0) -> 0 | AW24: =IF(AW$22=$R24,$S24*$H24,0) -> 0 | AX24: =IF(AX$22=$R24,$S24*$H24,0) -> 0 | AY24: =IF(AY$22=$R24,$S24*$H24,0) -> 0 | AZ24: =IF(AZ$22=$R24,$S24*$H24,0) -> 0 | ... BZ24: =IF(BZ$22=$R24,$S24*$H24,0) -> 0
H25: =SUM(F25:G25) -> 0 | L25: =((H25*I25*IF($E25="Bef",1,$AD$12))+(K25*H25)) -> 0 | O25: =I25*IF($E25="Bef",1,$AD$12) -> 0 | S25: =IFERROR(I$69/$H25,0) -> 0 | T25: =IF(U25="",S25,U25) -> 0 | W25: =IFERROR((T25*$H25),0) -> 0 | X25: =$W25/((1+$M$9)^MAX(0,$R25-$M$5)) -> 0 | Y25: =IFERROR((X25+(Z25*$H25)),0) -> 0 | Z25: =IF(OR($E25="Bef",$E25=""),0,$P$10/($H$28-SUMIF($E$23:$E$27,"Bef",$H$23:$H$27))) -> 0 | AA25: =$Z25*$H25 -> 0 | AM25: =OR(N25="",N25<$P$5+$P$17-1) -> TRUE | AS25: =IF(AS$22=$R25,$S25*$H25,0) -> 0 | AT25: =IF(AT$22=$R25,$S25*$H25,0) -> 0 | AU25: =IF(AU$22=$R25,$S25*$H25,0) -> 0 | AV25: =IF(AV$22=$R25,$S25*$H25,0) -> 0 | AW25: =IF(AW$22=$R25,$S25*$H25,0) -> 0 | AX25: =IF(AX$22=$R25,$S25*$H25,0) -> 0 | AY25: =IF(AY$22=$R25,$S25*$H25,0) -> 0 | AZ25: =IF(AZ$22=$R25,$S25*$H25,0) -> 0 | ... BZ25: =IF(BZ$22=$R25,$S25*$H25,0) -> 0
H26: =SUM(F26:G26) -> 0 | L26: =((H26*I26*IF($E26="Bef",1,$AD$12))+(K26*H26)) -> 0 | O26: =I26*IF($E26="Bef",1,$AD$12) -> 0 | S26: =IFERROR(J$69/$H26,0) -> 0 | T26: =IF(U26="",S26,U26) -> 0 | W26: =IFERROR((T26*$H26),0) -> 0 | X26: =$W26/((1+$M$9)^MAX(0,$R26-$M$5)) -> 0 | Y26: =IFERROR((X26+(Z26*$H26)),0) -> 0 | Z26: =IF(OR($E26="Bef",$E26=""),0,$P$10/($H$28-SUMIF($E$23:$E$27,"Bef",$H$23:$H$27))) -> 0 | AA26: =$Z26*$H26 -> 0 | AM26: =OR(N26="",N26<$P$5+$P$17-1) -> TRUE | AS26: =IF(AS$22=$R26,$S26*$H26,0) -> 0 | AT26: =IF(AT$22=$R26,$S26*$H26,0) -> 0 | AU26: =IF(AU$22=$R26,$S26*$H26,0) -> 0 | AV26: =IF(AV$22=$R26,$S26*$H26,0) -> 0 | AW26: =IF(AW$22=$R26,$S26*$H26,0) -> 0 | AX26: =IF(AX$22=$R26,$S26*$H26,0) -> 0 | AY26: =IF(AY$22=$R26,$S26*$H26,0) -> 0 | AZ26: =IF(AZ$22=$R26,$S26*$H26,0) -> 0 | ... BZ26: =IF(BZ$22=$R26,$S26*$H26,0) -> 0
H27: =SUM(F27:G27) -> 0 | L27: =((H27*I27*IF($E27="Bef",1,$AD$12))+(K27*H27)) -> 0 | O27: =I27*IF($E27="Bef",1,$AD$12) -> 0 | S27: =IFERROR(K$69/$H27,0) -> 0 | T27: =IF(U27="",S27,U27) -> 0 | W27: =IFERROR((T27*$H27),0) -> 0 | X27: =$W27/((1+$M$9)^MAX(0,$R27-$M$5)) -> 0 | Y27: =IFERROR((X27+(Z27*$H27)),0) -> 0 | Z27: =IF(OR($E27="Bef",$E27=""),0,$P$10/($H$28-SUMIF($E$23:$E$27,"Bef",$H$23:$H$27))) -> 0 | AA27: =$Z27*$H27 -> 0 | AM27: =OR(N27="",N27<$P$5+$P$17-1) -> TRUE | AS27: =IF(AS$22=$R27,$S27*$H27,0) -> 0 | AT27: =IF(AT$22=$R27,$S27*$H27,0) -> 0 | AU27: =IF(AU$22=$R27,$S27*$H27,0) -> 0 | AV27: =IF(AV$22=$R27,$S27*$H27,0) -> 0 | AW27: =IF(AW$22=$R27,$S27*$H27,0) -> 0 | AX27: =IF(AX$22=$R27,$S27*$H27,0) -> 0 | AY27: =IF(AY$22=$R27,$S27*$H27,0) -> 0 | AZ27: =IF(AZ$22=$R27,$S27*$H27,0) -> 0 | ... BZ27: =IF(BZ$22=$R27,$S27*$H27,0) -> 0
C28: Totalt | D28: =SUM($D$23:$D$27) -> 0 | F28: =SUM(F23:F27) -> 0 | G28: =SUM(G23:G27) -> 6100 | H28: =F28+G28 -> 6100 | L28: =SUM(L23:L27) -> 16165000 | O28: =(O23*H23+O24*H24+O25*H25+O26*H26+O27*H27) -> 16165000 | P28: =IFERROR(SUMPRODUCT(P23:P27,L23:L27)/L28,"") -> 0 | S28: =IF(H28=0,"",S29*H28) -> 2.4e+08 | T28: =IF(H28=0,"",T29*H28) -> 2.4e+08 | U28: =IF(H29=0,"",U29*H28) | W28: =SUM(W23:W27) -> 2.4e+08 | X28: =SUM(X23:X27) -> 2.4e+08 | Y28: =SUM(Y23:Y27) -> 2.4e+08 | Z28: =IF(H29=0,"",Z29*H28) | AA28: =SUM(AA23:AA27) -> 0 | AS28: =SUM(AS23:AS27) -> 2.4e+08 | AT28: =SUM(AT23:AT27) -> 0 | AU28: =SUM(AU23:AU27) -> 0 | AV28: =SUM(AV23:AV27) -> 0 | AW28: =SUM(AW23:AW27) -> 0 | AX28: =SUM(AX23:AX27) -> 0 | AY28: =SUM(AY23:AY27) -> 0 | AZ28: =SUM(AZ23:AZ27) -> 0 | ... BZ28: =SUM(BZ23:BZ27) -> 0
C29: Per kvm, viktat | L29: =IF(L28=0,"",L28/H28) -> 2650 | O29: =IF(O28=0,"",O28/H28) -> 2650 | S29: =IF(H28=0,"",SUMPRODUCT($S$23:$S$27,$H$23:$H$27)/$H$28) -> 39344.262 | T29: =IF(H28=0,"",SUMPRODUCT($T$23:$T$27,$H$23:$H$27)/$H$28) -> 39344.262 | U29: =IF(H29=0,"",SUMPRODUCT($U$23:$U$27,$H$23:$H$27)/$H$28) | Z29: =IF(H29=0,"",SUMPRODUCT($Z$23:$Z$27,$H$23:$H$27)/$H$28)
C31: KOSTNADER
C32: Kr/kvm och år i kalkylstartens penningvärde. Befintligt gäller objekt av typ Bef/Omb/Ins/Mar, Nybyggnad/Tillbyggnad gäller typ Nyb. Kostnadshöjning = stegvis höjning utöver inflation.
A33: 3 | C33: Drift och underhåll, kr/kvm och år | G33: Befintligt | H33: Nybyggnad/ Tillbyggnad | I33: Totalt, viktad | K33: Kostnadshöjning utöver inflation | L33: 10 | M33: 15 | N33: Total höjning | P33: Re-investering/ hyressatt UH | Q33: Byggnad/Lokal/ Objekt | R33: År | S33: =CONCATENATE("Kostnad kr/kvm ",$P$5) -> Kostnad kr/kvm 2026 | T33: Uppräknat, kr/kvm | U33: Justering | W33: Underhåll uppräknat | X33: Underhåll ,exkl uppräkning | Y33: =CONCATENATE("jmf budget kolumn ",$P$5) -> jmf budget kolumn 2026
C34: Fastighetsskötsel | G34: 0 | H34: 0 | I34: =IFERROR(SUMPRODUCT(G34:H34,$F$28:$G$28)/$H$28,0) -> 0 | K34: Fastighetsskötsel | L34: 0 | M34: 0 | N34: =L34+M34 -> 0 | T34: =IF(U34<>0,U34*((1+$M$9)^($R34-$P$5)),S34*((1+$M$9)^($R34-$P$5))) -> 0 | W34: =IFERROR(SUMIF($C$23:$C$27,$Q34,$H$23:$H$27)*$T34,"") -> 0 | X34: =IF($U34=0,$S34*SUMIF($C$23:$C$27,$Q34,$H$23:$H$27),$U34*SUMIF($C$23:$C$27,$Q34,$H$23:$H$27)) -> 0 | Y34: =IFERROR(SUMIF($C$23:$C$27,$Q34,$H$23:$H$27)*$S34,"") -> 0
C35: Reparationer | G35: 0 | H35: 0 | I35: =IFERROR(SUMPRODUCT(G35:H35,$F$28:$G$28)/$H$28,0) -> 0 | K35: Reparationer | L35: 0 | M35: 0 | N35: =L35+M35 -> 0 | T35: =IF(U35<>0,U35,S35*(1+$M$9)^($R35-$P$5)) -> 0 | W35: =IFERROR(SUMIF($C$23:$C$27,$Q35,$H$23:$H$27)*$T35,"") -> 0 | X35: =IF($U35=0,$S35*SUMIF($C$23:$C$27,$Q35,$H$23:$H$27),$U35*SUMIF($C$23:$C$27,$Q35,$H$23:$H$27)) -> 0 | Y35: =IFERROR(SUMIF($C$23:$C$27,$Q35,$H$23:$H$27)*$S35,"") -> 0
C36: Planerat underhåll | G36: 0 | H36: 0 | I36: =IFERROR(SUMPRODUCT(G36:H36,$F$28:$G$28)/$H$28,0) -> 0 | K36: Planerat underhåll | L36: 0 | M36: 0 | N36: =L36+M36 -> 0 | T36: =IF(U36<>0,U36,S36*(1+$M$9)^($R36-$P$5)) -> 0 | W36: =IFERROR(SUMIF($C$23:$C$27,$Q36,$H$23:$H$27)*$T36,"") -> 0 | X36: =IF($U36=0,$S36*SUMIF($C$23:$C$27,$Q36,$H$23:$H$27),$U36*SUMIF($C$23:$C$27,$Q36,$H$23:$H$27)) -> 0 | Y36: =IFERROR(SUMIF($C$23:$C$27,$Q36,$H$23:$H$27)*$S36,"") -> 0
C37: Media | G37: 0 | H37: 0 | I37: =IFERROR(SUMPRODUCT(G37:H37,$F$28:$G$28)/$H$28,0) -> 0 | K37: Media | L37: 0 | M37: 0 | N37: =L37+M37 -> 0 | T37: =IF(U37<>0,U37,S37*(1+$M$9)^($R37-$P$5)) -> 0 | W37: =IFERROR(SUMIF($C$23:$C$27,$Q37,$H$23:$H$27)*$T37,"") -> 0 | X37: =IF($U37=0,$S37*SUMIF($C$23:$C$27,$Q37,$H$23:$H$27),$U37*SUMIF($C$23:$C$27,$Q37,$H$23:$H$27)) -> 0 | Y37: =IFERROR(SUMIF($C$23:$C$27,$Q37,$H$23:$H$27)*$S37,"") -> 0
C38: Övriga förvaltningskostnader | G38: 0 | H38: 405 | I38: =IFERROR(SUMPRODUCT(G38:H38,$F$28:$G$28)/$H$28,0) -> 405 | K38: Övr. förvaltning | L38: 0 | M38: 0 | N38: =L38+M38 -> 0 | T38: =IF(U38<>0,U38,S38*(1+$M$9)^($R38-$P$5)) -> 0 | W38: =IFERROR(SUMIF($C$23:$C$27,$Q38,$H$23:$H$27)*$T38,"") -> 0 | X38: =IF($U38=0,$S38*SUMIF($C$23:$C$27,$Q38,$H$23:$H$27),$U38*SUMIF($C$23:$C$27,$Q38,$H$23:$H$27)) -> 0 | Y38: =IFERROR(SUMIF($C$23:$C$27,$Q38,$H$23:$H$27)*$S38,"") -> 0
C39: Summa kostnader | G39: =SUM(G34:G38) -> 0 | H39: =SUM(H34:H38) -> 405 | I39: =IFERROR(SUMPRODUCT(G39:H39,$F$28:$G$28)/$H$28,0) -> 405 | K39: =C39 -> Summa kostnader | L39: =IFERROR(SUMPRODUCT(L34:L38,$I$34:$I$38)/$I$39,0) -> 0 | M39: =IFERROR(SUMPRODUCT(M34:M38,$I$34:$I$38)/$I$39,0) -> 0 | N39: =IFERROR(SUMPRODUCT(N34:N38,$I$34:$I$38)/$I$39,0) -> 0 | T39: =IF(U39<>0,U39,S39*(1+$M$9)^($R39-$P$5)) -> 0 | W39: =SUM(W34:W38) -> 0 | X39: =SUM(X34:X38) -> 0 | Y39: =SUM(Y34:Y38) -> 0
C42: Beskriv antaganden: motivera otydliga poster och särskilda antaganden.
C52: INVESTERINGSSPECIFIKATION
C53: Projektbudget per objekt i dagens penningvärde, kr. Summan styr Budget kr/kvm (S23:S27). Manuell överstyrning görs i Justering (U23:U27).
A54: 4 | C54: Kostnadspost | G54: =IF($C$23="","Objekt 1",$C$23) -> Skola | H54: =IF($C$24="","Objekt 2",$C$24) -> Objekt 2 | I54: =IF($C$25="","Objekt 3",$C$25) -> Objekt 3 | J54: =IF($C$26="","Objekt 4",$C$26) -> Objekt 4 | K54: =IF($C$27="","Objekt 5",$C$27) -> Objekt 5 | L54: Totalt
C55: Tomt- och fastighetskostnader | L55: =SUM(G55:K55) -> 0
C56: Projekteringskostnader | L56: =SUM(G56:K56) -> 0
C57: Byggherrekostnader | L57: =SUM(G57:K57) -> 0
C58: Entreprenadkostnader | G58: 240000000 | L58: =SUM(G58:K58) -> 240000000
C59: Tillkommande arbeten | L59: =SUM(G59:K59) -> 0
C60: Avgifter & byggherrekostnader | L60: =SUM(G60:K60) -> 0
C61: Finansiering | L61: =SUM(G61:K61) -> 0
C62: Index | L62: =SUM(G62:K62) -> 0
C63: Övriga kostnader | L63: =SUM(G63:K63) -> 0
C64: Bidrag och intäkter (ange negativt) | L64: =SUM(G64:K64) -> 0
C65: Ersättningslokaler | L65: =SUM(G65:K65) -> 0
C66: Övrigt 1 | L66: =SUM(G66:K66) -> 0
C67: Övrigt 2 | L67: =SUM(G67:K67) -> 0
C68: Övrigt 3 | L68: =SUM(G68:K68) -> 0
C69: Summa investering | G69: =SUM(G55:G68) -> 240000000 | H69: =SUM(H55:H68) -> 0 | I69: =SUM(I55:I68) -> 0 | J69: =SUM(J55:J68) -> 0 | K69: =SUM(K55:K68) -> 0 | L69: =SUM(G69:K69) -> 240000000
C70: kr/kvm (BRA) | G70: =IFERROR(G69/$H23,0) -> 39344.262 | H70: =IFERROR(H69/$H24,0) -> 0 | I70: =IFERROR(I69/$H25,0) -> 0 | J70: =IFERROR(J69/$H26,0) -> 0 | K70: =IFERROR(K69/$H27,0) -> 0 | L70: =IFERROR(L69/$H$28,0) -> 39344.262
C72: RESTVÄRDESBEDÖMNING
C73: Extern direktavkastning (M6) är utgångsläget. Bedömningarna justerar kapitaliseringen (M11) i alla tre kraven, ±0,25/±0,50 pp per faktor (vakansrisk −0,25…+2,00). Kalkylränta restvärde = M6 + inflation.
A74: 5 | C74: Faktor | G74: Bedömning | H74: Effekt | I74: Motsv. vakans | J74: Motivering
C75: Läge (centralitet, infrastruktur) | G75: Neutralt | H75: =IFERROR((MATCH(G75,$AC$5:$AC$9,0)-3)*0.0025,0) -> 0
C76: Långsiktig vakansrisk | G76: Normal | H76: =IFERROR(INDEX($AL$5:$AL$9,MATCH(G76,$AK$5:$AK$9,0)),0) -> 0 | I76: =IFERROR(IF(H76=0,"≈ 0 %",IF(H76>0,"≈ ","≈ −")&ROUND(ABS(HLOOKUP('4. NPV'!$D$43+1,'4. NPV'!$D$4:$BA$86,83,FALSE)/HLOOKUP('4. NPV'!$D$43+1,'4. NPV'!$D$4:$BA$90,87,FALSE)*H76/$M$11)*100,0)&" %"),"") -> ≈ 0 %
C77: Lokalflexibilitet (omställbarhet) | G77: Neutralt | H77: =IFERROR((MATCH(G77,$AC$5:$AC$9,0)-3)*0.0025,0) -> 0
C78: Byggnadsteknisk standard | G78: Neutralt | H78: =IFERROR((MATCH(G78,$AC$5:$AC$9,0)-3)*0.0025,0) -> 0
C79: Summa justering av direktavkastning | H79: =SUM(H75:H78) -> 0
C80: Justerad direktavkastning (M11) | H80: =$M$11 -> 0.065

Sheet 3. Finansiering
B1: Datum | C1: =NOW() -> 46306.928
B3: FINANSIERING OCH AVSKRIVNING
B4: Finansieringsantagandena (ränta, amortering, belåningsgrad) matas in i C7:C10 och ändras endast efter OK från ansvarig för bolagets finansiering. Fliken räknar fram lån, räntekostnad och amortering per år samt bokfört värde och avskrivning. Eget kapital, skuld, ränta, amortering, avskrivning och bokfört värde används i 5. IRR; investeringen per år i 4. NPV.
B6: Finansiering | C6: Inmatning | D6: Innebär
B7: Ränta byggnadskreditiv (år 1) | C7: 0.0307
B8: Långsiktig ränta | C8: 0.0455 | D8: Nås år 11
B9: Amortering per år | C9: 0.03 | D9: =(FLOOR(100%/C9,1)) -> 33
B10: Belåningsgrad | C10: 0.37
D12: ='4. NPV'!D3 -> <=2026 | E12: ='4. NPV'!E3 -> <=2027 | F12: ='4. NPV'!F3 -> <=2028 | G12: ='4. NPV'!G3 -> <=2029 | H12: ='4. NPV'!H3 -> <=2030 | I12: ='4. NPV'!I3 -> <=2031 | J12: ='4. NPV'!J3 -> <=2032 | K12: ='4. NPV'!K3 -> <=2033 | ... BA12: ='4. NPV'!BA3 -> <=
B13: År | D13: =IF(D14<='2. Kalkyldata'!$P$17+1,'2. Kalkyldata'!$P$5+C14,"") -> 2026 | E13: =IF(E14<='2. Kalkyldata'!$P$17+1,'2. Kalkyldata'!$P$5+D14,"") -> 2027 | F13: =IF(F14<='2. Kalkyldata'!$P$17+1,'2. Kalkyldata'!$P$5+E14,"") -> 2028 | G13: =IF(G14<='2. Kalkyldata'!$P$17+1,'2. Kalkyldata'!$P$5+F14,"") -> 2029 | H13: =IF(H14<='2. Kalkyldata'!$P$17+1,'2. Kalkyldata'!$P$5+G14,"") -> 2030 | I13: =IF(I14<='2. Kalkyldata'!$P$17+1,'2. Kalkyldata'!$P$5+H14,"") -> 2031 | J13: =IF(J14<='2. Kalkyldata'!$P$17+1,'2. Kalkyldata'!$P$5+I14,"") -> 2032 | K13: =IF(K14<='2. Kalkyldata'!$P$17+1,'2. Kalkyldata'!$P$5+J14,"") -> 2033 | ... BA13: =IF(BA14<='2. Kalkyldata'!$P$17+1,'2. Kalkyldata'!$P$5+AZ14,"")
B14: Kalkylår · belopp i kr | D14: 1 | E14: 2 | F14: 3 | G14: 4 | H14: 5 | I14: 6 | J14: 7 | K14: 8 | L14: 9 | M14: 10 | N14: 11 | O14: 12 | P14: 13 | Q14: 14 | R14: 15 | S14: 16 | T14: 17 | U14: 18 | V14: 19 | W14: 20 | X14: 21 | Y14: 22 | Z14: 23 | AA14: 24 | AB14: 25 | AC14: 26 | AD14: 27 | AE14: 28 | AF14: 29 | AG14: 30 | AH14: 31 | AI14: 32 | AJ14: 33 | AK14: 34 | AL14: 35 | AM14: 36 | AN14: 37 | AO14: 38 | AP14: 39 | AQ14: 40 | AR14: 41 | AS14: 42 | AT14: 43 | AU14: 44 | AV14: 45 | AW14: 46 | AX14: 47 | AY14: 48 | AZ14: 49 | BA14: 50
B15: Investering (från 2. Kalkyldata) | C15: → 4. NPV | D15: =-SUMIF('2. Kalkyldata'!AS$22,'3. Finansiering'!D13,'2. Kalkyldata'!AS$28) -> -2.4e+08 | E15: =-SUMIF('2. Kalkyldata'!AT$22,'3. Finansiering'!E13,'2. Kalkyldata'!AT$28) -> 0 | F15: =-SUMIF('2. Kalkyldata'!AU$22,'3. Finansiering'!F13,'2. Kalkyldata'!AU$28) -> 0 | G15: =-SUMIF('2. Kalkyldata'!AV$22,'3. Finansiering'!G13,'2. Kalkyldata'!AV$28) -> 0 | H15: =-SUMIF('2. Kalkyldata'!AW$22,'3. Finansiering'!H13,'2. Kalkyldata'!AW$28) -> 0 | I15: =-SUMIF('2. Kalkyldata'!AX$22,'3. Finansiering'!I13,'2. Kalkyldata'!AX$28) -> 0 | J15: =-SUMIF('2. Kalkyldata'!AY$22,'3. Finansiering'!J13,'2. Kalkyldata'!AY$28) -> 0 | K15: =-SUMIF('2. Kalkyldata'!AZ$22,'3. Finansiering'!K13,'2. Kalkyldata'!AZ$28) -> 0 | ... BA15: =-SUMIF('2. Kalkyldata'!CP$22,'3. Finansiering'!BA13,'2. Kalkyldata'!CP$28) -> 0
B16: Eget kapital per investering | C16: → 5. IRR | D16: =-D$15*(1-'3. Finansiering'!$C$10) -> 1.512e+08 | E16: =-E$15*(1-'3. Finansiering'!$C$10) -> 0 | F16: =-F$15*(1-'3. Finansiering'!$C$10) -> 0 | G16: =-G$15*(1-'3. Finansiering'!$C$10) -> 0 | H16: =-H$15*(1-'3. Finansiering'!$C$10) -> 0 | I16: =-I$15*(1-'3. Finansiering'!$C$10) -> 0 | J16: =-J$15*(1-'3. Finansiering'!$C$10) -> 0 | K16: =-K$15*(1-'3. Finansiering'!$C$10) -> 0 | ... BA16: =-BA$15*(1-'3. Finansiering'!$C$10) -> 0
B17: Belåning per investering | D17: =-'3. Finansiering'!$C$10*D$15 -> 88800000 | E17: =-'3. Finansiering'!$C$10*E$15 -> 0 | F17: =-'3. Finansiering'!$C$10*F$15 -> 0 | G17: =-'3. Finansiering'!$C$10*G$15 -> 0 | H17: =-'3. Finansiering'!$C$10*H$15 -> 0 | I17: =-'3. Finansiering'!$C$10*I$15 -> 0 | J17: =-'3. Finansiering'!$C$10*J$15 -> 0 | K17: =-'3. Finansiering'!$C$10*K$15 -> 0 | ... BA17: =-'3. Finansiering'!$C$10*BA$15 -> 0
B19: Upptagna lån | D19: =SUM($D$17:D$17) -> 88800000 | E19: =SUM($D$17:E$17) -> 88800000 | F19: =SUM($D$17:F$17) -> 88800000 | G19: =SUM($D$17:G$17) -> 88800000 | H19: =SUM($D$17:H$17) -> 88800000 | I19: =SUM($D$17:I$17) -> 88800000 | J19: =SUM($D$17:J$17) -> 88800000 | K19: =SUM($D$17:K$17) -> 88800000 | ... BA19: =SUM($D$17:BA$17) -> 88800000
B20: Amortering | C20: → 5. IRR | D20: =IF(D19>=0,D19*-'3. Finansiering'!$C$9,0) -> -2664000 | E20: =IF(E19>=0,E19*-'3. Finansiering'!$C$9,0) -> -2664000 | F20: =IF(F19>=0,F19*-'3. Finansiering'!$C$9,0) -> -2664000 | G20: =IF(G19>=0,G19*-'3. Finansiering'!$C$9,0) -> -2664000 | H20: =IF(H19>=0,H19*-'3. Finansiering'!$C$9,0) -> -2664000 | I20: =IF(I19>=0,I19*-'3. Finansiering'!$C$9,0) -> -2664000 | J20: =IF(J19>=0,J19*-'3. Finansiering'!$C$9,0) -> -2664000 | K20: =IF(K19>=0,K19*-'3. Finansiering'!$C$9,0) -> -2664000 | ... BA20: =IF(BA19>=0,BA19*-'3. Finansiering'!$C$9,0) -> -2664000
B21: Ackumulerad amortering | D21: =IF(IF(-SUM($D$20:D$20)>D19,D19,SUM($D$20:D$20))>=D19,0,(IF(-SUM($D$20:D$20)>D19,D19,SUM($D$20:D$20)))) -> -2664000 | E21: =IF(IF(-SUM($D$20:E$20)>E19,E19,SUM($D$20:E$20))>=E19,0,(IF(-SUM($D$20:E$20)>E19,E19,SUM($D$20:E$20)))) -> -5328000 | F21: =IF(IF(-SUM($D$20:F$20)>F19,F19,SUM($D$20:F$20))>=F19,0,(IF(-SUM($D$20:F$20)>F19,F19,SUM($D$20:F$20)))) -> -7992000 | G21: =IF(IF(-SUM($D$20:G$20)>G19,G19,SUM($D$20:G$20))>=G19,0,(IF(-SUM($D$20:G$20)>G19,G19,SUM($D$20:G$20)))) -> -10656000 | H21: =IF(IF(-SUM($D$20:H$20)>H19,H19,SUM($D$20:H$20))>=H19,0,(IF(-SUM($D$20:H$20)>H19,H19,SUM($D$20:H$20)))) -> -13320000 | I21: =IF(IF(-SUM($D$20:I$20)>I19,I19,SUM($D$20:I$20))>=I19,0,(IF(-SUM($D$20:I$20)>I19,I19,SUM($D$20:I$20)))) -> -15984000 | J21: =IF(IF(-SUM($D$20:J$20)>J19,J19,SUM($D$20:J$20))>=J19,0,(IF(-SUM($D$20:J$20)>J19,J19,SUM($D$20:J$20)))) -> -18648000 | K21: =IF(IF(-SUM($D$20:K$20)>K19,K19,SUM($D$20:K$20))>=K19,0,(IF(-SUM($D$20:K$20)>K19,K19,SUM($D$20:K$20)))) -> -21312000 | ... BA21: =IF(IF(-SUM($D$20:BA$20)>BA19,BA19,SUM($D$20:BA$20))>=BA19,0,(IF(-SUM($D$20:BA$20)>BA19,BA19,SUM($D$20:BA$20)))) -> 0
B22: Återstående skuld vid årets slut | C22: → 5. IRR | D22: =IF(D$21>0,0,D$19+D$21) -> 86136000 | E22: =IF(E$21>0,0,E$19+E$21) -> 83472000 | F22: =IF(F$21>0,0,F$19+F$21) -> 80808000 | G22: =IF(G$21>0,0,G$19+G$21) -> 78144000 | H22: =IF(H$21>0,0,H$19+H$21) -> 75480000 | I22: =IF(I$21>0,0,I$19+I$21) -> 72816000 | J22: =IF(J$21>0,0,J$19+J$21) -> 70152000 | K22: =IF(K$21>0,0,K$19+K$21) -> 67488000 | ... BA22: =IF(BA$21>0,0,BA$19+BA$21) -> 88800000
B23: Räntesats (trappas upp år 1–11) | D23: ='3. Finansiering'!C7 -> 0.0307 | E23: =IF('3. Finansiering'!$C$7+(('3. Finansiering'!$C$8-'3. Finansiering'!$C$7)*(D14/$M$14))>'3. Finansiering'!$C$8,'3. Finansiering'!$C$8,('3. Finansiering'!$C$7+(('3. Finansiering'!$C$8-'3. Finansiering'!$C$7)*(D14/$M$14)))) -> 0.03218 | F23: =IF('3. Finansiering'!$C$7+(('3. Finansiering'!$C$8-'3. Finansiering'!$C$7)*(E14/$M$14))>'3. Finansiering'!$C$8,'3. Finansiering'!$C$8,('3. Finansiering'!$C$7+(('3. Finansiering'!$C$8-'3. Finansiering'!$C$7)*(E14/$M$14)))) -> 0.03366 | G23: =IF('3. Finansiering'!$C$7+(('3. Finansiering'!$C$8-'3. Finansiering'!$C$7)*(F14/$M$14))>'3. Finansiering'!$C$8,'3. Finansiering'!$C$8,('3. Finansiering'!$C$7+(('3. Finansiering'!$C$8-'3. Finansiering'!$C$7)*(F14/$M$14)))) -> 0.03514 | H23: =IF('3. Finansiering'!$C$7+(('3. Finansiering'!$C$8-'3. Finansiering'!$C$7)*(G14/$M$14))>'3. Finansiering'!$C$8,'3. Finansiering'!$C$8,('3. Finansiering'!$C$7+(('3. Finansiering'!$C$8-'3. Finansiering'!$C$7)*(G14/$M$14)))) -> 0.03662 | I23: =IF('3. Finansiering'!$C$7+(('3. Finansiering'!$C$8-'3. Finansiering'!$C$7)*(H14/$M$14))>'3. Finansiering'!$C$8,'3. Finansiering'!$C$8,('3. Finansiering'!$C$7+(('3. Finansiering'!$C$8-'3. Finansiering'!$C$7)*(H14/$M$14)))) -> 0.0381 | J23: =IF('3. Finansiering'!$C$7+(('3. Finansiering'!$C$8-'3. Finansiering'!$C$7)*(I14/$M$14))>'3. Finansiering'!$C$8,'3. Finansiering'!$C$8,('3. Finansiering'!$C$7+(('3. Finansiering'!$C$8-'3. Finansiering'!$C$7)*(I14/$M$14)))) -> 0.03958 | K23: =IF('3. Finansiering'!$C$7+(('3. Finansiering'!$C$8-'3. Finansiering'!$C$7)*(J14/$M$14))>'3. Finansiering'!$C$8,'3. Finansiering'!$C$8,('3. Finansiering'!$C$7+(('3. Finansiering'!$C$8-'3. Finansiering'!$C$7)*(J14/$M$14)))) -> 0.04106 | L23: =IF('3. Finansiering'!$C$7+(('3. Finansiering'!$C$8-'3. Finansiering'!$C$7)*(K14/$M$14))>'3. Finansiering'!$C$8,'3. Finansiering'!$C$8,('3. Finansiering'!$C$7+(('3. Finansiering'!$C$8-'3. Finansiering'!$C$7)*(K14/$M$14)))) -> 0.04254 | ... BA23: =IF('3. Finansiering'!$C$7+(('3. Finansiering'!$C$8-'3. Finansiering'!$C$7)*(AZ14/$M$14))>'3. Finansiering'!$C$8,'3. Finansiering'!$C$8,('3. Finansiering'!$C$7+(('3. Finansiering'!$C$8-'3. Finansiering'!$C$7)*(AZ14/$M$14)))) -> 0.0455
B24: Räntekostnad | C24: → 5. IRR | D24: =-D23*D22 -> -2644375.2 | E24: =-E23*E22 -> -2686129 | F24: =-F23*F22 -> -2719997.3 | G24: =-G23*G22 -> -2745980.2 | H24: =-H23*H22 -> -2764077.6 | I24: =-I23*I22 -> -2774289.6 | J24: =-J23*J22 -> -2776616.2 | K24: =-K23*K22 -> -2771057.3 | ... BA24: =-BA23*BA22 -> -4040400
B26: Finansieringskostnad (ränta + amortering) | D26: =IF(D24=0,0,D24+D20) -> -5308375.2 | E26: =IF(E24=0,0,E24+E20) -> -5350129 | F26: =IF(F24=0,0,F24+F20) -> -5383997.3 | G26: =IF(G24=0,0,G24+G20) -> -5409980.2 | H26: =IF(H24=0,0,H24+H20) -> -5428077.6 | I26: =IF(I24=0,0,I24+I20) -> -5438289.6 | J26: =IF(J24=0,0,J24+J20) -> -5440616.2 | K26: =IF(K24=0,0,K24+K20) -> -5435057.3 | ... BA26: =IF(BA24=0,0,BA24+BA20) -> -6704400
B27: Belåningsgrad vid årets slut | C27: → 7.Grafer | D27: =D22/(ABS(SUM($D$15:D$15))) -> 0.3589 | E27: =E22/(ABS(SUM($D$15:E$15))) -> 0.3478 | F27: =F22/(ABS(SUM($D$15:F$15))) -> 0.3367 | G27: =G22/(ABS(SUM($D$15:G$15))) -> 0.3256 | H27: =H22/(ABS(SUM($D$15:H$15))) -> 0.3145 | I27: =I22/(ABS(SUM($D$15:I$15))) -> 0.3034 | J27: =J22/(ABS(SUM($D$15:J$15))) -> 0.2923 | K27: =K22/(ABS(SUM($D$15:K$15))) -> 0.2812 | ... BA27: =BA22/(ABS(SUM($D$15:BA$15))) -> 0.37
B29: BOKFÖRT VÄRDE | C29: Högsta värde | D29: =IF(D14<='2. Kalkyldata'!$P$16,'3. Finansiering'!D13,"") -> 2026 | E29: =IF(E14<='2. Kalkyldata'!$P$16,'3. Finansiering'!E13,"") -> 2027 | F29: =IF(F14<='2. Kalkyldata'!$P$16,'3. Finansiering'!F13,"") -> 2028 | G29: =IF(G14<='2. Kalkyldata'!$P$16,'3. Finansiering'!G13,"") -> 2029 | H29: =IF(H14<='2. Kalkyldata'!$P$16,'3. Finansiering'!H13,"") -> 2030 | I29: =IF(I14<='2. Kalkyldata'!$P$16,'3. Finansiering'!I13,"") -> 2031 | J29: =IF(J14<='2. Kalkyldata'!$P$16,'3. Finansiering'!J13,"") -> 2032 | K29: =IF(K14<='2. Kalkyldata'!$P$16,'3. Finansiering'!K13,"") -> 2033 | ... BA29: =IF(BA14<='2. Kalkyldata'!$P$16,'3. Finansiering'!BA13,"") | BB29: =IF(BB13>=BB13+'2. Kalkyldata'!$P$16,"",'3. Finansiering'!BB13) -> 0
B30: Befintligt bokfört värde | D30: =IF(D$29="",0,('2. Kalkyldata'!$P$9-SUMIF('2. Kalkyldata'!$R$23:$R$27,'3. Finansiering'!D$12,'2. Kalkyldata'!$AA$23:$AA$27))) -> 0 | E30: =IF(E$29="",0,('2. Kalkyldata'!$P$9-SUMIF('2. Kalkyldata'!$R$23:$R$27,'3. Finansiering'!E$12,'2. Kalkyldata'!$AA$23:$AA$27))) -> 0 | F30: =IF(F$29="",0,('2. Kalkyldata'!$P$9-SUMIF('2. Kalkyldata'!$R$23:$R$27,'3. Finansiering'!F$12,'2. Kalkyldata'!$AA$23:$AA$27))) -> 0 | G30: =IF(G$29="",0,('2. Kalkyldata'!$P$9-SUMIF('2. Kalkyldata'!$R$23:$R$27,'3. Finansiering'!G$12,'2. Kalkyldata'!$AA$23:$AA$27))) -> 0 | H30: =IF(H$29="",0,('2. Kalkyldata'!$P$9-SUMIF('2. Kalkyldata'!$R$23:$R$27,'3. Finansiering'!H$12,'2. Kalkyldata'!$AA$23:$AA$27))) -> 0 | I30: =IF(I$29="",0,('2. Kalkyldata'!$P$9-SUMIF('2. Kalkyldata'!$R$23:$R$27,'3. Finansiering'!I$12,'2. Kalkyldata'!$AA$23:$AA$27))) -> 0 | J30: =IF(J$29="",0,('2. Kalkyldata'!$P$9-SUMIF('2. Kalkyldata'!$R$23:$R$27,'3. Finansiering'!J$12,'2. Kalkyldata'!$AA$23:$AA$27))) -> 0 | K30: =IF(K$29="",0,('2. Kalkyldata'!$P$9-SUMIF('2. Kalkyldata'!$R$23:$R$27,'3. Finansiering'!K$12,'2. Kalkyldata'!$AA$23:$AA$27))) -> 0 | ... BA30: =IF(BA$29="",0,('2. Kalkyldata'!$P$9-SUMIF('2. Kalkyldata'!$R$23:$R$27,'3. Finansiering'!BA$12,'2. Kalkyldata'!$AA$23:$AA$27))) -> 0
B31: ='2. Kalkyldata'!C23 -> Skola | D31: =IF(D$29="",0,SUMIFS('2. Kalkyldata'!$W$23:$W$27,'2. Kalkyldata'!$C$23:$C$27,'3. Finansiering'!$B31,'2. Kalkyldata'!$R$23:$R$27,'3. Finansiering'!D$12)) -> 2.4e+08 | E31: =IF(E$29="",0,SUMIFS('2. Kalkyldata'!$W$23:$W$27,'2. Kalkyldata'!$C$23:$C$27,'3. Finansiering'!$B31,'2. Kalkyldata'!$R$23:$R$27,'3. Finansiering'!E$12)) -> 2.4e+08 | F31: =IF(F$29="",0,SUMIFS('2. Kalkyldata'!$W$23:$W$27,'2. Kalkyldata'!$C$23:$C$27,'3. Finansiering'!$B31,'2. Kalkyldata'!$R$23:$R$27,'3. Finansiering'!F$12)) -> 2.4e+08 | G31: =IF(G$29="",0,SUMIFS('2. Kalkyldata'!$W$23:$W$27,'2. Kalkyldata'!$C$23:$C$27,'3. Finansiering'!$B31,'2. Kalkyldata'!$R$23:$R$27,'3. Finansiering'!G$12)) -> 2.4e+08 | H31: =IF(H$29="",0,SUMIFS('2. Kalkyldata'!$W$23:$W$27,'2. Kalkyldata'!$C$23:$C$27,'3. Finansiering'!$B31,'2. Kalkyldata'!$R$23:$R$27,'3. Finansiering'!H$12)) -> 2.4e+08 | I31: =IF(I$29="",0,SUMIFS('2. Kalkyldata'!$W$23:$W$27,'2. Kalkyldata'!$C$23:$C$27,'3. Finansiering'!$B31,'2. Kalkyldata'!$R$23:$R$27,'3. Finansiering'!I$12)) -> 2.4e+08 | J31: =IF(J$29="",0,SUMIFS('2. Kalkyldata'!$W$23:$W$27,'2. Kalkyldata'!$C$23:$C$27,'3. Finansiering'!$B31,'2. Kalkyldata'!$R$23:$R$27,'3. Finansiering'!J$12)) -> 2.4e+08 | K31: =IF(K$29="",0,SUMIFS('2. Kalkyldata'!$W$23:$W$27,'2. Kalkyldata'!$C$23:$C$27,'3. Finansiering'!$B31,'2. Kalkyldata'!$R$23:$R$27,'3. Finansiering'!K$12)) -> 2.4e+08 | ... BA31: =IF(BA$29="",0,SUMIFS('2. Kalkyldata'!$W$23:$W$27,'2. Kalkyldata'!$C$23:$C$27,'3. Finansiering'!$B31,'2. Kalkyldata'!$R$23:$R$27,'3. Finansiering'!BA$12)) -> 0
B32: ='2. Kalkyldata'!C24 -> 0 | D32: =IF(D$29="",0,SUMIFS('2. Kalkyldata'!$W$23:$W$27,'2. Kalkyldata'!$C$23:$C$27,'3. Finansiering'!$B32,'2. Kalkyldata'!$R$23:$R$27,'3. Finansiering'!D$12)) -> 0 | E32: =IF(E$29="",0,SUMIFS('2. Kalkyldata'!$W$23:$W$27,'2. Kalkyldata'!$C$23:$C$27,'3. Finansiering'!$B32,'2. Kalkyldata'!$R$23:$R$27,'3. Finansiering'!E$12)) -> 0 | F32: =IF(F$29="",0,SUMIFS('2. Kalkyldata'!$W$23:$W$27,'2. Kalkyldata'!$C$23:$C$27,'3. Finansiering'!$B32,'2. Kalkyldata'!$R$23:$R$27,'3. Finansiering'!F$12)) -> 0 | G32: =IF(G$29="",0,SUMIFS('2. Kalkyldata'!$W$23:$W$27,'2. Kalkyldata'!$C$23:$C$27,'3. Finansiering'!$B32,'2. Kalkyldata'!$R$23:$R$27,'3. Finansiering'!G$12)) -> 0 | H32: =IF(H$29="",0,SUMIFS('2. Kalkyldata'!$W$23:$W$27,'2. Kalkyldata'!$C$23:$C$27,'3. Finansiering'!$B32,'2. Kalkyldata'!$R$23:$R$27,'3. Finansiering'!H$12)) -> 0 | I32: =IF(I$29="",0,SUMIFS('2. Kalkyldata'!$W$23:$W$27,'2. Kalkyldata'!$C$23:$C$27,'3. Finansiering'!$B32,'2. Kalkyldata'!$R$23:$R$27,'3. Finansiering'!I$12)) -> 0 | J32: =IF(J$29="",0,SUMIFS('2. Kalkyldata'!$W$23:$W$27,'2. Kalkyldata'!$C$23:$C$27,'3. Finansiering'!$B32,'2. Kalkyldata'!$R$23:$R$27,'3. Finansiering'!J$12)) -> 0 | K32: =IF(K$29="",0,SUMIFS('2. Kalkyldata'!$W$23:$W$27,'2. Kalkyldata'!$C$23:$C$27,'3. Finansiering'!$B32,'2. Kalkyldata'!$R$23:$R$27,'3. Finansiering'!K$12)) -> 0 | ... BA32: =IF(BA$29="",0,SUMIFS('2. Kalkyldata'!$W$23:$W$27,'2. Kalkyldata'!$C$23:$C$27,'3. Finansiering'!$B32,'2. Kalkyldata'!$R$23:$R$27,'3. Finansiering'!BA$12)) -> 0
B33: ='2. Kalkyldata'!C25 -> 0 | D33: =IF(D$29="",0,SUMIFS('2. Kalkyldata'!$W$23:$W$27,'2. Kalkyldata'!$C$23:$C$27,'3. Finansiering'!$B33,'2. Kalkyldata'!$R$23:$R$27,'3. Finansiering'!D$12)) -> 0 | E33: =IF(E$29="",0,SUMIFS('2. Kalkyldata'!$W$23:$W$27,'2. Kalkyldata'!$C$23:$C$27,'3. Finansiering'!$B33,'2. Kalkyldata'!$R$23:$R$27,'3. Finansiering'!E$12)) -> 0 | F33: =IF(F$29="",0,SUMIFS('2. Kalkyldata'!$W$23:$W$27,'2. Kalkyldata'!$C$23:$C$27,'3. Finansiering'!$B33,'2. Kalkyldata'!$R$23:$R$27,'3. Finansiering'!F$12)) -> 0 | G33: =IF(G$29="",0,SUMIFS('2. Kalkyldata'!$W$23:$W$27,'2. Kalkyldata'!$C$23:$C$27,'3. Finansiering'!$B33,'2. Kalkyldata'!$R$23:$R$27,'3. Finansiering'!G$12)) -> 0 | H33: =IF(H$29="",0,SUMIFS('2. Kalkyldata'!$W$23:$W$27,'2. Kalkyldata'!$C$23:$C$27,'3. Finansiering'!$B33,'2. Kalkyldata'!$R$23:$R$27,'3. Finansiering'!H$12)) -> 0 | I33: =IF(I$29="",0,SUMIFS('2. Kalkyldata'!$W$23:$W$27,'2. Kalkyldata'!$C$23:$C$27,'3. Finansiering'!$B33,'2. Kalkyldata'!$R$23:$R$27,'3. Finansiering'!I$12)) -> 0 | J33: =IF(J$29="",0,SUMIFS('2. Kalkyldata'!$W$23:$W$27,'2. Kalkyldata'!$C$23:$C$27,'3. Finansiering'!$B33,'2. Kalkyldata'!$R$23:$R$27,'3. Finansiering'!J$12)) -> 0 | K33: =IF(K$29="",0,SUMIFS('2. Kalkyldata'!$W$23:$W$27,'2. Kalkyldata'!$C$23:$C$27,'3. Finansiering'!$B33,'2. Kalkyldata'!$R$23:$R$27,'3. Finansiering'!K$12)) -> 0 | ... BA33: =IF(BA$29="",0,SUMIFS('2. Kalkyldata'!$W$23:$W$27,'2. Kalkyldata'!$C$23:$C$27,'3. Finansiering'!$B33,'2. Kalkyldata'!$R$23:$R$27,'3. Finansiering'!BA$12)) -> 0
B34: ='2. Kalkyldata'!C26 -> 0 | D34: =IF(D$29="",0,SUMIFS('2. Kalkyldata'!$W$23:$W$27,'2. Kalkyldata'!$C$23:$C$27,'3. Finansiering'!$B34,'2. Kalkyldata'!$R$23:$R$27,'3. Finansiering'!D$12)) -> 0 | E34: =IF(E$29="",0,SUMIFS('2. Kalkyldata'!$W$23:$W$27,'2. Kalkyldata'!$C$23:$C$27,'3. Finansiering'!$B34,'2. Kalkyldata'!$R$23:$R$27,'3. Finansiering'!E$12)) -> 0 | F34: =IF(F$29="",0,SUMIFS('2. Kalkyldata'!$W$23:$W$27,'2. Kalkyldata'!$C$23:$C$27,'3. Finansiering'!$B34,'2. Kalkyldata'!$R$23:$R$27,'3. Finansiering'!F$12)) -> 0 | G34: =IF(G$29="",0,SUMIFS('2. Kalkyldata'!$W$23:$W$27,'2. Kalkyldata'!$C$23:$C$27,'3. Finansiering'!$B34,'2. Kalkyldata'!$R$23:$R$27,'3. Finansiering'!G$12)) -> 0 | H34: =IF(H$29="",0,SUMIFS('2. Kalkyldata'!$W$23:$W$27,'2. Kalkyldata'!$C$23:$C$27,'3. Finansiering'!$B34,'2. Kalkyldata'!$R$23:$R$27,'3. Finansiering'!H$12)) -> 0 | I34: =IF(I$29="",0,SUMIFS('2. Kalkyldata'!$W$23:$W$27,'2. Kalkyldata'!$C$23:$C$27,'3. Finansiering'!$B34,'2. Kalkyldata'!$R$23:$R$27,'3. Finansiering'!I$12)) -> 0 | J34: =IF(J$29="",0,SUMIFS('2. Kalkyldata'!$W$23:$W$27,'2. Kalkyldata'!$C$23:$C$27,'3. Finansiering'!$B34,'2. Kalkyldata'!$R$23:$R$27,'3. Finansiering'!J$12)) -> 0 | K34: =IF(K$29="",0,SUMIFS('2. Kalkyldata'!$W$23:$W$27,'2. Kalkyldata'!$C$23:$C$27,'3. Finansiering'!$B34,'2. Kalkyldata'!$R$23:$R$27,'3. Finansiering'!K$12)) -> 0 | ... BA34: =IF(BA$29="",0,SUMIFS('2. Kalkyldata'!$W$23:$W$27,'2. Kalkyldata'!$C$23:$C$27,'3. Finansiering'!$B34,'2. Kalkyldata'!$R$23:$R$27,'3. Finansiering'!BA$12)) -> 0
B35: ='2. Kalkyldata'!C27 -> 0 | D35: =IF(D$29="",0,SUMIFS('2. Kalkyldata'!$W$23:$W$27,'2. Kalkyldata'!$C$23:$C$27,'3. Finansiering'!$B35,'2. Kalkyldata'!$R$23:$R$27,'3. Finansiering'!D$12)) -> 0 | E35: =IF(E$29="",0,SUMIFS('2. Kalkyldata'!$W$23:$W$27,'2. Kalkyldata'!$C$23:$C$27,'3. Finansiering'!$B35,'2. Kalkyldata'!$R$23:$R$27,'3. Finansiering'!E$12)) -> 0 | F35: =IF(F$29="",0,SUMIFS('2. Kalkyldata'!$W$23:$W$27,'2. Kalkyldata'!$C$23:$C$27,'3. Finansiering'!$B35,'2. Kalkyldata'!$R$23:$R$27,'3. Finansiering'!F$12)) -> 0 | G35: =IF(G$29="",0,SUMIFS('2. Kalkyldata'!$W$23:$W$27,'2. Kalkyldata'!$C$23:$C$27,'3. Finansiering'!$B35,'2. Kalkyldata'!$R$23:$R$27,'3. Finansiering'!G$12)) -> 0 | H35: =IF(H$29="",0,SUMIFS('2. Kalkyldata'!$W$23:$W$27,'2. Kalkyldata'!$C$23:$C$27,'3. Finansiering'!$B35,'2. Kalkyldata'!$R$23:$R$27,'3. Finansiering'!H$12)) -> 0 | I35: =IF(I$29="",0,SUMIFS('2. Kalkyldata'!$W$23:$W$27,'2. Kalkyldata'!$C$23:$C$27,'3. Finansiering'!$B35,'2. Kalkyldata'!$R$23:$R$27,'3. Finansiering'!I$12)) -> 0 | J35: =IF(J$29="",0,SUMIFS('2. Kalkyldata'!$W$23:$W$27,'2. Kalkyldata'!$C$23:$C$27,'3. Finansiering'!$B35,'2. Kalkyldata'!$R$23:$R$27,'3. Finansiering'!J$12)) -> 0 | K35: =IF(K$29="",0,SUMIFS('2. Kalkyldata'!$W$23:$W$27,'2. Kalkyldata'!$C$23:$C$27,'3. Finansiering'!$B35,'2. Kalkyldata'!$R$23:$R$27,'3. Finansiering'!K$12)) -> 0 | ... BA35: =IF(BA$29="",0,SUMIFS('2. Kalkyldata'!$W$23:$W$27,'2. Kalkyldata'!$C$23:$C$27,'3. Finansiering'!$B35,'2. Kalkyldata'!$R$23:$R$27,'3. Finansiering'!BA$12)) -> 0
B36: Residual | D36: =IF(D$29="",0,SUMIFS('2. Kalkyldata'!$W$23:$W$27,'2. Kalkyldata'!$C$23:$C$27,'3. Finansiering'!$B36,'2. Kalkyldata'!$R$23:$R$27,'3. Finansiering'!D$12)) -> 0 | E36: =IF(E$29="",0,SUMIFS('2. Kalkyldata'!$W$23:$W$27,'2. Kalkyldata'!$C$23:$C$27,'3. Finansiering'!$B36,'2. Kalkyldata'!$R$23:$R$27,'3. Finansiering'!E$12)) -> 0 | F36: =IF(F$29="",0,SUMIFS('2. Kalkyldata'!$W$23:$W$27,'2. Kalkyldata'!$C$23:$C$27,'3. Finansiering'!$B36,'2. Kalkyldata'!$R$23:$R$27,'3. Finansiering'!F$12)) -> 0 | G36: =IF(G$29="",0,SUMIFS('2. Kalkyldata'!$W$23:$W$27,'2. Kalkyldata'!$C$23:$C$27,'3. Finansiering'!$B36,'2. Kalkyldata'!$R$23:$R$27,'3. Finansiering'!G$12)) -> 0 | H36: =IF(H$29="",0,SUMIFS('2. Kalkyldata'!$W$23:$W$27,'2. Kalkyldata'!$C$23:$C$27,'3. Finansiering'!$B36,'2. Kalkyldata'!$R$23:$R$27,'3. Finansiering'!H$12)) -> 0 | I36: =IF(I$29="",0,SUMIFS('2. Kalkyldata'!$W$23:$W$27,'2. Kalkyldata'!$C$23:$C$27,'3. Finansiering'!$B36,'2. Kalkyldata'!$R$23:$R$27,'3. Finansiering'!I$12)) -> 0 | J36: =IF(J$29="",0,SUMIFS('2. Kalkyldata'!$W$23:$W$27,'2. Kalkyldata'!$C$23:$C$27,'3. Finansiering'!$B36,'2. Kalkyldata'!$R$23:$R$27,'3. Finansiering'!J$12)) -> 0 | K36: =IF(K$29="",0,SUMIFS('2. Kalkyldata'!$W$23:$W$27,'2. Kalkyldata'!$C$23:$C$27,'3. Finansiering'!$B36,'2. Kalkyldata'!$R$23:$R$27,'3. Finansiering'!K$12)) -> 0 | ... BA36: =IF(BA$29="",0,SUMIFS('2. Kalkyldata'!$W$23:$W$27,'2. Kalkyldata'!$C$23:$C$27,'3. Finansiering'!$B36,'2. Kalkyldata'!$R$23:$R$27,'3. Finansiering'!BA$12)) -> 0
B37: ='2. Kalkyldata'!C28 -> Totalt | C37: =MAX($D$37:$BA$37) -> 2.4e+08 | D37: =SUM(D30:D35) -> 2.4e+08 | E37: =SUM(E30:E35) -> 2.4e+08 | F37: =SUM(F30:F35) -> 2.4e+08 | G37: =SUM(G30:G35) -> 2.4e+08 | H37: =SUM(H30:H35) -> 2.4e+08 | I37: =SUM(I30:I35) -> 2.4e+08 | J37: =SUM(J30:J35) -> 2.4e+08 | K37: =SUM(K30:K35) -> 2.4e+08 | ... BA37: =SUM(BA30:BA35) -> 0
B39: AVSKRIVNING | C39: Rak avskrivning; avskrivningstider enligt 2. Kalkyldata P13/P16. Per objekt i grupperade rader 40–46.
B40: Befintligt bokfört värde | D40: =-D30/'2. Kalkyldata'!$P$13 -> 0 | E40: =-E30/'2. Kalkyldata'!$P$13 -> 0 | F40: =-F30/'2. Kalkyldata'!$P$13 -> 0 | G40: =-G30/'2. Kalkyldata'!$P$13 -> 0 | H40: =-H30/'2. Kalkyldata'!$P$13 -> 0 | I40: =-I30/'2. Kalkyldata'!$P$13 -> 0 | J40: =-J30/'2. Kalkyldata'!$P$13 -> 0 | K40: =-K30/'2. Kalkyldata'!$P$13 -> 0 | ... BA40: =-BA30/'2. Kalkyldata'!$P$13 -> 0
B41: =B31 -> Skola | D41: =IF(D$29<'2. Kalkyldata'!$M23,0,-D31/'2. Kalkyldata'!$P$16) -> -7272727.3 | E41: =IF(E$29<'2. Kalkyldata'!$M23,0,-E31/'2. Kalkyldata'!$P$16) -> -7272727.3 | F41: =IF(F$29<'2. Kalkyldata'!$M23,0,-F31/'2. Kalkyldata'!$P$16) -> -7272727.3 | G41: =IF(G$29<'2. Kalkyldata'!$M23,0,-G31/'2. Kalkyldata'!$P$16) -> -7272727.3 | H41: =IF(H$29<'2. Kalkyldata'!$M23,0,-H31/'2. Kalkyldata'!$P$16) -> -7272727.3 | I41: =IF(I$29<'2. Kalkyldata'!$M23,0,-I31/'2. Kalkyldata'!$P$16) -> -7272727.3 | J41: =IF(J$29<'2. Kalkyldata'!$M23,0,-J31/'2. Kalkyldata'!$P$16) -> -7272727.3 | K41: =IF(K$29<'2. Kalkyldata'!$M23,0,-K31/'2. Kalkyldata'!$P$16) -> -7272727.3 | ... BA41: =IF(BA$29<'2. Kalkyldata'!$M23,0,-BA31/'2. Kalkyldata'!$P$16) -> 0
B42: =B32 -> 0 | D42: =IF(D$29<'2. Kalkyldata'!$M24,0,-D32/'2. Kalkyldata'!$P$16) -> 0 | E42: =IF(E$29<'2. Kalkyldata'!$M24,0,-E32/'2. Kalkyldata'!$P$16) -> 0 | F42: =IF(F$29<'2. Kalkyldata'!$M24,0,-F32/'2. Kalkyldata'!$P$16) -> 0 | G42: =IF(G$29<'2. Kalkyldata'!$M24,0,-G32/'2. Kalkyldata'!$P$16) -> 0 | H42: =IF(H$29<'2. Kalkyldata'!$M24,0,-H32/'2. Kalkyldata'!$P$16) -> 0 | I42: =IF(I$29<'2. Kalkyldata'!$M24,0,-I32/'2. Kalkyldata'!$P$16) -> 0 | J42: =IF(J$29<'2. Kalkyldata'!$M24,0,-J32/'2. Kalkyldata'!$P$16) -> 0 | K42: =IF(K$29<'2. Kalkyldata'!$M24,0,-K32/'2. Kalkyldata'!$P$16) -> 0 | ... BA42: =IF(BA$29<'2. Kalkyldata'!$M24,0,-BA32/'2. Kalkyldata'!$P$16) -> 0
B43: =B33 -> 0 | D43: =IF(D$29<'2. Kalkyldata'!$M25,0,-D33/'2. Kalkyldata'!$P$16) -> 0 | E43: =IF(E$29<'2. Kalkyldata'!$M25,0,-E33/'2. Kalkyldata'!$P$16) -> 0 | F43: =IF(F$29<'2. Kalkyldata'!$M25,0,-F33/'2. Kalkyldata'!$P$16) -> 0 | G43: =IF(G$29<'2. Kalkyldata'!$M25,0,-G33/'2. Kalkyldata'!$P$16) -> 0 | H43: =IF(H$29<'2. Kalkyldata'!$M25,0,-H33/'2. Kalkyldata'!$P$16) -> 0 | I43: =IF(I$29<'2. Kalkyldata'!$M25,0,-I33/'2. Kalkyldata'!$P$16) -> 0 | J43: =IF(J$29<'2. Kalkyldata'!$M25,0,-J33/'2. Kalkyldata'!$P$16) -> 0 | K43: =IF(K$29<'2. Kalkyldata'!$M25,0,-K33/'2. Kalkyldata'!$P$16) -> 0 | ... BA43: =IF(BA$29<'2. Kalkyldata'!$M25,0,-BA33/'2. Kalkyldata'!$P$16) -> 0
B44: =B34 -> 0 | D44: =IF(D$29<'2. Kalkyldata'!$M26,0,-D34/'2. Kalkyldata'!$P$16) -> 0 | E44: =IF(E$29<'2. Kalkyldata'!$M26,0,-E34/'2. Kalkyldata'!$P$16) -> 0 | F44: =IF(F$29<'2. Kalkyldata'!$M26,0,-F34/'2. Kalkyldata'!$P$16) -> 0 | G44: =IF(G$29<'2. Kalkyldata'!$M26,0,-G34/'2. Kalkyldata'!$P$16) -> 0 | H44: =IF(H$29<'2. Kalkyldata'!$M26,0,-H34/'2. Kalkyldata'!$P$16) -> 0 | I44: =IF(I$29<'2. Kalkyldata'!$M26,0,-I34/'2. Kalkyldata'!$P$16) -> 0 | J44: =IF(J$29<'2. Kalkyldata'!$M26,0,-J34/'2. Kalkyldata'!$P$16) -> 0 | K44: =IF(K$29<'2. Kalkyldata'!$M26,0,-K34/'2. Kalkyldata'!$P$16) -> 0 | ... BA44: =IF(BA$29<'2. Kalkyldata'!$M26,0,-BA34/'2. Kalkyldata'!$P$16) -> 0
B45: =B35 -> 0 | D45: =IF(D$29<'2. Kalkyldata'!$M27,0,-D35/'2. Kalkyldata'!$P$16) -> 0 | E45: =IF(E$29<'2. Kalkyldata'!$M27,0,-E35/'2. Kalkyldata'!$P$16) -> 0 | F45: =IF(F$29<'2. Kalkyldata'!$M27,0,-F35/'2. Kalkyldata'!$P$16) -> 0 | G45: =IF(G$29<'2. Kalkyldata'!$M27,0,-G35/'2. Kalkyldata'!$P$16) -> 0 | H45: =IF(H$29<'2. Kalkyldata'!$M27,0,-H35/'2. Kalkyldata'!$P$16) -> 0 | I45: =IF(I$29<'2. Kalkyldata'!$M27,0,-I35/'2. Kalkyldata'!$P$16) -> 0 | J45: =IF(J$29<'2. Kalkyldata'!$M27,0,-J35/'2. Kalkyldata'!$P$16) -> 0 | K45: =IF(K$29<'2. Kalkyldata'!$M27,0,-K35/'2. Kalkyldata'!$P$16) -> 0 | ... BA45: =IF(BA$29<'2. Kalkyldata'!$M27,0,-BA35/'2. Kalkyldata'!$P$16) -> 0
B46: Residual | D46: =IF(D$29<'2. Kalkyldata'!$M28,0,-D36/'2. Kalkyldata'!$P$16) -> 0 | E46: =IF(E$29<'2. Kalkyldata'!$M28,0,-E36/'2. Kalkyldata'!$P$16) -> 0 | F46: =IF(F$29<'2. Kalkyldata'!$M28,0,-F36/'2. Kalkyldata'!$P$16) -> 0 | G46: =IF(G$29<'2. Kalkyldata'!$M28,0,-G36/'2. Kalkyldata'!$P$16) -> 0 | H46: =IF(H$29<'2. Kalkyldata'!$M28,0,-H36/'2. Kalkyldata'!$P$16) -> 0 | I46: =IF(I$29<'2. Kalkyldata'!$M28,0,-I36/'2. Kalkyldata'!$P$16) -> 0 | J46: =IF(J$29<'2. Kalkyldata'!$M28,0,-J36/'2. Kalkyldata'!$P$16) -> 0 | K46: =IF(K$29<'2. Kalkyldata'!$M28,0,-K36/'2. Kalkyldata'!$P$16) -> 0 | ... BA46: =IF(BA$29<'2. Kalkyldata'!$M28,0,-BA36/'2. Kalkyldata'!$P$16) -> 0
B47: Årets avskrivning | C47: → 5. IRR | D47: =SUM(D40:D46) -> -7272727.3 | E47: =SUM(E40:E46) -> -7272727.3 | F47: =SUM(F40:F46) -> -7272727.3 | G47: =SUM(G40:G46) -> -7272727.3 | H47: =SUM(H40:H46) -> -7272727.3 | I47: =SUM(I40:I46) -> -7272727.3 | J47: =SUM(J40:J46) -> -7272727.3 | K47: =SUM(K40:K46) -> -7272727.3 | ... BA47: =SUM(BA40:BA46) -> 0
B49: ÅTERSTÅENDE BOKFÖRT VÄRDE | C49: Bokfört värde minus ackumulerad avskrivning (används i 5. IRR)
B50: Befintligt bokfört värde | D50: =IF(D30+SUM($D$40:D$40)<0,0,(D$30+SUM($D$40:D$40))) -> 0 | E50: =IF(E30+SUM($D$40:E$40)<0,0,(E$30+SUM($D$40:E$40))) -> 0 | F50: =IF(F30+SUM($D$40:F$40)<0,0,(F$30+SUM($D$40:F$40))) -> 0 | G50: =IF(G30+SUM($D$40:G$40)<0,0,(G$30+SUM($D$40:G$40))) -> 0 | H50: =IF(H30+SUM($D$40:H$40)<0,0,(H$30+SUM($D$40:H$40))) -> 0 | I50: =IF(I30+SUM($D$40:I$40)<0,0,(I$30+SUM($D$40:I$40))) -> 0 | J50: =IF(J30+SUM($D$40:J$40)<0,0,(J$30+SUM($D$40:J$40))) -> 0 | K50: =IF(K30+SUM($D$40:K$40)<0,0,(K$30+SUM($D$40:K$40))) -> 0 | ... BA50: =IF(BA30+SUM($D$40:BA$40)<0,0,(BA$30+SUM($D$40:BA$40))) -> 0
B51: =B41 -> Skola | D51: =IF(D31+SUM($D$41:D$41)<0,0,(D$31+SUM($D$41:D$41))) -> 2.3272727e+08 | E51: =IF(E31+SUM($D$41:E$41)<0,0,(E$31+SUM($D$41:E$41))) -> 2.2545455e+08 | F51: =IF(F31+SUM($D$41:F$41)<0,0,(F$31+SUM($D$41:F$41))) -> 2.1818182e+08 | G51: =IF(G31+SUM($D$41:G$41)<0,0,(G$31+SUM($D$41:G$41))) -> 2.1090909e+08 | H51: =IF(H31+SUM($D$41:H$41)<0,0,(H$31+SUM($D$41:H$41))) -> 2.0363636e+08 | I51: =IF(I31+SUM($D$41:I$41)<0,0,(I$31+SUM($D$41:I$41))) -> 1.9636364e+08 | J51: =IF(J31+SUM($D$41:J$41)<0,0,(J$31+SUM($D$41:J$41))) -> 1.8909091e+08 | K51: =IF(K31+SUM($D$41:K$41)<0,0,(K$31+SUM($D$41:K$41))) -> 1.8181818e+08 | ... BA51: =IF(BA31+SUM($D$41:BA$41)<0,0,(BA$31+SUM($D$41:BA$41))) -> 0
B52: =B42 -> 0 | D52: =IF(D32+SUM($D$42:D$42)<0,0,(D$32+SUM($D$42:D$42))) -> 0 | E52: =IF(E32+SUM($D$42:E$42)<0,0,(E$32+SUM($D$42:E$42))) -> 0 | F52: =IF(F32+SUM($D$42:F$42)<0,0,(F$32+SUM($D$42:F$42))) -> 0 | G52: =IF(G32+SUM($D$42:G$42)<0,0,(G$32+SUM($D$42:G$42))) -> 0 | H52: =IF(H32+SUM($D$42:H$42)<0,0,(H$32+SUM($D$42:H$42))) -> 0 | I52: =IF(I32+SUM($D$42:I$42)<0,0,(I$32+SUM($D$42:I$42))) -> 0 | J52: =IF(J32+SUM($D$42:J$42)<0,0,(J$32+SUM($D$42:J$42))) -> 0 | K52: =IF(K32+SUM($D$42:K$42)<0,0,(K$32+SUM($D$42:K$42))) -> 0 | ... BA52: =IF(BA32+SUM($D$42:BA$42)<0,0,(BA$32+SUM($D$42:BA$42))) -> 0
B53: =B43 -> 0 | D53: =IF(D33+SUM($D$43:D$43)<0,0,(D$33+SUM($D$43:D$43))) -> 0 | E53: =IF(E33+SUM($D$43:E$43)<0,0,(E$33+SUM($D$43:E$43))) -> 0 | F53: =IF(F33+SUM($D$43:F$43)<0,0,(F$33+SUM($D$43:F$43))) -> 0 | G53: =IF(G33+SUM($D$43:G$43)<0,0,(G$33+SUM($D$43:G$43))) -> 0 | H53: =IF(H33+SUM($D$43:H$43)<0,0,(H$33+SUM($D$43:H$43))) -> 0 | I53: =IF(I33+SUM($D$43:I$43)<0,0,(I$33+SUM($D$43:I$43))) -> 0 | J53: =IF(J33+SUM($D$43:J$43)<0,0,(J$33+SUM($D$43:J$43))) -> 0 | K53: =IF(K33+SUM($D$43:K$43)<0,0,(K$33+SUM($D$43:K$43))) -> 0 | ... BA53: =IF(BA33+SUM($D$43:BA$43)<0,0,(BA$33+SUM($D$43:BA$43))) -> 0
B54: =B44 -> 0 | D54: =IF(D34+SUM($D$44:D$44)<0,0,(D$34+SUM($D$44:D$44))) -> 0 | E54: =IF(E34+SUM($D$44:E$44)<0,0,(E$34+SUM($D$44:E$44))) -> 0 | F54: =IF(F34+SUM($D$44:F$44)<0,0,(F$34+SUM($D$44:F$44))) -> 0 | G54: =IF(G34+SUM($D$44:G$44)<0,0,(G$34+SUM($D$44:G$44))) -> 0 | H54: =IF(H34+SUM($D$44:H$44)<0,0,(H$34+SUM($D$44:H$44))) -> 0 | I54: =IF(I34+SUM($D$44:I$44)<0,0,(I$34+SUM($D$44:I$44))) -> 0 | J54: =IF(J34+SUM($D$44:J$44)<0,0,(J$34+SUM($D$44:J$44))) -> 0 | K54: =IF(K34+SUM($D$44:K$44)<0,0,(K$34+SUM($D$44:K$44))) -> 0 | ... BA54: =IF(BA34+SUM($D$44:BA$44)<0,0,(BA$34+SUM($D$44:BA$44))) -> 0
B55: =B45 -> 0 | D55: =IF(D35+SUM($D$45:D$45)<0,0,(D$35+SUM($D$45:D$45))) -> 0 | E55: =IF(E35+SUM($D$45:E$45)<0,0,(E$35+SUM($D$45:E$45))) -> 0 | F55: =IF(F35+SUM($D$45:F$45)<0,0,(F$35+SUM($D$45:F$45))) -> 0 | G55: =IF(G35+SUM($D$45:G$45)<0,0,(G$35+SUM($D$45:G$45))) -> 0 | H55: =IF(H35+SUM($D$45:H$45)<0,0,(H$35+SUM($D$45:H$45))) -> 0 | I55: =IF(I35+SUM($D$45:I$45)<0,0,(I$35+SUM($D$45:I$45))) -> 0 | J55: =IF(J35+SUM($D$45:J$45)<0,0,(J$35+SUM($D$45:J$45))) -> 0 | K55: =IF(K35+SUM($D$45:K$45)<0,0,(K$35+SUM($D$45:K$45))) -> 0 | ... BA55: =IF(BA35+SUM($D$45:BA$45)<0,0,(BA$35+SUM($D$45:BA$45))) -> 0
B56: =B46 -> Residual | D56: =IF(D29<>"",IF(D36+SUM($D$46:D$46)=0,0,(D36+SUM($D$46:D$46))),0) -> 0 | E56: =IF(E29<>"",IF(E36+SUM($D$46:E$46)=0,0,(E36+SUM($D$46:E$46))),0) -> 0 | F56: =IF(F29<>"",IF(F36+SUM($D$46:F$46)=0,0,(F36+SUM($D$46:F$46))),0) -> 0 | G56: =IF(G29<>"",IF(G36+SUM($D$46:G$46)=0,0,(G36+SUM($D$46:G$46))),0) -> 0 | H56: =IF(H29<>"",IF(H36+SUM($D$46:H$46)=0,0,(H36+SUM($D$46:H$46))),0) -> 0 | I56: =IF(I29<>"",IF(I36+SUM($D$46:I$46)=0,0,(I36+SUM($D$46:I$46))),0) -> 0 | J56: =IF(J29<>"",IF(J36+SUM($D$46:J$46)=0,0,(J36+SUM($D$46:J$46))),0) -> 0 | K56: =IF(K29<>"",IF(K36+SUM($D$46:K$46)=0,0,(K36+SUM($D$46:K$46))),0) -> 0 | ... BA56: =IF(BA29<>"",IF(BA36+SUM($D$46:BA$46)=0,0,(BA36+SUM($D$46:BA$46))),0) -> 0
B57: Bokfört värde vid årets slut | C57: → 5. IRR | D57: =IF(D29<>"",SUM(D50:D56),0) -> 2.3272727e+08 | E57: =IF(E29<>"",SUM(E50:E56),0) -> 2.2545455e+08 | F57: =IF(F29<>"",SUM(F50:F56),0) -> 2.1818182e+08 | G57: =IF(G29<>"",SUM(G50:G56),0) -> 2.1090909e+08 | H57: =IF(H29<>"",SUM(H50:H56),0) -> 2.0363636e+08 | I57: =IF(I29<>"",SUM(I50:I56),0) -> 1.9636364e+08 | J57: =IF(J29<>"",SUM(J50:J56),0) -> 1.8909091e+08 | K57: =IF(K29<>"",SUM(K50:K56),0) -> 1.8181818e+08 | ... BA57: =IF(BA29<>"",SUM(BA50:BA56),0) -> 0

Sheet 4. NPV
B1: Nettonuvärde (NPV)
B2: Nettonuvärdet (NPV) är nuvärdet av investeringens framtida driftnetton under kalkylperioden plus restvärdet vid periodens slut, diskonterat med kalkylräntan, minus investeringen. Beslutet läses på rad 82: NPV tillkommande (krav 1, ska vara ≥ 0). Rad 47–62 visar hela fastigheten (krav 3) och rad 84–91 hur restvärdet räknas.
D3: =CONCATENATE("<=",D4) -> <=2026 | E3: =CONCATENATE("<=",E4) -> <=2027 | F3: =CONCATENATE("<=",F4) -> <=2028 | G3: =CONCATENATE("<=",G4) -> <=2029 | H3: =CONCATENATE("<=",H4) -> <=2030 | I3: =CONCATENATE("<=",I4) -> <=2031 | J3: =CONCATENATE("<=",J4) -> <=2032 | K3: =CONCATENATE("<=",K4) -> <=2033 | ... BA3: =CONCATENATE("<=",BA4) -> <=
D4: =_xlfn.NUMBERVALUE('3. Finansiering'!D$13) -> 2026 | E4: ='3. Finansiering'!E$13 -> 2027 | F4: ='3. Finansiering'!F$13 -> 2028 | G4: ='3. Finansiering'!G$13 -> 2029 | H4: ='3. Finansiering'!H$13 -> 2030 | I4: ='3. Finansiering'!I$13 -> 2031 | J4: ='3. Finansiering'!J$13 -> 2032 | K4: ='3. Finansiering'!K$13 -> 2033 | L4: ='3. Finansiering'!L$13 -> 2034 | ... BA4: ='3. Finansiering'!BA$13
B5: Kalkylår nr | D5: ='3. Finansiering'!D14 -> 1 | E5: ='3. Finansiering'!E14 -> 2 | F5: ='3. Finansiering'!F14 -> 3 | G5: ='3. Finansiering'!G14 -> 4 | H5: ='3. Finansiering'!H14 -> 5 | I5: ='3. Finansiering'!I14 -> 6 | J5: ='3. Finansiering'!J14 -> 7 | K5: ='3. Finansiering'!K14 -> 8 | ... BA5: ='3. Finansiering'!BA14 -> 50
B6: Area nybyggnad, kvm | D6: =SUMIFS('2. Kalkyldata'!$H$23:$H$27,'2. Kalkyldata'!$E$23:$E$27,"nyb",'2. Kalkyldata'!$M$23:$M$27,'4. NPV'!D3) -> 6100 | E6: =SUMIFS('2. Kalkyldata'!$H$23:$H$27,'2. Kalkyldata'!$E$23:$E$27,"nyb",'2. Kalkyldata'!$M$23:$M$27,'4. NPV'!E3) -> 6100 | F6: =SUMIFS('2. Kalkyldata'!$H$23:$H$27,'2. Kalkyldata'!$E$23:$E$27,"nyb",'2. Kalkyldata'!$M$23:$M$27,'4. NPV'!F3) -> 6100 | G6: =SUMIFS('2. Kalkyldata'!$H$23:$H$27,'2. Kalkyldata'!$E$23:$E$27,"nyb",'2. Kalkyldata'!$M$23:$M$27,'4. NPV'!G3) -> 6100 | H6: =SUMIFS('2. Kalkyldata'!$H$23:$H$27,'2. Kalkyldata'!$E$23:$E$27,"nyb",'2. Kalkyldata'!$M$23:$M$27,'4. NPV'!H3) -> 6100 | I6: =SUMIFS('2. Kalkyldata'!$H$23:$H$27,'2. Kalkyldata'!$E$23:$E$27,"nyb",'2. Kalkyldata'!$M$23:$M$27,'4. NPV'!I3) -> 6100 | J6: =SUMIFS('2. Kalkyldata'!$H$23:$H$27,'2. Kalkyldata'!$E$23:$E$27,"nyb",'2. Kalkyldata'!$M$23:$M$27,'4. NPV'!J3) -> 6100 | K6: =SUMIFS('2. Kalkyldata'!$H$23:$H$27,'2. Kalkyldata'!$E$23:$E$27,"nyb",'2. Kalkyldata'!$M$23:$M$27,'4. NPV'!K3) -> 6100 | ... BA6: =SUMIFS('2. Kalkyldata'!$H$23:$H$27,'2. Kalkyldata'!$E$23:$E$27,"nyb",'2. Kalkyldata'!$M$23:$M$27,'4. NPV'!BA3) -> 0
B7: Area befintligt, kvm | D7: =SUMIFS('2. Kalkyldata'!$H$23:$H$27,'2. Kalkyldata'!$E$23:$E$27,"Bef",'2. Kalkyldata'!$M$23:$M$27,'4. NPV'!D3)+SUMIFS('2. Kalkyldata'!$H$23:$H$27,'2. Kalkyldata'!$E$23:$E$27,"Omb",'2. Kalkyldata'!$M$23:$M$27,'4. NPV'!D3)+SUMIFS('2. Kalkyldata'!$H$23:$H$27,'2. Kalkyldata'!$E$23:$E$27,"Ins",'2. Kalkyldata'!$M$23:$M$27,'4. NPV'!D3)+SUMIFS('2. Kalkyldata'!$H$23:$H$27,'2. Kalkyldata'!$E$23:$E$27,"Mar",'2. Kalkyldata'!$M$23:$M$27,'4. NPV'!D3) -> 0 | E7: =SUMIFS('2. Kalkyldata'!$H$23:$H$27,'2. Kalkyldata'!$E$23:$E$27,"Bef",'2. Kalkyldata'!$M$23:$M$27,'4. NPV'!E3)+SUMIFS('2. Kalkyldata'!$H$23:$H$27,'2. Kalkyldata'!$E$23:$E$27,"Omb",'2. Kalkyldata'!$M$23:$M$27,'4. NPV'!E3)+SUMIFS('2. Kalkyldata'!$H$23:$H$27,'2. Kalkyldata'!$E$23:$E$27,"Ins",'2. Kalkyldata'!$M$23:$M$27,'4. NPV'!E3)+SUMIFS('2. Kalkyldata'!$H$23:$H$27,'2. Kalkyldata'!$E$23:$E$27,"Mar",'2. Kalkyldata'!$M$23:$M$27,'4. NPV'!E3) -> 0 | F7: =SUMIFS('2. Kalkyldata'!$H$23:$H$27,'2. Kalkyldata'!$E$23:$E$27,"Bef",'2. Kalkyldata'!$M$23:$M$27,'4. NPV'!F3)+SUMIFS('2. Kalkyldata'!$H$23:$H$27,'2. Kalkyldata'!$E$23:$E$27,"Omb",'2. Kalkyldata'!$M$23:$M$27,'4. NPV'!F3)+SUMIFS('2. Kalkyldata'!$H$23:$H$27,'2. Kalkyldata'!$E$23:$E$27,"Ins",'2. Kalkyldata'!$M$23:$M$27,'4. NPV'!F3)+SUMIFS('2. Kalkyldata'!$H$23:$H$27,'2. Kalkyldata'!$E$23:$E$27,"Mar",'2. Kalkyldata'!$M$23:$M$27,'4. NPV'!F3) -> 0 | G7: =SUMIFS('2. Kalkyldata'!$H$23:$H$27,'2. Kalkyldata'!$E$23:$E$27,"Bef",'2. Kalkyldata'!$M$23:$M$27,'4. NPV'!G3)+SUMIFS('2. Kalkyldata'!$H$23:$H$27,'2. Kalkyldata'!$E$23:$E$27,"Omb",'2. Kalkyldata'!$M$23:$M$27,'4. NPV'!G3)+SUMIFS('2. Kalkyldata'!$H$23:$H$27,'2. Kalkyldata'!$E$23:$E$27,"Ins",'2. Kalkyldata'!$M$23:$M$27,'4. NPV'!G3)+SUMIFS('2. Kalkyldata'!$H$23:$H$27,'2. Kalkyldata'!$E$23:$E$27,"Mar",'2. Kalkyldata'!$M$23:$M$27,'4. NPV'!G3) -> 0 | H7: =SUMIFS('2. Kalkyldata'!$H$23:$H$27,'2. Kalkyldata'!$E$23:$E$27,"Bef",'2. Kalkyldata'!$M$23:$M$27,'4. NPV'!H3)+SUMIFS('2. Kalkyldata'!$H$23:$H$27,'2. Kalkyldata'!$E$23:$E$27,"Omb",'2. Kalkyldata'!$M$23:$M$27,'4. NPV'!H3)+SUMIFS('2. Kalkyldata'!$H$23:$H$27,'2. Kalkyldata'!$E$23:$E$27,"Ins",'2. Kalkyldata'!$M$23:$M$27,'4. NPV'!H3)+SUMIFS('2. Kalkyldata'!$H$23:$H$27,'2. Kalkyldata'!$E$23:$E$27,"Mar",'2. Kalkyldata'!$M$23:$M$27,'4. NPV'!H3) -> 0 | I7: =SUMIFS('2. Kalkyldata'!$H$23:$H$27,'2. Kalkyldata'!$E$23:$E$27,"Bef",'2. Kalkyldata'!$M$23:$M$27,'4. NPV'!I3)+SUMIFS('2. Kalkyldata'!$H$23:$H$27,'2. Kalkyldata'!$E$23:$E$27,"Omb",'2. Kalkyldata'!$M$23:$M$27,'4. NPV'!I3)+SUMIFS('2. Kalkyldata'!$H$23:$H$27,'2. Kalkyldata'!$E$23:$E$27,"Ins",'2. Kalkyldata'!$M$23:$M$27,'4. NPV'!I3)+SUMIFS('2. Kalkyldata'!$H$23:$H$27,'2. Kalkyldata'!$E$23:$E$27,"Mar",'2. Kalkyldata'!$M$23:$M$27,'4. NPV'!I3) -> 0 | J7: =SUMIFS('2. Kalkyldata'!$H$23:$H$27,'2. Kalkyldata'!$E$23:$E$27,"Bef",'2. Kalkyldata'!$M$23:$M$27,'4. NPV'!J3)+SUMIFS('2. Kalkyldata'!$H$23:$H$27,'2. Kalkyldata'!$E$23:$E$27,"Omb",'2. Kalkyldata'!$M$23:$M$27,'4. NPV'!J3)+SUMIFS('2. Kalkyldata'!$H$23:$H$27,'2. Kalkyldata'!$E$23:$E$27,"Ins",'2. Kalkyldata'!$M$23:$M$27,'4. NPV'!J3)+SUMIFS('2. Kalkyldata'!$H$23:$H$27,'2. Kalkyldata'!$E$23:$E$27,"Mar",'2. Kalkyldata'!$M$23:$M$27,'4. NPV'!J3) -> 0 | K7: =SUMIFS('2. Kalkyldata'!$H$23:$H$27,'2. Kalkyldata'!$E$23:$E$27,"Bef",'2. Kalkyldata'!$M$23:$M$27,'4. NPV'!K3)+SUMIFS('2. Kalkyldata'!$H$23:$H$27,'2. Kalkyldata'!$E$23:$E$27,"Omb",'2. Kalkyldata'!$M$23:$M$27,'4. NPV'!K3)+SUMIFS('2. Kalkyldata'!$H$23:$H$27,'2. Kalkyldata'!$E$23:$E$27,"Ins",'2. Kalkyldata'!$M$23:$M$27,'4. NPV'!K3)+SUMIFS('2. Kalkyldata'!$H$23:$H$27,'2. Kalkyldata'!$E$23:$E$27,"Mar",'2. Kalkyldata'!$M$23:$M$27,'4. NPV'!K3) -> 0 | ... BA7: =SUMIFS('2. Kalkyldata'!$H$23:$H$27,'2. Kalkyldata'!$E$23:$E$27,"Bef",'2. Kalkyldata'!$M$23:$M$27,'4. NPV'!BA3)+SUMIFS('2. Kalkyldata'!$H$23:$H$27,'2. Kalkyldata'!$E$23:$E$27,"Omb",'2. Kalkyldata'!$M$23:$M$27,'4. NPV'!BA3)+SUMIFS('2. Kalkyldata'!$H$23:$H$27,'2. Kalkyldata'!$E$23:$E$27,"Ins",'2. Kalkyldata'!$M$23:$M$27,'4. NPV'!BA3)+SUMIFS('2. Kalkyldata'!$H$23:$H$27,'2. Kalkyldata'!$E$23:$E$27,"Mar",'2. Kalkyldata'!$M$23:$M$27,'4. NPV'!BA3) -> 0
B8: Total area, kvm | C8: =D8 -> 6100 | D8: =D6+D7 -> 6100 | E8: =E6+E7 -> 6100 | F8: =F6+F7 -> 6100 | G8: =G6+G7 -> 6100 | H8: =H6+H7 -> 6100 | I8: =I6+I7 -> 6100 | J8: =J6+J7 -> 6100 | K8: =K6+K7 -> 6100 | ... BA8: =BA6+BA7 -> 0
B9: Investeringar | D9: ='3. Finansiering'!D15 -> -2.4e+08 | E9: ='3. Finansiering'!E15 -> 0 | F9: ='3. Finansiering'!F15 -> 0 | G9: ='3. Finansiering'!G15 -> 0 | H9: ='3. Finansiering'!H15 -> 0 | I9: ='3. Finansiering'!I15 -> 0 | J9: ='3. Finansiering'!J15 -> 0 | K9: ='3. Finansiering'!K15 -> 0 | ... BA9: ='3. Finansiering'!BA15 -> 0
X10: Sista kolumnen (år N+1): bara underlag för restvärdet
B11: kr per år (löpande priser) | C11: =CONCATENATE("kr/kvm, ",D4) -> kr/kvm, 2026 | D11: =D4 -> 2026 | E11: =E4 -> 2027 | F11: =F4 -> 2028 | G11: =G4 -> 2029 | H11: =H4 -> 2030 | I11: =I4 -> 2031 | J11: =J4 -> 2032 | K11: =K4 -> 2033 | ... BA11: =BA4
B12: =CONCATENATE("Intäkter ",'2. Kalkyldata'!C23) -> Intäkter Skola | C12: =IFERROR(D12/$C$8,0) -> 2650 | D12: =IF(D$4="",0,((1+'2. Kalkyldata'!$M$9*'2. Kalkyldata'!$J23)^(D$4-$D$4)))*IF((D$4>='2. Kalkyldata'!$M23),IF(D$4="",0,IF(AND(D$4>='2. Kalkyldata'!$M23,'4. NPV'!D$4<='2. Kalkyldata'!$N23),'2. Kalkyldata'!$L23,'2. Kalkyldata'!$O23*'2. Kalkyldata'!$H23)),0) -> 16165000 | E12: =IF(E$4="",0,((1+'2. Kalkyldata'!$M$9*'2. Kalkyldata'!$J23)^(E$4-MAX('2. Kalkyldata'!$M23,$D$4))))*IF((E$4>='2. Kalkyldata'!$M23),IF(E$4="",0,IF(AND(E$4>='2. Kalkyldata'!$M23,'4. NPV'!E$4<='2. Kalkyldata'!$N23),'2. Kalkyldata'!$L23,'2. Kalkyldata'!$O23*'2. Kalkyldata'!$H23)),0) -> 16391310 | F12: =IF(F$4="",0,((1+'2. Kalkyldata'!$M$9*'2. Kalkyldata'!$J23)^(F$4-MAX('2. Kalkyldata'!$M23,$D$4))))*IF((F$4>='2. Kalkyldata'!$M23),IF(F$4="",0,IF(AND(F$4>='2. Kalkyldata'!$M23,'4. NPV'!F$4<='2. Kalkyldata'!$N23),'2. Kalkyldata'!$L23,'2. Kalkyldata'!$O23*'2. Kalkyldata'!$H23)),0) -> 16620788 | G12: =IF(G$4="",0,((1+'2. Kalkyldata'!$M$9*'2. Kalkyldata'!$J23)^(G$4-MAX('2. Kalkyldata'!$M23,$D$4))))*IF((G$4>='2. Kalkyldata'!$M23),IF(G$4="",0,IF(AND(G$4>='2. Kalkyldata'!$M23,'4. NPV'!G$4<='2. Kalkyldata'!$N23),'2. Kalkyldata'!$L23,'2. Kalkyldata'!$O23*'2. Kalkyldata'!$H23)),0) -> 16853479 | H12: =IF(H$4="",0,((1+'2. Kalkyldata'!$M$9*'2. Kalkyldata'!$J23)^(H$4-MAX('2. Kalkyldata'!$M23,$D$4))))*IF((H$4>='2. Kalkyldata'!$M23),IF(H$4="",0,IF(AND(H$4>='2. Kalkyldata'!$M23,'4. NPV'!H$4<='2. Kalkyldata'!$N23),'2. Kalkyldata'!$L23,'2. Kalkyldata'!$O23*'2. Kalkyldata'!$H23)),0) -> 17089428 | I12: =IF(I$4="",0,((1+'2. Kalkyldata'!$M$9*'2. Kalkyldata'!$J23)^(I$4-MAX('2. Kalkyldata'!$M23,$D$4))))*IF((I$4>='2. Kalkyldata'!$M23),IF(I$4="",0,IF(AND(I$4>='2. Kalkyldata'!$M23,'4. NPV'!I$4<='2. Kalkyldata'!$N23),'2. Kalkyldata'!$L23,'2. Kalkyldata'!$O23*'2. Kalkyldata'!$H23)),0) -> 17328680 | J12: =IF(J$4="",0,((1+'2. Kalkyldata'!$M$9*'2. Kalkyldata'!$J23)^(J$4-MAX('2. Kalkyldata'!$M23,$D$4))))*IF((J$4>='2. Kalkyldata'!$M23),IF(J$4="",0,IF(AND(J$4>='2. Kalkyldata'!$M23,'4. NPV'!J$4<='2. Kalkyldata'!$N23),'2. Kalkyldata'!$L23,'2. Kalkyldata'!$O23*'2. Kalkyldata'!$H23)),0) -> 17571282 | K12: =IF(K$4="",0,((1+'2. Kalkyldata'!$M$9*'2. Kalkyldata'!$J23)^(K$4-MAX('2. Kalkyldata'!$M23,$D$4))))*IF((K$4>='2. Kalkyldata'!$M23),IF(K$4="",0,IF(AND(K$4>='2. Kalkyldata'!$M23,'4. NPV'!K$4<='2. Kalkyldata'!$N23),'2. Kalkyldata'!$L23,'2. Kalkyldata'!$O23*'2. Kalkyldata'!$H23)),0) -> 17817280 | L12: =IF(L$4="",0,((1+'2. Kalkyldata'!$M$9*'2. Kalkyldata'!$J23)^(L$4-MAX('2. Kalkyldata'!$M23,$D$4))))*IF((L$4>='2. Kalkyldata'!$M23),IF(L$4="",0,IF(AND(L$4>='2. Kalkyldata'!$M23,'4. NPV'!L$4<='2. Kalkyldata'!$N23),'2. Kalkyldata'!$L23,'2. Kalkyldata'!$O23*'2. Kalkyldata'!$H23)),0) -> 18066721 | ... BA12: =IF(BA$4="",0,((1+'2. Kalkyldata'!$M$9*'2. Kalkyldata'!$J23)^(BA$4-MAX('2. Kalkyldata'!$M23,$D$4))))*IF((BA$4>='2. Kalkyldata'!$M23),IF(BA$4="",0,IF(AND(BA$4>='2. Kalkyldata'!$M23,'4. NPV'!BA$4<='2. Kalkyldata'!$N23),'2. Kalkyldata'!$L23,'2. Kalkyldata'!$O23*'2. Kalkyldata'!$H23)),0) -> 0
B13: =CONCATENATE("Intäkter ",'2. Kalkyldata'!C24) -> Intäkter | C13: =IFERROR(D13/$C$8,0) -> 0 | D13: =IF(D$4="",0,((1+'2. Kalkyldata'!$M$9*'2. Kalkyldata'!$J24)^(D$4-$D$4)))*IF((D$4>='2. Kalkyldata'!$M24),IF(D$4="",0,IF(AND(D$4>='2. Kalkyldata'!$M24,'4. NPV'!D$4<='2. Kalkyldata'!$N24),'2. Kalkyldata'!$L24,'2. Kalkyldata'!$O24*'2. Kalkyldata'!$H24)),0) -> 0 | E13: =IF(E$4="",0,((1+'2. Kalkyldata'!$M$9*'2. Kalkyldata'!$J24)^(E$4-MAX('2. Kalkyldata'!$M24,$D$4))))*IF((E$4>='2. Kalkyldata'!$M24),IF(E$4="",0,IF(AND(E$4>='2. Kalkyldata'!$M24,'4. NPV'!E$4<='2. Kalkyldata'!$N24),'2. Kalkyldata'!$L24,'2. Kalkyldata'!$O24*'2. Kalkyldata'!$H24)),0) -> 0 | F13: =IF(F$4="",0,((1+'2. Kalkyldata'!$M$9*'2. Kalkyldata'!$J24)^(F$4-MAX('2. Kalkyldata'!$M24,$D$4))))*IF((F$4>='2. Kalkyldata'!$M24),IF(F$4="",0,IF(AND(F$4>='2. Kalkyldata'!$M24,'4. NPV'!F$4<='2. Kalkyldata'!$N24),'2. Kalkyldata'!$L24,'2. Kalkyldata'!$O24*'2. Kalkyldata'!$H24)),0) -> 0 | G13: =IF(G$4="",0,((1+'2. Kalkyldata'!$M$9*'2. Kalkyldata'!$J24)^(G$4-MAX('2. Kalkyldata'!$M24,$D$4))))*IF((G$4>='2. Kalkyldata'!$M24),IF(G$4="",0,IF(AND(G$4>='2. Kalkyldata'!$M24,'4. NPV'!G$4<='2. Kalkyldata'!$N24),'2. Kalkyldata'!$L24,'2. Kalkyldata'!$O24*'2. Kalkyldata'!$H24)),0) -> 0 | H13: =IF(H$4="",0,((1+'2. Kalkyldata'!$M$9*'2. Kalkyldata'!$J24)^(H$4-MAX('2. Kalkyldata'!$M24,$D$4))))*IF((H$4>='2. Kalkyldata'!$M24),IF(H$4="",0,IF(AND(H$4>='2. Kalkyldata'!$M24,'4. NPV'!H$4<='2. Kalkyldata'!$N24),'2. Kalkyldata'!$L24,'2. Kalkyldata'!$O24*'2. Kalkyldata'!$H24)),0) -> 0 | I13: =IF(I$4="",0,((1+'2. Kalkyldata'!$M$9*'2. Kalkyldata'!$J24)^(I$4-MAX('2. Kalkyldata'!$M24,$D$4))))*IF((I$4>='2. Kalkyldata'!$M24),IF(I$4="",0,IF(AND(I$4>='2. Kalkyldata'!$M24,'4. NPV'!I$4<='2. Kalkyldata'!$N24),'2. Kalkyldata'!$L24,'2. Kalkyldata'!$O24*'2. Kalkyldata'!$H24)),0) -> 0 | J13: =IF(J$4="",0,((1+'2. Kalkyldata'!$M$9*'2. Kalkyldata'!$J24)^(J$4-MAX('2. Kalkyldata'!$M24,$D$4))))*IF((J$4>='2. Kalkyldata'!$M24),IF(J$4="",0,IF(AND(J$4>='2. Kalkyldata'!$M24,'4. NPV'!J$4<='2. Kalkyldata'!$N24),'2. Kalkyldata'!$L24,'2. Kalkyldata'!$O24*'2. Kalkyldata'!$H24)),0) -> 0 | K13: =IF(K$4="",0,((1+'2. Kalkyldata'!$M$9*'2. Kalkyldata'!$J24)^(K$4-MAX('2. Kalkyldata'!$M24,$D$4))))*IF((K$4>='2. Kalkyldata'!$M24),IF(K$4="",0,IF(AND(K$4>='2. Kalkyldata'!$M24,'4. NPV'!K$4<='2. Kalkyldata'!$N24),'2. Kalkyldata'!$L24,'2. Kalkyldata'!$O24*'2. Kalkyldata'!$H24)),0) -> 0 | L13: =IF(L$4="",0,((1+'2. Kalkyldata'!$M$9*'2. Kalkyldata'!$J24)^(L$4-MAX('2. Kalkyldata'!$M24,$D$4))))*IF((L$4>='2. Kalkyldata'!$M24),IF(L$4="",0,IF(AND(L$4>='2. Kalkyldata'!$M24,'4. NPV'!L$4<='2. Kalkyldata'!$N24),'2. Kalkyldata'!$L24,'2. Kalkyldata'!$O24*'2. Kalkyldata'!$H24)),0) -> 0 | ... BA13: =IF(BA$4="",0,((1+'2. Kalkyldata'!$M$9*'2. Kalkyldata'!$J24)^(BA$4-MAX('2. Kalkyldata'!$M24,$D$4))))*IF((BA$4>='2. Kalkyldata'!$M24),IF(BA$4="",0,IF(AND(BA$4>='2. Kalkyldata'!$M24,'4. NPV'!BA$4<='2. Kalkyldata'!$N24),'2. Kalkyldata'!$L24,'2. Kalkyldata'!$O24*'2. Kalkyldata'!$H24)),0) -> 0
B14: =CONCATENATE("Intäkter ",'2. Kalkyldata'!C25) -> Intäkter | C14: =IFERROR(D14/$C$8,0) -> 0 | D14: =IF(D$4="",0,((1+'2. Kalkyldata'!$M$9*'2. Kalkyldata'!$J25)^(D$4-$D$4)))*IF((D$4>='2. Kalkyldata'!$M25),IF(D$4="",0,IF(AND(D$4>='2. Kalkyldata'!$M25,'4. NPV'!D$4<='2. Kalkyldata'!$N25),'2. Kalkyldata'!$L25,'2. Kalkyldata'!$O25*'2. Kalkyldata'!$H25)),0) -> 0 | E14: =IF(E$4="",0,((1+'2. Kalkyldata'!$M$9*'2. Kalkyldata'!$J25)^(E$4-MAX('2. Kalkyldata'!$M25,$D$4))))*IF((E$4>='2. Kalkyldata'!$M25),IF(E$4="",0,IF(AND(E$4>='2. Kalkyldata'!$M25,'4. NPV'!E$4<='2. Kalkyldata'!$N25),'2. Kalkyldata'!$L25,'2. Kalkyldata'!$O25*'2. Kalkyldata'!$H25)),0) -> 0 | F14: =IF(F$4="",0,((1+'2. Kalkyldata'!$M$9*'2. Kalkyldata'!$J25)^(F$4-MAX('2. Kalkyldata'!$M25,$D$4))))*IF((F$4>='2. Kalkyldata'!$M25),IF(F$4="",0,IF(AND(F$4>='2. Kalkyldata'!$M25,'4. NPV'!F$4<='2. Kalkyldata'!$N25),'2. Kalkyldata'!$L25,'2. Kalkyldata'!$O25*'2. Kalkyldata'!$H25)),0) -> 0 | G14: =IF(G$4="",0,((1+'2. Kalkyldata'!$M$9*'2. Kalkyldata'!$J25)^(G$4-MAX('2. Kalkyldata'!$M25,$D$4))))*IF((G$4>='2. Kalkyldata'!$M25),IF(G$4="",0,IF(AND(G$4>='2. Kalkyldata'!$M25,'4. NPV'!G$4<='2. Kalkyldata'!$N25),'2. Kalkyldata'!$L25,'2. Kalkyldata'!$O25*'2. Kalkyldata'!$H25)),0) -> 0 | H14: =IF(H$4="",0,((1+'2. Kalkyldata'!$M$9*'2. Kalkyldata'!$J25)^(H$4-MAX('2. Kalkyldata'!$M25,$D$4))))*IF((H$4>='2. Kalkyldata'!$M25),IF(H$4="",0,IF(AND(H$4>='2. Kalkyldata'!$M25,'4. NPV'!H$4<='2. Kalkyldata'!$N25),'2. Kalkyldata'!$L25,'2. Kalkyldata'!$O25*'2. Kalkyldata'!$H25)),0) -> 0 | I14: =IF(I$4="",0,((1+'2. Kalkyldata'!$M$9*'2. Kalkyldata'!$J25)^(I$4-MAX('2. Kalkyldata'!$M25,$D$4))))*IF((I$4>='2. Kalkyldata'!$M25),IF(I$4="",0,IF(AND(I$4>='2. Kalkyldata'!$M25,'4. NPV'!I$4<='2. Kalkyldata'!$N25),'2. Kalkyldata'!$L25,'2. Kalkyldata'!$O25*'2. Kalkyldata'!$H25)),0) -> 0 | J14: =IF(J$4="",0,((1+'2. Kalkyldata'!$M$9*'2. Kalkyldata'!$J25)^(J$4-MAX('2. Kalkyldata'!$M25,$D$4))))*IF((J$4>='2. Kalkyldata'!$M25),IF(J$4="",0,IF(AND(J$4>='2. Kalkyldata'!$M25,'4. NPV'!J$4<='2. Kalkyldata'!$N25),'2. Kalkyldata'!$L25,'2. Kalkyldata'!$O25*'2. Kalkyldata'!$H25)),0) -> 0 | K14: =IF(K$4="",0,((1+'2. Kalkyldata'!$M$9*'2. Kalkyldata'!$J25)^(K$4-MAX('2. Kalkyldata'!$M25,$D$4))))*IF((K$4>='2. Kalkyldata'!$M25),IF(K$4="",0,IF(AND(K$4>='2. Kalkyldata'!$M25,'4. NPV'!K$4<='2. Kalkyldata'!$N25),'2. Kalkyldata'!$L25,'2. Kalkyldata'!$O25*'2. Kalkyldata'!$H25)),0) -> 0 | L14: =IF(L$4="",0,((1+'2. Kalkyldata'!$M$9*'2. Kalkyldata'!$J25)^(L$4-MAX('2. Kalkyldata'!$M25,$D$4))))*IF((L$4>='2. Kalkyldata'!$M25),IF(L$4="",0,IF(AND(L$4>='2. Kalkyldata'!$M25,'4. NPV'!L$4<='2. Kalkyldata'!$N25),'2. Kalkyldata'!$L25,'2. Kalkyldata'!$O25*'2. Kalkyldata'!$H25)),0) -> 0 | ... BA14: =IF(BA$4="",0,((1+'2. Kalkyldata'!$M$9*'2. Kalkyldata'!$J25)^(BA$4-MAX('2. Kalkyldata'!$M25,$D$4))))*IF((BA$4>='2. Kalkyldata'!$M25),IF(BA$4="",0,IF(AND(BA$4>='2. Kalkyldata'!$M25,'4. NPV'!BA$4<='2. Kalkyldata'!$N25),'2. Kalkyldata'!$L25,'2. Kalkyldata'!$O25*'2. Kalkyldata'!$H25)),0) -> 0
B15: =CONCATENATE("Intäkter ",'2. Kalkyldata'!C26) -> Intäkter | C15: =IFERROR(D15/$C$8,0) -> 0 | D15: =IF(D$4="",0,((1+'2. Kalkyldata'!$M$9*'2. Kalkyldata'!$J26)^(D$4-$D$4)))*IF((D$4>='2. Kalkyldata'!$M26),IF(D$4="",0,IF(AND(D$4>='2. Kalkyldata'!$M26,'4. NPV'!D$4<='2. Kalkyldata'!$N26),'2. Kalkyldata'!$L26,'2. Kalkyldata'!$O26*'2. Kalkyldata'!$H26)),0) -> 0 | E15: =IF(E$4="",0,((1+'2. Kalkyldata'!$M$9*'2. Kalkyldata'!$J26)^(E$4-MAX('2. Kalkyldata'!$M26,$D$4))))*IF((E$4>='2. Kalkyldata'!$M26),IF(E$4="",0,IF(AND(E$4>='2. Kalkyldata'!$M26,'4. NPV'!E$4<='2. Kalkyldata'!$N26),'2. Kalkyldata'!$L26,'2. Kalkyldata'!$O26*'2. Kalkyldata'!$H26)),0) -> 0 | F15: =IF(F$4="",0,((1+'2. Kalkyldata'!$M$9*'2. Kalkyldata'!$J26)^(F$4-MAX('2. Kalkyldata'!$M26,$D$4))))*IF((F$4>='2. Kalkyldata'!$M26),IF(F$4="",0,IF(AND(F$4>='2. Kalkyldata'!$M26,'4. NPV'!F$4<='2. Kalkyldata'!$N26),'2. Kalkyldata'!$L26,'2. Kalkyldata'!$O26*'2. Kalkyldata'!$H26)),0) -> 0 | G15: =IF(G$4="",0,((1+'2. Kalkyldata'!$M$9*'2. Kalkyldata'!$J26)^(G$4-MAX('2. Kalkyldata'!$M26,$D$4))))*IF((G$4>='2. Kalkyldata'!$M26),IF(G$4="",0,IF(AND(G$4>='2. Kalkyldata'!$M26,'4. NPV'!G$4<='2. Kalkyldata'!$N26),'2. Kalkyldata'!$L26,'2. Kalkyldata'!$O26*'2. Kalkyldata'!$H26)),0) -> 0 | H15: =IF(H$4="",0,((1+'2. Kalkyldata'!$M$9*'2. Kalkyldata'!$J26)^(H$4-MAX('2. Kalkyldata'!$M26,$D$4))))*IF((H$4>='2. Kalkyldata'!$M26),IF(H$4="",0,IF(AND(H$4>='2. Kalkyldata'!$M26,'4. NPV'!H$4<='2. Kalkyldata'!$N26),'2. Kalkyldata'!$L26,'2. Kalkyldata'!$O26*'2. Kalkyldata'!$H26)),0) -> 0 | I15: =IF(I$4="",0,((1+'2. Kalkyldata'!$M$9*'2. Kalkyldata'!$J26)^(I$4-MAX('2. Kalkyldata'!$M26,$D$4))))*IF((I$4>='2. Kalkyldata'!$M26),IF(I$4="",0,IF(AND(I$4>='2. Kalkyldata'!$M26,'4. NPV'!I$4<='2. Kalkyldata'!$N26),'2. Kalkyldata'!$L26,'2. Kalkyldata'!$O26*'2. Kalkyldata'!$H26)),0) -> 0 | J15: =IF(J$4="",0,((1+'2. Kalkyldata'!$M$9*'2. Kalkyldata'!$J26)^(J$4-MAX('2. Kalkyldata'!$M26,$D$4))))*IF((J$4>='2. Kalkyldata'!$M26),IF(J$4="",0,IF(AND(J$4>='2. Kalkyldata'!$M26,'4. NPV'!J$4<='2. Kalkyldata'!$N26),'2. Kalkyldata'!$L26,'2. Kalkyldata'!$O26*'2. Kalkyldata'!$H26)),0) -> 0 | K15: =IF(K$4="",0,((1+'2. Kalkyldata'!$M$9*'2. Kalkyldata'!$J26)^(K$4-MAX('2. Kalkyldata'!$M26,$D$4))))*IF((K$4>='2. Kalkyldata'!$M26),IF(K$4="",0,IF(AND(K$4>='2. Kalkyldata'!$M26,'4. NPV'!K$4<='2. Kalkyldata'!$N26),'2. Kalkyldata'!$L26,'2. Kalkyldata'!$O26*'2. Kalkyldata'!$H26)),0) -> 0 | L15: =IF(L$4="",0,((1+'2. Kalkyldata'!$M$9*'2. Kalkyldata'!$J26)^(L$4-MAX('2. Kalkyldata'!$M26,$D$4))))*IF((L$4>='2. Kalkyldata'!$M26),IF(L$4="",0,IF(AND(L$4>='2. Kalkyldata'!$M26,'4. NPV'!L$4<='2. Kalkyldata'!$N26),'2. Kalkyldata'!$L26,'2. Kalkyldata'!$O26*'2. Kalkyldata'!$H26)),0) -> 0 | ... BA15: =IF(BA$4="",0,((1+'2. Kalkyldata'!$M$9*'2. Kalkyldata'!$J26)^(BA$4-MAX('2. Kalkyldata'!$M26,$D$4))))*IF((BA$4>='2. Kalkyldata'!$M26),IF(BA$4="",0,IF(AND(BA$4>='2. Kalkyldata'!$M26,'4. NPV'!BA$4<='2. Kalkyldata'!$N26),'2. Kalkyldata'!$L26,'2. Kalkyldata'!$O26*'2. Kalkyldata'!$H26)),0) -> 0
B16: =CONCATENATE("Intäkter ",'2. Kalkyldata'!C27) -> Intäkter | C16: =IFERROR(D16/$C$8,0) -> 0 | D16: =IF(D$4="",0,((1+'2. Kalkyldata'!$M$9*'2. Kalkyldata'!$J27)^(D$4-$D$4)))*IF((D$4>='2. Kalkyldata'!$M27),IF(D$4="",0,IF(AND(D$4>='2. Kalkyldata'!$M27,'4. NPV'!D$4<='2. Kalkyldata'!$N27),'2. Kalkyldata'!$L27,'2. Kalkyldata'!$O27*'2. Kalkyldata'!$H27)),0) -> 0 | E16: =IF(E$4="",0,((1+'2. Kalkyldata'!$M$9*'2. Kalkyldata'!$J27)^(E$4-MAX('2. Kalkyldata'!$M27,$D$4))))*IF((E$4>='2. Kalkyldata'!$M27),IF(E$4="",0,IF(AND(E$4>='2. Kalkyldata'!$M27,'4. NPV'!E$4<='2. Kalkyldata'!$N27),'2. Kalkyldata'!$L27,'2. Kalkyldata'!$O27*'2. Kalkyldata'!$H27)),0) -> 0 | F16: =IF(F$4="",0,((1+'2. Kalkyldata'!$M$9*'2. Kalkyldata'!$J27)^(F$4-MAX('2. Kalkyldata'!$M27,$D$4))))*IF((F$4>='2. Kalkyldata'!$M27),IF(F$4="",0,IF(AND(F$4>='2. Kalkyldata'!$M27,'4. NPV'!F$4<='2. Kalkyldata'!$N27),'2. Kalkyldata'!$L27,'2. Kalkyldata'!$O27*'2. Kalkyldata'!$H27)),0) -> 0 | G16: =IF(G$4="",0,((1+'2. Kalkyldata'!$M$9*'2. Kalkyldata'!$J27)^(G$4-MAX('2. Kalkyldata'!$M27,$D$4))))*IF((G$4>='2. Kalkyldata'!$M27),IF(G$4="",0,IF(AND(G$4>='2. Kalkyldata'!$M27,'4. NPV'!G$4<='2. Kalkyldata'!$N27),'2. Kalkyldata'!$L27,'2. Kalkyldata'!$O27*'2. Kalkyldata'!$H27)),0) -> 0 | H16: =IF(H$4="",0,((1+'2. Kalkyldata'!$M$9*'2. Kalkyldata'!$J27)^(H$4-MAX('2. Kalkyldata'!$M27,$D$4))))*IF((H$4>='2. Kalkyldata'!$M27),IF(H$4="",0,IF(AND(H$4>='2. Kalkyldata'!$M27,'4. NPV'!H$4<='2. Kalkyldata'!$N27),'2. Kalkyldata'!$L27,'2. Kalkyldata'!$O27*'2. Kalkyldata'!$H27)),0) -> 0 | I16: =IF(I$4="",0,((1+'2. Kalkyldata'!$M$9*'2. Kalkyldata'!$J27)^(I$4-MAX('2. Kalkyldata'!$M27,$D$4))))*IF((I$4>='2. Kalkyldata'!$M27),IF(I$4="",0,IF(AND(I$4>='2. Kalkyldata'!$M27,'4. NPV'!I$4<='2. Kalkyldata'!$N27),'2. Kalkyldata'!$L27,'2. Kalkyldata'!$O27*'2. Kalkyldata'!$H27)),0) -> 0 | J16: =IF(J$4="",0,((1+'2. Kalkyldata'!$M$9*'2. Kalkyldata'!$J27)^(J$4-MAX('2. Kalkyldata'!$M27,$D$4))))*IF((J$4>='2. Kalkyldata'!$M27),IF(J$4="",0,IF(AND(J$4>='2. Kalkyldata'!$M27,'4. NPV'!J$4<='2. Kalkyldata'!$N27),'2. Kalkyldata'!$L27,'2. Kalkyldata'!$O27*'2. Kalkyldata'!$H27)),0) -> 0 | K16: =IF(K$4="",0,((1+'2. Kalkyldata'!$M$9*'2. Kalkyldata'!$J27)^(K$4-MAX('2. Kalkyldata'!$M27,$D$4))))*IF((K$4>='2. Kalkyldata'!$M27),IF(K$4="",0,IF(AND(K$4>='2. Kalkyldata'!$M27,'4. NPV'!K$4<='2. Kalkyldata'!$N27),'2. Kalkyldata'!$L27,'2. Kalkyldata'!$O27*'2. Kalkyldata'!$H27)),0) -> 0 | L16: =IF(L$4="",0,((1+'2. Kalkyldata'!$M$9*'2. Kalkyldata'!$J27)^(L$4-MAX('2. Kalkyldata'!$M27,$D$4))))*IF((L$4>='2. Kalkyldata'!$M27),IF(L$4="",0,IF(AND(L$4>='2. Kalkyldata'!$M27,'4. NPV'!L$4<='2. Kalkyldata'!$N27),'2. Kalkyldata'!$L27,'2. Kalkyldata'!$O27*'2. Kalkyldata'!$H27)),0) -> 0 | ... BA16: =IF(BA$4="",0,((1+'2. Kalkyldata'!$M$9*'2. Kalkyldata'!$J27)^(BA$4-MAX('2. Kalkyldata'!$M27,$D$4))))*IF((BA$4>='2. Kalkyldata'!$M27),IF(BA$4="",0,IF(AND(BA$4>='2. Kalkyldata'!$M27,'4. NPV'!BA$4<='2. Kalkyldata'!$N27),'2. Kalkyldata'!$L27,'2. Kalkyldata'!$O27*'2. Kalkyldata'!$H27)),0) -> 0
B17: Bruttohyra | C17: =IFERROR(D17/C8,"") -> 2650 | D17: =SUM(D12:D16) -> 16165000 | E17: =SUM(E12:E16) -> 16391310 | F17: =SUM(F12:F16) -> 16620788 | G17: =SUM(G12:G16) -> 16853479 | H17: =SUM(H12:H16) -> 17089428 | I17: =SUM(I12:I16) -> 17328680 | J17: =SUM(J12:J16) -> 17571282 | K17: =SUM(K12:K16) -> 17817280 | ... BA17: =SUM(BA12:BA16) -> 0
B18: Vakans (efter avtal) | C18: =IFERROR(D18/$C$8,"") -> 0 | D18: =IFERROR(-(((IF(AND(D$4>='2. Kalkyldata'!$M23,D$4<='2. Kalkyldata'!$N23),0,D$12*'2. Kalkyldata'!$P23)))+((IF(AND(D$4>='2. Kalkyldata'!$M24,D$4<='2. Kalkyldata'!$N24),0,D$13*'2. Kalkyldata'!$P24)))+((IF(AND(D$4>='2. Kalkyldata'!$M25,D$4<='2. Kalkyldata'!$N25),0,D$14*'2. Kalkyldata'!$P25)))+((IF(AND(D$4>='2. Kalkyldata'!$M26,D$4<='2. Kalkyldata'!$N26),0,D$15*'2. Kalkyldata'!$P26)))+((IF(AND(D$4>='2. Kalkyldata'!$M27,D$4<='2. Kalkyldata'!$N27),0,D$16*'2. Kalkyldata'!$P27)))),0) -> 0 | E18: =IFERROR(-(((IF(AND(E$4>='2. Kalkyldata'!$M23,E$4<='2. Kalkyldata'!$N23),0,E$12*'2. Kalkyldata'!$P23)))+((IF(AND(E$4>='2. Kalkyldata'!$M24,E$4<='2. Kalkyldata'!$N24),0,E$13*'2. Kalkyldata'!$P24)))+((IF(AND(E$4>='2. Kalkyldata'!$M25,E$4<='2. Kalkyldata'!$N25),0,E$14*'2. Kalkyldata'!$P25)))+((IF(AND(E$4>='2. Kalkyldata'!$M26,E$4<='2. Kalkyldata'!$N26),0,E$15*'2. Kalkyldata'!$P26)))+((IF(AND(E$4>='2. Kalkyldata'!$M27,E$4<='2. Kalkyldata'!$N27),0,E$16*'2. Kalkyldata'!$P27)))),0) -> 0 | F18: =IFERROR(-(((IF(AND(F$4>='2. Kalkyldata'!$M23,F$4<='2. Kalkyldata'!$N23),0,F$12*'2. Kalkyldata'!$P23)))+((IF(AND(F$4>='2. Kalkyldata'!$M24,F$4<='2. Kalkyldata'!$N24),0,F$13*'2. Kalkyldata'!$P24)))+((IF(AND(F$4>='2. Kalkyldata'!$M25,F$4<='2. Kalkyldata'!$N25),0,F$14*'2. Kalkyldata'!$P25)))+((IF(AND(F$4>='2. Kalkyldata'!$M26,F$4<='2. Kalkyldata'!$N26),0,F$15*'2. Kalkyldata'!$P26)))+((IF(AND(F$4>='2. Kalkyldata'!$M27,F$4<='2. Kalkyldata'!$N27),0,F$16*'2. Kalkyldata'!$P27)))),0) -> 0 | G18: =IFERROR(-(((IF(AND(G$4>='2. Kalkyldata'!$M23,G$4<='2. Kalkyldata'!$N23),0,G$12*'2. Kalkyldata'!$P23)))+((IF(AND(G$4>='2. Kalkyldata'!$M24,G$4<='2. Kalkyldata'!$N24),0,G$13*'2. Kalkyldata'!$P24)))+((IF(AND(G$4>='2. Kalkyldata'!$M25,G$4<='2. Kalkyldata'!$N25),0,G$14*'2. Kalkyldata'!$P25)))+((IF(AND(G$4>='2. Kalkyldata'!$M26,G$4<='2. Kalkyldata'!$N26),0,G$15*'2. Kalkyldata'!$P26)))+((IF(AND(G$4>='2. Kalkyldata'!$M27,G$4<='2. Kalkyldata'!$N27),0,G$16*'2. Kalkyldata'!$P27)))),0) -> 0 | H18: =IFERROR(-(((IF(AND(H$4>='2. Kalkyldata'!$M23,H$4<='2. Kalkyldata'!$N23),0,H$12*'2. Kalkyldata'!$P23)))+((IF(AND(H$4>='2. Kalkyldata'!$M24,H$4<='2. Kalkyldata'!$N24),0,H$13*'2. Kalkyldata'!$P24)))+((IF(AND(H$4>='2. Kalkyldata'!$M25,H$4<='2. Kalkyldata'!$N25),0,H$14*'2. Kalkyldata'!$P25)))+((IF(AND(H$4>='2. Kalkyldata'!$M26,H$4<='2. Kalkyldata'!$N26),0,H$15*'2. Kalkyldata'!$P26)))+((IF(AND(H$4>='2. Kalkyldata'!$M27,H$4<='2. Kalkyldata'!$N27),0,H$16*'2. Kalkyldata'!$P27)))),0) -> 0 | I18: =IFERROR(-(((IF(AND(I$4>='2. Kalkyldata'!$M23,I$4<='2. Kalkyldata'!$N23),0,I$12*'2. Kalkyldata'!$P23)))+((IF(AND(I$4>='2. Kalkyldata'!$M24,I$4<='2. Kalkyldata'!$N24),0,I$13*'2. Kalkyldata'!$P24)))+((IF(AND(I$4>='2. Kalkyldata'!$M25,I$4<='2. Kalkyldata'!$N25),0,I$14*'2. Kalkyldata'!$P25)))+((IF(AND(I$4>='2. Kalkyldata'!$M26,I$4<='2. Kalkyldata'!$N26),0,I$15*'2. Kalkyldata'!$P26)))+((IF(AND(I$4>='2. Kalkyldata'!$M27,I$4<='2. Kalkyldata'!$N27),0,I$16*'2. Kalkyldata'!$P27)))),0) -> 0 | J18: =IFERROR(-(((IF(AND(J$4>='2. Kalkyldata'!$M23,J$4<='2. Kalkyldata'!$N23),0,J$12*'2. Kalkyldata'!$P23)))+((IF(AND(J$4>='2. Kalkyldata'!$M24,J$4<='2. Kalkyldata'!$N24),0,J$13*'2. Kalkyldata'!$P24)))+((IF(AND(J$4>='2. Kalkyldata'!$M25,J$4<='2. Kalkyldata'!$N25),0,J$14*'2. Kalkyldata'!$P25)))+((IF(AND(J$4>='2. Kalkyldata'!$M26,J$4<='2. Kalkyldata'!$N26),0,J$15*'2. Kalkyldata'!$P26)))+((IF(AND(J$4>='2. Kalkyldata'!$M27,J$4<='2. Kalkyldata'!$N27),0,J$16*'2. Kalkyldata'!$P27)))),0) -> 0 | K18: =IFERROR(-(((IF(AND(K$4>='2. Kalkyldata'!$M23,K$4<='2. Kalkyldata'!$N23),0,K$12*'2. Kalkyldata'!$P23)))+((IF(AND(K$4>='2. Kalkyldata'!$M24,K$4<='2. Kalkyldata'!$N24),0,K$13*'2. Kalkyldata'!$P24)))+((IF(AND(K$4>='2. Kalkyldata'!$M25,K$4<='2. Kalkyldata'!$N25),0,K$14*'2. Kalkyldata'!$P25)))+((IF(AND(K$4>='2. Kalkyldata'!$M26,K$4<='2. Kalkyldata'!$N26),0,K$15*'2. Kalkyldata'!$P26)))+((IF(AND(K$4>='2. Kalkyldata'!$M27,K$4<='2. Kalkyldata'!$N27),0,K$16*'2. Kalkyldata'!$P27)))),0) -> 0 | ... BA18: =IFERROR(-(((IF(AND(BA$4>='2. Kalkyldata'!$M23,BA$4<='2. Kalkyldata'!$N23),0,BA$12*'2. Kalkyldata'!$P23)))+((IF(AND(BA$4>='2. Kalkyldata'!$M24,BA$4<='2. Kalkyldata'!$N24),0,BA$13*'2. Kalkyldata'!$P24)))+((IF(AND(BA$4>='2. Kalkyldata'!$M25,BA$4<='2. Kalkyldata'!$N25),0,BA$14*'2. Kalkyldata'!$P25)))+((IF(AND(BA$4>='2. Kalkyldata'!$M26,BA$4<='2. Kalkyldata'!$N26),0,BA$15*'2. Kalkyldata'!$P26)))+((IF(AND(BA$4>='2. Kalkyldata'!$M27,BA$4<='2. Kalkyldata'!$N27),0,BA$16*'2. Kalkyldata'!$P27)))),0) -> 0
B19: Nettohyra | C19: =IFERROR(D19/$C$8,"") -> 2650 | D19: =D17+D18 -> 16165000 | E19: =E17+E18 -> 16391310 | F19: =F17+F18 -> 16620788 | G19: =G17+G18 -> 16853479 | H19: =H17+H18 -> 17089428 | I19: =I17+I18 -> 17328680 | J19: =J17+J18 -> 17571282 | K19: =K17+K18 -> 17817280 | ... BA19: =BA17+BA18 -> 0
B20: Total Fastighetsskötsel | C20: =IFERROR($D20/$C$8,"") -> 0 | D20: =-(((D$6*NybFastighetsskötsel+D$7*BefFastighetsskötsel)*(1+Inflation)^(D5-1))*(IF($D$4+Höjnin1<='4. NPV'!D$4,TioÅrFastighetsskötsel,0)+IF($D$4+Höjning2<='4. NPV'!D$4,FemtonÅrFastighetsskötsel,0))+((D$6*NybFastighetsskötsel+D$7*BefFastighetsskötsel)*((1+Inflation)^('4. NPV'!D$5-1)))) -> 0 | E20: =-(((E$6*NybFastighetsskötsel+E$7*BefFastighetsskötsel)*(1+Inflation)^(E5-1))*(IF($D$4+Höjnin1<='4. NPV'!E$4,TioÅrFastighetsskötsel,0)+IF($D$4+Höjning2<='4. NPV'!E$4,FemtonÅrFastighetsskötsel,0))+((E$6*NybFastighetsskötsel+E$7*BefFastighetsskötsel)*((1+Inflation)^('4. NPV'!E$5-1)))) -> 0 | F20: =-(((F$6*NybFastighetsskötsel+F$7*BefFastighetsskötsel)*(1+Inflation)^(F5-1))*(IF($D$4+Höjnin1<='4. NPV'!F$4,TioÅrFastighetsskötsel,0)+IF($D$4+Höjning2<='4. NPV'!F$4,FemtonÅrFastighetsskötsel,0))+((F$6*NybFastighetsskötsel+F$7*BefFastighetsskötsel)*((1+Inflation)^('4. NPV'!F$5-1)))) -> 0 | G20: =-(((G$6*NybFastighetsskötsel+G$7*BefFastighetsskötsel)*(1+Inflation)^(G5-1))*(IF($D$4+Höjnin1<='4. NPV'!G$4,TioÅrFastighetsskötsel,0)+IF($D$4+Höjning2<='4. NPV'!G$4,FemtonÅrFastighetsskötsel,0))+((G$6*NybFastighetsskötsel+G$7*BefFastighetsskötsel)*((1+Inflation)^('4. NPV'!G$5-1)))) -> 0 | H20: =-(((H$6*NybFastighetsskötsel+H$7*BefFastighetsskötsel)*(1+Inflation)^(H5-1))*(IF($D$4+Höjnin1<='4. NPV'!H$4,TioÅrFastighetsskötsel,0)+IF($D$4+Höjning2<='4. NPV'!H$4,FemtonÅrFastighetsskötsel,0))+((H$6*NybFastighetsskötsel+H$7*BefFastighetsskötsel)*((1+Inflation)^('4. NPV'!H$5-1)))) -> 0 | I20: =-(((I$6*NybFastighetsskötsel+I$7*BefFastighetsskötsel)*(1+Inflation)^(I5-1))*(IF($D$4+Höjnin1<='4. NPV'!I$4,TioÅrFastighetsskötsel,0)+IF($D$4+Höjning2<='4. NPV'!I$4,FemtonÅrFastighetsskötsel,0))+((I$6*NybFastighetsskötsel+I$7*BefFastighetsskötsel)*((1+Inflation)^('4. NPV'!I$5-1)))) -> 0 | J20: =-(((J$6*NybFastighetsskötsel+J$7*BefFastighetsskötsel)*(1+Inflation)^(J5-1))*(IF($D$4+Höjnin1<='4. NPV'!J$4,TioÅrFastighetsskötsel,0)+IF($D$4+Höjning2<='4. NPV'!J$4,FemtonÅrFastighetsskötsel,0))+((J$6*NybFastighetsskötsel+J$7*BefFastighetsskötsel)*((1+Inflation)^('4. NPV'!J$5-1)))) -> 0 | K20: =-(((K$6*NybFastighetsskötsel+K$7*BefFastighetsskötsel)*(1+Inflation)^(K5-1))*(IF($D$4+Höjnin1<='4. NPV'!K$4,TioÅrFastighetsskötsel,0)+IF($D$4+Höjning2<='4. NPV'!K$4,FemtonÅrFastighetsskötsel,0))+((K$6*NybFastighetsskötsel+K$7*BefFastighetsskötsel)*((1+Inflation)^('4. NPV'!K$5-1)))) -> 0 | ... BA20: =-(((BA$6*NybFastighetsskötsel+BA$7*BefFastighetsskötsel)*(1+Inflation)^(BA5-1))*(IF($D$4+Höjnin1<='4. NPV'!BA$4,TioÅrFastighetsskötsel,0)+IF($D$4+Höjning2<='4. NPV'!BA$4,FemtonÅrFastighetsskötsel,0))+((BA$6*NybFastighetsskötsel+BA$7*BefFastighetsskötsel)*((1+Inflation)^('4. NPV'!BA$5-1)))) -> 0
B21: Total Reparationer | C21: =IFERROR($D21/$C$8,"") -> 0 | D21: =-(((D$6*NybReparationer+D$7*BefReparationer)*(1+Inflation)^(D5-1))*(IF($D$4+Höjnin1<='4. NPV'!D$4,TioÅrReparationer,0)+IF($D$4+Höjning2<='4. NPV'!D$4,FemtonÅrReparationer,0))+((D$6*NybReparationer+D$7*BefReparationer)*((1+Inflation)^('4. NPV'!D$5-1)))) -> 0 | E21: =-(((E$6*NybReparationer+E$7*BefReparationer)*(1+Inflation)^(E5-1))*(IF($D$4+Höjnin1<='4. NPV'!E$4,TioÅrReparationer,0)+IF($D$4+Höjning2<='4. NPV'!E$4,FemtonÅrReparationer,0))+((E$6*NybReparationer+E$7*BefReparationer)*((1+Inflation)^('4. NPV'!E$5-1)))) -> 0 | F21: =-(((F$6*NybReparationer+F$7*BefReparationer)*(1+Inflation)^(F5-1))*(IF($D$4+Höjnin1<='4. NPV'!F$4,TioÅrReparationer,0)+IF($D$4+Höjning2<='4. NPV'!F$4,FemtonÅrReparationer,0))+((F$6*NybReparationer+F$7*BefReparationer)*((1+Inflation)^('4. NPV'!F$5-1)))) -> 0 | G21: =-(((G$6*NybReparationer+G$7*BefReparationer)*(1+Inflation)^(G5-1))*(IF($D$4+Höjnin1<='4. NPV'!G$4,TioÅrReparationer,0)+IF($D$4+Höjning2<='4. NPV'!G$4,FemtonÅrReparationer,0))+((G$6*NybReparationer+G$7*BefReparationer)*((1+Inflation)^('4. NPV'!G$5-1)))) -> 0 | H21: =-(((H$6*NybReparationer+H$7*BefReparationer)*(1+Inflation)^(H5-1))*(IF($D$4+Höjnin1<='4. NPV'!H$4,TioÅrReparationer,0)+IF($D$4+Höjning2<='4. NPV'!H$4,FemtonÅrReparationer,0))+((H$6*NybReparationer+H$7*BefReparationer)*((1+Inflation)^('4. NPV'!H$5-1)))) -> 0 | I21: =-(((I$6*NybReparationer+I$7*BefReparationer)*(1+Inflation)^(I5-1))*(IF($D$4+Höjnin1<='4. NPV'!I$4,TioÅrReparationer,0)+IF($D$4+Höjning2<='4. NPV'!I$4,FemtonÅrReparationer,0))+((I$6*NybReparationer+I$7*BefReparationer)*((1+Inflation)^('4. NPV'!I$5-1)))) -> 0 | J21: =-(((J$6*NybReparationer+J$7*BefReparationer)*(1+Inflation)^(J5-1))*(IF($D$4+Höjnin1<='4. NPV'!J$4,TioÅrReparationer,0)+IF($D$4+Höjning2<='4. NPV'!J$4,FemtonÅrReparationer,0))+((J$6*NybReparationer+J$7*BefReparationer)*((1+Inflation)^('4. NPV'!J$5-1)))) -> 0 | K21: =-(((K$6*NybReparationer+K$7*BefReparationer)*(1+Inflation)^(K5-1))*(IF($D$4+Höjnin1<='4. NPV'!K$4,TioÅrReparationer,0)+IF($D$4+Höjning2<='4. NPV'!K$4,FemtonÅrReparationer,0))+((K$6*NybReparationer+K$7*BefReparationer)*((1+Inflation)^('4. NPV'!K$5-1)))) -> 0 | ... BA21: =-(((BA$6*NybReparationer+BA$7*BefReparationer)*(1+Inflation)^(BA5-1))*(IF($D$4+Höjnin1<='4. NPV'!BA$4,TioÅrReparationer,0)+IF($D$4+Höjning2<='4. NPV'!BA$4,FemtonÅrReparationer,0))+((BA$6*NybReparationer+BA$7*BefReparationer)*((1+Inflation)^('4. NPV'!BA$5-1)))) -> 0
B22: Total Planerat underhåll | C22: =IFERROR($D22/$C$8,"") -> 0 | D22: =-(((D$6*NybPlaneratunderhåll+D$7*BefPlaneratunderhåll)*(1+Inflation)^(D5-1))*(IF($D$4+Höjnin1<='4. NPV'!D$4,TioÅrPlaneratUnderhåll,0)+IF($D$4+Höjning2<='4. NPV'!D$4,FemtonÅrPlaneratUnderhåll,0))+((D$6*NybPlaneratunderhåll+D$7*BefPlaneratunderhåll)*((1+Inflation)^('4. NPV'!D$5-1)))) -> 0 | E22: =-(((E$6*NybPlaneratunderhåll+E$7*BefPlaneratunderhåll)*(1+Inflation)^(E5-1))*(IF($D$4+Höjnin1<='4. NPV'!E$4,TioÅrPlaneratUnderhåll,0)+IF($D$4+Höjning2<='4. NPV'!E$4,FemtonÅrPlaneratUnderhåll,0))+((E$6*NybPlaneratunderhåll+E$7*BefPlaneratunderhåll)*((1+Inflation)^('4. NPV'!E$5-1)))) -> 0 | F22: =-(((F$6*NybPlaneratunderhåll+F$7*BefPlaneratunderhåll)*(1+Inflation)^(F5-1))*(IF($D$4+Höjnin1<='4. NPV'!F$4,TioÅrPlaneratUnderhåll,0)+IF($D$4+Höjning2<='4. NPV'!F$4,FemtonÅrPlaneratUnderhåll,0))+((F$6*NybPlaneratunderhåll+F$7*BefPlaneratunderhåll)*((1+Inflation)^('4. NPV'!F$5-1)))) -> 0 | G22: =-(((G$6*NybPlaneratunderhåll+G$7*BefPlaneratunderhåll)*(1+Inflation)^(G5-1))*(IF($D$4+Höjnin1<='4. NPV'!G$4,TioÅrPlaneratUnderhåll,0)+IF($D$4+Höjning2<='4. NPV'!G$4,FemtonÅrPlaneratUnderhåll,0))+((G$6*NybPlaneratunderhåll+G$7*BefPlaneratunderhåll)*((1+Inflation)^('4. NPV'!G$5-1)))) -> 0 | H22: =-(((H$6*NybPlaneratunderhåll+H$7*BefPlaneratunderhåll)*(1+Inflation)^(H5-1))*(IF($D$4+Höjnin1<='4. NPV'!H$4,TioÅrPlaneratUnderhåll,0)+IF($D$4+Höjning2<='4. NPV'!H$4,FemtonÅrPlaneratUnderhåll,0))+((H$6*NybPlaneratunderhåll+H$7*BefPlaneratunderhåll)*((1+Inflation)^('4. NPV'!H$5-1)))) -> 0 | I22: =-(((I$6*NybPlaneratunderhåll+I$7*BefPlaneratunderhåll)*(1+Inflation)^(I5-1))*(IF($D$4+Höjnin1<='4. NPV'!I$4,TioÅrPlaneratUnderhåll,0)+IF($D$4+Höjning2<='4. NPV'!I$4,FemtonÅrPlaneratUnderhåll,0))+((I$6*NybPlaneratunderhåll+I$7*BefPlaneratunderhåll)*((1+Inflation)^('4. NPV'!I$5-1)))) -> 0 | J22: =-(((J$6*NybPlaneratunderhåll+J$7*BefPlaneratunderhåll)*(1+Inflation)^(J5-1))*(IF($D$4+Höjnin1<='4. NPV'!J$4,TioÅrPlaneratUnderhåll,0)+IF($D$4+Höjning2<='4. NPV'!J$4,FemtonÅrPlaneratUnderhåll,0))+((J$6*NybPlaneratunderhåll+J$7*BefPlaneratunderhåll)*((1+Inflation)^('4. NPV'!J$5-1)))) -> 0 | K22: =-(((K$6*NybPlaneratunderhåll+K$7*BefPlaneratunderhåll)*(1+Inflation)^(K5-1))*(IF($D$4+Höjnin1<='4. NPV'!K$4,TioÅrPlaneratUnderhåll,0)+IF($D$4+Höjning2<='4. NPV'!K$4,FemtonÅrPlaneratUnderhåll,0))+((K$6*NybPlaneratunderhåll+K$7*BefPlaneratunderhåll)*((1+Inflation)^('4. NPV'!K$5-1)))) -> 0 | ... BA22: =-(((BA$6*NybPlaneratunderhåll+BA$7*BefPlaneratunderhåll)*(1+Inflation)^(BA5-1))*(IF($D$4+Höjnin1<='4. NPV'!BA$4,TioÅrPlaneratUnderhåll,0)+IF($D$4+Höjning2<='4. NPV'!BA$4,FemtonÅrPlaneratUnderhåll,0))+((BA$6*NybPlaneratunderhåll+BA$7*BefPlaneratunderhåll)*((1+Inflation)^('4. NPV'!BA$5-1)))) -> 0
B23: Total Media | C23: =IFERROR($D23/$C$8,"") -> 0 | D23: =-(((D$6*NybMedia+D$7*BefMedia)*(1+Inflation)^(D5-1))*(IF($D$4+Höjnin1<='4. NPV'!D$4,TioÅrMedia,0)+IF($D$4+Höjning2<='4. NPV'!D$4,FemtonÅrMedia,0))+((D$6*NybMedia+D$7*BefMedia)*((1+Inflation)^('4. NPV'!D$5-1)))) -> 0 | E23: =-(((E$6*NybMedia+E$7*BefMedia)*(1+Inflation)^(E5-1))*(IF($D$4+Höjnin1<='4. NPV'!E$4,TioÅrMedia,0)+IF($D$4+Höjning2<='4. NPV'!E$4,FemtonÅrMedia,0))+((E$6*NybMedia+E$7*BefMedia)*((1+Inflation)^('4. NPV'!E$5-1)))) -> 0 | F23: =-(((F$6*NybMedia+F$7*BefMedia)*(1+Inflation)^(F5-1))*(IF($D$4+Höjnin1<='4. NPV'!F$4,TioÅrMedia,0)+IF($D$4+Höjning2<='4. NPV'!F$4,FemtonÅrMedia,0))+((F$6*NybMedia+F$7*BefMedia)*((1+Inflation)^('4. NPV'!F$5-1)))) -> 0 | G23: =-(((G$6*NybMedia+G$7*BefMedia)*(1+Inflation)^(G5-1))*(IF($D$4+Höjnin1<='4. NPV'!G$4,TioÅrMedia,0)+IF($D$4+Höjning2<='4. NPV'!G$4,FemtonÅrMedia,0))+((G$6*NybMedia+G$7*BefMedia)*((1+Inflation)^('4. NPV'!G$5-1)))) -> 0 | H23: =-(((H$6*NybMedia+H$7*BefMedia)*(1+Inflation)^(H5-1))*(IF($D$4+Höjnin1<='4. NPV'!H$4,TioÅrMedia,0)+IF($D$4+Höjning2<='4. NPV'!H$4,FemtonÅrMedia,0))+((H$6*NybMedia+H$7*BefMedia)*((1+Inflation)^('4. NPV'!H$5-1)))) -> 0 | I23: =-(((I$6*NybMedia+I$7*BefMedia)*(1+Inflation)^(I5-1))*(IF($D$4+Höjnin1<='4. NPV'!I$4,TioÅrMedia,0)+IF($D$4+Höjning2<='4. NPV'!I$4,FemtonÅrMedia,0))+((I$6*NybMedia+I$7*BefMedia)*((1+Inflation)^('4. NPV'!I$5-1)))) -> 0 | J23: =-(((J$6*NybMedia+J$7*BefMedia)*(1+Inflation)^(J5-1))*(IF($D$4+Höjnin1<='4. NPV'!J$4,TioÅrMedia,0)+IF($D$4+Höjning2<='4. NPV'!J$4,FemtonÅrMedia,0))+((J$6*NybMedia+J$7*BefMedia)*((1+Inflation)^('4. NPV'!J$5-1)))) -> 0 | K23: =-(((K$6*NybMedia+K$7*BefMedia)*(1+Inflation)^(K5-1))*(IF($D$4+Höjnin1<='4. NPV'!K$4,TioÅrMedia,0)+IF($D$4+Höjning2<='4. NPV'!K$4,FemtonÅrMedia,0))+((K$6*NybMedia+K$7*BefMedia)*((1+Inflation)^('4. NPV'!K$5-1)))) -> 0 | ... BA23: =-(((BA$6*NybMedia+BA$7*BefMedia)*(1+Inflation)^(BA5-1))*(IF($D$4+Höjnin1<='4. NPV'!BA$4,TioÅrMedia,0)+IF($D$4+Höjning2<='4. NPV'!BA$4,FemtonÅrMedia,0))+((BA$6*NybMedia+BA$7*BefMedia)*((1+Inflation)^('4. NPV'!BA$5-1)))) -> 0
B24: Total Övriga förvaltningskostnader | C24: =IFERROR($D24/$C$8,"") -> -405 | D24: =-(((D$6*NybÖvrigaförvaltningskostnader+D$7*BefÖvrigaförvaltningskostnader)*(1+Inflation)^(D5-1))*(IF($D$4+Höjnin1<='4. NPV'!D$4,TioÅrÖvrigaFörvaltningskostnader,0)+IF($D$4+Höjning2<='4. NPV'!D$4,FemtonÅrÖvrigaFörvaltningskostnader,0))+((D$6*NybÖvrigaförvaltningskostnader+D$7*BefÖvrigaförvaltningskostnader)*((1+Inflation)^('4. NPV'!D$5-1)))) -> -2470500 | E24: =-(((E$6*NybÖvrigaförvaltningskostnader+E$7*BefÖvrigaförvaltningskostnader)*(1+Inflation)^(E5-1))*(IF($D$4+Höjnin1<='4. NPV'!E$4,TioÅrÖvrigaFörvaltningskostnader,0)+IF($D$4+Höjning2<='4. NPV'!E$4,FemtonÅrÖvrigaFörvaltningskostnader,0))+((E$6*NybÖvrigaförvaltningskostnader+E$7*BefÖvrigaförvaltningskostnader)*((1+Inflation)^('4. NPV'!E$5-1)))) -> -2519910 | F24: =-(((F$6*NybÖvrigaförvaltningskostnader+F$7*BefÖvrigaförvaltningskostnader)*(1+Inflation)^(F5-1))*(IF($D$4+Höjnin1<='4. NPV'!F$4,TioÅrÖvrigaFörvaltningskostnader,0)+IF($D$4+Höjning2<='4. NPV'!F$4,FemtonÅrÖvrigaFörvaltningskostnader,0))+((F$6*NybÖvrigaförvaltningskostnader+F$7*BefÖvrigaförvaltningskostnader)*((1+Inflation)^('4. NPV'!F$5-1)))) -> -2570308.2 | G24: =-(((G$6*NybÖvrigaförvaltningskostnader+G$7*BefÖvrigaförvaltningskostnader)*(1+Inflation)^(G5-1))*(IF($D$4+Höjnin1<='4. NPV'!G$4,TioÅrÖvrigaFörvaltningskostnader,0)+IF($D$4+Höjning2<='4. NPV'!G$4,FemtonÅrÖvrigaFörvaltningskostnader,0))+((G$6*NybÖvrigaförvaltningskostnader+G$7*BefÖvrigaförvaltningskostnader)*((1+Inflation)^('4. NPV'!G$5-1)))) -> -2621714.4 | H24: =-(((H$6*NybÖvrigaförvaltningskostnader+H$7*BefÖvrigaförvaltningskostnader)*(1+Inflation)^(H5-1))*(IF($D$4+Höjnin1<='4. NPV'!H$4,TioÅrÖvrigaFörvaltningskostnader,0)+IF($D$4+Höjning2<='4. NPV'!H$4,FemtonÅrÖvrigaFörvaltningskostnader,0))+((H$6*NybÖvrigaförvaltningskostnader+H$7*BefÖvrigaförvaltningskostnader)*((1+Inflation)^('4. NPV'!H$5-1)))) -> -2674148.7 | I24: =-(((I$6*NybÖvrigaförvaltningskostnader+I$7*BefÖvrigaförvaltningskostnader)*(1+Inflation)^(I5-1))*(IF($D$4+Höjnin1<='4. NPV'!I$4,TioÅrÖvrigaFörvaltningskostnader,0)+IF($D$4+Höjning2<='4. NPV'!I$4,FemtonÅrÖvrigaFörvaltningskostnader,0))+((I$6*NybÖvrigaförvaltningskostnader+I$7*BefÖvrigaförvaltningskostnader)*((1+Inflation)^('4. NPV'!I$5-1)))) -> -2727631.6 | J24: =-(((J$6*NybÖvrigaförvaltningskostnader+J$7*BefÖvrigaförvaltningskostnader)*(1+Inflation)^(J5-1))*(IF($D$4+Höjnin1<='4. NPV'!J$4,TioÅrÖvrigaFörvaltningskostnader,0)+IF($D$4+Höjning2<='4. NPV'!J$4,FemtonÅrÖvrigaFörvaltningskostnader,0))+((J$6*NybÖvrigaförvaltningskostnader+J$7*BefÖvrigaförvaltningskostnader)*((1+Inflation)^('4. NPV'!J$5-1)))) -> -2782184.3 | K24: =-(((K$6*NybÖvrigaförvaltningskostnader+K$7*BefÖvrigaförvaltningskostnader)*(1+Inflation)^(K5-1))*(IF($D$4+Höjnin1<='4. NPV'!K$4,TioÅrÖvrigaFörvaltningskostnader,0)+IF($D$4+Höjning2<='4. NPV'!K$4,FemtonÅrÖvrigaFörvaltningskostnader,0))+((K$6*NybÖvrigaförvaltningskostnader+K$7*BefÖvrigaförvaltningskostnader)*((1+Inflation)^('4. NPV'!K$5-1)))) -> -2837827.9 | ... BA24: =-(((BA$6*NybÖvrigaförvaltningskostnader+BA$7*BefÖvrigaförvaltningskostnader)*(1+Inflation)^(BA5-1))*(IF($D$4+Höjnin1<='4. NPV'!BA$4,TioÅrÖvrigaFörvaltningskostnader,0)+IF($D$4+Höjning2<='4. NPV'!BA$4,FemtonÅrÖvrigaFörvaltningskostnader,0))+((BA$6*NybÖvrigaförvaltningskostnader+BA$7*BefÖvrigaförvaltningskostnader)*((1+Inflation)^('4. NPV'!BA$5-1)))) -> 0
B25: Re-investering/hyressatt underhåll | C25: =IFERROR($D25/$C$8,"") -> 0 | D25: =IF(D$4="",0,IFERROR(-(SUMIF('2. Kalkyldata'!$R$34:$R$39,'4. NPV'!D$4,'2. Kalkyldata'!$W$34:$W$39)),0)) -> 0 | E25: =IF(E$4="",0,IFERROR(-(SUMIF('2. Kalkyldata'!$R$34:$R$39,'4. NPV'!E$4,'2. Kalkyldata'!$W$34:$W$39)),0)) -> 0 | F25: =IF(F$4="",0,IFERROR(-(SUMIF('2. Kalkyldata'!$R$34:$R$39,'4. NPV'!F$4,'2. Kalkyldata'!$W$34:$W$39)),0)) -> 0 | G25: =IF(G$4="",0,IFERROR(-(SUMIF('2. Kalkyldata'!$R$34:$R$39,'4. NPV'!G$4,'2. Kalkyldata'!$W$34:$W$39)),0)) -> 0 | H25: =IF(H$4="",0,IFERROR(-(SUMIF('2. Kalkyldata'!$R$34:$R$39,'4. NPV'!H$4,'2. Kalkyldata'!$W$34:$W$39)),0)) -> 0 | I25: =IF(I$4="",0,IFERROR(-(SUMIF('2. Kalkyldata'!$R$34:$R$39,'4. NPV'!I$4,'2. Kalkyldata'!$W$34:$W$39)),0)) -> 0 | J25: =IF(J$4="",0,IFERROR(-(SUMIF('2. Kalkyldata'!$R$34:$R$39,'4. NPV'!J$4,'2. Kalkyldata'!$W$34:$W$39)),0)) -> 0 | K25: =IF(K$4="",0,IFERROR(-(SUMIF('2. Kalkyldata'!$R$34:$R$39,'4. NPV'!K$4,'2. Kalkyldata'!$W$34:$W$39)),0)) -> 0 | ... BA25: =IF(BA$4="",0,IFERROR(-(SUMIF('2. Kalkyldata'!$R$34:$R$39,'4. NPV'!BA$4,'2. Kalkyldata'!$W$34:$W$39)),0)) -> 0
B26: Summa drift och underhåll | C26: =IFERROR($D26/$C$8,"") -> -405 | D26: =SUM(D20:D25) -> -2470500 | E26: =SUM(E20:E25) -> -2519910 | F26: =SUM(F20:F25) -> -2570308.2 | G26: =SUM(G20:G25) -> -2621714.4 | H26: =SUM(H20:H25) -> -2674148.7 | I26: =SUM(I20:I25) -> -2727631.6 | J26: =SUM(J20:J25) -> -2782184.3 | K26: =SUM(K20:K25) -> -2837827.9 | ... BA26: =SUM(BA20:BA25) -> 0
B27: Fastighetsskatt | C27: =IFERROR($D27/$C$8,"") -> 0 | D27: =(IF(D$4="",0,-IF(LOOKUP(D$4,'2. Kalkyldata'!$P$5:$R$5,'2. Kalkyldata'!$P$7:$R$7)=0,0,LOOKUP(D$4,'2. Kalkyldata'!$P$5:$R$5,'2. Kalkyldata'!$P$7:$R$7)))*((1+'2. Kalkyldata'!$M$9)^(D$4-$D$4)))*'2. Kalkyldata'!$P$8 -> 0 | E27: =IF(E$4="",0,-IF(LOOKUP(E$4,'2. Kalkyldata'!$P$5:$R$5,'2. Kalkyldata'!$P$7:$R$7)=0,-D$27,LOOKUP(E$4,'2. Kalkyldata'!$P$5:$R$5,'2. Kalkyldata'!$P$7:$R$7))*((1+'2. Kalkyldata'!$M$9)^(E$4-$D$4)))*'2. Kalkyldata'!$P$8 -> 0 | F27: =IF(F$4="",0,-IF(LOOKUP(F$4,'2. Kalkyldata'!$P$5:$R$5,'2. Kalkyldata'!$P$7:$R$7)=0,-E$27,LOOKUP(F$4,'2. Kalkyldata'!$P$5:$R$5,'2. Kalkyldata'!$P$7:$R$7))*((1+'2. Kalkyldata'!$M$9)^(F$4-$D$4)))*'2. Kalkyldata'!$P$8 -> 0 | G27: =IF(G$4="",0,-IF(LOOKUP(G$4,'2. Kalkyldata'!$P$5:$R$5,'2. Kalkyldata'!$P$7:$R$7)=0,-F$27,LOOKUP(G$4,'2. Kalkyldata'!$P$5:$R$5,'2. Kalkyldata'!$P$7:$R$7))*((1+'2. Kalkyldata'!$M$9)^(G$4-$D$4)))*'2. Kalkyldata'!$P$8 -> 0 | H27: =IF(H$4="",0,-IF(LOOKUP(H$4,'2. Kalkyldata'!$P$5:$R$5,'2. Kalkyldata'!$P$7:$R$7)=0,-G$27,LOOKUP(H$4,'2. Kalkyldata'!$P$5:$R$5,'2. Kalkyldata'!$P$7:$R$7))*((1+'2. Kalkyldata'!$M$9)^(H$4-$D$4)))*'2. Kalkyldata'!$P$8 -> 0 | I27: =IF(I$4="",0,-IF(LOOKUP(I$4,'2. Kalkyldata'!$P$5:$R$5,'2. Kalkyldata'!$P$7:$R$7)=0,-H$27,LOOKUP(I$4,'2. Kalkyldata'!$P$5:$R$5,'2. Kalkyldata'!$P$7:$R$7))*((1+'2. Kalkyldata'!$M$9)^(I$4-$D$4)))*'2. Kalkyldata'!$P$8 -> 0 | J27: =IF(J$4="",0,-IF(LOOKUP(J$4,'2. Kalkyldata'!$P$5:$R$5,'2. Kalkyldata'!$P$7:$R$7)=0,-I$27,LOOKUP(J$4,'2. Kalkyldata'!$P$5:$R$5,'2. Kalkyldata'!$P$7:$R$7))*((1+'2. Kalkyldata'!$M$9)^(J$4-$D$4)))*'2. Kalkyldata'!$P$8 -> 0 | K27: =IF(K$4="",0,-IF(LOOKUP(K$4,'2. Kalkyldata'!$P$5:$R$5,'2. Kalkyldata'!$P$7:$R$7)=0,-J$27,LOOKUP(K$4,'2. Kalkyldata'!$P$5:$R$5,'2. Kalkyldata'!$P$7:$R$7))*((1+'2. Kalkyldata'!$M$9)^(K$4-$D$4)))*'2. Kalkyldata'!$P$8 -> 0 | L27: =IF(L$4="",0,-IF(LOOKUP(L$4,'2. Kalkyldata'!$P$5:$R$5,'2. Kalkyldata'!$P$7:$R$7)=0,-K$27,LOOKUP(L$4,'2. Kalkyldata'!$P$5:$R$5,'2. Kalkyldata'!$P$7:$R$7))*((1+'2. Kalkyldata'!$M$9)^(L$4-$D$4)))*'2. Kalkyldata'!$P$8 -> 0 | ... BA27: =IF(BA$4="",0,-IF(LOOKUP(BA$4,'2. Kalkyldata'!$P$5:$R$5,'2. Kalkyldata'!$P$7:$R$7)=0,-AZ$27,LOOKUP(BA$4,'2. Kalkyldata'!$P$5:$R$5,'2. Kalkyldata'!$P$7:$R$7))*((1+'2. Kalkyldata'!$M$9)^(BA$4-$D$4)))*'2. Kalkyldata'!$P$8 -> 0
B28: Tomträttsavgäld | C28: =IFERROR($D28/$C$8,"") -> 0 | D28: =IF(D$4="",0,-IF(LOOKUP(D$4,'2. Kalkyldata'!$P$5:$R$5,'2. Kalkyldata'!$P$6:$R$6)=0,0,LOOKUP(D$4,'2. Kalkyldata'!$P$5:$R$5,'2. Kalkyldata'!$P$6:$R$6))) -> 0 | E28: =IF(E$4="",0,-IF(LOOKUP(E$4,'2. Kalkyldata'!$P$5:$R$5,'2. Kalkyldata'!$P$6:$R$6)=0,-D$28,LOOKUP(E$4,'2. Kalkyldata'!$P$5:$R$5,'2. Kalkyldata'!$P$6:$R$6))) -> 0 | F28: =IF(F$4="",0,-IF(LOOKUP(F$4,'2. Kalkyldata'!$P$5:$R$5,'2. Kalkyldata'!$P$6:$R$6)=0,-E$28,LOOKUP(F$4,'2. Kalkyldata'!$P$5:$R$5,'2. Kalkyldata'!$P$6:$R$6))) -> 0 | G28: =IF(G$4="",0,-IF(LOOKUP(G$4,'2. Kalkyldata'!$P$5:$R$5,'2. Kalkyldata'!$P$6:$R$6)=0,-F$28,LOOKUP(G$4,'2. Kalkyldata'!$P$5:$R$5,'2. Kalkyldata'!$P$6:$R$6))) -> 0 | H28: =IF(H$4="",0,-IF(LOOKUP(H$4,'2. Kalkyldata'!$P$5:$R$5,'2. Kalkyldata'!$P$6:$R$6)=0,-G$28,LOOKUP(H$4,'2. Kalkyldata'!$P$5:$R$5,'2. Kalkyldata'!$P$6:$R$6))) -> 0 | I28: =IF(I$4="",0,-IF(LOOKUP(I$4,'2. Kalkyldata'!$P$5:$R$5,'2. Kalkyldata'!$P$6:$R$6)=0,-H$28,LOOKUP(I$4,'2. Kalkyldata'!$P$5:$R$5,'2. Kalkyldata'!$P$6:$R$6))) -> 0 | J28: =IF(J$4="",0,-IF(LOOKUP(J$4,'2. Kalkyldata'!$P$5:$R$5,'2. Kalkyldata'!$P$6:$R$6)=0,-I$28,LOOKUP(J$4,'2. Kalkyldata'!$P$5:$R$5,'2. Kalkyldata'!$P$6:$R$6))) -> 0 | K28: =IF(K$4="",0,-IF(LOOKUP(K$4,'2. Kalkyldata'!$P$5:$R$5,'2. Kalkyldata'!$P$6:$R$6)=0,-J$28,LOOKUP(K$4,'2. Kalkyldata'!$P$5:$R$5,'2. Kalkyldata'!$P$6:$R$6))) -> 0 | L28: =IF(L$4="",0,-IF(LOOKUP(L$4,'2. Kalkyldata'!$P$5:$R$5,'2. Kalkyldata'!$P$6:$R$6)=0,-K$28,LOOKUP(L$4,'2. Kalkyldata'!$P$5:$R$5,'2. Kalkyldata'!$P$6:$R$6))) -> 0 | ... BA28: =IF(BA$4="",0,-IF(LOOKUP(BA$4,'2. Kalkyldata'!$P$5:$R$5,'2. Kalkyldata'!$P$6:$R$6)=0,-AZ$28,LOOKUP(BA$4,'2. Kalkyldata'!$P$5:$R$5,'2. Kalkyldata'!$P$6:$R$6))) -> 0
B29: Driftnetto | C29: =IFERROR($D29/$C$8,"") -> 2245 | D29: =D19+D26+D27+D28 -> 13694500 | E29: =E19+E26+E27+E28 -> 13871400 | F29: =F19+F26+F27+F28 -> 14050480 | G29: =G19+G26+G27+G28 -> 14231765 | H29: =H19+H26+H27+H28 -> 14415279 | I29: =I19+I26+I27+I28 -> 14601048 | J29: =J19+J26+J27+J28 -> 14789097 | K29: =K19+K26+K27+K28 -> 14979452 | ... BA29: =BA19+BA26+BA27+BA28 -> 0
B30: Driftnetto, kr/kvm | D30: =IFERROR(D29/D8,0) -> 2245 | E30: =IFERROR(E29/E8,0) -> 2274 | F30: =IFERROR(F29/F8,0) -> 2303.3574 | G30: =IFERROR(G29/G8,0) -> 2333.0762 | H30: =IFERROR(H29/H8,0) -> 2363.1606 | I30: =IFERROR(I29/I8,0) -> 2393.6145 | J30: =IFERROR(J29/J8,0) -> 2424.4422 | K30: =IFERROR(K29/K8,0) -> 2455.6478 | ... BA30: =IFERROR(BA29/BA8,0) -> 0
B31: Nettohyra, kr/kvm | D31: =IFERROR(D$19/D$8,0) -> 2650 | E31: =IFERROR(E$19/E$8,0) -> 2687.1 | F31: =IFERROR(F$19/F$8,0) -> 2724.7194 | G31: =IFERROR(G$19/G$8,0) -> 2762.8655 | H31: =IFERROR(H$19/H$8,0) -> 2801.5456 | I31: =IFERROR(I$19/I$8,0) -> 2840.7672 | J31: =IFERROR(J$19/J$8,0) -> 2880.538 | K31: =IFERROR(K$19/K$8,0) -> 2920.8655 | ... BA31: =IFERROR(BA$19/BA$8,0) -> 0
B32: Drift och underhåll exkl extraordinärt UH, kr/kvm | D32: =IFERROR(SUM(D$20:D$24)/D$8,0) -> -405 | E32: =IFERROR(SUM(E$20:E$24)/E$8,0) -> -413.1 | F32: =IFERROR(SUM(F$20:F$24)/F$8,0) -> -421.362 | G32: =IFERROR(SUM(G$20:G$24)/G$8,0) -> -429.78924 | H32: =IFERROR(SUM(H$20:H$24)/H$8,0) -> -438.38502 | I32: =IFERROR(SUM(I$20:I$24)/I$8,0) -> -447.15273 | J32: =IFERROR(SUM(J$20:J$24)/J$8,0) -> -456.09578 | K32: =IFERROR(SUM(K$20:K$24)/K$8,0) -> -465.2177 | ... BA32: =IFERROR(SUM(BA$20:BA$24)/BA$8,0) -> 0
B33: Överskottsgrad exkl extraordinärt UH | D33: =IF(D4="","",IFERROR((D29-D25)/D19,0)) -> 0.84716981 | E33: =IF(E4="","",IFERROR((E29-E25)/E19,0)) -> 0.84626549 | F33: =IF(F4="","",IFERROR((F29-F25)/F19,0)) -> 0.84535582 | G33: =IF(G4="","",IFERROR((G29-G25)/G19,0)) -> 0.84444076 | H33: =IF(H4="","",IFERROR((H29-H25)/H19,0)) -> 0.8435203 | I33: =IF(I4="","",IFERROR((I29-I25)/I19,0)) -> 0.84259438 | J33: =IF(J4="","",IFERROR((J29-J25)/J19,0)) -> 0.84166299 | K33: =IF(K4="","",IFERROR((K29-K25)/K19,0)) -> 0.84072608 | ... BA33: =IF(BA4="","",IFERROR((BA29-BA25)/BA19,0))
B34: Direktavkastning marknadsvärde | D34: =IFERROR(D$29/'7.Grafer'!C$44,0) -> 0.064171064 | E34: =IFERROR(E$29/'7.Grafer'!D$44,0) -> 0.064171544 | F34: =IFERROR(F$29/'7.Grafer'!E$44,0) -> 0.064172027 | G34: =IFERROR(G$29/'7.Grafer'!F$44,0) -> 0.064172514 | H34: =IFERROR(H$29/'7.Grafer'!G$44,0) -> 0.064173006 | I34: =IFERROR(I$29/'7.Grafer'!H$44,0) -> 0.064173501 | J34: =IFERROR(J$29/'7.Grafer'!I$44,0) -> 0.064174 | K34: =IFERROR(K$29/'7.Grafer'!J$44,0) -> 0.064174503 | ... BA34: =IFERROR(BA$29/'7.Grafer'!AZ$44,0) -> 0
B35: Direktavkastning bokfört värde | D35: =IFERROR(D$29/'7.Grafer'!C$48,0) -> 0.058843555 | E35: =IFERROR(E$29/'7.Grafer'!D$48,0) -> 0.061526371 | F35: =IFERROR(F$29/'7.Grafer'!E$48,0) -> 0.064398034 | G35: =IFERROR(G$29/'7.Grafer'!F$48,0) -> 0.067478196 | H35: =IFERROR(H$29/'7.Grafer'!G$48,0) -> 0.070789319 | I35: =IFERROR(I$29/'7.Grafer'!H$48,0) -> 0.074357191 | J35: =IFERROR(J$29/'7.Grafer'!I$48,0) -> 0.078211573 | K35: =IFERROR(K$29/'7.Grafer'!J$48,0) -> 0.082386984 | ... BA35: =IFERROR(BA$29/'7.Grafer'!AZ$48,0) -> 0
B36: PV | D36: =(D$29-D$25)/((1+'2. Kalkyldata'!$M$7)^'4. NPV'!D$5) -> 13098517 | E36: =(E$29-E$25)/((1+'2. Kalkyldata'!$M$7)^'4. NPV'!E$5) -> 12690310 | F36: =(F$29-F$25)/((1+'2. Kalkyldata'!$M$7)^'4. NPV'!F$5) -> 12294732 | G36: =(G$29-G$25)/((1+'2. Kalkyldata'!$M$7)^'4. NPV'!G$5) -> 11911395 | H36: =(H$29-H$25)/((1+'2. Kalkyldata'!$M$7)^'4. NPV'!H$5) -> 11539922 | I36: =(I$29-I$25)/((1+'2. Kalkyldata'!$M$7)^'4. NPV'!I$5) -> 11179949 | J36: =(J$29-J$25)/((1+'2. Kalkyldata'!$M$7)^'4. NPV'!J$5) -> 10831121 | K36: =(K$29-K$25)/((1+'2. Kalkyldata'!$M$7)^'4. NPV'!K$5) -> 10493095 | ... BA36: =(BA$29-BA$25)/((1+'2. Kalkyldata'!$M$7)^'4. NPV'!BA$5) -> 0
B37: Driftnetto exkl extraordinärt UH | D37: =D$29-D$25 -> 13694500 | E37: =E$29-E$25 -> 13871400 | F37: =F$29-F$25 -> 14050480 | G37: =G$29-G$25 -> 14231765 | H37: =H$29-H$25 -> 14415279 | I37: =I$29-I$25 -> 14601048 | J37: =J$29-J$25 -> 14789097 | K37: =K$29-K$25 -> 14979452 | ... BA37: =BA$29-BA$25 -> 0
B38: PV Extraordinärt UH | D38: =-(D$25/((1+'2. Kalkyldata'!$M$7)^D$5)) -> 0 | E38: =-(E$25/((1+'2. Kalkyldata'!$M$7)^E$5)) -> 0 | F38: =-(F$25/((1+'2. Kalkyldata'!$M$7)^F$5)) -> 0 | G38: =-(G$25/((1+'2. Kalkyldata'!$M$7)^G$5)) -> 0 | H38: =-(H$25/((1+'2. Kalkyldata'!$M$7)^H$5)) -> 0 | I38: =-(I$25/((1+'2. Kalkyldata'!$M$7)^I$5)) -> 0 | J38: =-(J$25/((1+'2. Kalkyldata'!$M$7)^J$5)) -> 0 | K38: =-(K$25/((1+'2. Kalkyldata'!$M$7)^K$5)) -> 0 | ... BA38: =-(BA$25/((1+'2. Kalkyldata'!$M$7)^BA$5)) -> 0
B39: Ackumulerat Driftnetto | D39: =IF(-D$25+SUM(($D$29:D$29))>'2. Kalkyldata'!$W$28,"",(SUM(($D$29:D$29)))) -> 13694500 | E39: =IF(-E$25+SUM(($D$29:E$29))>'2. Kalkyldata'!$W$28,"",(SUM(($D$29:E$29)))) -> 27565900 | F39: =IF(-F$25+SUM(($D$29:F$29))>'2. Kalkyldata'!$W$28,"",(SUM(($D$29:F$29)))) -> 41616380 | G39: =IF(-G$25+SUM(($D$29:G$29))>'2. Kalkyldata'!$W$28,"",(SUM(($D$29:G$29)))) -> 55848145 | H39: =IF(-H$25+SUM(($D$29:H$29))>'2. Kalkyldata'!$W$28,"",(SUM(($D$29:H$29)))) -> 70263425 | I39: =IF(-I$25+SUM(($D$29:I$29))>'2. Kalkyldata'!$W$28,"",(SUM(($D$29:I$29)))) -> 84864473 | J39: =IF(-J$25+SUM(($D$29:J$29))>'2. Kalkyldata'!$W$28,"",(SUM(($D$29:J$29)))) -> 99653570 | K39: =IF(-K$25+SUM(($D$29:K$29))>'2. Kalkyldata'!$W$28,"",(SUM(($D$29:K$29)))) -> 1.1463302e+08 | ... BA39: =IF(-BA$25+SUM(($D$29:BA$29))>'2. Kalkyldata'!$W$28,"",(SUM(($D$29:BA$29))))
B40: Beräkning nettonuvärde 10 år | D40: =IF(OR(D$5=$C$47),E$37,0) -> 0 | E40: =IF(OR(E$5=$C$47),F$37,0) -> 0 | F40: =IF(OR(F$5=$C$47),G$37,0) -> 0 | G40: =IF(OR(G$5=$C$47),H$37,0) -> 0 | H40: =IF(OR(H$5=$C$47),I$37,0) -> 0 | I40: =IF(OR(I$5=$C$47),J$37,0) -> 0 | J40: =IF(OR(J$5=$C$47),K$37,0) -> 0 | K40: =IF(OR(K$5=$C$47),L$37,0) -> 0 | ... BA40: =IF(OR(BA$5=$C$47),BB$37,0) -> 0
B41: Beräkning nettonuvärde 20 år | D41: =IF(OR(D$5=$E$47),E$37,0) -> 0 | E41: =IF(OR(E$5=$E$47),F$37,0) -> 0 | F41: =IF(OR(F$5=$E$47),G$37,0) -> 0 | G41: =IF(OR(G$5=$E$47),H$37,0) -> 0 | H41: =IF(OR(H$5=$E$47),I$37,0) -> 0 | I41: =IF(OR(I$5=$E$47),J$37,0) -> 0 | J41: =IF(OR(J$5=$E$47),K$37,0) -> 0 | K41: =IF(OR(K$5=$E$47),L$37,0) -> 0 | ... BA41: =IF(OR(BA$5=$E$47),BB$37,0) -> 0
B42: DoU, realt | D42: =(D$32)/((1+'2. Kalkyldata'!$M$9)^(D$5-1)) -> -405 | E42: =(E$32)/((1+'2. Kalkyldata'!$M$9)^(E$5-1)) -> -405 | F42: =(F$32)/((1+'2. Kalkyldata'!$M$9)^(F$5-1)) -> -405 | G42: =(G$32)/((1+'2. Kalkyldata'!$M$9)^(G$5-1)) -> -405 | H42: =(H$32)/((1+'2. Kalkyldata'!$M$9)^(H$5-1)) -> -405 | I42: =(I$32)/((1+'2. Kalkyldata'!$M$9)^(I$5-1)) -> -405 | J42: =(J$32)/((1+'2. Kalkyldata'!$M$9)^(J$5-1)) -> -405 | K42: =(K$32)/((1+'2. Kalkyldata'!$M$9)^(K$5-1)) -> -405 | ... BA42: =(BA$32)/((1+'2. Kalkyldata'!$M$9)^(BA$5-1)) -> 0
C43: =$D$4+(C47-1) -> 2035 | D43: =$D$4+(E47-1) -> 2045 | F43: =IF(OR(C43="",D43=""),"ÅR SAKNAS ovan NPV år!!!","")
C44: =LOOKUP(C43,D4:BA4,D3:BA3) -> <=2035 | D44: =LOOKUP(D43,E4:BB4,E3:BB3) -> <=2045 | F44: =IF(OR(C44="",D44=""),"ÅR SAKNAS ovan NPV år!!!","")
B47: NPV HELA FASTIGHETEN, krav 3 | C47: 10 | E47: ='2. Kalkyldata'!P17 -> 20 | F47: Hela fastigheten inkl. Bef-objekt. PV TOTALT (rad 52) prövas mot bokfört värde i krav 3 (2. Kalkyldata D15).
B48: PV Driftnetto | C48: =ROUND((SUMIFS($D$36:$BA$36,$D$4:$BA$4,$C$44))/10000,0)*10000 -> 114050000 | E48: =ROUND((SUMIFS($D$36:$BA$36,$D$4:$BA$4,$D$44))/10000,0)*10000 -> 197100000
B49: PV Extraordinärt UH | C49: =-ROUND((SUMIFS($D$38:$BA$38,$D$4:$BA$4,$C$44))/10000,0)*10000 -> 0 | E49: =-ROUND((SUMIFS($D$38:$BA$38,$D$4:$BA$4,$D$44))/10000,0)*10000 -> 0
B50: Restvärde (rad 89) | C50: =ROUND((HLOOKUP(C$43,$D$4:$BA$89,86,FALSE))/10000,0)*10000 -> 239460000 | E50: =ROUND((HLOOKUP(D$43,$D$4:$BA$89,86,FALSE))/10000,0)*10000 -> 271940000
B51: PV Restvärde | C51: =ROUND((C50/((1+'2. Kalkyldata'!$M$8)^(C47)))/10000,0)*10000 -> 105910000 | E51: =ROUND((E50/((1+'2. Kalkyldata'!$M$8)^(E47)))/10000,0)*10000 -> 53200000
B52: PV TOTALT (krav 3) | C52: =IFERROR(C48+C49+C51,0) -> 219960000 | E52: =IFERROR(E51+E48+E49,0) -> 250300000
B53: kr/kvm | C53: =IFERROR(C52/'2. Kalkyldata'!$H$28,0) -> 36059.016 | E53: =IFERROR(E52/'2. Kalkyldata'!$H$28,0) -> 41032.787
B55: Investeringar | C55: =-'2. Kalkyldata'!$W$28 -> -2.4e+08 | E55: =$C$55 -> -2.4e+08
B56: PV Investeringar | C56: =-'2. Kalkyldata'!$X$28 -> -2.4e+08 | E56: =$C$56 -> -2.4e+08
B57: kr/kvm | C57: =IFERROR($C$56/'2. Kalkyldata'!$H$28,0) -> -39344.262 | E57: =IFERROR($E$56/'2. Kalkyldata'!$H$28,0) -> -39344.262
B59: NPV hela fastigheten | C59: =$C$52+$C$56 -> -20040000 | E59: =$E$52+$E$56 -> 10300000 | F59: Informativ, ej krav. Lika med NPV tillkommande (rad 82) när Bef-rader saknas.
B60: kr/kvm | C60: =IFERROR($C$59/'2. Kalkyldata'!$H$28,0) -> -3285.2459 | E60: =IFERROR($E$59/'2. Kalkyldata'!$H$28,0) -> 1688.5246
B62: Pay-off tid | C62: =IF(COUNT(D39:BA39)=50,"N/A",COUNT(D39:BA39)) -> 15 | F62: År tills ackumulerat driftnetto (ej diskonterat) täcker investeringen. Informativ, förs till 2. Kalkyldata D16.
B64: TILLKOMMANDE FLÖDE — hela fastigheten minus Bef-objekt (nollalternativet)
B65: Area Bef-objekt | D65: =IF(D$4="",0,SUMIFS('2. Kalkyldata'!$H$23:$H$27,'2. Kalkyldata'!$E$23:$E$27,"Bef",'2. Kalkyldata'!$M$23:$M$27,D$3)) -> 0 | E65: =IF(E$4="",0,SUMIFS('2. Kalkyldata'!$H$23:$H$27,'2. Kalkyldata'!$E$23:$E$27,"Bef",'2. Kalkyldata'!$M$23:$M$27,E$3)) -> 0 | F65: =IF(F$4="",0,SUMIFS('2. Kalkyldata'!$H$23:$H$27,'2. Kalkyldata'!$E$23:$E$27,"Bef",'2. Kalkyldata'!$M$23:$M$27,F$3)) -> 0 | G65: =IF(G$4="",0,SUMIFS('2. Kalkyldata'!$H$23:$H$27,'2. Kalkyldata'!$E$23:$E$27,"Bef",'2. Kalkyldata'!$M$23:$M$27,G$3)) -> 0 | H65: =IF(H$4="",0,SUMIFS('2. Kalkyldata'!$H$23:$H$27,'2. Kalkyldata'!$E$23:$E$27,"Bef",'2. Kalkyldata'!$M$23:$M$27,H$3)) -> 0 | I65: =IF(I$4="",0,SUMIFS('2. Kalkyldata'!$H$23:$H$27,'2. Kalkyldata'!$E$23:$E$27,"Bef",'2. Kalkyldata'!$M$23:$M$27,I$3)) -> 0 | J65: =IF(J$4="",0,SUMIFS('2. Kalkyldata'!$H$23:$H$27,'2. Kalkyldata'!$E$23:$E$27,"Bef",'2. Kalkyldata'!$M$23:$M$27,J$3)) -> 0 | K65: =IF(K$4="",0,SUMIFS('2. Kalkyldata'!$H$23:$H$27,'2. Kalkyldata'!$E$23:$E$27,"Bef",'2. Kalkyldata'!$M$23:$M$27,K$3)) -> 0 | ... BA65: =IF(BA$4="",0,SUMIFS('2. Kalkyldata'!$H$23:$H$27,'2. Kalkyldata'!$E$23:$E$27,"Bef",'2. Kalkyldata'!$M$23:$M$27,BA$3)) -> 0
B66: Intäkter Bef-objekt | D66: =IF(D$4="",0,SUMPRODUCT(--('2. Kalkyldata'!$E$23:$E$27="Bef"),D12:D16)) -> 0 | E66: =IF(E$4="",0,SUMPRODUCT(--('2. Kalkyldata'!$E$23:$E$27="Bef"),E12:E16)) -> 0 | F66: =IF(F$4="",0,SUMPRODUCT(--('2. Kalkyldata'!$E$23:$E$27="Bef"),F12:F16)) -> 0 | G66: =IF(G$4="",0,SUMPRODUCT(--('2. Kalkyldata'!$E$23:$E$27="Bef"),G12:G16)) -> 0 | H66: =IF(H$4="",0,SUMPRODUCT(--('2. Kalkyldata'!$E$23:$E$27="Bef"),H12:H16)) -> 0 | I66: =IF(I$4="",0,SUMPRODUCT(--('2. Kalkyldata'!$E$23:$E$27="Bef"),I12:I16)) -> 0 | J66: =IF(J$4="",0,SUMPRODUCT(--('2. Kalkyldata'!$E$23:$E$27="Bef"),J12:J16)) -> 0 | K66: =IF(K$4="",0,SUMPRODUCT(--('2. Kalkyldata'!$E$23:$E$27="Bef"),K12:K16)) -> 0 | ... BA66: =IF(BA$4="",0,SUMPRODUCT(--('2. Kalkyldata'!$E$23:$E$27="Bef"),BA12:BA16)) -> 0
B67: Vakans Bef-objekt | D67: =IF(D$4="",0,-SUMPRODUCT(--('2. Kalkyldata'!$E$23:$E$27="Bef"),1-(D$4>='2. Kalkyldata'!$M$23:$M$27)*(D$4<='2. Kalkyldata'!$N$23:$N$27),D12:D16,'2. Kalkyldata'!$P$23:$P$27)) -> 0 | E67: =IF(E$4="",0,-SUMPRODUCT(--('2. Kalkyldata'!$E$23:$E$27="Bef"),1-(E$4>='2. Kalkyldata'!$M$23:$M$27)*(E$4<='2. Kalkyldata'!$N$23:$N$27),E12:E16,'2. Kalkyldata'!$P$23:$P$27)) -> 0 | F67: =IF(F$4="",0,-SUMPRODUCT(--('2. Kalkyldata'!$E$23:$E$27="Bef"),1-(F$4>='2. Kalkyldata'!$M$23:$M$27)*(F$4<='2. Kalkyldata'!$N$23:$N$27),F12:F16,'2. Kalkyldata'!$P$23:$P$27)) -> 0 | G67: =IF(G$4="",0,-SUMPRODUCT(--('2. Kalkyldata'!$E$23:$E$27="Bef"),1-(G$4>='2. Kalkyldata'!$M$23:$M$27)*(G$4<='2. Kalkyldata'!$N$23:$N$27),G12:G16,'2. Kalkyldata'!$P$23:$P$27)) -> 0 | H67: =IF(H$4="",0,-SUMPRODUCT(--('2. Kalkyldata'!$E$23:$E$27="Bef"),1-(H$4>='2. Kalkyldata'!$M$23:$M$27)*(H$4<='2. Kalkyldata'!$N$23:$N$27),H12:H16,'2. Kalkyldata'!$P$23:$P$27)) -> 0 | I67: =IF(I$4="",0,-SUMPRODUCT(--('2. Kalkyldata'!$E$23:$E$27="Bef"),1-(I$4>='2. Kalkyldata'!$M$23:$M$27)*(I$4<='2. Kalkyldata'!$N$23:$N$27),I12:I16,'2. Kalkyldata'!$P$23:$P$27)) -> 0 | J67: =IF(J$4="",0,-SUMPRODUCT(--('2. Kalkyldata'!$E$23:$E$27="Bef"),1-(J$4>='2. Kalkyldata'!$M$23:$M$27)*(J$4<='2. Kalkyldata'!$N$23:$N$27),J12:J16,'2. Kalkyldata'!$P$23:$P$27)) -> 0 | K67: =IF(K$4="",0,-SUMPRODUCT(--('2. Kalkyldata'!$E$23:$E$27="Bef"),1-(K$4>='2. Kalkyldata'!$M$23:$M$27)*(K$4<='2. Kalkyldata'!$N$23:$N$27),K12:K16,'2. Kalkyldata'!$P$23:$P$27)) -> 0 | ... BA67: =IF(BA$4="",0,-SUMPRODUCT(--('2. Kalkyldata'!$E$23:$E$27="Bef"),1-(BA$4>='2. Kalkyldata'!$M$23:$M$27)*(BA$4<='2. Kalkyldata'!$N$23:$N$27),BA12:BA16,'2. Kalkyldata'!$P$23:$P$27)) -> 0
B68: Drift och underhåll Bef-objekt | D68: =IF(D$4="",0,-D65*(1+Inflation)^(D$5-1)*(BefFastighetsskötsel*(1+IF($D$4+Höjnin1<=D$4,TioÅrFastighetsskötsel,0)+IF($D$4+Höjning2<=D$4,FemtonÅrFastighetsskötsel,0))+BefReparationer*(1+IF($D$4+Höjnin1<=D$4,TioÅrReparationer,0)+IF($D$4+Höjning2<=D$4,FemtonÅrReparationer,0))+BefPlaneratunderhåll*(1+IF($D$4+Höjnin1<=D$4,TioÅrPlaneratUnderhåll,0)+IF($D$4+Höjning2<=D$4,FemtonÅrPlaneratUnderhåll,0))+BefMedia*(1+IF($D$4+Höjnin1<=D$4,TioÅrMedia,0)+IF($D$4+Höjning2<=D$4,FemtonÅrMedia,0))+BefÖvrigaförvaltningskostnader*(1+IF($D$4+Höjnin1<=D$4,TioÅrÖvrigaFörvaltningskostnader,0)+IF($D$4+Höjning2<=D$4,FemtonÅrÖvrigaFörvaltningskostnader,0)))) -> 0 | E68: =IF(E$4="",0,-E65*(1+Inflation)^(E$5-1)*(BefFastighetsskötsel*(1+IF($D$4+Höjnin1<=E$4,TioÅrFastighetsskötsel,0)+IF($D$4+Höjning2<=E$4,FemtonÅrFastighetsskötsel,0))+BefReparationer*(1+IF($D$4+Höjnin1<=E$4,TioÅrReparationer,0)+IF($D$4+Höjning2<=E$4,FemtonÅrReparationer,0))+BefPlaneratunderhåll*(1+IF($D$4+Höjnin1<=E$4,TioÅrPlaneratUnderhåll,0)+IF($D$4+Höjning2<=E$4,FemtonÅrPlaneratUnderhåll,0))+BefMedia*(1+IF($D$4+Höjnin1<=E$4,TioÅrMedia,0)+IF($D$4+Höjning2<=E$4,FemtonÅrMedia,0))+BefÖvrigaförvaltningskostnader*(1+IF($D$4+Höjnin1<=E$4,TioÅrÖvrigaFörvaltningskostnader,0)+IF($D$4+Höjning2<=E$4,FemtonÅrÖvrigaFörvaltningskostnader,0)))) -> 0 | F68: =IF(F$4="",0,-F65*(1+Inflation)^(F$5-1)*(BefFastighetsskötsel*(1+IF($D$4+Höjnin1<=F$4,TioÅrFastighetsskötsel,0)+IF($D$4+Höjning2<=F$4,FemtonÅrFastighetsskötsel,0))+BefReparationer*(1+IF($D$4+Höjnin1<=F$4,TioÅrReparationer,0)+IF($D$4+Höjning2<=F$4,FemtonÅrReparationer,0))+BefPlaneratunderhåll*(1+IF($D$4+Höjnin1<=F$4,TioÅrPlaneratUnderhåll,0)+IF($D$4+Höjning2<=F$4,FemtonÅrPlaneratUnderhåll,0))+BefMedia*(1+IF($D$4+Höjnin1<=F$4,TioÅrMedia,0)+IF($D$4+Höjning2<=F$4,FemtonÅrMedia,0))+BefÖvrigaförvaltningskostnader*(1+IF($D$4+Höjnin1<=F$4,TioÅrÖvrigaFörvaltningskostnader,0)+IF($D$4+Höjning2<=F$4,FemtonÅrÖvrigaFörvaltningskostnader,0)))) -> 0 | G68: =IF(G$4="",0,-G65*(1+Inflation)^(G$5-1)*(BefFastighetsskötsel*(1+IF($D$4+Höjnin1<=G$4,TioÅrFastighetsskötsel,0)+IF($D$4+Höjning2<=G$4,FemtonÅrFastighetsskötsel,0))+BefReparationer*(1+IF($D$4+Höjnin1<=G$4,TioÅrReparationer,0)+IF($D$4+Höjning2<=G$4,FemtonÅrReparationer,0))+BefPlaneratunderhåll*(1+IF($D$4+Höjnin1<=G$4,TioÅrPlaneratUnderhåll,0)+IF($D$4+Höjning2<=G$4,FemtonÅrPlaneratUnderhåll,0))+BefMedia*(1+IF($D$4+Höjnin1<=G$4,TioÅrMedia,0)+IF($D$4+Höjning2<=G$4,FemtonÅrMedia,0))+BefÖvrigaförvaltningskostnader*(1+IF($D$4+Höjnin1<=G$4,TioÅrÖvrigaFörvaltningskostnader,0)+IF($D$4+Höjning2<=G$4,FemtonÅrÖvrigaFörvaltningskostnader,0)))) -> 0 | H68: =IF(H$4="",0,-H65*(1+Inflation)^(H$5-1)*(BefFastighetsskötsel*(1+IF($D$4+Höjnin1<=H$4,TioÅrFastighetsskötsel,0)+IF($D$4+Höjning2<=H$4,FemtonÅrFastighetsskötsel,0))+BefReparationer*(1+IF($D$4+Höjnin1<=H$4,TioÅrReparationer,0)+IF($D$4+Höjning2<=H$4,FemtonÅrReparationer,0))+BefPlaneratunderhåll*(1+IF($D$4+Höjnin1<=H$4,TioÅrPlaneratUnderhåll,0)+IF($D$4+Höjning2<=H$4,FemtonÅrPlaneratUnderhåll,0))+BefMedia*(1+IF($D$4+Höjnin1<=H$4,TioÅrMedia,0)+IF($D$4+Höjning2<=H$4,FemtonÅrMedia,0))+BefÖvrigaförvaltningskostnader*(1+IF($D$4+Höjnin1<=H$4,TioÅrÖvrigaFörvaltningskostnader,0)+IF($D$4+Höjning2<=H$4,FemtonÅrÖvrigaFörvaltningskostnader,0)))) -> 0 | I68: =IF(I$4="",0,-I65*(1+Inflation)^(I$5-1)*(BefFastighetsskötsel*(1+IF($D$4+Höjnin1<=I$4,TioÅrFastighetsskötsel,0)+IF($D$4+Höjning2<=I$4,FemtonÅrFastighetsskötsel,0))+BefReparationer*(1+IF($D$4+Höjnin1<=I$4,TioÅrReparationer,0)+IF($D$4+Höjning2<=I$4,FemtonÅrReparationer,0))+BefPlaneratunderhåll*(1+IF($D$4+Höjnin1<=I$4,TioÅrPlaneratUnderhåll,0)+IF($D$4+Höjning2<=I$4,FemtonÅrPlaneratUnderhåll,0))+BefMedia*(1+IF($D$4+Höjnin1<=I$4,TioÅrMedia,0)+IF($D$4+Höjning2<=I$4,FemtonÅrMedia,0))+BefÖvrigaförvaltningskostnader*(1+IF($D$4+Höjnin1<=I$4,TioÅrÖvrigaFörvaltningskostnader,0)+IF($D$4+Höjning2<=I$4,FemtonÅrÖvrigaFörvaltningskostnader,0)))) -> 0 | J68: =IF(J$4="",0,-J65*(1+Inflation)^(J$5-1)*(BefFastighetsskötsel*(1+IF($D$4+Höjnin1<=J$4,TioÅrFastighetsskötsel,0)+IF($D$4+Höjning2<=J$4,FemtonÅrFastighetsskötsel,0))+BefReparationer*(1+IF($D$4+Höjnin1<=J$4,TioÅrReparationer,0)+IF($D$4+Höjning2<=J$4,FemtonÅrReparationer,0))+BefPlaneratunderhåll*(1+IF($D$4+Höjnin1<=J$4,TioÅrPlaneratUnderhåll,0)+IF($D$4+Höjning2<=J$4,FemtonÅrPlaneratUnderhåll,0))+BefMedia*(1+IF($D$4+Höjnin1<=J$4,TioÅrMedia,0)+IF($D$4+Höjning2<=J$4,FemtonÅrMedia,0))+BefÖvrigaförvaltningskostnader*(1+IF($D$4+Höjnin1<=J$4,TioÅrÖvrigaFörvaltningskostnader,0)+IF($D$4+Höjning2<=J$4,FemtonÅrÖvrigaFörvaltningskostnader,0)))) -> 0 | K68: =IF(K$4="",0,-K65*(1+Inflation)^(K$5-1)*(BefFastighetsskötsel*(1+IF($D$4+Höjnin1<=K$4,TioÅrFastighetsskötsel,0)+IF($D$4+Höjning2<=K$4,FemtonÅrFastighetsskötsel,0))+BefReparationer*(1+IF($D$4+Höjnin1<=K$4,TioÅrReparationer,0)+IF($D$4+Höjning2<=K$4,FemtonÅrReparationer,0))+BefPlaneratunderhåll*(1+IF($D$4+Höjnin1<=K$4,TioÅrPlaneratUnderhåll,0)+IF($D$4+Höjning2<=K$4,FemtonÅrPlaneratUnderhåll,0))+BefMedia*(1+IF($D$4+Höjnin1<=K$4,TioÅrMedia,0)+IF($D$4+Höjning2<=K$4,FemtonÅrMedia,0))+BefÖvrigaförvaltningskostnader*(1+IF($D$4+Höjnin1<=K$4,TioÅrÖvrigaFörvaltningskostnader,0)+IF($D$4+Höjning2<=K$4,FemtonÅrÖvrigaFörvaltningskostnader,0)))) -> 0 | ... BA68: =IF(BA$4="",0,-BA65*(1+Inflation)^(BA$5-1)*(BefFastighetsskötsel*(1+IF($D$4+Höjnin1<=BA$4,TioÅrFastighetsskötsel,0)+IF($D$4+Höjning2<=BA$4,FemtonÅrFastighetsskötsel,0))+BefReparationer*(1+IF($D$4+Höjnin1<=BA$4,TioÅrReparationer,0)+IF($D$4+Höjning2<=BA$4,FemtonÅrReparationer,0))+BefPlaneratunderhåll*(1+IF($D$4+Höjnin1<=BA$4,TioÅrPlaneratUnderhåll,0)+IF($D$4+Höjning2<=BA$4,FemtonÅrPlaneratUnderhåll,0))+BefMedia*(1+IF($D$4+Höjnin1<=BA$4,TioÅrMedia,0)+IF($D$4+Höjning2<=BA$4,FemtonÅrMedia,0))+BefÖvrigaförvaltningskostnader*(1+IF($D$4+Höjnin1<=BA$4,TioÅrÖvrigaFörvaltningskostnader,0)+IF($D$4+Höjning2<=BA$4,FemtonÅrÖvrigaFörvaltningskostnader,0)))) -> 0
B69: Re-investering Bef-objekt | D69: =IF(D$4="",0,-SUMPRODUCT(--('2. Kalkyldata'!$E$23:$E$27="Bef"),SUMIFS('2. Kalkyldata'!$W$34:$W$39,'2. Kalkyldata'!$R$34:$R$39,D$4,'2. Kalkyldata'!$Q$34:$Q$39,'2. Kalkyldata'!$C$23:$C$27))) -> 0 | E69: =IF(E$4="",0,-SUMPRODUCT(--('2. Kalkyldata'!$E$23:$E$27="Bef"),SUMIFS('2. Kalkyldata'!$W$34:$W$39,'2. Kalkyldata'!$R$34:$R$39,E$4,'2. Kalkyldata'!$Q$34:$Q$39,'2. Kalkyldata'!$C$23:$C$27))) -> 0 | F69: =IF(F$4="",0,-SUMPRODUCT(--('2. Kalkyldata'!$E$23:$E$27="Bef"),SUMIFS('2. Kalkyldata'!$W$34:$W$39,'2. Kalkyldata'!$R$34:$R$39,F$4,'2. Kalkyldata'!$Q$34:$Q$39,'2. Kalkyldata'!$C$23:$C$27))) -> 0 | G69: =IF(G$4="",0,-SUMPRODUCT(--('2. Kalkyldata'!$E$23:$E$27="Bef"),SUMIFS('2. Kalkyldata'!$W$34:$W$39,'2. Kalkyldata'!$R$34:$R$39,G$4,'2. Kalkyldata'!$Q$34:$Q$39,'2. Kalkyldata'!$C$23:$C$27))) -> 0 | H69: =IF(H$4="",0,-SUMPRODUCT(--('2. Kalkyldata'!$E$23:$E$27="Bef"),SUMIFS('2. Kalkyldata'!$W$34:$W$39,'2. Kalkyldata'!$R$34:$R$39,H$4,'2. Kalkyldata'!$Q$34:$Q$39,'2. Kalkyldata'!$C$23:$C$27))) -> 0 | I69: =IF(I$4="",0,-SUMPRODUCT(--('2. Kalkyldata'!$E$23:$E$27="Bef"),SUMIFS('2. Kalkyldata'!$W$34:$W$39,'2. Kalkyldata'!$R$34:$R$39,I$4,'2. Kalkyldata'!$Q$34:$Q$39,'2. Kalkyldata'!$C$23:$C$27))) -> 0 | J69: =IF(J$4="",0,-SUMPRODUCT(--('2. Kalkyldata'!$E$23:$E$27="Bef"),SUMIFS('2. Kalkyldata'!$W$34:$W$39,'2. Kalkyldata'!$R$34:$R$39,J$4,'2. Kalkyldata'!$Q$34:$Q$39,'2. Kalkyldata'!$C$23:$C$27))) -> 0 | K69: =IF(K$4="",0,-SUMPRODUCT(--('2. Kalkyldata'!$E$23:$E$27="Bef"),SUMIFS('2. Kalkyldata'!$W$34:$W$39,'2. Kalkyldata'!$R$34:$R$39,K$4,'2. Kalkyldata'!$Q$34:$Q$39,'2. Kalkyldata'!$C$23:$C$27))) -> 0 | ... BA69: =IF(BA$4="",0,-SUMPRODUCT(--('2. Kalkyldata'!$E$23:$E$27="Bef"),SUMIFS('2. Kalkyldata'!$W$34:$W$39,'2. Kalkyldata'!$R$34:$R$39,BA$4,'2. Kalkyldata'!$Q$34:$Q$39,'2. Kalkyldata'!$C$23:$C$27))) -> 0
B70: Driftnetto Bef-objekt | D70: =D66+D67+D68+D69 -> 0 | E70: =E66+E67+E68+E69 -> 0 | F70: =F66+F67+F68+F69 -> 0 | G70: =G66+G67+G68+G69 -> 0 | H70: =H66+H67+H68+H69 -> 0 | I70: =I66+I67+I68+I69 -> 0 | J70: =J66+J67+J68+J69 -> 0 | K70: =K66+K67+K68+K69 -> 0 | ... BA70: =BA66+BA67+BA68+BA69 -> 0
B71: Driftnetto tillkommande | D71: =D29-D70 -> 13694500 | E71: =E29-E70 -> 13871400 | F71: =F29-F70 -> 14050480 | G71: =G29-G70 -> 14231765 | H71: =H29-H70 -> 14415279 | I71: =I29-I70 -> 14601048 | J71: =J29-J70 -> 14789097 | K71: =K29-K70 -> 14979452 | ... BA71: =BA29-BA70 -> 0
B72: Re-investering tillkommande | D72: =D25-D69 -> 0 | E72: =E25-E69 -> 0 | F72: =F25-F69 -> 0 | G72: =G25-G69 -> 0 | H72: =H25-H69 -> 0 | I72: =I25-I69 -> 0 | J72: =J25-J69 -> 0 | K72: =K25-K69 -> 0 | ... BA72: =BA25-BA69 -> 0
B73: PV driftnetto tillkommande | D73: =(D71-D72)/((1+'2. Kalkyldata'!$M$7)^D$5) -> 13098517 | E73: =(E71-E72)/((1+'2. Kalkyldata'!$M$7)^E$5) -> 12690310 | F73: =(F71-F72)/((1+'2. Kalkyldata'!$M$7)^F$5) -> 12294732 | G73: =(G71-G72)/((1+'2. Kalkyldata'!$M$7)^G$5) -> 11911395 | H73: =(H71-H72)/((1+'2. Kalkyldata'!$M$7)^H$5) -> 11539922 | I73: =(I71-I72)/((1+'2. Kalkyldata'!$M$7)^I$5) -> 11179949 | J73: =(J71-J72)/((1+'2. Kalkyldata'!$M$7)^J$5) -> 10831121 | K73: =(K71-K72)/((1+'2. Kalkyldata'!$M$7)^K$5) -> 10493095 | ... BA73: =(BA71-BA72)/((1+'2. Kalkyldata'!$M$7)^BA$5) -> 0
B74: PV extraordinärt UH tillkommande | D74: =-(D72/((1+'2. Kalkyldata'!$M$7)^D$5)) -> 0 | E74: =-(E72/((1+'2. Kalkyldata'!$M$7)^E$5)) -> 0 | F74: =-(F72/((1+'2. Kalkyldata'!$M$7)^F$5)) -> 0 | G74: =-(G72/((1+'2. Kalkyldata'!$M$7)^G$5)) -> 0 | H74: =-(H72/((1+'2. Kalkyldata'!$M$7)^H$5)) -> 0 | I74: =-(I72/((1+'2. Kalkyldata'!$M$7)^I$5)) -> 0 | J74: =-(J72/((1+'2. Kalkyldata'!$M$7)^J$5)) -> 0 | K74: =-(K72/((1+'2. Kalkyldata'!$M$7)^K$5)) -> 0 | ... BA74: =-(BA72/((1+'2. Kalkyldata'!$M$7)^BA$5)) -> 0
B75: Utan Bef-rader (befintliga avtal som löper vidare) är tillkommande flöde = hela fastigheten, och blocket nedan visar samma siffror som rad 48–59.
B76: NPV TILLKOMMANDE, krav 1 | C76: =C47 -> 10 | E76: =E47 -> 20
B77: PV Driftnetto tillkommande | C77: =ROUND((SUMIFS($D$73:$BA$73,$D$4:$BA$4,$C$44))/10000,0)*10000 -> 114050000 | E77: =ROUND((SUMIFS($D$73:$BA$73,$D$4:$BA$4,$D$44))/10000,0)*10000 -> 197100000
B78: PV Extraordinärt UH | C78: =-ROUND((SUMIFS($D$74:$BA$74,$D$4:$BA$4,$C$44))/10000,0)*10000 -> 0 | E78: =-ROUND((SUMIFS($D$74:$BA$74,$D$4:$BA$4,$D$44))/10000,0)*10000 -> 0
B79: Restvärde tillkommande (rad 88) | C79: =ROUND((HLOOKUP(C$43,$D$4:$BA$88,85,FALSE))/10000,0)*10000 -> 239460000 | E79: =ROUND((HLOOKUP(D$43,$D$4:$BA$88,85,FALSE))/10000,0)*10000 -> 271940000
B80: PV Restvärde | C80: =ROUND((C79/((1+'2. Kalkyldata'!$M$8)^(C47)))/10000,0)*10000 -> 105910000 | E80: =ROUND((E79/((1+'2. Kalkyldata'!$M$8)^(E47)))/10000,0)*10000 -> 53200000
B81: PV TOTALT tillkommande | C81: =IFERROR(C77+C78+C80,0) -> 219960000 | E81: =IFERROR(E77+E78+E80,0) -> 250300000
B82: NPV tillkommande | C82: =C81+$C$56 -> -20040000 | E82: =E81+$E$56 -> 10300000 | F82: ← Krav 1: NPV vid kalkylperiodens slut (kolumn E) ska vara ≥ 0. Förs till 2. Kalkyldata D13.
B84: RESTVÄRDE — driftnetto år t+1 / justerad direktavkastning (2. Kalkyldata M11)
B85: Vakans tillkommande (efter avtal) | D85: =IF(D$4="",0,D18-D67) -> 0 | E85: =IF(E$4="",0,E18-E67) -> 0 | F85: =IF(F$4="",0,F18-F67) -> 0 | G85: =IF(G$4="",0,G18-G67) -> 0 | H85: =IF(H$4="",0,H18-H67) -> 0 | I85: =IF(I$4="",0,I18-I67) -> 0 | J85: =IF(J$4="",0,J18-J67) -> 0 | K85: =IF(K$4="",0,K18-K67) -> 0 | ... BA85: =IF(BA$4="",0,BA18-BA67) -> 0
B86: Kapitaliseringsbart driftnetto, tillkommande | D86: =IF(D$4="",0,D71-D72-D85) -> 13694500 | E86: =IF(E$4="",0,E71-E72-E85) -> 13871400 | F86: =IF(F$4="",0,F71-F72-F85) -> 14050480 | G86: =IF(G$4="",0,G71-G72-G85) -> 14231765 | H86: =IF(H$4="",0,H71-H72-H85) -> 14415279 | I86: =IF(I$4="",0,I71-I72-I85) -> 14601048 | J86: =IF(J$4="",0,J71-J72-J85) -> 14789097 | K86: =IF(K$4="",0,K71-K72-K85) -> 14979452 | ... BA86: =IF(BA$4="",0,BA71-BA72-BA85) -> 0
B87: Kapitaliseringsbart driftnetto, hela fastigheten | D87: =IF(D$4="",0,D29-D25-D18) -> 13694500 | E87: =IF(E$4="",0,E29-E25-E18) -> 13871400 | F87: =IF(F$4="",0,F29-F25-F18) -> 14050480 | G87: =IF(G$4="",0,G29-G25-G18) -> 14231765 | H87: =IF(H$4="",0,H29-H25-H18) -> 14415279 | I87: =IF(I$4="",0,I29-I25-I18) -> 14601048 | J87: =IF(J$4="",0,J29-J25-J18) -> 14789097 | K87: =IF(K$4="",0,K29-K25-K18) -> 14979452 | ... BA87: =IF(BA$4="",0,BA29-BA25-BA18) -> 0
B88: Restvärde tillkommande, årets slut (krav 1–2) | D88: =IF(E$4="",0,E86/'2. Kalkyldata'!$M$11) -> 2.1340615e+08 | E88: =IF(F$4="",0,F86/'2. Kalkyldata'!$M$11) -> 2.1616123e+08 | F88: =IF(G$4="",0,G86/'2. Kalkyldata'!$M$11) -> 2.1895023e+08 | G88: =IF(H$4="",0,H86/'2. Kalkyldata'!$M$11) -> 2.2177353e+08 | H88: =IF(I$4="",0,I86/'2. Kalkyldata'!$M$11) -> 2.2463151e+08 | I88: =IF(J$4="",0,J86/'2. Kalkyldata'!$M$11) -> 2.2752457e+08 | J88: =IF(K$4="",0,K86/'2. Kalkyldata'!$M$11) -> 2.304531e+08 | K88: =IF(L$4="",0,L86/'2. Kalkyldata'!$M$11) -> 2.3341749e+08 | ... BA88: =IF(BB$4="",0,BB86/'2. Kalkyldata'!$M$11) -> 0
B89: Restvärde hela fastigheten, årets slut (krav 3) | D89: =IF(E$4="",0,E87/'2. Kalkyldata'!$M$11) -> 2.1340615e+08 | E89: =IF(F$4="",0,F87/'2. Kalkyldata'!$M$11) -> 2.1616123e+08 | F89: =IF(G$4="",0,G87/'2. Kalkyldata'!$M$11) -> 2.1895023e+08 | G89: =IF(H$4="",0,H87/'2. Kalkyldata'!$M$11) -> 2.2177353e+08 | H89: =IF(I$4="",0,I87/'2. Kalkyldata'!$M$11) -> 2.2463151e+08 | I89: =IF(J$4="",0,J87/'2. Kalkyldata'!$M$11) -> 2.2752457e+08 | J89: =IF(K$4="",0,K87/'2. Kalkyldata'!$M$11) -> 2.304531e+08 | K89: =IF(L$4="",0,L87/'2. Kalkyldata'!$M$11) -> 2.3341749e+08 | ... BA89: =IF(BB$4="",0,BB87/'2. Kalkyldata'!$M$11) -> 0
B90: Bruttohyra tillk. (underlag Motsv. vakans) | D90: =IF(D$4="",0,D17-D66) -> 16165000 | E90: =IF(E$4="",0,E17-E66) -> 16391310 | F90: =IF(F$4="",0,F17-F66) -> 16620788 | G90: =IF(G$4="",0,G17-G66) -> 16853479 | H90: =IF(H$4="",0,H17-H66) -> 17089428 | I90: =IF(I$4="",0,I17-I66) -> 17328680 | J90: =IF(J$4="",0,J17-J66) -> 17571282 | K90: =IF(K$4="",0,K17-K66) -> 17817280 | ... BA90: =IF(BA$4="",0,BA17-BA66) -> 0
B91: Kapitaliseringsbart driftnetto = fullt uthyrt (vakans efter avtal återlagd), exkl. extraordinärt UH. Restvärdet vid slutet av år t = driftnetto år t+1 / justerad direktavkastning.

Sheet 5. IRR
B1: Internräntemetoden (IRR)
B2: Internräntemetoden (IRR) beräknar den årliga avkastningen på eget kapital för det tillkommande kassaflödet och jämförs med IRR-kravet på 2. Kalkyldata rad 14. Restvärdet vid kalkylperiodens slut förs in som försäljningsvärde. Standard är rent marknadsvärde (driftnetto år N+1 / justerad direktavkastning). Vikterna i kolumn A kan väga in återstående kapitalutlägg eller bokfört värde.
A5: Vikt | B5: BERÄKNING AV EXIT-VÄRDE VID KALKYLPERIODENS SLUT | C5: ='2. Kalkyldata'!$P$17 -> 20 | D5: =D15 -> 2026 | E5: =E15 -> 2027 | F5: =F15 -> 2028 | G5: =G15 -> 2029 | H5: =H15 -> 2030 | I5: =I15 -> 2031 | J5: =J15 -> 2032 | K5: =K15 -> 2033 | ... BA5: =BA15
A6: 0 | B6: Återstående ack. kapitalutlägg | C6: =ROUND((LOOKUP('2. Kalkyldata'!$P$17,'5. IRR'!$D$14:$BA$14,'5. IRR'!$D$6:BA6))/100000,0)*100000 -> 104500000 | D6: =IFERROR(IF('6. Ack.kapitalutlägg'!C$13>'2. Kalkyldata'!$U$17*((1+'2. Kalkyldata'!$M$9)^('5. IRR'!D$15-'5. IRR'!$D$15)),'6. Ack.kapitalutlägg'!C$13,('2. Kalkyldata'!$U$17*((1+'2. Kalkyldata'!$M$9)^('5. IRR'!D$15-'5. IRR'!$D$15)))),"") -> 2.372255e+08 | E6: =IFERROR(IF('6. Ack.kapitalutlägg'!D$13>'2. Kalkyldata'!$U$17*((1+'2. Kalkyldata'!$M$9)^('5. IRR'!E$15-'5. IRR'!$D$15)),'6. Ack.kapitalutlägg'!D$13,('2. Kalkyldata'!$U$17*((1+'2. Kalkyldata'!$M$9)^('5. IRR'!E$15-'5. IRR'!$D$15)))),"") -> 2.3414786e+08 | F6: =IFERROR(IF('6. Ack.kapitalutlägg'!E$13>'2. Kalkyldata'!$U$17*((1+'2. Kalkyldata'!$M$9)^('5. IRR'!F$15-'5. IRR'!$D$15)),'6. Ack.kapitalutlägg'!E$13,('2. Kalkyldata'!$U$17*((1+'2. Kalkyldata'!$M$9)^('5. IRR'!F$15-'5. IRR'!$D$15)))),"") -> 2.3075111e+08 | G6: =IFERROR(IF('6. Ack.kapitalutlägg'!F$13>'2. Kalkyldata'!$U$17*((1+'2. Kalkyldata'!$M$9)^('5. IRR'!G$15-'5. IRR'!$D$15)),'6. Ack.kapitalutlägg'!F$13,('2. Kalkyldata'!$U$17*((1+'2. Kalkyldata'!$M$9)^('5. IRR'!G$15-'5. IRR'!$D$15)))),"") -> 2.2701852e+08 | H6: =IFERROR(IF('6. Ack.kapitalutlägg'!G$13>'2. Kalkyldata'!$U$17*((1+'2. Kalkyldata'!$M$9)^('5. IRR'!H$15-'5. IRR'!$D$15)),'6. Ack.kapitalutlägg'!G$13,('2. Kalkyldata'!$U$17*((1+'2. Kalkyldata'!$M$9)^('5. IRR'!H$15-'5. IRR'!$D$15)))),"") -> 2.2293258e+08 | I6: =IFERROR(IF('6. Ack.kapitalutlägg'!H$13>'2. Kalkyldata'!$U$17*((1+'2. Kalkyldata'!$M$9)^('5. IRR'!I$15-'5. IRR'!$D$15)),'6. Ack.kapitalutlägg'!H$13,('2. Kalkyldata'!$U$17*((1+'2. Kalkyldata'!$M$9)^('5. IRR'!I$15-'5. IRR'!$D$15)))),"") -> 2.1847497e+08 | J6: =IFERROR(IF('6. Ack.kapitalutlägg'!I$13>'2. Kalkyldata'!$U$17*((1+'2. Kalkyldata'!$M$9)^('5. IRR'!J$15-'5. IRR'!$D$15)),'6. Ack.kapitalutlägg'!I$13,('2. Kalkyldata'!$U$17*((1+'2. Kalkyldata'!$M$9)^('5. IRR'!J$15-'5. IRR'!$D$15)))),"") -> 2.1362648e+08 | K6: =IFERROR(IF('6. Ack.kapitalutlägg'!J$13>'2. Kalkyldata'!$U$17*((1+'2. Kalkyldata'!$M$9)^('5. IRR'!K$15-'5. IRR'!$D$15)),'6. Ack.kapitalutlägg'!J$13,('2. Kalkyldata'!$U$17*((1+'2. Kalkyldata'!$M$9)^('5. IRR'!K$15-'5. IRR'!$D$15)))),"") -> 2.0836703e+08 | ... BA6: =IFERROR(IF('6. Ack.kapitalutlägg'!AZ$13>'2. Kalkyldata'!$U$17*((1+'2. Kalkyldata'!$M$9)^('5. IRR'!BA$15-'5. IRR'!$D$15)),'6. Ack.kapitalutlägg'!AZ$13,('2. Kalkyldata'!$U$17*((1+'2. Kalkyldata'!$M$9)^('5. IRR'!BA$15-'5. IRR'!$D$15)))),"")
A7: 1 | B7: ="Marknadsvärde, direktavk. "&ROUND('2. Kalkyldata'!$M$11*100,2)&" %" -> Marknadsvärde, direktavk. 6,5 % | C7: ='4. NPV'!$E$79 -> 271940000 | D7: =IF(D$5="","",'4. NPV'!D$88) -> 2.1340615e+08 | E7: =IF(E$5="","",'4. NPV'!E$88) -> 2.1616123e+08 | F7: =IF(F$5="","",'4. NPV'!F$88) -> 2.1895023e+08 | G7: =IF(G$5="","",'4. NPV'!G$88) -> 2.2177353e+08 | H7: =IF(H$5="","",'4. NPV'!H$88) -> 2.2463151e+08 | I7: =IF(I$5="","",'4. NPV'!I$88) -> 2.2752457e+08 | J7: =IF(J$5="","",'4. NPV'!J$88) -> 2.304531e+08 | K7: =IF(K$5="","",'4. NPV'!K$88) -> 2.3341749e+08 | ... BA7: =IF(BA$5="","",'4. NPV'!BA$88)
A8: 0 | B8: Bokfört värde | C8: =ROUND((LOOKUP('2. Kalkyldata'!$P$17,'5. IRR'!$D$14:$BA$14,'5. IRR'!$D$8:BA8))/100000,0)*100000 -> 94500000 | D8: =IF(D$5="","",'3. Finansiering'!D$57) -> 2.3272727e+08 | E8: =IF(E$5="","",'3. Finansiering'!E$57) -> 2.2545455e+08 | F8: =IF(F$5="","",'3. Finansiering'!F$57) -> 2.1818182e+08 | G8: =IF(G$5="","",'3. Finansiering'!G$57) -> 2.1090909e+08 | H8: =IF(H$5="","",'3. Finansiering'!H$57) -> 2.0363636e+08 | I8: =IF(I$5="","",'3. Finansiering'!I$57) -> 1.9636364e+08 | J8: =IF(J$5="","",'3. Finansiering'!J$57) -> 1.8909091e+08 | K8: =IF(K$5="","",'3. Finansiering'!K$57) -> 1.8181818e+08 | ... BA8: =IF(BA$5="","",'3. Finansiering'!BA$57)
B9: Återstående lån (löses rad 35) | C9: =ROUND((LOOKUP('2. Kalkyldata'!$P$17,'5. IRR'!$D$14:$BA$14,'5. IRR'!$D$9:BA9))/100000,0)*100000 -> 35500000 | D9: =IF(D$5="","",'3. Finansiering'!D$22) -> 86136000 | E9: =IF(E$5="","",'3. Finansiering'!E$22) -> 83472000 | F9: =IF(F$5="","",'3. Finansiering'!F$22) -> 80808000 | G9: =IF(G$5="","",'3. Finansiering'!G$22) -> 78144000 | H9: =IF(H$5="","",'3. Finansiering'!H$22) -> 75480000 | I9: =IF(I$5="","",'3. Finansiering'!I$22) -> 72816000 | J9: =IF(J$5="","",'3. Finansiering'!J$22) -> 70152000 | K9: =IF(K$5="","",'3. Finansiering'!K$22) -> 67488000 | ... BA9: =IF(BA$5="","",'3. Finansiering'!BA$22)
B10: Bedömt försäljningsvärde, exit | C10: =IF($C$11=0,($C$6*$A$6+$C$7*$A$7+$C$8*$A$8),C11) -> 271940000 | D10: = vikt × värde, rad 6–8 (eller C11 om ifyllt). Förs in som Försäljningsvärde (rad 18) exit-året.
B11: Justering av försäljningsvärde | D11: ← Lämnas normalt tomt. Ett belopp här ersätter exit-värdet i C10 helt – bara i undantagsfall och med motivering.
B13: Vikter i kolumn A (summa 100 %): 0 % / 100 % / 0 % = rent marknadsvärde vid justerad direktavkastning (standard). 0 % / 40 % / 60 % = tidigare LM 371-viktning mot bokfört värde.
B14: RESULTATRÄKNING / KASSAFLÖDE | D14: ='4. NPV'!D5 -> 1 | E14: ='4. NPV'!E5 -> 2 | F14: 3 | G14: ='4. NPV'!G5 -> 4 | H14: ='4. NPV'!H5 -> 5 | I14: ='4. NPV'!I5 -> 6 | J14: ='4. NPV'!J5 -> 7 | K14: ='4. NPV'!K5 -> 8 | L14: ='4. NPV'!L5 -> 9 | M14: ='4. NPV'!M5 -> 10 | N14: ='4. NPV'!N5 -> 11 | ... BA14: ='4. NPV'!BA5 -> 50
B15: År | C15: Belopp i kr | D15: =IF(D$14<='2. Kalkyldata'!$P$17,'3. Finansiering'!D$13,"") -> 2026 | E15: =IF(E$14<='2. Kalkyldata'!$P$17,'3. Finansiering'!E$13,"") -> 2027 | F15: =IF(F$14<='2. Kalkyldata'!$P$17,'3. Finansiering'!F$13,"") -> 2028 | G15: =IF(G$14<='2. Kalkyldata'!$P$17,'3. Finansiering'!G$13,"") -> 2029 | H15: =IF(H$14<='2. Kalkyldata'!$P$17,'3. Finansiering'!H$13,"") -> 2030 | I15: =IF(I$14<='2. Kalkyldata'!$P$17,'3. Finansiering'!I$13,"") -> 2031 | J15: =IF(J$14<='2. Kalkyldata'!$P$17,'3. Finansiering'!J$13,"") -> 2032 | K15: =IF(K$14<='2. Kalkyldata'!$P$17,'3. Finansiering'!K$13,"") -> 2033 | ... BA15: =IF(BA$14<='2. Kalkyldata'!$P$17,'3. Finansiering'!BA$13,"")
B16: Investering | C16: (ingår ej i IRR) | D16: ='4. NPV'!D9 -> -2.4e+08 | E16: ='4. NPV'!E9 -> 0 | F16: ='4. NPV'!F9 -> 0 | G16: ='4. NPV'!G9 -> 0 | H16: ='4. NPV'!H9 -> 0 | I16: ='4. NPV'!I9 -> 0 | J16: ='4. NPV'!J9 -> 0 | K16: ='4. NPV'!K9 -> 0 | ... BA16: ='4. NPV'!BA9 -> 0
B17: Ackumulerade investeringar | C17: (ingår ej i IRR) | D17: =IF(D15<>"",IFERROR(SUM($D$16:D$16),0),0) -> -2.4e+08 | E17: =IF(E15<>"",IFERROR(SUM($D$16:E$16),0),0) -> -2.4e+08 | F17: =IF(F15<>"",IFERROR(SUM($D$16:F$16),0),0) -> -2.4e+08 | G17: =IF(G15<>"",IFERROR(SUM($D$16:G$16),0),0) -> -2.4e+08 | H17: =IF(H15<>"",IFERROR(SUM($D$16:H$16),0),0) -> -2.4e+08 | I17: =IF(I15<>"",IFERROR(SUM($D$16:I$16),0),0) -> -2.4e+08 | J17: =IF(J15<>"",IFERROR(SUM($D$16:J$16),0),0) -> -2.4e+08 | K17: =IF(K15<>"",IFERROR(SUM($D$16:K$16),0),0) -> -2.4e+08 | ... BA17: =IF(BA15<>"",IFERROR(SUM($D$16:BA$16),0),0) -> 0
B18: Försäljningsvärde | D18: =IF(D$14=$C$5,$C$10,0) -> 0 | E18: =IF(E$14=$C$5,$C$10,0) -> 0 | F18: =IF(F$14=$C$5,$C$10,0) -> 0 | G18: =IF(G$14=$C$5,$C$10,0) -> 0 | H18: =IF(H$14=$C$5,$C$10,0) -> 0 | I18: =IF(I$14=$C$5,$C$10,0) -> 0 | J18: =IF(J$14=$C$5,$C$10,0) -> 0 | K18: =IF(K$14=$C$5,$C$10,0) -> 0 | ... BA18: =IF(BA$14=$C$5,$C$10,0) -> 0
B20: Investering, eget kapital | D20: =-'3. Finansiering'!D$16 -> -1.512e+08 | E20: =-'3. Finansiering'!E$16 -> 0 | F20: =-'3. Finansiering'!F$16 -> 0 | G20: =-'3. Finansiering'!G$16 -> 0 | H20: =-'3. Finansiering'!H$16 -> 0 | I20: =-'3. Finansiering'!I$16 -> 0 | J20: =-'3. Finansiering'!J$16 -> 0 | K20: =-'3. Finansiering'!K$16 -> 0 | ... BA20: =-'3. Finansiering'!BA$16 -> 0
B21: Bokfört värde – projektbelastning (avskrivning) | D21: =-'2. Kalkyldata'!$AA$28 -> 0
B23: Driftnetto tillkommande (4. NPV) | D23: =IFERROR(IF(D15="","",'4. NPV'!D$71),0) -> 13694500 | E23: =IFERROR(IF(E15="","",'4. NPV'!E$71),0) -> 13871400 | F23: =IFERROR(IF(F15="","",'4. NPV'!F$71),0) -> 14050480 | G23: =IFERROR(IF(G15="","",'4. NPV'!G$71),0) -> 14231765 | H23: =IFERROR(IF(H15="","",'4. NPV'!H$71),0) -> 14415279 | I23: =IFERROR(IF(I15="","",'4. NPV'!I$71),0) -> 14601048 | J23: =IFERROR(IF(J15="","",'4. NPV'!J$71),0) -> 14789097 | K23: =IFERROR(IF(K15="","",'4. NPV'!K$71),0) -> 14979452 | ... BA23: =IFERROR(IF(BA15="","",'4. NPV'!BA$71),0)
B24: Ersättningslokaler, kr/år | D24: =-IF(AND('2. Kalkyldata'!$Q$11<='5. IRR'!D15,'2. Kalkyldata'!$R$11>'5. IRR'!D15),'2. Kalkyldata'!$P$11,0) -> 0 | E24: =-IF(AND('2. Kalkyldata'!$Q$11<='5. IRR'!E15,'2. Kalkyldata'!$R$11>'5. IRR'!E15),'2. Kalkyldata'!$P$11,0) -> 0 | F24: =-IF(AND('2. Kalkyldata'!$Q$11<='5. IRR'!F15,'2. Kalkyldata'!$R$11>'5. IRR'!F15),'2. Kalkyldata'!$P$11,0) -> 0 | G24: =-IF(AND('2. Kalkyldata'!$Q$11<='5. IRR'!G15,'2. Kalkyldata'!$R$11>'5. IRR'!G15),'2. Kalkyldata'!$P$11,0) -> 0 | H24: =-IF(AND('2. Kalkyldata'!$Q$11<='5. IRR'!H15,'2. Kalkyldata'!$R$11>'5. IRR'!H15),'2. Kalkyldata'!$P$11,0) -> 0 | I24: =-IF(AND('2. Kalkyldata'!$Q$11<='5. IRR'!I15,'2. Kalkyldata'!$R$11>'5. IRR'!I15),'2. Kalkyldata'!$P$11,0) -> 0 | J24: =-IF(AND('2. Kalkyldata'!$Q$11<='5. IRR'!J15,'2. Kalkyldata'!$R$11>'5. IRR'!J15),'2. Kalkyldata'!$P$11,0) -> 0 | K24: =-IF(AND('2. Kalkyldata'!$Q$11<='5. IRR'!K15,'2. Kalkyldata'!$R$11>'5. IRR'!K15),'2. Kalkyldata'!$P$11,0) -> 0 | ... BA24: =-IF(AND('2. Kalkyldata'!$Q$11<='5. IRR'!BA15,'2. Kalkyldata'!$R$11>'5. IRR'!BA15),'2. Kalkyldata'!$P$11,0) -> 0
B25: Tillfälliga intäkter, kr/år | D25: =IF(AND('2. Kalkyldata'!$Q$12<='5. IRR'!D15,'2. Kalkyldata'!$R$12>'5. IRR'!D15),'2. Kalkyldata'!$P$12,0) -> 0 | E25: =IF(AND('2. Kalkyldata'!$Q$12<='5. IRR'!E15,'2. Kalkyldata'!$R$12>'5. IRR'!E15),'2. Kalkyldata'!$P$12,0) -> 0 | F25: =IF(AND('2. Kalkyldata'!$Q$12<='5. IRR'!F15,'2. Kalkyldata'!$R$12>'5. IRR'!F15),'2. Kalkyldata'!$P$12,0) -> 0 | G25: =IF(AND('2. Kalkyldata'!$Q$12<='5. IRR'!G15,'2. Kalkyldata'!$R$12>'5. IRR'!G15),'2. Kalkyldata'!$P$12,0) -> 0 | H25: =IF(AND('2. Kalkyldata'!$Q$12<='5. IRR'!H15,'2. Kalkyldata'!$R$12>'5. IRR'!H15),'2. Kalkyldata'!$P$12,0) -> 0 | I25: =IF(AND('2. Kalkyldata'!$Q$12<='5. IRR'!I15,'2. Kalkyldata'!$R$12>'5. IRR'!I15),'2. Kalkyldata'!$P$12,0) -> 0 | J25: =IF(AND('2. Kalkyldata'!$Q$12<='5. IRR'!J15,'2. Kalkyldata'!$R$12>'5. IRR'!J15),'2. Kalkyldata'!$P$12,0) -> 0 | K25: =IF(AND('2. Kalkyldata'!$Q$12<='5. IRR'!K15,'2. Kalkyldata'!$R$12>'5. IRR'!K15),'2. Kalkyldata'!$P$12,0) -> 0 | ... BA25: =IF(AND('2. Kalkyldata'!$Q$12<='5. IRR'!BA15,'2. Kalkyldata'!$R$12>'5. IRR'!BA15),'2. Kalkyldata'!$P$12,0) -> 0
B26: Central administration | D26: =IF(D15="",0,-'2. Kalkyldata'!$P$14*('4. NPV'!D$8-'4. NPV'!D$65)) -> -488000 | E26: =IF(E15="",0,-'2. Kalkyldata'!$P$14*('4. NPV'!E$8-'4. NPV'!E$65))*(1+'2. Kalkyldata'!$M$9)^('5. IRR'!E14-1) -> -497760 | F26: =IF(F15="",0,-'2. Kalkyldata'!$P$14*('4. NPV'!F$8-'4. NPV'!F$65))*(1+'2. Kalkyldata'!$M$9)^('5. IRR'!F14-1) -> -507715.2 | G26: =IF(G15="",0,-'2. Kalkyldata'!$P$14*('4. NPV'!G$8-'4. NPV'!G$65))*(1+'2. Kalkyldata'!$M$9)^('5. IRR'!G14-1) -> -517869.5 | H26: =IF(H15="",0,-'2. Kalkyldata'!$P$14*('4. NPV'!H$8-'4. NPV'!H$65))*(1+'2. Kalkyldata'!$M$9)^('5. IRR'!H14-1) -> -528226.89 | I26: =IF(I15="",0,-'2. Kalkyldata'!$P$14*('4. NPV'!I$8-'4. NPV'!I$65))*(1+'2. Kalkyldata'!$M$9)^('5. IRR'!I14-1) -> -538791.43 | J26: =IF(J15="",0,-'2. Kalkyldata'!$P$14*('4. NPV'!J$8-'4. NPV'!J$65))*(1+'2. Kalkyldata'!$M$9)^('5. IRR'!J14-1) -> -549567.26 | K26: =IF(K15="",0,-'2. Kalkyldata'!$P$14*('4. NPV'!K$8-'4. NPV'!K$65))*(1+'2. Kalkyldata'!$M$9)^('5. IRR'!K14-1) -> -560558.61 | L26: =IF(L15="",0,-'2. Kalkyldata'!$P$14*('4. NPV'!L$8-'4. NPV'!L$65))*(1+'2. Kalkyldata'!$M$9)^('5. IRR'!L14-1) -> -571769.78 | ... BA26: =IF(BA15="",0,-'2. Kalkyldata'!$P$14*('4. NPV'!BA$8-'4. NPV'!BA$65))*(1+'2. Kalkyldata'!$M$9)^('5. IRR'!BA14-1) -> 0
B27: Kapitalvinst vid försäljning | D27: =IF(IF(D$18<=0,0,D$18-D$8)<=0,0,IF(D$18<=0,0,D$18-D$8)) -> 0 | E27: =IF(IF(E$18<=0,0,E$18-E$8)<=0,0,IF(E$18<=0,0,E$18-E$8)) -> 0 | F27: =IF(IF(F$18<=0,0,F$18-F$8)<=0,0,IF(F$18<=0,0,F$18-F$8)) -> 0 | G27: =IF(IF(G$18<=0,0,G$18-G$8)<=0,0,IF(G$18<=0,0,G$18-G$8)) -> 0 | H27: =IF(IF(H$18<=0,0,H$18-H$8)<=0,0,IF(H$18<=0,0,H$18-H$8)) -> 0 | I27: =IF(IF(I$18<=0,0,I$18-I$8)<=0,0,IF(I$18<=0,0,I$18-I$8)) -> 0 | J27: =IF(IF(J$18<=0,0,J$18-J$8)<=0,0,IF(J$18<=0,0,J$18-J$8)) -> 0 | K27: =IF(IF(K$18<=0,0,K$18-K$8)<=0,0,IF(K$18<=0,0,K$18-K$8)) -> 0 | ... BA27: =IF(IF(BA$18<=0,0,BA$18-BA$8)<=0,0,IF(BA$18<=0,0,BA$18-BA$8)) -> 0
B28: Resultat före avskrivningar (EBITDA) | D28: =IFERROR(D23+SUM(D24:D27),0) -> 13206500 | E28: =IFERROR(E23+SUM(E24:E27),0) -> 13373640 | F28: =IFERROR(F23+SUM(F24:F27),0) -> 13542765 | G28: =IFERROR(G23+SUM(G24:G27),0) -> 13713896 | H28: =IFERROR(H23+SUM(H24:H27),0) -> 13887053 | I28: =IFERROR(I23+SUM(I24:I27),0) -> 14062257 | J28: =IFERROR(J23+SUM(J24:J27),0) -> 14239530 | K28: =IFERROR(K23+SUM(K24:K27),0) -> 14418893 | ... BA28: =IFERROR(BA23+SUM(BA24:BA27),0) -> 0
B29: Avskrivningar | D29: =IF(D15="","",'3. Finansiering'!D$47) -> -7272727.3 | E29: =IF(E15="","",'3. Finansiering'!E$47) -> -7272727.3 | F29: =IF(F15="","",'3. Finansiering'!F$47) -> -7272727.3 | G29: =IF(G15="","",'3. Finansiering'!G$47) -> -7272727.3 | H29: =IF(H15="","",'3. Finansiering'!H$47) -> -7272727.3 | I29: =IF(I15="","",'3. Finansiering'!I$47) -> -7272727.3 | J29: =IF(J15="","",'3. Finansiering'!J$47) -> -7272727.3 | K29: =IF(K15="","",'3. Finansiering'!K$47) -> -7272727.3 | ... BA29: =IF(BA15="","",'3. Finansiering'!BA$47)
B30: Räntekostnad | D30: =IF(D15="","",IF(D15<>"",'3. Finansiering'!D$24,0)) -> -2644375.2 | E30: =IF(E15="","",IF(E15<>"",'3. Finansiering'!E$24,0)) -> -2686129 | F30: =IF(F15="","",IF(F15<>"",'3. Finansiering'!F$24,0)) -> -2719997.3 | G30: =IF(G15="","",IF(G15<>"",'3. Finansiering'!G$24,0)) -> -2745980.2 | H30: =IF(H15="","",IF(H15<>"",'3. Finansiering'!H$24,0)) -> -2764077.6 | I30: =IF(I15="","",IF(I15<>"",'3. Finansiering'!I$24,0)) -> -2774289.6 | J30: =IF(J15="","",IF(J15<>"",'3. Finansiering'!J$24,0)) -> -2776616.2 | K30: =IF(K15="","",IF(K15<>"",'3. Finansiering'!K$24,0)) -> -2771057.3 | ... BA30: =IF(BA15="","",IF(BA15<>"",'3. Finansiering'!BA$24,0))
B31: Resultat efter finans | D31: =D28+SUM(D29:D30) -> 3289397.5 | E31: =E28+SUM(E29:E30) -> 3414783.8 | F31: =F28+SUM(F29:F30) -> 3550040.4 | G31: =G28+SUM(G29:G30) -> 3695188.1 | H31: =H28+SUM(H29:H30) -> 3850247.7 | I31: =I28+SUM(I29:I30) -> 4015240.2 | J31: =J28+SUM(J29:J30) -> 4190186.7 | K31: =K28+SUM(K29:K30) -> 4375108.4 | ... BA31: =BA28+SUM(BA29:BA30) -> 0
B32: =CONCATENATE("Bolagsskatt, ",'2. Kalkyldata'!M16*100,"%") -> Bolagsskatt, 20,6% | D32: =IF(D15="","",IF(D$31<=0,0,(-(D$31)*'2. Kalkyldata'!$M$16))) -> -677615.89 | E32: =IF(E15="","",IF(E$31<=0,0,(-(E$31)*'2. Kalkyldata'!$M$16))) -> -703445.46 | F32: =IF(F15="","",IF(F$31<=0,0,(-(F$31)*'2. Kalkyldata'!$M$16))) -> -731308.32 | G32: =IF(G15="","",IF(G$31<=0,0,(-(G$31)*'2. Kalkyldata'!$M$16))) -> -761208.74 | H32: =IF(H15="","",IF(H$31<=0,0,(-(H$31)*'2. Kalkyldata'!$M$16))) -> -793151.02 | I32: =IF(I15="","",IF(I$31<=0,0,(-(I$31)*'2. Kalkyldata'!$M$16))) -> -827139.47 | J32: =IF(J15="","",IF(J$31<=0,0,(-(J$31)*'2. Kalkyldata'!$M$16))) -> -863178.45 | K32: =IF(K15="","",IF(K$31<=0,0,(-(K$31)*'2. Kalkyldata'!$M$16))) -> -901272.34 | ... BA32: =IF(BA15="","",IF(BA$31<=0,0,(-(BA$31)*'2. Kalkyldata'!$M$16)))
B33: Resultat efter skatt | D33: =IFERROR(D$31+D$32,0) -> 2611781.6 | E33: =IFERROR(E$31+E$32,0) -> 2711338.3 | F33: =IFERROR(F$31+F$32,0) -> 2818732.1 | G33: =IFERROR(G$31+G$32,0) -> 2933979.3 | H33: =IFERROR(H$31+H$32,0) -> 3057096.6 | I33: =IFERROR(I$31+I$32,0) -> 3188100.7 | J33: =IFERROR(J$31+J$32,0) -> 3327008.2 | K33: =IFERROR(K$31+K$32,0) -> 3473836.1 | ... BA33: =IFERROR(BA$31+BA$32,0) -> 0
B34: Amortering | D34: =IF(D15="","",IF(D15<>"",'3. Finansiering'!D$20,0)) -> -2664000 | E34: =IF(E15="","",IF(E15<>"",'3. Finansiering'!E$20,0)) -> -2664000 | F34: =IF(F15="","",IF(F15<>"",'3. Finansiering'!F$20,0)) -> -2664000 | G34: =IF(G15="","",IF(G15<>"",'3. Finansiering'!G$20,0)) -> -2664000 | H34: =IF(H15="","",IF(H15<>"",'3. Finansiering'!H$20,0)) -> -2664000 | I34: =IF(I15="","",IF(I15<>"",'3. Finansiering'!I$20,0)) -> -2664000 | J34: =IF(J15="","",IF(J15<>"",'3. Finansiering'!J$20,0)) -> -2664000 | K34: =IF(K15="","",IF(K15<>"",'3. Finansiering'!K$20,0)) -> -2664000 | ... BA34: =IF(BA15="","",IF(BA15<>"",'3. Finansiering'!BA$20,0))
B35: Amortering återstående skuld (vid exit) | D35: =IF(E$15="",IF('2. Kalkyldata'!$M$3+'2. Kalkyldata'!$Q$17-1='5. IRR'!D15,-HLOOKUP(D$15,'3. Finansiering'!$D$13:$BA$26,10,FALSE),0),0) -> 0 | E35: =IF(F$15="",IF('2. Kalkyldata'!$M$3+'2. Kalkyldata'!$Q$17-1='5. IRR'!E15,-HLOOKUP(E$15,'3. Finansiering'!$D$13:$BA$26,10,FALSE),0),0) -> 0 | F35: =IF(G$15="",IF('2. Kalkyldata'!$M$3+'2. Kalkyldata'!$Q$17-1='5. IRR'!F15,-HLOOKUP(F$15,'3. Finansiering'!$D$13:$BA$26,10,FALSE),0),0) -> 0 | G35: =IF(H$15="",IF('2. Kalkyldata'!$M$3+'2. Kalkyldata'!$Q$17-1='5. IRR'!G15,-HLOOKUP(G$15,'3. Finansiering'!$D$13:$BA$26,10,FALSE),0),0) -> 0 | H35: =IF(I$15="",IF('2. Kalkyldata'!$M$3+'2. Kalkyldata'!$Q$17-1='5. IRR'!H15,-HLOOKUP(H$15,'3. Finansiering'!$D$13:$BA$26,10,FALSE),0),0) -> 0 | I35: =IF(J$15="",IF('2. Kalkyldata'!$M$3+'2. Kalkyldata'!$Q$17-1='5. IRR'!I15,-HLOOKUP(I$15,'3. Finansiering'!$D$13:$BA$26,10,FALSE),0),0) -> 0 | J35: =IF(K$15="",IF('2. Kalkyldata'!$M$3+'2. Kalkyldata'!$Q$17-1='5. IRR'!J15,-HLOOKUP(J$15,'3. Finansiering'!$D$13:$BA$26,10,FALSE),0),0) -> 0 | K35: =IF(L$15="",IF('2. Kalkyldata'!$M$3+'2. Kalkyldata'!$Q$17-1='5. IRR'!K15,-HLOOKUP(K$15,'3. Finansiering'!$D$13:$BA$26,10,FALSE),0),0) -> 0 | ... BA35: =IF(BB$15="",IF('2. Kalkyldata'!$M$3+'2. Kalkyldata'!$Q$17-1='5. IRR'!BA15,-HLOOKUP(BA$15,'3. Finansiering'!$D$13:$BA$26,10,FALSE),0),0) -> 0
B37: KASSAFLÖDE, före skatt | C37: (avskr. återförda) | D37: =IFERROR(((D$18+D$20+D$21+D$31+D$34+D$35)-D$29)-D$27,"") -> -1.4330188e+08 | E37: =IFERROR(((E$18+E$20+E$21+E$31+E$34+E$35)-E$29)-E$27,"") -> 8023511 | F37: =IFERROR(((F$18+F$20+F$21+F$31+F$34+F$35)-F$29)-F$27,"") -> 8158767.7 | G37: =IFERROR(((G$18+G$20+G$21+G$31+G$34+G$35)-G$29)-G$27,"") -> 8303915.3 | H37: =IFERROR(((H$18+H$20+H$21+H$31+H$34+H$35)-H$29)-H$27,"") -> 8458974.9 | I37: =IFERROR(((I$18+I$20+I$21+I$31+I$34+I$35)-I$29)-I$27,"") -> 8623967.4 | J37: =IFERROR(((J$18+J$20+J$21+J$31+J$34+J$35)-J$29)-J$27,"") -> 8798913.9 | K37: =IFERROR(((K$18+K$20+K$21+K$31+K$34+K$35)-K$29)-K$27,"") -> 8983835.7 | ... BA37: =IFERROR(((BA$18+BA$20+BA$21+BA$31+BA$34+BA$35)-BA$29)-BA$27,"")
B38: KASSAFLÖDE, efter skatt | D38: =IFERROR(((D$18+D$20+D$21+D$33+D$34+D$35)-D$29)-D$27,"") -> -1.4397949e+08 | E38: =IFERROR(((E$18+E$20+E$21+E$33+E$34+E$35)-E$29)-E$27,"") -> 7320065.6 | F38: =IFERROR(((F$18+F$20+F$21+F$33+F$34+F$35)-F$29)-F$27,"") -> 7427459.3 | G38: =IFERROR(((G$18+G$20+G$21+G$33+G$34+G$35)-G$29)-G$27,"") -> 7542706.6 | H38: =IFERROR(((H$18+H$20+H$21+H$33+H$34+H$35)-H$29)-H$27,"") -> 7665823.9 | I38: =IFERROR(((I$18+I$20+I$21+I$33+I$34+I$35)-I$29)-I$27,"") -> 7796828 | J38: =IFERROR(((J$18+J$20+J$21+J$33+J$34+J$35)-J$29)-J$27,"") -> 7935735.5 | K38: =IFERROR(((K$18+K$20+K$21+K$33+K$34+K$35)-K$29)-K$27,"") -> 8082563.4 | ... BA38: =IFERROR(((BA$18+BA$20+BA$21+BA$33+BA$34+BA$35)-BA$29)-BA$27,"")
B40: IRR eget kapital, före skatt | D40: =IFERROR(IRR(D37:BA37),"N/A") -> 0.080803743 | E40: ← Krav 2: jämförs med IRR-kravet på 2. Kalkyldata (F14)
B41: IRR eget kapital, efter skatt | D41: =IFERROR(IRR(D38:BA38),"N/A") -> 0.069043685
L42: Kontrollberäkning
L43: Försäljning | M43: =M18 -> 0 | N43: =N18 -> 0 | O43: =O18 -> 0 | P43: =P18 -> 0 | Q43: =Q18 -> 0 | R43: =R18 -> 0 | S43: =S18 -> 0 | T43: =T18 -> 0 | ... AJ43: =AJ18 -> 0
L44: Driftnetto | M44: =M23 -> 15367179 | N44: =N23 -> 15564605 | O44: =O23 -> 15764440 | P44: =P23 -> 15966712 | Q44: =Q23 -> 16171447 | R44: =R23 -> 16378672 | S44: =S23 -> 16588415 | T44: =T23 -> 16800703 | ... AJ44: =AJ23
L45: Bolagskostnader | M45: =M26+M30 -> -3319488.4 | N45: =N26+N30 -> -3301937.3 | O45: =O26+O30 -> -3192622.7 | P45: =P26+P30 -> -3083546 | Q45: =Q26+Q30 -> -2974712 | R45: =R26+R30 -> -2866125.6 | S45: =S26+S30 -> -2757791.7 | T45: =T26+T30 -> -2649715.4 | ... AJ45: =AJ26+AJ30 -> #VALUE!
L46: skatt | M46: =M32 -> -983642.53 | N46: =N32 -> -1027927.7 | O46: =O32 -> -1091612.6 | P46: =P32 -> -1155750.4 | Q46: =Q32 -> -1220345.5 | R46: =R32 -> -1285402.7 | S46: =S32 -> -1350926.5 | T46: =T32 -> -1416921.6 | ... AJ46: =AJ32
L47: Amortering | M47: =M34+M35 -> -2664000 | N47: =N34+N35 -> -2664000 | O47: =O34+O35 -> -2664000 | P47: =P34+P35 -> -2664000 | Q47: =Q34+Q35 -> -2664000 | R47: =R34+R35 -> -2664000 | S47: =S34+S35 -> -2664000 | T47: =T34+T35 -> -2664000 | ... AJ47: =AJ34+AJ35 -> #VALUE!
L48: CF utan skatt | M48: =SUM(M43:M47)-M46 -> 9383691 | N48: =N49-N46 -> 9598667.7 | O48: =O49-O46 -> 9907817.7 | P48: =P49-P46 -> 10219166 | Q48: =Q49-Q46 -> 10532735 | R48: =R49-R46 -> 10848546 | S48: =S49-S46 -> 11166623 | T48: =T49-T46 -> 11486987 | U48: =U49-U46 -> 11809662 | ... X48: =X49-X46 -> #VALUE! | Y48: =SUM(Y43:Y47)-Y46 -> #VALUE! | Z48: =Z49-Z46 -> #VALUE! | AA48: =AA49-AA46 -> #VALUE! | AB48: =AB49-AB46 -> #VALUE! | AC48: =AC49-AC46 -> #VALUE! | AD48: =AD49-AD46 -> #VALUE! | AE48: =AE49-AE46 -> #VALUE! | AF48: =AF49-AF46 -> #VALUE! | AG48: =AG49-AG46 -> #VALUE! | ... AJ48: =AJ49-AJ46 -> #VALUE!
L49: CF med skatt | M49: =SUM(M43:M47) -> 8400048.5 | N49: =SUM(N43:N47) -> 8570740 | O49: =SUM(O43:O47) -> 8816205.1 | P49: =SUM(P43:P47) -> 9063415.6 | Q49: =SUM(Q43:Q47) -> 9312389.2 | R49: =SUM(R43:R47) -> 9563143.6 | S49: =SUM(S43:S47) -> 9815696.4 | T49: =SUM(T43:T47) -> 10070066 | ... AJ49: =SUM(AJ43:AJ47) -> #VALUE!
B53: KÄNSLIGHET RESTVÄRDE — direktavkastning ±1,00 pp (tillkommande flöde)
B54: Scenario | C54: Direktavk. vid exit | D54: ="Exit-värde år "&$C$5 -> Exit-värde år 20 | E54: IRR före skatt | F54: NPV tillk., kr | G54: Mot IRR-krav | H54: Kravhyra krav 1–2, kr/kvm
B55: Optimistisk (−1,00 pp) | C55: ='2. Kalkyldata'!$M$11-0.01 -> 0.055 | D55: =$C$7*'2. Kalkyldata'!$M$11/C55 -> 3.2138364e+08 | E55: =IFERROR(IRR(D59:BA59),"N/A") -> 0.087247261 | F55: ='4. NPV'!$E$77+'4. NPV'!$E$78+ROUND(ROUND('4. NPV'!$E$79*'2. Kalkyldata'!$M$11/C55/10000,0)*10000/((1+'2. Kalkyldata'!$M$8)^'4. NPV'!$E$47)/10000,0)*10000+'4. NPV'!$E$56 -> 19970000 | G55: =IF(ISNUMBER(E55),IF(E55>='2. Kalkyldata'!$F$14,"✓ klarar krav","⚠ under krav"),"") -> ✓ klarar krav | H55: =CEILING('2. Kalkyldata'!$AD$20*'2. Kalkyldata'!$AF$19,1) -> 2480 | I55: IRR per scenario räknas i dolda hjälprader 59–61.
B56: Bedömt (2. Kalkyldata sektion 5) | C56: ='2. Kalkyldata'!$M$11 -> 0.065 | D56: =$C$7*'2. Kalkyldata'!$M$11/C56 -> 271940000 | E56: =IFERROR(IRR(D60:BA60),"N/A") -> 0.080803743 | F56: ='4. NPV'!$E$77+'4. NPV'!$E$78+ROUND(ROUND('4. NPV'!$E$79*'2. Kalkyldata'!$M$11/C56/10000,0)*10000/((1+'2. Kalkyldata'!$M$8)^'4. NPV'!$E$47)/10000,0)*10000+'4. NPV'!$E$56 -> 10300000 | G56: =IF(ISNUMBER(E56),IF(E56>='2. Kalkyldata'!$F$14,"✓ klarar krav","⚠ under krav"),"") -> ✓ klarar krav | H56: =CEILING('2. Kalkyldata'!$AD$20*'2. Kalkyldata'!$AD$19,1) -> 2559
B57: Pessimistisk (+1,00 pp) | C57: ='2. Kalkyldata'!$M$11+0.01 -> 0.075 | D57: =$C$7*'2. Kalkyldata'!$M$11/C57 -> 2.3568133e+08 | E57: =IFERROR(IRR(D61:BA61),"N/A") -> 0.075506366 | F57: ='4. NPV'!$E$77+'4. NPV'!$E$78+ROUND(ROUND('4. NPV'!$E$79*'2. Kalkyldata'!$M$11/C57/10000,0)*10000/((1+'2. Kalkyldata'!$M$8)^'4. NPV'!$E$47)/10000,0)*10000+'4. NPV'!$E$56 -> 3200000 | G57: =IF(ISNUMBER(E57),IF(E57>='2. Kalkyldata'!$F$14,"✓ klarar krav","⚠ under krav"),"") -> ✓ klarar krav | H57: =CEILING('2. Kalkyldata'!$AD$20*'2. Kalkyldata'!$AG$19,1) -> 2621
B59: Kassaflöde före skatt — optimistisk | D59: =IF(D$37="","",IF(D$14=$C$5,D$37+$A$7*($D55-$C$7),D$37)) -> -1.4330188e+08 | E59: =IF(E$37="","",IF(E$14=$C$5,E$37+$A$7*($D55-$C$7),E$37)) -> 8023511 | F59: =IF(F$37="","",IF(F$14=$C$5,F$37+$A$7*($D55-$C$7),F$37)) -> 8158767.7 | G59: =IF(G$37="","",IF(G$14=$C$5,G$37+$A$7*($D55-$C$7),G$37)) -> 8303915.3 | H59: =IF(H$37="","",IF(H$14=$C$5,H$37+$A$7*($D55-$C$7),H$37)) -> 8458974.9 | I59: =IF(I$37="","",IF(I$14=$C$5,I$37+$A$7*($D55-$C$7),I$37)) -> 8623967.4 | J59: =IF(J$37="","",IF(J$14=$C$5,J$37+$A$7*($D55-$C$7),J$37)) -> 8798913.9 | K59: =IF(K$37="","",IF(K$14=$C$5,K$37+$A$7*($D55-$C$7),K$37)) -> 8983835.7 | ... BA59: =IF(BA$37="","",IF(BA$14=$C$5,BA$37+$A$7*($D55-$C$7),BA$37))
B60: Kassaflöde före skatt — bedömt (= rad 37) | D60: =IF(D$37="","",IF(D$14=$C$5,D$37+$A$7*($D56-$C$7),D$37)) -> -1.4330188e+08 | E60: =IF(E$37="","",IF(E$14=$C$5,E$37+$A$7*($D56-$C$7),E$37)) -> 8023511 | F60: =IF(F$37="","",IF(F$14=$C$5,F$37+$A$7*($D56-$C$7),F$37)) -> 8158767.7 | G60: =IF(G$37="","",IF(G$14=$C$5,G$37+$A$7*($D56-$C$7),G$37)) -> 8303915.3 | H60: =IF(H$37="","",IF(H$14=$C$5,H$37+$A$7*($D56-$C$7),H$37)) -> 8458974.9 | I60: =IF(I$37="","",IF(I$14=$C$5,I$37+$A$7*($D56-$C$7),I$37)) -> 8623967.4 | J60: =IF(J$37="","",IF(J$14=$C$5,J$37+$A$7*($D56-$C$7),J$37)) -> 8798913.9 | K60: =IF(K$37="","",IF(K$14=$C$5,K$37+$A$7*($D56-$C$7),K$37)) -> 8983835.7 | ... BA60: =IF(BA$37="","",IF(BA$14=$C$5,BA$37+$A$7*($D56-$C$7),BA$37))
B61: Kassaflöde före skatt — pessimistisk | D61: =IF(D$37="","",IF(D$14=$C$5,D$37+$A$7*($D57-$C$7),D$37)) -> -1.4330188e+08 | E61: =IF(E$37="","",IF(E$14=$C$5,E$37+$A$7*($D57-$C$7),E$37)) -> 8023511 | F61: =IF(F$37="","",IF(F$14=$C$5,F$37+$A$7*($D57-$C$7),F$37)) -> 8158767.7 | G61: =IF(G$37="","",IF(G$14=$C$5,G$37+$A$7*($D57-$C$7),G$37)) -> 8303915.3 | H61: =IF(H$37="","",IF(H$14=$C$5,H$37+$A$7*($D57-$C$7),H$37)) -> 8458974.9 | I61: =IF(I$37="","",IF(I$14=$C$5,I$37+$A$7*($D57-$C$7),I$37)) -> 8623967.4 | J61: =IF(J$37="","",IF(J$14=$C$5,J$37+$A$7*($D57-$C$7),J$37)) -> 8798913.9 | K61: =IF(K$37="","",IF(K$14=$C$5,K$37+$A$7*($D57-$C$7),K$37)) -> 8983835.7 | ... BA61: =IF(BA$37="","",IF(BA$14=$C$5,BA$37+$A$7*($D57-$C$7),BA$37))

Sheet 6. Ack.kapitalutlägg
A1: ACKUMULERAT KAPITALUTLÄGG
A2: Visar hur mycket av investeringen, inklusive räntekrav på bundet kapital, som återstår att tjäna in år för år. När Ack. kapitalutlägg (sista raden) når 0 är kapitalet återvunnet.
B3: Belopp i kr | C3: ='4. NPV'!D$4 -> 2026 | D3: ='4. NPV'!E$4 -> 2027 | E3: ='4. NPV'!F$4 -> 2028 | F3: ='4. NPV'!G$4 -> 2029 | G3: ='4. NPV'!H$4 -> 2030 | H3: ='4. NPV'!I$4 -> 2031 | I3: ='4. NPV'!J$4 -> 2032 | J3: ='4. NPV'!K$4 -> 2033 | ... AZ3: ='4. NPV'!BA$4
B4: År i kalkylen | C4: ='5. IRR'!D14 -> 1 | D4: ='5. IRR'!E14 -> 2 | E4: ='5. IRR'!F14 -> 3 | F4: ='5. IRR'!G14 -> 4 | G4: ='5. IRR'!H14 -> 5 | H4: ='5. IRR'!I14 -> 6 | I4: ='5. IRR'!J14 -> 7 | J4: ='5. IRR'!K14 -> 8 | ... AZ4: ='5. IRR'!BA14 -> 50
B5: (+) Ingående balans (bokfört värde) | C5: ='2. Kalkyldata'!$P$9-'2. Kalkyldata'!$P$10 -> 0
B6: (-) Driftnetto (hela fastigheten, 4. NPV) | C6: ='4. NPV'!D$29 -> 13694500 | D6: ='4. NPV'!E$29 -> 13871400 | E6: ='4. NPV'!F$29 -> 14050480 | F6: ='4. NPV'!G$29 -> 14231765 | G6: ='4. NPV'!H$29 -> 14415279 | H6: ='4. NPV'!I$29 -> 14601048 | I6: ='4. NPV'!J$29 -> 14789097 | J6: ='4. NPV'!K$29 -> 14979452 | ... AZ6: ='4. NPV'!BA$29 -> 0
B7: (-) Räntebidrag | C7: 0 | D7: 0 | E7: 0 | F7: 0 | G7: 0 | H7: 0 | I7: 0 | J7: 0 | K7: 0 | L7: 0 | M7: 0 | N7: 0 | O7: 0 | P7: 0 | Q7: 0 | R7: 0 | S7: 0 | T7: 0 | U7: 0 | V7: 0 | W7: 0 | X7: 0 | Y7: 0 | Z7: 0 | AA7: 0 | AB7: 0 | AC7: 0 | AD7: 0 | AE7: 0 | AF7: 0 | AG7: 0 | AH7: 0 | AI7: 0 | AJ7: 0 | AK7: 0 | AL7: 0 | AM7: 0 | AN7: 0 | AO7: 0 | AP7: 0 | AQ7: 0 | AR7: 0 | AS7: 0 | AT7: 0 | AU7: 0 | AV7: 0 | AW7: 0 | AX7: 0 | AY7: 0 | AZ7: 0
B8: (+) Investeringar inkl projektbelastat bokfört värde | C8: =('4. NPV'!D$9)-'2. Kalkyldata'!$AA$28 -> -2.4e+08 | D8: =('4. NPV'!E$9) -> 0 | E8: =('4. NPV'!F$9) -> 0 | F8: =('4. NPV'!G$9) -> 0 | G8: =('4. NPV'!H$9) -> 0 | H8: =('4. NPV'!I$9) -> 0 | I8: =('4. NPV'!J$9) -> 0 | J8: =('4. NPV'!K$9) -> 0 | K8: =('4. NPV'!L$9) -> 0 | ... AZ8: =('4. NPV'!BA$9) -> 0
B9: (-) Övriga intäkter/kostnader (5. IRR rad 24–25) | C9: =('5. IRR'!D$24+'5. IRR'!D$25) -> 0 | D9: =('5. IRR'!E$24+'5. IRR'!E$25) -> 0 | E9: =('5. IRR'!F$24+'5. IRR'!F$25) -> 0 | F9: =('5. IRR'!G$24+'5. IRR'!G$25) -> 0 | G9: =('5. IRR'!H$24+'5. IRR'!H$25) -> 0 | H9: =('5. IRR'!I$24+'5. IRR'!I$25) -> 0 | I9: =('5. IRR'!J$24+'5. IRR'!J$25) -> 0 | J9: =('5. IRR'!K$24+'5. IRR'!K$25) -> 0 | ... AZ9: =('5. IRR'!BA$24+'5. IRR'!BA$25) -> 0
B10: (=) Kassaflöde | C10: =C6+C7+C8 -> -2.263055e+08 | D10: =D6+D7+D8 -> 13871400 | E10: =E6+E7+E8 -> 14050480 | F10: =F6+F7+F8 -> 14231765 | G10: =G6+G7+G8 -> 14415279 | H10: =H6+H7+H8 -> 14601048 | I10: =I6+I7+I8 -> 14789097 | J10: =J6+J7+J8 -> 14979452 | ... AZ10: =AZ6+AZ7+AZ8 -> 0
B11: (+) Räntekrav (kalkylränta driftnetto, flik 2) | C11: =-(SUM(C$8:$C$8)*'2. Kalkyldata'!$M$7) -> 10920000 | D11: =C$13*'2. Kalkyldata'!$M$7 -> 10793760 | E11: =D$13*'2. Kalkyldata'!$M$7 -> 10653728 | F11: =E$13*'2. Kalkyldata'!$M$7 -> 10499175 | G11: =F$13*'2. Kalkyldata'!$M$7 -> 10329343 | H11: =G$13*'2. Kalkyldata'!$M$7 -> 10143432 | I11: =H$13*'2. Kalkyldata'!$M$7 -> 9940610.9 | J11: =I$13*'2. Kalkyldata'!$M$7 -> 9720004.8 | K11: =J$13*'2. Kalkyldata'!$M$7 -> 9480700 | ... AZ11: =AY$13*'2. Kalkyldata'!$M$7 -> 0
B12: (=) Återvunnet kapital (kassaflöde − räntekrav) | C12: =C10-C11 -> -2.372255e+08 | D12: =D10-D11 -> 3077639.8 | E12: =E10-E11 -> 3396752.5 | F12: =F10-F11 -> 3732589.6 | G12: =G10-G11 -> 4085936.9 | H12: =H10-H11 -> 4457616 | I12: =I10-I11 -> 4848486.4 | J12: =J10-J11 -> 5259446.8 | ... AZ12: =AZ10-AZ11 -> 0
B13: (=) Ack. kapitalutlägg (kvar att återvinna) | C13: =IF(C$3="",0,C$5-C$6-C$8+-C$9+C$11) -> 2.372255e+08 | D13: =IF(D$3="",0,C$13-D$6-D$8+-D$9+D$11) -> 2.3414786e+08 | E13: =IF(E$3="",0,D$13-E$6-E$8+-E$9+E$11) -> 2.3075111e+08 | F13: =IF(F$3="",0,E$13-F$6-F$8+-F$9+F$11) -> 2.2701852e+08 | G13: =IF(G$3="",0,F$13-G$6-G$8+-G$9+G$11) -> 2.2293258e+08 | H13: =IF(H$3="",0,G$13-H$6-H$8+-H$9+H$11) -> 2.1847497e+08 | I13: =IF(I$3="",0,H$13-I$6-I$8+-I$9+I$11) -> 2.1362648e+08 | J13: =IF(J$3="",0,I$13-J$6-J$8+-J$9+J$11) -> 2.0836703e+08 | K13: =IF(K$3="",0,J$13-K$6-K$8+-K$9+K$11) -> 2.026756e+08 | ... AZ13: =IF(AZ$3="",0,AY$13-AZ$6-AZ$8+-AZ$9+AZ$11) -> 0
B15: Tecknen (+)/(−) anger effekten på Ack. kapitalutlägg. Kassaflöde = rad 6 + 7 + 8. Räntekrav = föregående års Ack. kapitalutlägg × kalkylränta driftnetto (2. Kalkyldata M7); år 1 investeringen × samma ränta.
B16: Räntebidrag (rad 7, dold) ingår i Kassaflöde men inte i Ack. kapitalutlägg. Övriga intäkter/kostnader (rad 9) ingår i Ack. kapitalutlägg men inte i Kassaflöde.
B17: Ack. kapitalutlägg används i 5. IRR rad 6. Med standardvikterna (0 % / 100 % / 0 %) påverkar fliken inte exit-värdet – den är information.

Sheet 7.Grafer
A36: Diagramunderlag per kalkylår
A37: Inget fylls i här. Raderna hämtas från flik 3–5 och kan markeras för egna diagram (Infoga › Diagram). Rad 44 och 48 används av 4. NPV rad 34–35 – ändra inte.
B38: Kalenderår | C38: ='3. Finansiering'!D$13 -> 2026 | D38: ='3. Finansiering'!E$13 -> 2027 | E38: ='3. Finansiering'!F$13 -> 2028 | F38: ='3. Finansiering'!G$13 -> 2029 | G38: ='3. Finansiering'!H$13 -> 2030 | H38: ='3. Finansiering'!I$13 -> 2031 | I38: ='3. Finansiering'!J$13 -> 2032 | J38: ='3. Finansiering'!K$13 -> 2033 | ... AZ38: ='3. Finansiering'!BA$13
B39: Kalkylår | C39: ='3. Finansiering'!D$14 -> 1 | D39: ='3. Finansiering'!E$14 -> 2 | E39: ='3. Finansiering'!F$14 -> 3 | F39: ='3. Finansiering'!G$14 -> 4 | G39: ='3. Finansiering'!H$14 -> 5 | H39: ='3. Finansiering'!I$14 -> 6 | I39: ='3. Finansiering'!J$14 -> 7 | J39: ='3. Finansiering'!K$14 -> 8 | ... AZ39: ='3. Finansiering'!BA$14 -> 50
A40: kr | B40: Driftnetto tillkommande exkl. extraordinärt UH | C40: =IFERROR(('4. NPV'!D$71-'4. NPV'!D$72),0) -> 13694500 | D40: =IFERROR(('4. NPV'!E$71-'4. NPV'!E$72),0) -> 13871400 | E40: =IFERROR(('4. NPV'!F$71-'4. NPV'!F$72),0) -> 14050480 | F40: =IFERROR(('4. NPV'!G$71-'4. NPV'!G$72),0) -> 14231765 | G40: =IFERROR(('4. NPV'!H$71-'4. NPV'!H$72),0) -> 14415279 | H40: =IFERROR(('4. NPV'!I$71-'4. NPV'!I$72),0) -> 14601048 | I40: =IFERROR(('4. NPV'!J$71-'4. NPV'!J$72),0) -> 14789097 | J40: =IFERROR(('4. NPV'!K$71-'4. NPV'!K$72),0) -> 14979452 | ... AZ40: =IFERROR(('4. NPV'!BA$71-'4. NPV'!BA$72),0) -> 0
A41: kr | B41: Intäkter | C41: =IFERROR('4. NPV'!D$19,0) -> 16165000 | D41: =IFERROR('4. NPV'!E$19,0) -> 16391310 | E41: =IFERROR('4. NPV'!F$19,0) -> 16620788 | F41: =IFERROR('4. NPV'!G$19,0) -> 16853479 | G41: =IFERROR('4. NPV'!H$19,0) -> 17089428 | H41: =IFERROR('4. NPV'!I$19,0) -> 17328680 | I41: =IFERROR('4. NPV'!J$19,0) -> 17571282 | J41: =IFERROR('4. NPV'!K$19,0) -> 17817280 | ... AZ41: =IFERROR('4. NPV'!BA$19,0) -> 0
A42: kr | B42: Kostnader exkl. extraordinärt UH | C42: =-IFERROR(('4. NPV'!D$26+'4. NPV'!D$27+'4. NPV'!D$28-'4. NPV'!D$25),0) -> 2470500 | D42: =-IFERROR(('4. NPV'!E$26+'4. NPV'!E$27+'4. NPV'!E$28-'4. NPV'!E$25),0) -> 2519910 | E42: =-IFERROR(('4. NPV'!F$26+'4. NPV'!F$27+'4. NPV'!F$28-'4. NPV'!F$25),0) -> 2570308.2 | F42: =-IFERROR(('4. NPV'!G$26+'4. NPV'!G$27+'4. NPV'!G$28-'4. NPV'!G$25),0) -> 2621714.4 | G42: =-IFERROR(('4. NPV'!H$26+'4. NPV'!H$27+'4. NPV'!H$28-'4. NPV'!H$25),0) -> 2674148.7 | H42: =-IFERROR(('4. NPV'!I$26+'4. NPV'!I$27+'4. NPV'!I$28-'4. NPV'!I$25),0) -> 2727631.6 | I42: =-IFERROR(('4. NPV'!J$26+'4. NPV'!J$27+'4. NPV'!J$28-'4. NPV'!J$25),0) -> 2782184.3 | J42: =-IFERROR(('4. NPV'!K$26+'4. NPV'!K$27+'4. NPV'!K$28-'4. NPV'!K$25),0) -> 2837827.9 | ... AZ42: =-IFERROR(('4. NPV'!BA$26+'4. NPV'!BA$27+'4. NPV'!BA$28-'4. NPV'!BA$25),0) -> 0
A43: kr | B43: Extraordinärt UH | C43: =-'4. NPV'!D$25 -> 0 | D43: =-'4. NPV'!E$25 -> 0 | E43: =-'4. NPV'!F$25 -> 0 | F43: =-'4. NPV'!G$25 -> 0 | G43: =-'4. NPV'!H$25 -> 0 | H43: =-'4. NPV'!I$25 -> 0 | I43: =-'4. NPV'!J$25 -> 0 | J43: =-'4. NPV'!K$25 -> 0 | ... AZ43: =-'4. NPV'!BA$25 -> 0
A44: kr | B44: Restvärde tillkommande, årets slut | C44: =IF(C40=0,C48,'4. NPV'!D$88) -> 2.1340615e+08 | D44: =IF(D40=0,D48,'4. NPV'!E$88) -> 2.1616123e+08 | E44: =IF(E40=0,E48,'4. NPV'!F$88) -> 2.1895023e+08 | F44: =IF(F40=0,F48,'4. NPV'!G$88) -> 2.2177353e+08 | G44: =IF(G40=0,G48,'4. NPV'!H$88) -> 2.2463151e+08 | H44: =IF(H40=0,H48,'4. NPV'!I$88) -> 2.2752457e+08 | I44: =IF(I40=0,I48,'4. NPV'!J$88) -> 2.304531e+08 | J44: =IF(J40=0,J48,'4. NPV'!K$88) -> 2.3341749e+08 | ... AZ44: =IF(AZ40=0,AZ48,'4. NPV'!BA$88) -> 0
A45: kr | B45: Investeringar | C45: =-'5. IRR'!D16 -> 2.4e+08 | D45: =-'5. IRR'!E16 -> 0 | E45: =-'5. IRR'!F16 -> 0 | F45: =-'5. IRR'!G16 -> 0 | G45: =-'5. IRR'!H16 -> 0 | H45: =-'5. IRR'!I16 -> 0 | I45: =-'5. IRR'!J16 -> 0 | J45: =-'5. IRR'!K16 -> 0 | ... XFC45: =-'5. IRR'!XFD16 -> 0
A46: kr | B46: Ackumulerade investeringar | C46: =-'5. IRR'!D$17 -> 2.4e+08 | D46: =-'5. IRR'!E$17 -> 2.4e+08 | E46: =-'5. IRR'!F$17 -> 2.4e+08 | F46: =-'5. IRR'!G$17 -> 2.4e+08 | G46: =-'5. IRR'!H$17 -> 2.4e+08 | H46: =-'5. IRR'!I$17 -> 2.4e+08 | I46: =-'5. IRR'!J$17 -> 2.4e+08 | J46: =-'5. IRR'!K$17 -> 2.4e+08 | ... AZ46: =-'5. IRR'!BA$17 -> 0
A47: kr | B47: Ackumulerat driftnetto inkl. extraordinärt UH | C47: =IF('6. Ack.kapitalutlägg'!C3="",0,SUM('4. NPV'!D$29:'4. NPV'!$D$29)) -> 13694500 | D47: =IF('6. Ack.kapitalutlägg'!D3="",0,SUM('4. NPV'!E$29:'4. NPV'!$D$29)) -> 27565900 | E47: =IF('6. Ack.kapitalutlägg'!E3="",0,SUM('4. NPV'!F$29:'4. NPV'!$D$29)) -> 41616380 | F47: =IF('6. Ack.kapitalutlägg'!F3="",0,SUM('4. NPV'!G$29:'4. NPV'!$D$29)) -> 55848145 | G47: =IF('6. Ack.kapitalutlägg'!G3="",0,SUM('4. NPV'!H$29:'4. NPV'!$D$29)) -> 70263425 | H47: =IF('6. Ack.kapitalutlägg'!H3="",0,SUM('4. NPV'!I$29:'4. NPV'!$D$29)) -> 84864473 | I47: =IF('6. Ack.kapitalutlägg'!I3="",0,SUM('4. NPV'!J$29:'4. NPV'!$D$29)) -> 99653570 | J47: =IF('6. Ack.kapitalutlägg'!J3="",0,SUM('4. NPV'!K$29:'4. NPV'!$D$29)) -> 1.1463302e+08 | ... AZ47: =IF('6. Ack.kapitalutlägg'!AZ3="",0,SUM('4. NPV'!BA$29:'4. NPV'!$D$29)) -> 0
A48: kr | B48: Bokfört värde | C48: ='3. Finansiering'!D57 -> 2.3272727e+08 | D48: ='3. Finansiering'!E57 -> 2.2545455e+08 | E48: ='3. Finansiering'!F57 -> 2.1818182e+08 | F48: ='3. Finansiering'!G57 -> 2.1090909e+08 | G48: ='3. Finansiering'!H57 -> 2.0363636e+08 | H48: ='3. Finansiering'!I57 -> 1.9636364e+08 | I48: ='3. Finansiering'!J57 -> 1.8909091e+08 | J48: ='3. Finansiering'!K57 -> 1.8181818e+08 | ... AZ48: ='3. Finansiering'!BA57 -> 0
B49: Rad 40, 44 och 50 avser tillkommande flöde (Bef = nollalternativ), övriga rader hela fastigheten. Utan Bef-objekt sammanfaller de.
A50: kr/kvm | B50: Driftnetto (= rad 40 per kvm) | C50: =IFERROR(C40/'4. NPV'!D$8,0) -> 2245 | D50: =IFERROR(D40/'4. NPV'!E$8,0) -> 2274 | E50: =IFERROR(E40/'4. NPV'!F$8,0) -> 2303.3574 | F50: =IFERROR(F40/'4. NPV'!G$8,0) -> 2333.0762 | G50: =IFERROR(G40/'4. NPV'!H$8,0) -> 2363.1606 | H50: =IFERROR(H40/'4. NPV'!I$8,0) -> 2393.6145 | I50: =IFERROR(I40/'4. NPV'!J$8,0) -> 2424.4422 | J50: =IFERROR(J40/'4. NPV'!K$8,0) -> 2455.6478 | ... AZ50: =IFERROR(AZ40/'4. NPV'!BA$8,0) -> 0
A51: kr/kvm | B51: Intäkter (= rad 41 per kvm) | C51: =IFERROR(C41/'4. NPV'!D$8,0) -> 2650 | D51: =IFERROR(D41/'4. NPV'!E$8,0) -> 2687.1 | E51: =IFERROR(E41/'4. NPV'!F$8,0) -> 2724.7194 | F51: =IFERROR(F41/'4. NPV'!G$8,0) -> 2762.8655 | G51: =IFERROR(G41/'4. NPV'!H$8,0) -> 2801.5456 | H51: =IFERROR(H41/'4. NPV'!I$8,0) -> 2840.7672 | I51: =IFERROR(I41/'4. NPV'!J$8,0) -> 2880.538 | J51: =IFERROR(J41/'4. NPV'!K$8,0) -> 2920.8655 | ... AZ51: =IFERROR(AZ41/'4. NPV'!BA$8,0) -> 0
A52: kr/kvm | B52: Kostnader exkl. extraordinärt UH (= rad 42 per kvm) | C52: =IFERROR(C42/'4. NPV'!D$8,0) -> 405 | D52: =IFERROR(D42/'4. NPV'!E$8,0) -> 413.1 | E52: =IFERROR(E42/'4. NPV'!F$8,0) -> 421.362 | F52: =IFERROR(F42/'4. NPV'!G$8,0) -> 429.78924 | G52: =IFERROR(G42/'4. NPV'!H$8,0) -> 438.38502 | H52: =IFERROR(H42/'4. NPV'!I$8,0) -> 447.15273 | I52: =IFERROR(I42/'4. NPV'!J$8,0) -> 456.09578 | J52: =IFERROR(J42/'4. NPV'!K$8,0) -> 465.2177 | ... AZ52: =IFERROR(AZ42/'4. NPV'!BA$8,0) -> 0
B53: ='4. NPV'!B23 -> Total Media | C53: =IFERROR('4. NPV'!D23/'4. NPV'!D$8,0) -> 0 | D53: =-IFERROR('4. NPV'!E23/'4. NPV'!E$8,0) -> 0 | E53: =-IFERROR('4. NPV'!F23/'4. NPV'!F$8,0) -> 0 | F53: =-IFERROR('4. NPV'!G23/'4. NPV'!G$8,0) -> 0 | G53: =-IFERROR('4. NPV'!H23/'4. NPV'!H$8,0) -> 0 | H53: =-IFERROR('4. NPV'!I23/'4. NPV'!I$8,0) -> 0 | I53: =-IFERROR('4. NPV'!J23/'4. NPV'!J$8,0) -> 0 | J53: =-IFERROR('4. NPV'!K23/'4. NPV'!K$8,0) -> 0 | K53: =-IFERROR('4. NPV'!L23/'4. NPV'!L$8,0) -> 0 | ... XFC53: =-IFERROR('4. NPV'!XFD23/'4. NPV'!XFD$8,0) -> 0
B55: ='4. NPV'!B24 -> Total Övriga förvaltningskostnader | C55: =IFERROR('4. NPV'!D24/'4. NPV'!D$8,0) -> -405 | D55: =-IFERROR('4. NPV'!E24/'4. NPV'!E$8,0) -> 413.1 | E55: =-IFERROR('4. NPV'!F24/'4. NPV'!F$8,0) -> 421.362 | F55: =-IFERROR('4. NPV'!G24/'4. NPV'!G$8,0) -> 429.78924 | G55: =-IFERROR('4. NPV'!H24/'4. NPV'!H$8,0) -> 438.38502 | H55: =-IFERROR('4. NPV'!I24/'4. NPV'!I$8,0) -> 447.15273 | I55: =-IFERROR('4. NPV'!J24/'4. NPV'!J$8,0) -> 456.09578 | J55: =-IFERROR('4. NPV'!K24/'4. NPV'!K$8,0) -> 465.2177 | K55: =-IFERROR('4. NPV'!L24/'4. NPV'!L$8,0) -> 474.52205 | ... XFC55: =-IFERROR('4. NPV'!XFD24/'4. NPV'!XFD$8,0) -> 0
A57: % | B57: Belåningsgrad | C57: ='3. Finansiering'!D27 -> 0.3589 | D57: ='3. Finansiering'!E27 -> 0.3478 | E57: ='3. Finansiering'!F27 -> 0.3367 | F57: ='3. Finansiering'!G27 -> 0.3256 | G57: ='3. Finansiering'!H27 -> 0.3145 | H57: ='3. Finansiering'!I27 -> 0.3034 | I57: ='3. Finansiering'!J27 -> 0.2923 | J57: ='3. Finansiering'!K27 -> 0.2812 | ... AZ57: ='3. Finansiering'!BA27 -> 0.37

Sheet Kontoplan RR
A1: Media → flik 2, rad 37 | E1: KONTOPLAN RR
A2: 4610 El | E2: Konton som ingår i driftkostnadsposterna på 2. Kalkyldata (rad 34–38). Tabellerna nedan är källor till rullistor – ändra inte texterna.
A3: 4620 Värme
A4: 4623 Fjärrvärme
A5: 4630 Vatten | E5: Typ av åtgärd | F5: Förkortning | H5: Typ av projekt
A6: 4640 Sophämtning | E6: Befintligt | F6: Bef | H6: Nyproduktion
A7: 4690 Övrig mediakostnad | E7: Ombyggnad | F7: Omb | H7: Tillbyggnad
E8: Nybyggnad | F8: Nyb | H8: Ombyggnad
A9: Fastighetsskötsel → flik 2, rad 34 | E9: Installationer | F9: Ins | H9: Installationer
A10: 4112 Fastighetsskötsel mark | E10: Mark | F10: Mar | H10: Hyresgästanpassning
A11: 4113 Snöröjning och halkbekämpning | H11: N/A
A12: 4150 Bevakningskostnader | E12: Förkortning = rullistan Typ på 2. Kalkyldata (E23:E27).
A13: 4190 Övrig fastighetsskötsel | E13: Typ av projekt = rullistan på 1. Framskrivningsunderlag (G11).
A14: 4199 Drift o skötsel övr budgetkto | E14: Ändra inte texterna – formler på flik 1 läser listorna.
A16: Reparationer → flik 2, rad 35
A17: 4310 Reparation invändigt
A18: 4340 Reparation installationer
A19: 4350 Reparation utvändigt
A20: 4360 Reparation markytor
A21: 4390 Reparationsavtal 7000kr
A22: 4399 Reparationer budgetkonto
A24: Planerat underhåll → flik 2, rad 36
A25: 4510 Planerat underhåll invändigt
A26: 4540 Planerat underhåll installationer
A27: 4550 Planerat underhåll utvändigt
A28: 4560 Planerat underhåll markytor
... A37: 4799 Övrigt (budget)
